{
    "TSLA": {
        "Generated Report": "Tesla, Inc. (TSLA) presents a mixed ESG profile, with a total risk score of 24.76, indicating a medium level of risk in the sustainability domain. The Environmental Risk Score of 3.04 suggests that the company has relatively low environmental risks, which is consistent with its focus on electric vehicles and renewable energy solutions that aim to reduce carbon emissions. This positions Tesla favorably within the growing market for sustainable energy.\n\nHowever, the Social Risk Score of 14.13 is notably higher, indicating significant challenges related to labor practices, workplace culture, and potential human rights issues. This score raises concerns about the company's treatment of employees and its broader social impact, which could pose reputational risks and affect stakeholder relations.\n\nAdditionally, the Governance Risk Score of 7.6 indicates moderate concerns regarding corporate governance practices. Issues related to transparency, board diversity, and executive compensation could lead to potential governance-related challenges.\n\nThe Controversy Level of 3.0, in comparison to peer averages (min: 0.0, avg: 1.75, max: 4.0), underscores that Tesla faces notable scrutiny, particularly in relation to its social and governance practices. While the company\u2019s environmental initiatives are commendable, the elevated social and governance risks highlight areas for improvement.\n\nIn summary, while Tesla leads in environmental sustainability, it must address social and governance issues to mitigate risks and enhance its overall ESG standing.",
        "Reference ESG Data": {
            "Stock": "TSLA",
            "Total ESG Risk Score": 24.76,
            "Environmental Risk Score": 3.04,
            "Social Risk Score": 14.13,
            "Governance Risk Score": 7.6,
            "Controversy Level": 3.0,
            "Peer Controversy Min": 0.0,
            "Peer Controversy Avg": 1.75,
            "Peer Controversy Max": 4.0
        },
        "Faithfulness Evaluation": {
            "Score": 1.0,
            "Explanation": "The generated ESG report accurately reflects the reference ESG data for Tesla, Inc. (TSLA). It correctly states the total ESG risk score of 24.76 and provides a detailed breakdown of the Environmental Risk Score (3.04), Social Risk Score (14.13), and Governance Risk Score (7.6), all of which align with the reference data. The report also appropriately discusses the implications of these scores, particularly highlighting the significant social and governance challenges Tesla faces, which is consistent with the provided data. The mention of the Controversy Level of 3.0 and its comparison to peer averages further supports the accuracy of the report. Overall, the report is grounded in the actual data and presents a faithful representation of Tesla's ESG profile."
        }
    },
    "NVDA": {
        "Generated Report": "NVIDIA (NVDA) presents a mixed ESG profile based on its risk scores and controversy level. With a Total ESG Risk Score of 12.46, the company falls within a moderate risk category, indicating some exposure to sustainability challenges.\n\nThe Environmental Risk Score of 2.73 is relatively low, suggesting that NVIDIA has made strides in managing its environmental impacts, which is crucial for a technology company reliant on energy-intensive manufacturing processes. However, it is essential to monitor its commitments to sustainability, particularly concerning energy consumption and waste management.\n\nThe Social Risk Score of 4.08 indicates higher risks in social dimensions, potentially linked to workforce management, diversity, and community engagement. This score highlights the need for NVIDIA to strengthen its social responsibility initiatives to mitigate risks related to labor practices and stakeholder relations.\n\nThe Governance Risk Score of 5.65 is the highest among the three categories, signaling potential weaknesses in corporate governance. This could encompass board diversity, executive compensation, and shareholder rights, which are critical factors for investors focused on long-term sustainability.\n\nLastly, a Controversy Level of 2.0, compared to a peer average of 0.56, suggests that NVIDIA has faced notable incidents or criticisms, although not at the highest level. This warrants attention as controversies can affect reputation and stakeholder trust.\n\nIn summary, while NVIDIA demonstrates a relatively robust environmental performance, it must address social and governance risks to enhance its sustainability profile and mitigate potential vulnerabilities.",
        "Reference ESG Data": {
            "Stock": "NVDA",
            "Total ESG Risk Score": 12.46,
            "Environmental Risk Score": 2.73,
            "Social Risk Score": 4.08,
            "Governance Risk Score": 5.65,
            "Controversy Level": 2.0,
            "Peer Controversy Min": 0.0,
            "Peer Controversy Avg": 0.5583333333333333,
            "Peer Controversy Max": 3.0
        },
        "Faithfulness Evaluation": {
            "Score": 0.9,
            "Explanation": "The generated ESG report accurately reflects the key metrics from the reference ESG data, including the Total ESG Risk Score, Environmental Risk Score, Social Risk Score, Governance Risk Score, and Controversy Level. The report correctly categorizes NVIDIA's overall risk as moderate and highlights the specific areas of concern in social and governance dimensions, which aligns with the provided scores. \n\nHowever, the report could improve by providing more context regarding the implications of the scores and how they compare to industry peers, especially regarding the governance score, which is notably high. Additionally, while it mentions the need for NVIDIA to strengthen its social responsibility initiatives, it does not specify what those initiatives could be or how they might be implemented, which would enhance the report's practical relevance. Overall, the report is mostly faithful to the data, but slight improvements in depth and context could elevate its accuracy further."
        }
    },
    "AAPL": {
        "Generated Report": "Apple Inc. (AAPL) presents a mixed picture in terms of ESG performance, with a total ESG Risk Score of 18.75. The Environmental Risk Score is relatively low at 2.05, indicating that Apple has made strides in minimizing its environmental impact, particularly in renewable energy initiatives and product recycling programs. However, the Social and Governance Risk Scores, both at 8.35, suggest significant risks in these areas.\n\nThe Social Risk Score reflects potential concerns regarding labor practices, supply chain transparency, and product accessibility. Given Apple's global supply chain, particularly in regions with variable labor standards, this score raises red flags about labor rights and working conditions.\n\nSimilarly, the Governance Risk Score indicates issues related to board diversity, executive compensation, and shareholder rights. While Apple has made progress in corporate governance, the score suggests that there are still areas for improvement.\n\nThe Controversy Level of 3.0 aligns with the upper range of its peers, indicating that Apple has faced notable controversies, which could affect its brand reputation and investor perception. Comparatively, the peer controversy average of 0.56 highlights that Apple is more prone to scrutiny than many of its competitors.\n\nIn summary, while Apple shows strong environmental performance, its elevated social and governance risks, combined with a higher controversy level, warrant close attention from investors. Addressing these concerns will be essential for enhancing its sustainability profile and mitigating potential risks.",
        "Reference ESG Data": {
            "Stock": "AAPL",
            "Total ESG Risk Score": 18.75,
            "Environmental Risk Score": 2.05,
            "Social Risk Score": 8.35,
            "Governance Risk Score": 8.35,
            "Controversy Level": 3.0,
            "Peer Controversy Min": 0.0,
            "Peer Controversy Avg": 0.5598290598290598,
            "Peer Controversy Max": 3.0
        },
        "Faithfulness Evaluation": {
            "Score": 0.9,
            "Explanation": "The generated ESG report accurately reflects the total ESG Risk Score of 18.75 and the Environmental Risk Score of 2.05, which are consistent with the reference data. It correctly identifies the Social and Governance Risk Scores as both being 8.35, indicating significant risks in those areas. The report also appropriately discusses the implications of these scores, particularly in relation to labor practices and governance issues.\n\nHowever, the report could improve its faithfulness by providing a more nuanced discussion of the Controversy Level. While it states that the Controversy Level of 3.0 aligns with the upper range of its peers, it does not clarify that this is the maximum level among peers, which could mislead readers regarding the context of Apple's controversies. Additionally, the report could benefit from a more precise comparison with peer controversy averages, as it mentions the average of 0.56 but does not emphasize how starkly Apple stands out in this regard.\n\nOverall, the report is largely faithful to the reference data, with minor areas for improvement in contextual clarity."
        }
    },
    "SPY": {
        "Generated Report": "No ESG data available for SPY",
        "Reference ESG Data": {
            "error": "No ESG data available for SPY"
        },
        "Faithfulness Evaluation": "Could not evaluate due to error in data or report generation."
    },
    "QQQ": {
        "Generated Report": "No ESG data available for QQQ",
        "Reference ESG Data": {
            "error": "No ESG data available for QQQ"
        },
        "Faithfulness Evaluation": "Could not evaluate due to error in data or report generation."
    },
    "META": {
        "Generated Report": "META's total ESG risk score of 32.73 indicates a moderate level of overall sustainability risk, with specific vulnerabilities in social and governance dimensions. The environmental risk score of 2.41 suggests that the company has a relatively low impact in this area, indicating effective management of environmental factors. \n\nHowever, the social risk score of 21.64 is notably high, reflecting significant concerns around issues such as data privacy, misinformation, and the societal impact of its platforms. This elevated score is compounded by a controversy level of 4.0, which aligns with the maximum observed among peers, signifying that META faces considerable scrutiny and public backlash. Comparatively, the peer controversy average of approximately 0.66 highlights that META's challenges are significantly greater than the industry norm.\n\nThe governance risk score of 8.68 also raises flags, suggesting potential weaknesses in corporate governance practices, transparency, and accountability. \n\nIn summary, while META demonstrates effective environmental management, the high social risk and controversy levels present substantial reputational and operational risks. Investors should closely monitor the company's strategies for addressing social concerns and governance practices, as these factors could impact long-term sustainability and financial performance.",
        "Reference ESG Data": {
            "Stock": "META",
            "Total ESG Risk Score": 32.73,
            "Environmental Risk Score": 2.41,
            "Social Risk Score": 21.64,
            "Governance Risk Score": 8.68,
            "Controversy Level": 4.0,
            "Peer Controversy Min": 0.0,
            "Peer Controversy Avg": 0.6598984771573604,
            "Peer Controversy Max": 4.0
        },
        "Faithfulness Evaluation": {
            "Score": 1.0,
            "Explanation": "The generated ESG report accurately reflects the provided reference ESG data for META. It correctly states the total ESG risk score of 32.73 and breaks down the environmental, social, and governance risk scores, which align with the reference data. The report highlights the low environmental risk score of 2.41, the high social risk score of 21.64, and the governance risk score of 8.68, all of which are consistent with the reference data. Additionally, it appropriately discusses the controversy level of 4.0, noting that it is at the maximum among peers and significantly higher than the peer controversy average of approximately 0.66. The report's conclusions about the implications of these scores for investors are well-founded and reflect the risks associated with META's social and governance dimensions. Overall, the report is faithful to the actual data provided."
        }
    },
    "AMZN": {
        "Generated Report": "Amazon (AMZN) presents a mixed ESG profile, highlighted by a Total ESG Risk Score of 26.1. The Environmental Risk Score of 8.3 indicates notable challenges, particularly related to its carbon footprint, packaging waste, and energy usage in operations. Despite efforts to enhance sustainability through initiatives like renewable energy investments, the environmental impact remains a critical area of concern.\n\nThe Social Risk Score of 11.05 is concerning, reflecting issues around labor practices, employee treatment, and community impact. The company has faced criticism over warehouse conditions, worker treatment, and the broader implications of its market dominance on local economies. These social challenges could lead to reputational risks and potential regulatory scrutiny.\n\nWith a Governance Risk Score of 6.75, Amazon appears to fare better in governance aspects, although there is room for improvement in shareholder engagement and board diversity. The Controversy Level of 3.0 signals a moderate level of scrutiny, with peer comparisons showing that AMZN's controversies surpass the average of 0.91 but remain below the maximum of 4.0 among its peers.\n\nIn summary, while Amazon is making strides in certain areas, significant environmental and social risks persist that could impact its long-term sustainability and investment attractiveness. Stakeholders should monitor developments, as addressing these challenges will be crucial for mitigating risks and enhancing the company's ESG standing.",
        "Reference ESG Data": {
            "Stock": "AMZN",
            "Total ESG Risk Score": 26.1,
            "Environmental Risk Score": 8.3,
            "Social Risk Score": 11.05,
            "Governance Risk Score": 6.75,
            "Controversy Level": 3.0,
            "Peer Controversy Min": 0.0,
            "Peer Controversy Avg": 0.9104477611940298,
            "Peer Controversy Max": 4.0
        },
        "Faithfulness Evaluation": {
            "Score": 1.0,
            "Explanation": "The generated ESG report accurately reflects the reference ESG data for Amazon (AMZN) in all key aspects. The Total ESG Risk Score of 26.1 is correctly stated, and the individual scores for Environmental (8.3), Social (11.05), and Governance (6.75) risks are also accurately reported. The report appropriately highlights the challenges associated with each risk category, particularly in environmental and social areas, which aligns with the provided data. Furthermore, the mention of the Controversy Level of 3.0 and its context relative to peer controversy averages is consistent with the reference data. Overall, the report is faithful to the actual data, providing a comprehensive and accurate overview of Amazon's ESG profile."
        }
    },
    "TQQQ": {
        "Generated Report": "No ESG data available for TQQQ",
        "Reference ESG Data": {
            "error": "No ESG data available for TQQQ"
        },
        "Faithfulness Evaluation": "Could not evaluate due to error in data or report generation."
    },
    "AMD": {
        "Generated Report": "Advanced Micro Devices, Inc. (AMD) presents a mixed ESG profile, with a total risk score of 12.51, indicating moderate ESG risks. The environmental risk score of 3.01 suggests that while AMD engages in responsible practices, there are still areas for improvement, particularly regarding energy consumption and waste management associated with semiconductor manufacturing.\n\nThe social risk score of 4.22 indicates potential vulnerabilities in labor practices, community engagement, and product safety. This aspect warrants close attention, especially as the tech industry faces increasing scrutiny over diversity, equity, and inclusion initiatives.\n\nThe governance risk score of 5.28 is relatively high, reflecting potential issues in corporate governance practices, including board diversity and executive compensation structures. Effective governance is crucial for managing risks and aligning with stakeholder interests.\n\nAMD's controversy level of 1.0 is low compared to its peers, with an average controversy score of 0.56. This suggests that while some controversies exist, they are less severe in comparison to industry counterparts, which may mitigate reputational risks.\n\nIn summary, AMD's ESG profile indicates room for improvement, particularly in governance and social aspects. However, its low controversy level is a positive sign. Investors should monitor AMD's ESG practices closely, especially as regulatory pressures and stakeholder expectations around sustainability continue to rise.",
        "Reference ESG Data": {
            "Stock": "AMD",
            "Total ESG Risk Score": 12.51,
            "Environmental Risk Score": 3.01,
            "Social Risk Score": 4.22,
            "Governance Risk Score": 5.28,
            "Controversy Level": 1.0,
            "Peer Controversy Min": 0.0,
            "Peer Controversy Avg": 0.5583333333333333,
            "Peer Controversy Max": 3.0
        },
        "Faithfulness Evaluation": {
            "Score": 1.0,
            "Explanation": "The generated ESG report accurately reflects the reference ESG data provided for AMD. It correctly states the total ESG risk score of 12.51 and breaks down the environmental, social, and governance risk scores as 3.01, 4.22, and 5.28, respectively. The report also appropriately describes the controversy level of 1.0 and compares it to the peer controversy average of 0.56, highlighting that AMD's controversies are less severe than its peers. The analysis of areas for improvement in governance and social aspects aligns with the risk scores presented. Overall, the report is grounded in the actual data and provides a faithful representation of AMD's ESG profile."
        }
    },
    "NFLX": {
        "Generated Report": "Netflix (NFLX) exhibits a total ESG risk score of 15.88, indicating a moderate level of risk in terms of environmental, social, and governance factors. The environmental risk score is notably low at 0.16, suggesting that the company has minimal negative impacts on environmental sustainability. This could be attributed to its digital nature, which reduces physical resource consumption compared to traditional media.\n\nHowever, the social risk score of 7.38 highlights significant concerns regarding social factors, which may include issues related to content representation, labor practices, or community impact. This score suggests that Netflix may face scrutiny or backlash from stakeholders regarding its social policies and practices.\n\nThe governance risk score of 8.35 indicates potential weaknesses in corporate governance structures, which could lead to issues such as board diversity, executive compensation, or shareholder rights. These governance challenges can expose the company to risks, including regulatory scrutiny and reputational damage.\n\nThe controversy level of 2.0, while higher than the peer average of 1.01, indicates that NFLX has faced some public scrutiny or criticism, but it is within a manageable range. This suggests that while the company is not without its controversies, it is not at the highest level of risk compared to its peers.\n\nOverall, while Netflix shows strengths in environmental sustainability, its social and governance risks warrant careful monitoring, as they pose potential reputational and operational challenges in the evolving landscape of ESG expectations.",
        "Reference ESG Data": {
            "Stock": "NFLX",
            "Total ESG Risk Score": 15.88,
            "Environmental Risk Score": 0.16,
            "Social Risk Score": 7.38,
            "Governance Risk Score": 8.35,
            "Controversy Level": 2.0,
            "Peer Controversy Min": 0.0,
            "Peer Controversy Avg": 1.0070921985815602,
            "Peer Controversy Max": 3.0
        },
        "Faithfulness Evaluation": {
            "Score": 1.0,
            "Explanation": "The generated ESG report accurately reflects the provided reference ESG data for Netflix (NFLX). It correctly states the total ESG risk score of 15.88 and breaks down the environmental (0.16), social (7.38), and governance (8.35) risk scores, aligning perfectly with the reference data. The report also appropriately contextualizes the environmental score as low due to Netflix's digital nature, which is a reasonable interpretation. Furthermore, it accurately discusses the implications of the social and governance scores, noting potential weaknesses and risks associated with them. The controversy level of 2.0 is correctly compared to the peer average of 1.01, providing a clear understanding of Netflix's position relative to its peers. Overall, the report is comprehensive, well-grounded in the actual data, and provides a faithful representation of Netflix's ESG standing."
        }
    }
}