{
    "TSLA": {
        "Generated Report": "Tesla, Inc. (TSLA) presents a mixed profile in terms of ESG performance, with a total ESG risk score of 24.76. The environmental risk score of 3.04 indicates that Tesla, a company fundamentally focused on sustainable energy solutions and electric vehicles, has relatively low environmental risks. This aligns with its mission to reduce carbon emissions and promote renewable energy, showcasing its commitment to environmental stewardship.\n\nHowever, the social risk score of 14.13 is notably higher, suggesting significant challenges in this area. Issues may stem from labor practices, workplace safety, and community relations, which can impact the company\u2019s reputation and operational stability. This risk is further compounded by a controversy level of 3.0, indicating that Tesla faces notable scrutiny and public attention regarding its social practices. Comparatively, the peer controversy average of 1.75 highlights that Tesla experiences a higher level of controversy than its industry counterparts, suggesting a need for improved stakeholder engagement and resolution of social issues.\n\nThe governance risk score of 7.6 indicates moderate concerns, which may include board diversity, executive compensation, and transparency. While these governance aspects are not critical red flags, they warrant ongoing attention to enhance investor confidence and corporate accountability.\n\nIn summary, while Tesla excels in environmental sustainability, it must address significant social risks and governance challenges to mitigate potential reputational damage and align better with stakeholder expectations.",
        "Reference ESG Data": {
            "Stock": "TSLA",
            "Total ESG Risk Score": 24.76,
            "Environmental Risk Score": 3.04,
            "Social Risk Score": 14.13,
            "Governance Risk Score": 7.6,
            "Controversy Level": 3.0,
            "Peer Controversy Min": 0.0,
            "Peer Controversy Avg": 1.75,
            "Peer Controversy Max": 4.0
        },
        "Faithfulness Evaluation": {
            "Score": 1.0,
            "Explanation": "The generated ESG report accurately reflects the provided reference ESG data for Tesla, Inc. (TSLA). It correctly states the total ESG risk score of 24.76, the environmental risk score of 3.04, the social risk score of 14.13, the governance risk score of 7.6, and the controversy level of 3.0. The report effectively contextualizes these scores, explaining the implications of the social and governance risks while highlighting Tesla's strengths in environmental sustainability. Additionally, it appropriately compares Tesla's controversy level to the peer average, indicating a higher level of scrutiny. Overall, the report is faithful to the actual data, providing a clear and accurate representation of Tesla's ESG profile."
        }
    },
    "NVDA": {
        "Generated Report": "NVIDIA Corporation (NVDA) exhibits a total ESG risk score of 12.46, positioning it within a moderate risk category. The breakdown of scores reveals a relatively low Environmental Risk Score of 2.73, indicating that the company is performing well in environmental sustainability practices compared to its peers. This is particularly relevant in the technology sector, where energy consumption and waste management are critical concerns.\n\nHowever, the Social Risk Score of 4.08 suggests potential vulnerabilities in areas such as labor practices, community engagement, and product safety. This score is indicative of challenges that may arise from workforce management and social equity, which could impact the company's reputation and operational stability.\n\nThe Governance Risk Score of 5.65 indicates a need for improvement in corporate governance practices. This score is the highest among the three dimensions, suggesting that stakeholders may have concerns regarding board diversity, executive compensation, and shareholder rights.\n\nThe Controversy Level of 2.0, while moderate, is notable compared to peer averages. NVDA\u2019s controversies could stem from social or governance-related issues, which may attract scrutiny from investors and advocates.\n\nOverall, while NVDA shows strengths in environmental practices, the moderate social and governance scores highlight potential risks that could affect long-term sustainability and investor sentiment. Continuous monitoring and proactive strategies in these areas will be essential for mitigating risks and enhancing overall ESG performance.",
        "Reference ESG Data": {
            "Stock": "NVDA",
            "Total ESG Risk Score": 12.46,
            "Environmental Risk Score": 2.73,
            "Social Risk Score": 4.08,
            "Governance Risk Score": 5.65,
            "Controversy Level": 2.0,
            "Peer Controversy Min": 0.0,
            "Peer Controversy Avg": 0.5583333333333333,
            "Peer Controversy Max": 3.0
        },
        "Faithfulness Evaluation": {
            "Score": 1.0,
            "Explanation": "The generated ESG report accurately reflects the reference ESG data provided for NVIDIA Corporation (NVDA). It correctly states the total ESG risk score of 12.46 and breaks down the scores for environmental (2.73), social (4.08), and governance (5.65) risks, aligning perfectly with the reference data. The report also appropriately describes the implications of these scores, such as the relatively low environmental risk and the higher governance risk, which is consistent with the data. Furthermore, the mention of the controversy level of 2.0 and its comparison to peer averages is accurate and relevant. Overall, the report is grounded in the actual data, making it fully faithful."
        }
    },
    "AAPL": {
        "Generated Report": "Apple Inc. (AAPL) presents a mixed picture in terms of its ESG performance, with a total ESG risk score of 18.75. The environmental risk score of 2.05 indicates relatively low exposure to environmental risks, suggesting that the company has made strides in sustainability initiatives, such as reducing carbon emissions and increasing the use of recycled materials in its products.\n\nHowever, the social and governance risk scores are notably higher, both at 8.35. This indicates significant potential risks in these areas, particularly concerning labor practices, supply chain management, and corporate governance. The social score may reflect issues related to workforce management, community engagement, or product safety, while the governance score suggests concerns over board diversity, executive compensation, or shareholder rights.\n\nThe controversy level of 3.0 is noteworthy, as it aligns with the maximum controversy level seen among peers, indicating that Apple has faced significant public scrutiny or backlash. While the peer controversy average is much lower (0.56), Apple\u2019s controversies may stem from its labor practices, environmental practices, or tax strategies.\n\nIn summary, while Apple excels in environmental sustainability, it faces substantial social and governance challenges. Investors should weigh these risks against the company's strengths in innovation and market leadership, keeping a close eye on evolving public sentiment and regulatory landscapes that could impact its ESG standing moving forward.",
        "Reference ESG Data": {
            "Stock": "AAPL",
            "Total ESG Risk Score": 18.75,
            "Environmental Risk Score": 2.05,
            "Social Risk Score": 8.35,
            "Governance Risk Score": 8.35,
            "Controversy Level": 3.0,
            "Peer Controversy Min": 0.0,
            "Peer Controversy Avg": 0.5598290598290598,
            "Peer Controversy Max": 3.0
        },
        "Faithfulness Evaluation": {
            "Score": 0.9,
            "Explanation": "The generated ESG report is largely faithful to the reference ESG data, accurately reflecting the total ESG risk score of 18.75 and the environmental risk score of 2.05. It correctly identifies the social and governance risk scores as both being 8.35, indicating significant risks in those areas. The report also appropriately mentions the controversy level of 3.0 and its implications, noting that it is at the maximum level among peers, which is consistent with the reference data.\n\nHowever, the report could improve its accuracy by providing more specific examples or clarifications regarding the nature of the controversies and risks associated with Apple, as well as a more detailed comparison with peer averages. While it mentions the peer controversy average, it does not explicitly state how Apple's scores compare to its peers beyond the controversy level. This lack of detail slightly detracts from the overall faithfulness of the report. Nonetheless, the core data points are correctly represented, justifying a high score of 0.9."
        }
    },
    "SPY": {
        "Generated Report": "No ESG data available for SPY",
        "Reference ESG Data": {
            "error": "No ESG data available for SPY"
        },
        "Faithfulness Evaluation": "Could not evaluate due to error in data or report generation."
    },
    "QQQ": {
        "Generated Report": "No ESG data available for QQQ",
        "Reference ESG Data": {
            "error": "No ESG data available for QQQ"
        },
        "Faithfulness Evaluation": "Could not evaluate due to error in data or report generation."
    },
    "META": {
        "Generated Report": "Meta's ESG risk scores indicate a mixed sustainability profile, with a total ESG Risk Score of 32.73. The Environmental Risk Score is relatively low at 2.41, suggesting that Meta\u2019s environmental impact is manageable and less of a concern compared to other areas. However, the Social Risk Score of 21.64 is considerably higher, indicating significant risks associated with social factors, which may include issues related to user privacy, data security, and the societal impact of its platforms.\n\nThe Governance Risk Score of 8.68 suggests some concerns related to corporate governance practices, which could encompass board diversity, executive compensation, and shareholder rights. The controversy level is rated at 4.0, which is on the higher end, highlighting that Meta has faced notable controversies, potentially affecting its reputation and stakeholder trust. Compared to its peers, with an average controversy score of approximately 0.66, Meta's score indicates it is an outlier, facing challenges that may not be as prevalent among its competitors.\n\nIn summary, while Meta appears to maintain a sound environmental profile, significant social and governance risks persist. Investors should be cautious about the implications of these risks, particularly the heightened scrutiny from regulators and the public, which could impact Meta's long-term sustainability and performance. Enhanced focus on social responsibility and governance practices may be crucial for risk mitigation and improving overall ESG standing.",
        "Reference ESG Data": {
            "Stock": "META",
            "Total ESG Risk Score": 32.73,
            "Environmental Risk Score": 2.41,
            "Social Risk Score": 21.64,
            "Governance Risk Score": 8.68,
            "Controversy Level": 4.0,
            "Peer Controversy Min": 0.0,
            "Peer Controversy Avg": 0.6598984771573604,
            "Peer Controversy Max": 4.0
        },
        "Faithfulness Evaluation": {
            "Score": 1.0,
            "Explanation": "The generated ESG report accurately reflects the provided reference ESG data for Meta. It correctly states the total ESG Risk Score of 32.73 and breaks down the individual scores for Environmental (2.41), Social (21.64), and Governance (8.68) risks, aligning perfectly with the reference data. The report also appropriately highlights the controversy level of 4.0, noting that this is significantly higher than the peer average of approximately 0.66, which emphasizes Meta's outlier status in terms of controversies. Overall, the report provides a faithful and comprehensive summary of Meta's ESG profile, making it a reliable representation of the actual data."
        }
    },
    "AMZN": {
        "Generated Report": "Amazon (AMZN) presents a mixed ESG profile, with a Total ESG Risk Score of 26.1 indicating a moderate level of risk. The Environmental Risk Score of 8.3 suggests that the company faces significant challenges related to its environmental impact, particularly concerning carbon emissions, waste management, and resource usage associated with its extensive logistics network. \n\nThe Social Risk Score of 11.05 signals notable concerns in areas such as labor practices, community relations, and consumer protection. Amazon has faced criticism regarding employee treatment, warehouse conditions, and its impact on local economies, which could pose reputational risks and potential regulatory scrutiny.\n\nThe Governance Risk Score of 6.75 reflects a relatively stable governance structure, although there may be room for improvement in shareholder engagement and transparency. The Controversy Level of 3.0, higher than the peer average of 0.91, indicates that Amazon has been involved in multiple ESG controversies, which could adversely affect its public perception and investor sentiment.\n\nIn summary, while Amazon has made strides in improving its sustainability initiatives, its moderate ESG risk scores and elevated controversy level highlight significant areas where the company must address environmental and social issues. These factors could impact its long-term viability and appeal to ESG-focused investors, suggesting a cautious approach is warranted in assessing its sustainability performance.",
        "Reference ESG Data": {
            "Stock": "AMZN",
            "Total ESG Risk Score": 26.1,
            "Environmental Risk Score": 8.3,
            "Social Risk Score": 11.05,
            "Governance Risk Score": 6.75,
            "Controversy Level": 3.0,
            "Peer Controversy Min": 0.0,
            "Peer Controversy Avg": 0.9104477611940298,
            "Peer Controversy Max": 4.0
        },
        "Faithfulness Evaluation": {
            "Score": 1.0,
            "Explanation": "The generated ESG report accurately reflects the provided reference ESG data for Amazon (AMZN). It correctly states the Total ESG Risk Score of 26.1 and breaks down the Environmental Risk Score (8.3), Social Risk Score (11.05), and Governance Risk Score (6.75) in a coherent manner. The report also appropriately addresses the Controversy Level of 3.0 and compares it to the peer average, highlighting the company's involvement in multiple ESG controversies. Furthermore, the report's commentary on the implications of these scores aligns with the data, emphasizing the challenges Amazon faces in environmental and social areas while acknowledging its governance structure. Overall, the report is faithful to the actual data, providing a comprehensive and accurate overview of Amazon's ESG profile."
        }
    },
    "TQQQ": {
        "Generated Report": "No ESG data available for TQQQ",
        "Reference ESG Data": {
            "error": "No ESG data available for TQQQ"
        },
        "Faithfulness Evaluation": "Could not evaluate due to error in data or report generation."
    },
    "AMD": {
        "Generated Report": "AMD's total ESG risk score of 12.51 suggests a moderate level of overall risk, with particular attention needed on its governance and social dimensions. The Environmental Risk Score of 3.01 indicates that while there are some environmental concerns, they are not overly severe compared to industry standards, particularly in a sector that often faces scrutiny over energy consumption and resource use.\n\nThe Social Risk Score of 4.22 reflects a more significant area of concern, potentially highlighting issues related to employee relations, community impact, or product responsibility. Given the increasing importance of social factors in ESG assessments, this score may require AMD to enhance its initiatives around workplace diversity, labor practices, and community engagement.\n\nThe Governance Risk Score of 5.28 is the highest among the three categories, signaling potential vulnerabilities in governance structures, transparency, or shareholder rights. This could attract attention from investors who prioritize strong governance practices.\n\nMoreover, AMD's controversy level of 1.0 is relatively low compared to its peers, whose average is 0.56, suggesting that while there are some controversies, they are not significant enough to severely impact the company's reputation or operations. This positions AMD favorably against competitors.\n\nIn summary, while AMD shows promise with a low controversy level, attention should be given to improving its social and governance practices to mitigate potential risks and enhance its overall sustainability profile.",
        "Reference ESG Data": {
            "Stock": "AMD",
            "Total ESG Risk Score": 12.51,
            "Environmental Risk Score": 3.01,
            "Social Risk Score": 4.22,
            "Governance Risk Score": 5.28,
            "Controversy Level": 1.0,
            "Peer Controversy Min": 0.0,
            "Peer Controversy Avg": 0.5583333333333333,
            "Peer Controversy Max": 3.0
        },
        "Faithfulness Evaluation": {
            "Score": 1.0,
            "Explanation": "The generated ESG report accurately reflects the reference ESG data provided for AMD. It correctly states the total ESG risk score of 12.51 and appropriately categorizes the Environmental, Social, and Governance Risk Scores as 3.01, 4.22, and 5.28, respectively. The report emphasizes the need for attention in governance and social dimensions, which aligns with the scores. Additionally, it correctly interprets the controversy level of 1.0 as low compared to the peer average of 0.56, indicating a favorable position against competitors. Overall, the report is faithful to the actual data, providing a clear and accurate assessment of AMD's ESG performance."
        }
    },
    "NFLX": {
        "Generated Report": "Netflix (NFLX) presents a mixed picture in terms of ESG performance. With a total ESG risk score of 15.88, it indicates a moderate level of risk, particularly in the social and governance dimensions, which have scores of 7.38 and 8.35, respectively. These scores suggest potential vulnerabilities in areas such as labor practices, consumer protection, and corporate governance, which could impact the company's reputation and operational stability.\n\nThe environmental risk score is notably low at 0.16, indicating that Netflix's operations are relatively sustainable in terms of environmental impact. This is positive, especially given the growing importance of environmental considerations among stakeholders.\n\nHowever, the controversy level of 2.0, while below the maximum peer controversy score of 3.0, is above the peer average of 1.01. This suggests that Netflix has faced some significant criticisms or issues that could affect stakeholder perceptions and investor confidence. \n\nOverall, while Netflix demonstrates strong environmental practices, the elevated social and governance risks, coupled with a higher-than-average controversy level, suggest that the company may need to enhance its policies and practices in these areas to mitigate potential risks and improve its overall sustainability profile. Addressing these concerns could enhance Netflix's long-term viability and appeal to socially conscious investors.",
        "Reference ESG Data": {
            "Stock": "NFLX",
            "Total ESG Risk Score": 15.88,
            "Environmental Risk Score": 0.16,
            "Social Risk Score": 7.38,
            "Governance Risk Score": 8.35,
            "Controversy Level": 2.0,
            "Peer Controversy Min": 0.0,
            "Peer Controversy Avg": 1.0070921985815602,
            "Peer Controversy Max": 3.0
        },
        "Faithfulness Evaluation": {
            "Score": 0.9,
            "Explanation": "The generated ESG report accurately reflects the reference ESG data for Netflix (NFLX) in several key areas. The total ESG risk score of 15.88 is correctly stated, and the social (7.38) and governance (8.35) risk scores are also accurately reported, highlighting the vulnerabilities in these dimensions. The environmental risk score of 0.16 is presented as low, which aligns with the reference data, indicating relatively sustainable operations.\n\nHowever, the report slightly misrepresents the controversy level. While it correctly states that the controversy level is 2.0 and acknowledges that it is above the peer average of 1.01, it does not clarify that the peer controversy minimum is 0.0. This omission could imply a lack of context regarding the severity of Netflix's controversy compared to its peers. \n\nOverall, the report is largely faithful to the reference data, but the slight oversight regarding the peer controversy context prevents it from achieving a perfect score."
        }
    }
}