{
    "TSLA": {
        "Generated Report": "Tesla, Inc. (TSLA) presents a mixed ESG profile based on the provided risk scores and controversy level. With a total ESG Risk Score of 24.76, the company reflects a moderate level of sustainability risk. \n\n**Environmental Risk**: Tesla's Environmental Risk Score of 3.04 is relatively low, which is positive considering the company's core business model centered around electric vehicles and renewable energy solutions. This indicates a commitment to reducing carbon emissions and promoting sustainability. \n\n**Social Risk**: The Social Risk Score stands at 14.13, which is notably higher, suggesting potential issues related to labor practices, community relations, or product safety. This aspect warrants closer scrutiny, as it could affect the company\u2019s reputation and operational stability.\n\n**Governance Risk**: The Governance Risk Score of 7.6 indicates moderate concerns, possibly linked to board diversity, executive compensation, or shareholder rights. Strong governance is essential for long-term sustainability and mitigating risks.\n\n**Controversy Level**: With a controversy level of 3.0, Tesla is positioned above the industry average (1.75) but below the maximum of 4.0. This suggests the company has faced significant scrutiny, potentially from labor disputes, regulatory challenges, or environmental concerns.\n\nIn summary, while Tesla demonstrates a commitment to environmental sustainability, the elevated social risk and controversy levels highlight areas that require attention to mitigate potential risks to its reputation and operational efficiency.",
        "Reference ESG Data": {
            "Stock": "TSLA",
            "Total ESG Risk Score": 24.76,
            "Environmental Risk Score": 3.04,
            "Social Risk Score": 14.13,
            "Governance Risk Score": 7.6,
            "Controversy Level": 3.0,
            "Peer Controversy Min": 0.0,
            "Peer Controversy Avg": 1.75,
            "Peer Controversy Max": 4.0
        },
        "Faithfulness Evaluation": {
            "Score": 0.9,
            "Explanation": "The generated ESG report accurately reflects the key data points from the reference ESG data, including the total ESG Risk Score, Environmental Risk Score, Social Risk Score, Governance Risk Score, and Controversy Level. The descriptions provided in the report align well with the scores, particularly in how they interpret the implications of the Environmental and Social Risk Scores. \n\nHowever, while the report is largely faithful to the data, it could benefit from a more nuanced discussion of the specific issues contributing to the elevated Social Risk Score and the controversy level. The mention of potential issues related to labor practices, community relations, or product safety is appropriate, but it lacks specific examples or context that would enhance understanding. \n\nOverall, the report is very accurate and grounded in the actual data, but the slight lack of detail in explaining the social risks and controversies prevents it from achieving a perfect score."
        }
    },
    "NVDA": {
        "Generated Report": "NVIDIA Corporation (NVDA) presents a mixed profile in terms of ESG risks, with a total ESG risk score of 12.46 indicating moderate risk exposure. The Environmental Risk Score stands at 2.73, suggesting that while the company is engaged in energy-intensive activities associated with semiconductor manufacturing, it may be taking steps to mitigate its environmental impact. This score is relatively low, which could reflect efforts towards sustainability initiatives, such as energy-efficient products or renewable energy usage.\n\nThe Social Risk Score of 4.08 indicates potential challenges related to labor practices, diversity, or community relations. This score is notably higher than the environmental score, suggesting that NVDA may face scrutiny regarding its social practices, which could present reputational risks.\n\nThe Governance Risk Score of 5.65 is the highest among the three categories, hinting at potential issues such as board diversity, executive compensation, or shareholder rights. This could raise red flags for investors concerned about governance structures and practices.\n\nThe controversy level of 2.0 is moderate, with NVDA sitting above the peer average (0.56), indicating that it has faced notable but not severe controversies. This could affect its reputation and investor sentiment.\n\nOverall, while NVDA shows strengths in environmental management, its higher social and governance risks warrant close monitoring. Investors should consider these factors in conjunction with the company's financial performance and market position when assessing overall sustainability and potential risks.",
        "Reference ESG Data": {
            "Stock": "NVDA",
            "Total ESG Risk Score": 12.46,
            "Environmental Risk Score": 2.73,
            "Social Risk Score": 4.08,
            "Governance Risk Score": 5.65,
            "Controversy Level": 2.0,
            "Peer Controversy Min": 0.0,
            "Peer Controversy Avg": 0.5583333333333333,
            "Peer Controversy Max": 3.0
        },
        "Faithfulness Evaluation": {
            "Score": 1.0,
            "Explanation": "The generated ESG report accurately reflects the provided reference ESG data for NVIDIA Corporation (NVDA). The total ESG risk score of 12.46 is correctly reported as indicating moderate risk exposure. The environmental, social, and governance risk scores (2.73, 4.08, and 5.65, respectively) are presented accurately, with appropriate context regarding their implications. The report correctly identifies the governance risk score as the highest, indicating potential issues, and appropriately contextualizes the controversy level of 2.0 in relation to peer averages. Overall, the report is faithful to the reference data, providing a clear and accurate summary of NVDA's ESG profile without introducing inaccuracies or misinterpretations."
        }
    },
    "AAPL": {
        "Generated Report": "Apple Inc. (AAPL) exhibits a Total ESG Risk Score of 18.75, indicating a moderate level of ESG-related risks. The Environmental Risk Score is relatively low at 2.05, suggesting that the company is effectively managing its environmental impacts, particularly in areas such as carbon emissions and resource utilization. This is consistent with Apple's commitment to sustainability, including its initiatives towards renewable energy and recycling.\n\nHowever, the Social and Governance Risk Scores are notably higher, both at 8.35. This indicates potential vulnerabilities in areas such as labor practices, supply chain management, and corporate governance. Apple has faced scrutiny over labor conditions in its supply chain, particularly concerning suppliers in developing countries, which could pose reputational risks. Furthermore, governance issues may arise from board diversity and shareholder rights, which are increasingly critical in ESG assessments.\n\nThe Controversy Level of 3.0 reflects a moderate level of public and media scrutiny, aligning with the peer average but highlighting the need for ongoing vigilance. Given that the maximum controversy score among peers is also 3.0, Apple is operating at the upper end of the controversy spectrum within its industry.\n\nIn conclusion, while Apple demonstrates strengths in environmental sustainability, it faces significant social and governance challenges that could impact its long-term sustainability and investor sentiment. Addressing these areas will be crucial for mitigating risks and enhancing its overall ESG profile.",
        "Reference ESG Data": {
            "Stock": "AAPL",
            "Total ESG Risk Score": 18.75,
            "Environmental Risk Score": 2.05,
            "Social Risk Score": 8.35,
            "Governance Risk Score": 8.35,
            "Controversy Level": 3.0,
            "Peer Controversy Min": 0.0,
            "Peer Controversy Avg": 0.5598290598290598,
            "Peer Controversy Max": 3.0
        },
        "Faithfulness Evaluation": {
            "Score": 1.0,
            "Explanation": "The generated ESG report accurately reflects the provided reference ESG data for Apple Inc. (AAPL). It correctly states the Total ESG Risk Score of 18.75 and the Environmental Risk Score of 2.05, both of which are consistent with the reference data. The report also appropriately highlights the Social and Governance Risk Scores of 8.35 each, indicating potential vulnerabilities, and discusses relevant issues such as labor practices and corporate governance, which align with the context of the scores. Additionally, the mention of a Controversy Level of 3.0 is accurate and contextualized well within the industry, noting that it aligns with the peer average and maximum. Overall, the report is grounded in the actual data and provides a faithful representation of Apple's ESG profile."
        }
    },
    "SPY": {
        "Generated Report": "No ESG data available for SPY",
        "Reference ESG Data": {
            "error": "No ESG data available for SPY"
        },
        "Faithfulness Evaluation": "Could not evaluate due to error in data or report generation."
    },
    "QQQ": {
        "Generated Report": "No ESG data available for QQQ",
        "Reference ESG Data": {
            "error": "No ESG data available for QQQ"
        },
        "Faithfulness Evaluation": "Could not evaluate due to error in data or report generation."
    },
    "META": {
        "Generated Report": "META's total ESG risk score of 32.73 indicates a moderate level of risk, with significant variation across the environmental, social, and governance dimensions. The company's environmental risk score of 2.41 is relatively low, suggesting limited environmental impact or strong management of associated risks. However, the higher social risk score of 21.64 raises concern, indicating potential challenges related to social issues, which may include user privacy, misinformation, and the societal impact of its platforms.\n\nThe governance risk score of 8.68 reflects potential vulnerabilities in corporate governance practices, which can affect decision-making and stakeholder trust. The controversy level of 4.0 is notably high, particularly when compared to the peer controversy average of 0.66, suggesting that META has faced significant public scrutiny or backlash, possibly related to data breaches, regulatory challenges, or ethical concerns.\n\nIn summary, while META demonstrates relatively low environmental risks, the high social risk score and controversy level indicate substantial reputational and operational risks. These factors could impact the company\u2019s long-term sustainability and investor confidence. Stakeholders should closely monitor efforts to address social concerns and improve governance practices to mitigate risks and enhance overall ESG performance.",
        "Reference ESG Data": {
            "Stock": "META",
            "Total ESG Risk Score": 32.73,
            "Environmental Risk Score": 2.41,
            "Social Risk Score": 21.64,
            "Governance Risk Score": 8.68,
            "Controversy Level": 4.0,
            "Peer Controversy Min": 0.0,
            "Peer Controversy Avg": 0.6598984771573604,
            "Peer Controversy Max": 4.0
        },
        "Faithfulness Evaluation": {
            "Score": 1.0,
            "Explanation": "The generated ESG report accurately reflects the reference ESG data for META. It correctly states the total ESG risk score of 32.73 and breaks down the scores into environmental (2.41), social (21.64), and governance (8.68) dimensions, aligning with the provided data. The report appropriately highlights the low environmental risk, the significant social risk, and potential governance vulnerabilities, which are consistent with the reference scores. Additionally, the mention of a controversy level of 4.0 and its comparison to the peer average of 0.66 is accurate and relevant, providing context for the company's public perception and scrutiny. Overall, the report is faithful to the data, making it a reliable summary of META's ESG performance."
        }
    },
    "AMZN": {
        "Generated Report": "Amazon (AMZN) presents a mixed ESG profile, with a Total ESG Risk Score of 26.1 indicating moderate risk. The Environmental Risk Score of 8.3 suggests that the company faces significant challenges in sustainability, particularly related to its carbon footprint, waste management, and resource use. Efforts to enhance renewable energy usage and reduce emissions are crucial for improving this aspect.\n\nThe Social Risk Score of 11.05 is a critical area of concern, reflecting issues such as labor practices, employee treatment, and community impact. The high score indicates potential risks related to workforce management, which could affect reputational standing and employee retention.\n\nThe Governance Risk Score of 6.75 suggests moderate governance challenges, which may include issues of board diversity, executive compensation, and transparency. While not the highest risk area, governance practices play a vital role in stakeholder trust.\n\nWith a Controversy Level of 3.0, Amazon has faced notable scrutiny, particularly in labor relations and environmental impact, compared to its peers. The peer controversy averages around 0.91, indicating that Amazon experiences higher levels of controversy than many competitors, which could lead to reputational risks and regulatory scrutiny.\n\nIn conclusion, while Amazon has opportunities to improve its ESG performance, it faces considerable challenges that could impact its sustainability and long-term viability. Addressing these risks is essential for enhancing its ESG standing and mitigating potential future liabilities.",
        "Reference ESG Data": {
            "Stock": "AMZN",
            "Total ESG Risk Score": 26.1,
            "Environmental Risk Score": 8.3,
            "Social Risk Score": 11.05,
            "Governance Risk Score": 6.75,
            "Controversy Level": 3.0,
            "Peer Controversy Min": 0.0,
            "Peer Controversy Avg": 0.9104477611940298,
            "Peer Controversy Max": 4.0
        },
        "Faithfulness Evaluation": {
            "Score": 1.0,
            "Explanation": "The generated ESG report accurately reflects the provided reference ESG data for Amazon (AMZN). It correctly states the Total ESG Risk Score of 26.1 and breaks down the Environmental, Social, and Governance Risk Scores as 8.3, 11.05, and 6.75, respectively. The report also appropriately highlights the Controversy Level of 3.0 and compares it to the peer controversy average of approximately 0.91, indicating that Amazon faces higher scrutiny than its competitors. The descriptions of the challenges in sustainability, labor practices, and governance are consistent with the scores provided, demonstrating a faithful representation of the actual data. Overall, the report is grounded in the reference data and provides a comprehensive overview of Amazon's ESG profile."
        }
    },
    "TQQQ": {
        "Generated Report": "No ESG data available for TQQQ",
        "Reference ESG Data": {
            "error": "No ESG data available for TQQQ"
        },
        "Faithfulness Evaluation": "Could not evaluate due to error in data or report generation."
    },
    "AMD": {
        "Generated Report": "Advanced Micro Devices (AMD) has a Total ESG Risk Score of 12.51, indicating a moderate level of risk concerning environmental, social, and governance factors. The Environmental Risk Score is relatively low at 3.01, suggesting that AMD has made acceptable progress in managing its environmental impact. However, continued scrutiny on energy consumption and e-waste management within the semiconductor industry remains vital.\n\nThe Social Risk Score of 4.22 reflects potential issues related to labor practices, employee diversity, and community engagement. This score suggests that while AMD may have initiatives in place, there is room for improvement in fostering a more inclusive workplace and enhancing its social impact.\n\nThe Governance Risk Score is the highest at 5.28, indicating potential vulnerabilities in corporate governance practices. This aspect may involve board diversity, executive compensation, and shareholder rights, which could present risks if not adequately addressed.\n\nWith a Controversy Level of 1.0, AMD's exposure to ESG controversies is relatively low compared to peers, where the average controversy level is 0.56. This suggests that the company has managed to avoid significant reputational risks thus far.\n\nOverall, AMD appears to be on a sustainable path, but it should remain vigilant in addressing governance and social issues to mitigate potential risks and enhance its ESG profile. Continued focus on transparency and stakeholder engagement will be crucial for addressing these risks effectively.",
        "Reference ESG Data": {
            "Stock": "AMD",
            "Total ESG Risk Score": 12.51,
            "Environmental Risk Score": 3.01,
            "Social Risk Score": 4.22,
            "Governance Risk Score": 5.28,
            "Controversy Level": 1.0,
            "Peer Controversy Min": 0.0,
            "Peer Controversy Avg": 0.5583333333333333,
            "Peer Controversy Max": 3.0
        },
        "Faithfulness Evaluation": {
            "Score": 1.0,
            "Explanation": "The generated ESG report accurately reflects the provided reference ESG data for AMD. The Total ESG Risk Score of 12.51 is correctly stated, and the breakdown of the Environmental Risk Score (3.01), Social Risk Score (4.22), and Governance Risk Score (5.28) aligns perfectly with the reference data. The report also correctly identifies the Controversy Level of 1.0 and contextualizes it against the peer average of 0.56, indicating a low level of exposure to controversies. The interpretations regarding AMD's strengths and areas for improvement in environmental, social, and governance aspects are consistent with the scores provided. Therefore, the report is fully faithful to the reference data."
        }
    },
    "NFLX": {
        "Generated Report": "Netflix (NFLX) exhibits a total ESG risk score of 15.88, which indicates a moderate level of risk in its environmental, social, and governance practices. The Environmental Risk Score is notably low at 0.16, suggesting that the company has minimal environmental impact relative to its industry peers, which is commendable in the context of increasing scrutiny on corporate sustainability.\n\nHowever, the Social Risk Score of 7.38 raises concerns regarding social practices, which could include issues related to employee relations, diversity and inclusion, and community impact. This score is significantly higher than the industry average, indicating potential vulnerabilities that may affect reputation and operational stability.\n\nThe Governance Risk Score of 8.35 is also elevated, reflecting possible risks associated with corporate governance practices, such as board diversity, executive compensation, and shareholder rights. This score suggests that investors should closely monitor governance structures to mitigate potential challenges.\n\nWith a controversy level of 2.0, Netflix has faced moderate scrutiny compared to peers, whose controversy levels range from 0.0 to 3.0. While this indicates some level of reputational risk, it is within an acceptable range compared to industry standards.\n\nIn summary, while Netflix demonstrates strong environmental performance, attention should be paid to its social and governance practices, which may pose risks to its long-term sustainability and investor confidence.",
        "Reference ESG Data": {
            "Stock": "NFLX",
            "Total ESG Risk Score": 15.88,
            "Environmental Risk Score": 0.16,
            "Social Risk Score": 7.38,
            "Governance Risk Score": 8.35,
            "Controversy Level": 2.0,
            "Peer Controversy Min": 0.0,
            "Peer Controversy Avg": 1.0070921985815602,
            "Peer Controversy Max": 3.0
        },
        "Faithfulness Evaluation": {
            "Score": 1.0,
            "Explanation": "The generated ESG report accurately reflects the reference ESG data for Netflix (NFLX). It correctly states the total ESG risk score of 15.88 and provides a detailed breakdown of the Environmental Risk Score (0.16), Social Risk Score (7.38), and Governance Risk Score (8.35). The report also appropriately contextualizes these scores, noting the low environmental impact and highlighting the higher social and governance risks. Additionally, the controversy level of 2.0 is accurately reported, along with a comparison to peer controversy levels. Overall, the report is grounded in the actual data, making it perfectly faithful to the reference ESG data provided."
        }
    }
}