{
    "TSLA": {
        "Generated Report": "Tesla Inc. (TSLA) presents a mixed ESG profile, characterized by a total ESG risk score of 24.76, which indicates a moderate level of risk. The Environmental Risk Score at 3.04 is relatively low, reflecting the company's commitment to sustainability through electric vehicle production and renewable energy initiatives. This aligns with its mission to accelerate the world's transition to sustainable energy.\n\nHowever, the Social Risk Score of 14.13 raises concerns, signaling potential issues related to labor practices, employee relations, and community impact. This score is notable given the broader context of worker treatment and diversity within the technology and automotive sectors, where Tesla has faced scrutiny and criticism.\n\nThe Governance Risk Score of 7.6 indicates some governance challenges, which could stem from issues related to board structure, executive compensation, or shareholder rights. These governance factors are crucial as they can influence long-term sustainability and investor confidence.\n\nThe Controversy Level of 3.0 is significant, especially when compared to peers, as it exceeds the average controversy level (1.75) and highlights the company's involvement in various public and regulatory challenges. The range of peer controversy (0.0 to 4.0) shows that while Tesla's challenges are notable, they are not unique within the industry.\n\nIn summary, while Tesla demonstrates strong environmental credentials, its elevated social and governance risks, compounded by controversy, warrant close monitoring by investors concerned with ESG factors.",
        "Reference ESG Data": {
            "Stock": "TSLA",
            "Total ESG Risk Score": 24.76,
            "Environmental Risk Score": 3.04,
            "Social Risk Score": 14.13,
            "Governance Risk Score": 7.6,
            "Controversy Level": 3.0,
            "Peer Controversy Min": 0.0,
            "Peer Controversy Avg": 1.75,
            "Peer Controversy Max": 4.0
        },
        "Faithfulness Evaluation": {
            "Score": 1.0,
            "Explanation": "The generated ESG report accurately reflects the provided reference ESG data for Tesla Inc. (TSLA). It correctly states the total ESG risk score of 24.76 and breaks down the environmental (3.04), social (14.13), and governance (7.6) risk scores in a manner that aligns with the reference data. The report also appropriately discusses the controversy level of 3.0, noting its significance in relation to peer averages. Each aspect of the report is grounded in the actual data, providing a faithful representation of Tesla's ESG profile without introducing inaccuracies or misinterpretations. Therefore, the report is rated as perfectly faithful."
        }
    },
    "NVDA": {
        "Generated Report": "NVIDIA Corporation (NVDA) exhibits a total ESG risk score of 12.46, indicating a moderate level of risk in its operations concerning environmental, social, and governance factors. \n\n**Environmental Risk (2.73):** This relatively low score suggests that NVDA is taking steps to mitigate its environmental impact, particularly in areas like energy consumption and waste management. However, as a key player in the semiconductor industry, ongoing scrutiny regarding resource sourcing and energy-intensive production processes remains pertinent.\n\n**Social Risk (4.08):** The social risk score indicates moderate challenges, potentially linked to labor practices, diversity, and community engagement. As social expectations heighten, especially concerning inclusivity and equitable treatment within the tech sector, NVDA may face pressure to enhance its social responsibility initiatives.\n\n**Governance Risk (5.65):** With the highest score among the three pillars, governance poses a more significant concern. Issues may revolve around board diversity, executive compensation, and shareholder rights. Transparent practices and strong ethical standards will be crucial for NVDA to mitigate governance-related risks.\n\n**Controversy Level (2.0):** This level indicates NVDA has experienced some controversies, but it is relatively moderate compared to peers. The average peer controversy score stands at 0.56, suggesting NVDA has faced issues that could impact reputation and investor confidence.\n\nIn summary, while NVDA shows strengths in environmental practices, its governance risks and social challenges warrant ongoing attention to enhance overall sustainability and mitigate potential risks.",
        "Reference ESG Data": {
            "Stock": "NVDA",
            "Total ESG Risk Score": 12.46,
            "Environmental Risk Score": 2.73,
            "Social Risk Score": 4.08,
            "Governance Risk Score": 5.65,
            "Controversy Level": 2.0,
            "Peer Controversy Min": 0.0,
            "Peer Controversy Avg": 0.5583333333333333,
            "Peer Controversy Max": 3.0
        },
        "Faithfulness Evaluation": {
            "Score": 1.0,
            "Explanation": "The generated ESG report accurately reflects the provided reference ESG data for NVIDIA Corporation (NVDA). It correctly states the total ESG risk score of 12.46 and breaks down the environmental, social, and governance risk scores as 2.73, 4.08, and 5.65, respectively. The report also appropriately contextualizes these scores, indicating a moderate level of risk and highlighting the specific areas of concern within each category. Additionally, it accurately mentions the controversy level of 2.0 and compares it to the peer controversy average of 0.56, providing a clear understanding of NVDA's standing relative to its peers. Overall, the report is faithful to the actual data, making it a reliable summary of NVDA's ESG performance."
        }
    },
    "AAPL": {
        "Generated Report": "Apple Inc. (AAPL) presents a mixed ESG profile, with a Total ESG Risk Score of 18.75. This score indicates a moderate level of ESG-related risks, which warrants attention from investors concerned about sustainability.\n\nThe Environmental Risk Score is relatively low at 2.05, suggesting that Apple has made strides in managing its environmental impacts, including initiatives in renewable energy and product recycling. However, the company still faces challenges related to supply chain sustainability, particularly regarding raw material sourcing and electronic waste.\n\nIn contrast, the Social and Governance Risk Scores are notably higher, both at 8.35. This indicates potential vulnerabilities in areas such as labor practices, employee relations, and diversity. The recent controversies surrounding labor conditions in supplier factories and data privacy issues can contribute to this elevated score, emphasizing the need for ongoing scrutiny.\n\nThe Controversy Level of 3.0 aligns with the upper spectrum of peer controversies, where the minimum is 0.0 and the average is significantly lower at approximately 0.56. This suggests that while Apple is a leader in many respects, it is also not immune to significant public scrutiny.\n\nOverall, while Apple demonstrates a commitment to environmental sustainability, the elevated social and governance risks indicate that the company must enhance its practices in these areas to mitigate potential reputational and operational risks. Investors should monitor these factors closely as they may impact long-term performance and stakeholder trust.",
        "Reference ESG Data": {
            "Stock": "AAPL",
            "Total ESG Risk Score": 18.75,
            "Environmental Risk Score": 2.05,
            "Social Risk Score": 8.35,
            "Governance Risk Score": 8.35,
            "Controversy Level": 3.0,
            "Peer Controversy Min": 0.0,
            "Peer Controversy Avg": 0.5598290598290598,
            "Peer Controversy Max": 3.0
        },
        "Faithfulness Evaluation": {
            "Score": 1.0,
            "Explanation": "The generated ESG report accurately reflects the reference ESG data provided for Apple Inc. (AAPL). It correctly states the Total ESG Risk Score of 18.75 and the Environmental Risk Score of 2.05, which is described as relatively low, indicating effective management of environmental impacts. The report also accurately notes the Social and Governance Risk Scores of 8.35 each, highlighting the associated vulnerabilities in labor practices and governance issues. Furthermore, the Controversy Level of 3.0 is correctly aligned with the reference data, noting that it is at the upper end of peer controversies. The report effectively contextualizes these scores, indicating both strengths and areas for improvement, which is consistent with the provided data. Overall, the report is faithful to the actual ESG data, warranting a perfect score of 1.0."
        }
    },
    "SPY": {
        "Generated Report": "No ESG data available for SPY",
        "Reference ESG Data": {
            "error": "No ESG data available for SPY"
        },
        "Faithfulness Evaluation": "Could not evaluate due to error in data or report generation."
    },
    "QQQ": {
        "Generated Report": "No ESG data available for QQQ",
        "Reference ESG Data": {
            "error": "No ESG data available for QQQ"
        },
        "Faithfulness Evaluation": "Could not evaluate due to error in data or report generation."
    },
    "META": {
        "Generated Report": "META's total ESG risk score of 32.73 indicates a moderate level of risk, particularly in the social and governance dimensions. The environmental risk score of 2.41 suggests minimal environmental concerns, which is relatively positive for a tech company; however, this should be viewed in the context of its operational footprint and ongoing sustainability initiatives.\n\nThe social risk score of 21.64 is notably high, reflecting significant challenges related to user privacy, data security, and the societal impact of its platforms. This aligns with public controversies and scrutiny surrounding misinformation, mental health effects, and user safety, which can adversely affect the company's reputation and regulatory standing.\n\nThe governance risk score of 8.68 indicates moderate governance issues, potentially related to board diversity, executive compensation, and oversight of ethical practices. The controversy level of 4.0 further underscores the heightened scrutiny META faces compared to its peers, with the average controversy level among peers at approximately 0.66. This disparity highlights the need for META to enhance its governance practices and address social concerns to mitigate risks.\n\nIn summary, while META demonstrates strong performance in environmental sustainability, significant social and governance risks could impact its long-term viability and investor confidence. Addressing these areas proactively will be crucial for improving its overall ESG profile and sustaining stakeholder trust.",
        "Reference ESG Data": {
            "Stock": "META",
            "Total ESG Risk Score": 32.73,
            "Environmental Risk Score": 2.41,
            "Social Risk Score": 21.64,
            "Governance Risk Score": 8.68,
            "Controversy Level": 4.0,
            "Peer Controversy Min": 0.0,
            "Peer Controversy Avg": 0.6598984771573604,
            "Peer Controversy Max": 4.0
        },
        "Faithfulness Evaluation": {
            "Score": 0.9,
            "Explanation": "The generated ESG report accurately reflects the reference ESG data for META, particularly in terms of the total ESG risk score (32.73), environmental risk score (2.41), social risk score (21.64), governance risk score (8.68), and controversy level (4.0). The report correctly identifies the social and governance dimensions as areas of concern and contextualizes the environmental score positively. \n\nHowever, while the report does a good job of discussing the implications of these scores, it could have provided more specific examples or data points related to the controversies and governance issues mentioned, which would enhance its grounding in the actual data. Overall, the report is mostly faithful to the reference data, but slight improvements in specificity could elevate its accuracy further."
        }
    },
    "AMZN": {
        "Generated Report": "Amazon (AMZN) presents a mixed ESG profile based on its risk scores and controversy level. The total ESG Risk Score of 26.1 suggests a moderate level of risk, with distinct challenges in environmental, social, and governance aspects.\n\nThe Environmental Risk Score of 8.3 indicates that Amazon faces notable risks related to its environmental practices, particularly in areas such as carbon emissions, waste management, and resource usage. As a major logistics and e-commerce player, addressing these issues is crucial for improving sustainability and aligning with global climate goals.\n\nThe Social Risk Score of 11.05 highlights significant concerns, particularly around labor practices, employee treatment, and community impact. Reports of working conditions in warehouses and treatment of gig workers have raised red flags, impacting the company's social reputation and potentially leading to regulatory scrutiny.\n\nThe Governance Risk Score of 6.75 suggests that while governance practices are somewhat robust, there is still room for improvement, particularly in shareholder engagement and transparency.\n\nWith a Controversy Level of 3.0, Amazon experiences a higher incidence of negative press compared to its peers (average 0.91). This elevated controversy can erode brand value and investor confidence, leading to reputational risks.\n\nIn summary, while Amazon is a leader in e-commerce, its ESG risks\u2014especially in environmental and social domains\u2014pose challenges to its long-term sustainability. Addressing these risks proactively will be critical for enhancing its ESG standing and ensuring continued investor support.",
        "Reference ESG Data": {
            "Stock": "AMZN",
            "Total ESG Risk Score": 26.1,
            "Environmental Risk Score": 8.3,
            "Social Risk Score": 11.05,
            "Governance Risk Score": 6.75,
            "Controversy Level": 3.0,
            "Peer Controversy Min": 0.0,
            "Peer Controversy Avg": 0.9104477611940298,
            "Peer Controversy Max": 4.0
        },
        "Faithfulness Evaluation": {
            "Score": 1.0,
            "Explanation": "The generated ESG report accurately reflects the reference ESG data for Amazon (AMZN) in terms of risk scores and controversy levels. The total ESG Risk Score of 26.1 is correctly identified as moderate, and the breakdown of the Environmental Risk Score (8.3), Social Risk Score (11.05), and Governance Risk Score (6.75) aligns perfectly with the reference data. The report also appropriately highlights the implications of these scores, such as the need for improvement in environmental practices and social issues, which are consistent with the provided data. Furthermore, the mention of the Controversy Level of 3.0 in relation to peer averages is accurate, emphasizing the company's elevated risk profile. Overall, the report is faithful to the actual data, providing a comprehensive and accurate assessment of Amazon's ESG performance."
        }
    },
    "TQQQ": {
        "Generated Report": "No ESG data available for TQQQ",
        "Reference ESG Data": {
            "error": "No ESG data available for TQQQ"
        },
        "Faithfulness Evaluation": "Could not evaluate due to error in data or report generation."
    },
    "AMD": {
        "Generated Report": "Advanced Micro Devices, Inc. (AMD) presents a moderate ESG risk profile, with a Total ESG Risk Score of 12.51. The Environmental Risk Score of 3.01 suggests that AMD is relatively low risk in terms of its environmental impact, indicating effective management of resources and a commitment to sustainability practices. However, there is room for improvement, particularly as the tech industry faces increasing scrutiny regarding energy consumption and resource use.\n\nThe Social Risk Score of 4.22 indicates that AMD may encounter challenges related to its workforce, community engagement, and product responsibility. This score suggests potential risks in labor practices or product safety that could impact its reputation and operational continuity.\n\nThe Governance Risk Score of 5.28 is the highest among the three categories, pointing to possible concerns regarding corporate governance practices. This could relate to board diversity, executive compensation, or shareholder rights, which are critical in today\u2019s investment landscape.\n\nThe Controversy Level of 1.0 is relatively low compared to peers, with a min of 0.0 and an average of 0.56, reflecting that AMD has not been significantly embroiled in controversies compared to its competitors. This positions the company favorably in the eyes of socially conscious investors.\n\nIn summary, while AMD demonstrates strengths in environmental management and a low controversy level, it should focus on improving social and governance practices to enhance its overall sustainability and mitigate potential risks.",
        "Reference ESG Data": {
            "Stock": "AMD",
            "Total ESG Risk Score": 12.51,
            "Environmental Risk Score": 3.01,
            "Social Risk Score": 4.22,
            "Governance Risk Score": 5.28,
            "Controversy Level": 1.0,
            "Peer Controversy Min": 0.0,
            "Peer Controversy Avg": 0.5583333333333333,
            "Peer Controversy Max": 3.0
        },
        "Faithfulness Evaluation": {
            "Score": 1.0,
            "Explanation": "The generated ESG report for Advanced Micro Devices, Inc. (AMD) is perfectly faithful to the provided reference ESG data. It accurately reflects the Total ESG Risk Score of 12.51 and provides a breakdown of the Environmental Risk Score (3.01), Social Risk Score (4.22), and Governance Risk Score (5.28) in a manner consistent with the reference data. \n\nThe report also correctly identifies the Controversy Level of 1.0 and compares it to the peer controversy metrics, highlighting that AMD's level is low relative to its peers. The explanations regarding the implications of these scores, particularly in terms of environmental management, social challenges, and governance concerns, are well-aligned with the data provided. \n\nOverall, the report maintains a clear and accurate representation of AMD's ESG profile, making it a faithful summary of the reference data."
        }
    },
    "NFLX": {
        "Generated Report": "Netflix (NFLX) presents a mixed ESG profile, with a total ESG risk score of 15.88. The environmental risk score is notably low at 0.16, suggesting that the company has minimal exposure to environmental issues, which is a positive indicator of its commitment to sustainable practices. This could be attributed to its digital content delivery model, which inherently has a smaller ecological footprint compared to traditional media.\n\nHowever, the social risk score of 7.38 and governance risk score of 8.35 indicate more significant concerns. The social risk may stem from issues related to content diversity, labor practices, and community engagement, while the governance score suggests potential challenges in board diversity, executive compensation, and shareholder rights. These areas require attention, as they can impact Netflix's reputation and stakeholder trust.\n\nThe controversy level of 2.0, while higher than the peer average of 1.01, suggests that Netflix is facing some criticisms but is not at the highest end of the spectrum. This level of controversy warrants monitoring, as it can influence investor sentiment and brand perception.\n\nIn conclusion, while Netflix demonstrates strong environmental performance, the elevated social and governance risk scores, alongside its controversy level, indicate potential vulnerabilities that could affect its long-term sustainability. Continuous improvement in these areas will be essential for mitigating risks and enhancing its overall ESG standing.",
        "Reference ESG Data": {
            "Stock": "NFLX",
            "Total ESG Risk Score": 15.88,
            "Environmental Risk Score": 0.16,
            "Social Risk Score": 7.38,
            "Governance Risk Score": 8.35,
            "Controversy Level": 2.0,
            "Peer Controversy Min": 0.0,
            "Peer Controversy Avg": 1.0070921985815602,
            "Peer Controversy Max": 3.0
        },
        "Faithfulness Evaluation": {
            "Score": 1.0,
            "Explanation": "The generated ESG report accurately reflects the provided reference ESG data for Netflix (NFLX). It correctly states the total ESG risk score of 15.88 and the environmental risk score of 0.16, indicating minimal exposure to environmental issues. The report also appropriately highlights the higher social risk score of 7.38 and governance risk score of 8.35, discussing the potential concerns in these areas. Furthermore, it accurately mentions the controversy level of 2.0 and compares it with the peer average, providing a balanced view of Netflix's ESG profile. Overall, the report is faithful to the reference data, presenting a clear and accurate assessment of Netflix's ESG standing."
        }
    }
}