{
    "TSLA": {
        "Generated Report": "Tesla, Inc. (TSLA) presents a mixed ESG profile, with a total ESG risk score of 24.76, indicating a moderate level of risk in its operations. The Environmental Risk Score is relatively low at 3.04, reflecting Tesla's commitment to sustainability through its electric vehicles and renewable energy solutions, positioning the company favorably within the environmental sector. \n\nHowever, the Social Risk Score of 14.13 raises concerns, suggesting potential issues related to labor practices, community engagement, and customer relations. This score is significantly higher than the peer controversy average of 1.75, indicating that Tesla may face unique social challenges that could impact its reputation and operational stability.\n\nThe Governance Risk Score of 7.6 also warrants attention, highlighting potential governance issues, such as board structure, executive compensation, and shareholder rights. While Tesla's governance is not the highest risk among its peers, it is essential to monitor these factors as they can influence investor confidence and regulatory scrutiny.\n\nThe controversy level of 3.0 suggests that Tesla has faced notable incidents that could affect its public perception and stakeholder trust. This level is above the peer average, indicating that while the company is a leader in the EV market, it is also susceptible to reputational risks.\n\nOverall, while Tesla demonstrates strong environmental credentials, its elevated social risk and governance concerns present potential challenges that investors should consider when assessing the company's long-term sustainability and risk profile.",
        "Reference ESG Data": {
            "Stock": "TSLA",
            "Total ESG Risk Score": 24.76,
            "Environmental Risk Score": 3.04,
            "Social Risk Score": 14.13,
            "Governance Risk Score": 7.6,
            "Controversy Level": 3.0,
            "Peer Controversy Min": 0.0,
            "Peer Controversy Avg": 1.75,
            "Peer Controversy Max": 4.0
        },
        "Faithfulness Evaluation": {
            "Score": 0.9,
            "Explanation": "The generated ESG report is largely faithful to the reference ESG data, accurately reflecting the total ESG risk score of 24.76 and the individual scores for environmental (3.04), social (14.13), and governance (7.6) risks. It correctly identifies the social risk score as significantly higher than the peer controversy average of 1.75, which is an important point of concern. The mention of the controversy level being 3.0, which is above the peer average, is also accurate and highlights potential reputational risks.\n\nHowever, the report could be slightly improved by providing more context regarding the implications of the scores, particularly how the social and governance risks compare to industry standards or specific incidents that have led to the controversy level. Additionally, while the report states that Tesla has strong environmental credentials, it could clarify that the environmental risk score is relatively low, which is a positive aspect. Overall, the report is well-grounded in the actual data, but minor enhancements could increase its accuracy and comprehensiveness."
        }
    },
    "NVDA": {
        "Generated Report": "NVIDIA Corporation (NVDA) presents a mixed ESG profile, with a total ESG risk score of 12.46, indicating moderate risks in its operations. The Environmental Risk Score of 2.73 suggests that while the company faces some environmental challenges, they are relatively manageable compared to industry peers. This reflects positively on NVDA's sustainability efforts, particularly in areas like energy efficiency and sustainable sourcing, which are critical in the tech sector.\n\nHowever, the Social Risk Score of 4.08 indicates notable challenges in labor practices, community relations, or product impacts, suggesting that NVDA may need to enhance its stakeholder engagement and social responsibility initiatives. The Governance Risk Score of 5.65 is the highest among the three categories, pointing to potential concerns around corporate governance practices, such as board diversity, executive compensation, or shareholder rights.\n\nThe controversy level of 2.0 is moderate, with NVDA positioned above the peer average of 0.56 but below the maximum of 3.0. This suggests that while the company has experienced some controversies, they are not excessively severe compared to competitors. Overall, NVDA's sustainability efforts are commendable, but the company should address social and governance risks to improve its ESG standing and mitigate potential reputational and operational risks. Continued focus on enhancing governance structures and social responsibility will be essential for long-term resilience and stakeholder trust.",
        "Reference ESG Data": {
            "Stock": "NVDA",
            "Total ESG Risk Score": 12.46,
            "Environmental Risk Score": 2.73,
            "Social Risk Score": 4.08,
            "Governance Risk Score": 5.65,
            "Controversy Level": 2.0,
            "Peer Controversy Min": 0.0,
            "Peer Controversy Avg": 0.5583333333333333,
            "Peer Controversy Max": 3.0
        },
        "Faithfulness Evaluation": {
            "Score": 1.0,
            "Explanation": "The generated ESG report accurately reflects the provided reference ESG data for NVIDIA Corporation (NVDA). The total ESG risk score of 12.46 is correctly stated, and the individual scores for Environmental (2.73), Social (4.08), and Governance (5.65) risks are all consistent with the reference data. The commentary on the environmental challenges being manageable and the social and governance risks being notable aligns well with the respective scores. Additionally, the controversy level of 2.0 is correctly interpreted in relation to the peer average and maximum, indicating a moderate level of controversy. Overall, the report is faithful to the reference data, providing a clear and accurate assessment of NVIDIA's ESG profile."
        }
    },
    "AAPL": {
        "Generated Report": "Apple Inc. (AAPL) presents an overall total ESG risk score of 18.75, indicating a moderate level of risk. The breakdown of scores highlights specific areas of concern and strength. \n\nThe Environmental Risk Score of 2.05 suggests that Apple is relatively low-risk in terms of environmental impact, which reflects its ongoing initiatives in sustainability, such as the commitment to carbon neutrality across its supply chain and products by 2030. However, further enhancement in this area could bolster its reputation as a leader in environmental stewardship.\n\nConversely, both the Social and Governance Risk Scores are higher at 8.35 each, indicating potential vulnerabilities in these domains. The social score may reflect challenges related to labor practices within its supply chain, particularly concerning working conditions and fair wages in manufacturing facilities. Governance concerns could stem from issues related to board diversity, executive compensation, or shareholder rights.\n\nThe controversy level of 3.0 aligns with the upper range of its peers, indicating that while Apple faces notable scrutiny, it is not unique in this regard. The peer controversy metrics show an average of 0.56, suggesting that AAPL's controversies are more pronounced relative to its competitors.\n\nIn summary, while Apple demonstrates strengths in environmental performance, it faces considerable risks in social and governance aspects that could impact its long-term sustainability. Addressing these concerns is crucial to mitigate risks and enhance its overall ESG profile.",
        "Reference ESG Data": {
            "Stock": "AAPL",
            "Total ESG Risk Score": 18.75,
            "Environmental Risk Score": 2.05,
            "Social Risk Score": 8.35,
            "Governance Risk Score": 8.35,
            "Controversy Level": 3.0,
            "Peer Controversy Min": 0.0,
            "Peer Controversy Avg": 0.5598290598290598,
            "Peer Controversy Max": 3.0
        },
        "Faithfulness Evaluation": {
            "Score": 1.0,
            "Explanation": "The generated ESG report accurately reflects the reference ESG data provided for Apple Inc. (AAPL). It correctly states the total ESG risk score of 18.75 and breaks down the individual scores for environmental (2.05), social (8.35), and governance (8.35) risks, aligning perfectly with the reference data. The report also appropriately contextualizes the controversy level of 3.0, noting that it is at the upper range of its peers, and it correctly references the average peer controversy score of 0.56. The analysis of strengths and weaknesses in environmental, social, and governance aspects is consistent with the scores provided, making the report both accurate and grounded in the actual data."
        }
    },
    "SPY": {
        "Generated Report": "No ESG data available for SPY",
        "Reference ESG Data": {
            "error": "No ESG data available for SPY"
        },
        "Faithfulness Evaluation": "Could not evaluate due to error in data or report generation."
    },
    "QQQ": {
        "Generated Report": "No ESG data available for QQQ",
        "Reference ESG Data": {
            "error": "No ESG data available for QQQ"
        },
        "Faithfulness Evaluation": "Could not evaluate due to error in data or report generation."
    },
    "META": {
        "Generated Report": "META's total ESG risk score of 32.73 indicates a moderate level of risk, with the social risk component being significantly higher at 21.64. This suggests that the company faces substantial challenges related to its societal impact, which may include issues such as data privacy, content moderation, and user safety. The high social risk score highlights the importance of addressing public concerns and regulatory scrutiny, especially given the increasing focus on user rights and ethical practices in the tech industry.\n\nThe environmental risk score of 2.41 is relatively low, indicating that META\u2019s operations are not currently associated with significant environmental risks, which is a positive aspect for sustainability. However, the governance risk score of 8.68 suggests some vulnerabilities in governance practices, possibly related to transparency, accountability, or shareholder engagement.\n\nThe controversy level of 4.0 places META at the higher end of the scale compared to its peers, where the average controversy level is approximately 0.66. This heightened controversy may stem from high-profile incidents and public backlash, potentially affecting the company's reputation and stakeholder trust.\n\nIn conclusion, while META exhibits strengths in environmental performance, the elevated social risk and controversy levels warrant careful monitoring. Addressing these social challenges and governance issues will be critical for mitigating risks and enhancing long-term sustainability.",
        "Reference ESG Data": {
            "Stock": "META",
            "Total ESG Risk Score": 32.73,
            "Environmental Risk Score": 2.41,
            "Social Risk Score": 21.64,
            "Governance Risk Score": 8.68,
            "Controversy Level": 4.0,
            "Peer Controversy Min": 0.0,
            "Peer Controversy Avg": 0.6598984771573604,
            "Peer Controversy Max": 4.0
        },
        "Faithfulness Evaluation": {
            "Score": 1.0,
            "Explanation": "The generated ESG report accurately reflects the provided reference ESG data for META. It correctly states the total ESG risk score of 32.73 and breaks down the individual components: the environmental risk score of 2.41, social risk score of 21.64, and governance risk score of 8.68. The report also appropriately highlights the significant social challenges META faces, aligning with the high social risk score. Additionally, it accurately notes the controversy level of 4.0, emphasizing its position relative to peer averages. Overall, the report is grounded in the actual data and provides a faithful representation of META's ESG profile."
        }
    },
    "AMZN": {
        "Generated Report": "Amazon (AMZN) presents a mixed ESG profile, with a Total ESG Risk Score of 26.1 indicating moderate risk levels. The Environmental Risk Score of 8.3 is relatively low, suggesting that while Amazon is making strides in sustainability initiatives, it still faces challenges, particularly regarding its carbon footprint and waste management associated with its vast logistics network.\n\nThe Social Risk Score of 11.05 is more concerning, reflecting potential issues related to labor practices, employee treatment, and community impact. Amazon has faced scrutiny over workplace conditions and treatment of warehouse employees, which could pose reputational risks and impact employee retention and public perception.\n\nThe Governance Risk Score of 6.75 indicates a relatively stronger governance framework, yet it remains important to consider the implications of its corporate structure and executive compensation practices in the context of shareholder interests and stakeholder engagement.\n\nThe Controversy Level of 3.0, significantly higher than the peer average of 0.91, indicates that Amazon has been involved in notable controversies, which can lead to heightened scrutiny from regulators and the public. \n\nOverall, while Amazon is actively addressing some sustainability challenges, ongoing social concerns and its high controversy level suggest potential reputational and operational risks that investors should monitor closely. Enhanced transparency and proactive engagement on social issues could mitigate these risks and improve its ESG standing.",
        "Reference ESG Data": {
            "Stock": "AMZN",
            "Total ESG Risk Score": 26.1,
            "Environmental Risk Score": 8.3,
            "Social Risk Score": 11.05,
            "Governance Risk Score": 6.75,
            "Controversy Level": 3.0,
            "Peer Controversy Min": 0.0,
            "Peer Controversy Avg": 0.9104477611940298,
            "Peer Controversy Max": 4.0
        },
        "Faithfulness Evaluation": {
            "Score": 0.9,
            "Explanation": "The generated ESG report accurately reflects the provided reference ESG data for Amazon (AMZN), including the Total ESG Risk Score of 26.1, Environmental Risk Score of 8.3, Social Risk Score of 11.05, Governance Risk Score of 6.75, and Controversy Level of 3.0. The descriptions of the environmental, social, and governance aspects are consistent with the scores given, particularly highlighting the challenges in sustainability and social issues. \n\nHowever, while the report mentions that the Environmental Risk Score is \"relatively low,\" it could be argued that a score of 8.3 still indicates significant environmental risks, which may not be fully conveyed by the term \"relatively low.\" Additionally, the report does not provide context for the significance of the scores in relation to industry standards or specific benchmarks, which could enhance the understanding of Amazon's ESG performance. \n\nOverall, the report is largely faithful to the data but could improve clarity and context in certain areas."
        }
    },
    "TQQQ": {
        "Generated Report": "No ESG data available for TQQQ",
        "Reference ESG Data": {
            "error": "No ESG data available for TQQQ"
        },
        "Faithfulness Evaluation": "Could not evaluate due to error in data or report generation."
    },
    "AMD": {
        "Generated Report": "AMD's total ESG Risk Score of 12.51 indicates a moderate level of risk, with specific insights into its environmental, social, and governance performance. The Environmental Risk Score of 3.01 suggests that AMD is relatively mindful of its environmental impact, although there is room for improvement, especially in sustainable practices and energy efficiency.\n\nThe Social Risk Score of 4.22 highlights potential challenges related to labor practices, community engagement, and product safety. This score signals the need for AMD to strengthen its initiatives to foster a positive social impact, particularly in areas like diversity and inclusion within its workforce.\n\nWith a Governance Risk Score of 5.28, AMD appears to face higher risks related to its governance practices. This may include issues around board composition, executive compensation, and shareholder rights, which could affect its reputation and stakeholder trust.\n\nAdditionally, AMD's Controversy Level of 1.0 is relatively low compared to its peers, whose controversy levels range from 0.0 to 3.0. This suggests that AMD has effectively navigated potential controversies and maintains a favorable image in the market.\n\nIn summary, while AMD demonstrates a solid commitment to ESG principles, it must address areas of concern, particularly in governance and social responsibility, to enhance its sustainability profile and mitigate potential risks. Continued focus on these aspects will be crucial for long-term resilience and stakeholder confidence.",
        "Reference ESG Data": {
            "Stock": "AMD",
            "Total ESG Risk Score": 12.51,
            "Environmental Risk Score": 3.01,
            "Social Risk Score": 4.22,
            "Governance Risk Score": 5.28,
            "Controversy Level": 1.0,
            "Peer Controversy Min": 0.0,
            "Peer Controversy Avg": 0.5583333333333333,
            "Peer Controversy Max": 3.0
        },
        "Faithfulness Evaluation": {
            "Score": 1.0,
            "Explanation": "The generated ESG report accurately reflects the reference ESG data provided for AMD. It correctly states the total ESG Risk Score of 12.51 and provides a breakdown of the Environmental Risk Score (3.01), Social Risk Score (4.22), and Governance Risk Score (5.28). The report appropriately characterizes the environmental score as indicating room for improvement and highlights the social score's implications for labor practices and community engagement. It also correctly identifies the governance score as a potential area of concern. Furthermore, the report notes the Controversy Level of 1.0 and compares it favorably against peer controversy levels, which aligns with the reference data. Overall, the report is grounded in the actual data and provides a faithful representation of AMD's ESG performance."
        }
    },
    "NFLX": {
        "Generated Report": "Netflix (NFLX) presents a mixed ESG profile, with a Total ESG Risk Score of 15.88 that suggests moderate risk exposure relative to its peers. The Environmental Risk Score is notably low at 0.16, indicating minimal environmental concerns associated with its operations, which is a positive aspect for sustainability-focused investors. This could be attributed to its digital streaming model, which typically has a lower carbon footprint compared to traditional media production.\n\nHowever, the Social Risk Score of 7.38 raises potential red flags. This relatively high score indicates significant social challenges, which could stem from issues like content representation, labor practices, or customer data privacy. The Governance Risk Score of 8.35 further highlights concerns regarding corporate governance, which may be related to executive compensation practices, board diversity, or shareholder rights.\n\nThe Controversy Level of 2.0, while below the maximum observed within its peer group (3.0), is above the average (1.007). This suggests that Netflix has faced some public scrutiny or criticism, which could impact its reputation and investor sentiment.\n\nIn summary, while Netflix shows strength in environmental sustainability, its elevated social and governance risks warrant attention. Investors should monitor these aspects closely, as they could pose reputational and operational risks that might affect long-term growth and stability in an increasingly ESG-conscious market.",
        "Reference ESG Data": {
            "Stock": "NFLX",
            "Total ESG Risk Score": 15.88,
            "Environmental Risk Score": 0.16,
            "Social Risk Score": 7.38,
            "Governance Risk Score": 8.35,
            "Controversy Level": 2.0,
            "Peer Controversy Min": 0.0,
            "Peer Controversy Avg": 1.0070921985815602,
            "Peer Controversy Max": 3.0
        },
        "Faithfulness Evaluation": {
            "Score": 1.0,
            "Explanation": "The generated ESG report accurately reflects the reference ESG data for Netflix (NFLX). The Total ESG Risk Score of 15.88 is correctly stated as indicating moderate risk exposure. The Environmental Risk Score of 0.16 is also accurately described as low, highlighting minimal environmental concerns. The report correctly identifies the Social Risk Score of 7.38 as a significant concern and the Governance Risk Score of 8.35 as indicative of governance issues. Additionally, the Controversy Level of 2.0 is presented in context, noting that it is below the maximum but above the average, which aligns with the reference data. Overall, the report is faithful to the provided ESG data, providing a clear and accurate summary of Netflix's ESG profile."
        }
    }
}