{
    "TSLA": {
        "Generated Report": "Tesla Inc. (TSLA) presents a mixed ESG profile, with a total risk score of 24.76. The environmental risk score of 3.04 is relatively low, indicating that the company performs well in environmental considerations, which is expected given its focus on electric vehicles and renewable energy. However, the social risk score of 14.13 is notably higher, reflecting potential concerns in areas such as labor practices, community relations, and consumer protection. This suggests that Tesla may face scrutiny regarding its workforce policies and social impacts.\n\nThe governance risk score of 7.6 points to some weaknesses in corporate governance structures, which may include issues related to board diversity, executive compensation, and transparency. The controversy level of 3.0 indicates that Tesla has faced significant public and media scrutiny, particularly regarding its leadership and operational practices. This level of controversy is higher than the peer average of 1.75, suggesting that Tesla is more exposed to reputational risks compared to its competitors.\n\nOverall, while Tesla is a leader in the environmental sector, its elevated social and governance risk scores, combined with a higher controversy level, suggest that the company may encounter challenges that could impact its sustainability efforts and investor sentiment. Stakeholders should closely monitor these areas as they could pose potential risks to the company's long-term viability and reputation.",
        "Reference ESG Data": {
            "Stock": "TSLA",
            "Total ESG Risk Score": 24.76,
            "Environmental Risk Score": 3.04,
            "Social Risk Score": 14.13,
            "Governance Risk Score": 7.6,
            "Controversy Level": 3.0,
            "Peer Controversy Min": 0.0,
            "Peer Controversy Avg": 1.75,
            "Peer Controversy Max": 4.0
        },
        "Faithfulness Evaluation": {
            "Score": 1.0,
            "Explanation": "The generated ESG report accurately reflects the reference ESG data for Tesla Inc. (TSLA). It correctly states the total ESG risk score of 24.76 and provides the specific environmental (3.04), social (14.13), and governance (7.6) risk scores as outlined in the reference data. The report also appropriately discusses the implications of these scores, particularly highlighting the relatively low environmental risk and the higher social and governance risks, which aligns with the data provided. Furthermore, the mention of the controversy level (3.0) and its comparison to the peer average (1.75) is accurate and contextualizes Tesla's position within its industry. Overall, the report is grounded in the actual data and provides a faithful representation of Tesla's ESG profile."
        }
    },
    "NVDA": {
        "Generated Report": "NVIDIA Corporation (NVDA) presents a mixed ESG profile based on its risk scores and controversy level. With a total ESG Risk Score of 12.46, the company demonstrates a moderate risk level, particularly in governance, where it scores 5.65, indicating potential vulnerabilities in its management practices or stakeholder engagement.\n\nThe environmental risk score of 2.73 suggests that NVIDIA is relatively proactive in addressing ecological impacts, but there remains room for improvement, especially given the increasing scrutiny of the tech sector's carbon footprint and resource consumption. The social risk score of 4.08 indicates that while the company may have policies in place to support social responsibility, there are still significant challenges, possibly related to labor practices or community engagement.\n\nThe controversy level of 2.0 is noteworthy, as it is above the peer average of 0.56, highlighting that NVIDIA has faced notable issues that could impact its reputation and stakeholder trust. Companies in similar sectors exhibit a broader range of controversy, with a maximum score of 3.0, suggesting that while NVIDIA is not the most controversial player, it is still prone to scrutiny.\n\nIn summary, while NVIDIA shows strengths in environmental initiatives, its governance and social practices, along with a relatively high controversy level, indicate potential risks that investors should monitor closely. Addressing these challenges could enhance its sustainability profile and long-term investment appeal.",
        "Reference ESG Data": {
            "Stock": "NVDA",
            "Total ESG Risk Score": 12.46,
            "Environmental Risk Score": 2.73,
            "Social Risk Score": 4.08,
            "Governance Risk Score": 5.65,
            "Controversy Level": 2.0,
            "Peer Controversy Min": 0.0,
            "Peer Controversy Avg": 0.5583333333333333,
            "Peer Controversy Max": 3.0
        },
        "Faithfulness Evaluation": {
            "Score": 0.9,
            "Explanation": "The generated ESG report accurately reflects the reference ESG data for NVIDIA Corporation (NVDA) in several key areas, including the total ESG Risk Score (12.46), governance risk score (5.65), environmental risk score (2.73), social risk score (4.08), and controversy level (2.0). The report correctly identifies the governance score as indicating potential vulnerabilities and acknowledges the environmental score as relatively proactive, aligning with the data provided.\n\nHowever, the report's interpretation of the controversy level could be slightly misleading. While it correctly states that NVIDIA's controversy level (2.0) is above the peer average (0.56), it does not clarify that the peer controversy range is broader, with a maximum of 3.0, which could imply that NVIDIA's level of controversy is not as severe compared to the highest-scoring peers. \n\nOverall, the report is well-grounded in the actual data, but the slight overemphasis on the controversy level could lead to misinterpretation. Thus, it receives a high score of 0.9 for faithfulness."
        }
    },
    "AAPL": {
        "Generated Report": "Apple Inc. (AAPL) presents a mixed ESG profile, with a total risk score of 18.75, indicating moderate risk in the environmental, social, and governance domains. The environmental risk score of 2.05 is relatively low, suggesting that Apple has made significant strides in minimizing its environmental footprint, likely through initiatives focused on renewable energy and sustainable sourcing. \n\nHowever, the social and governance risk scores, both at 8.35, raise concerns about the company's practices in these areas. The social score could reflect issues related to labor practices, supply chain management, or product accessibility, which are critical for a company with a vast global footprint. The governance score suggests potential concerns regarding corporate governance structures, transparency, or board diversity.\n\nThe controversy level at 3.0 indicates that Apple has faced notable controversies, aligning with the upper range of peer controversy scores, which average 0.56. This level of controversy may affect investor sentiment and brand reputation, emphasizing the need for Apple to address these issues proactively.\n\nIn summary, while Apple demonstrates commendable environmental efforts, its social and governance risks warrant careful scrutiny. Investors should monitor the company's initiatives to improve in these areas, as unresolved issues could pose reputational and operational risks in an increasingly ESG-conscious market.",
        "Reference ESG Data": {
            "Stock": "AAPL",
            "Total ESG Risk Score": 18.75,
            "Environmental Risk Score": 2.05,
            "Social Risk Score": 8.35,
            "Governance Risk Score": 8.35,
            "Controversy Level": 3.0,
            "Peer Controversy Min": 0.0,
            "Peer Controversy Avg": 0.5598290598290598,
            "Peer Controversy Max": 3.0
        },
        "Faithfulness Evaluation": {
            "Score": 1.0,
            "Explanation": "The generated ESG report accurately reflects the reference ESG data for Apple Inc. (AAPL). The total ESG risk score of 18.75 is correctly reported, and the environmental risk score of 2.05 is described as low, which aligns with the data indicating significant strides in minimizing environmental impact. The social and governance risk scores of 8.35 are also accurately noted, with appropriate context provided regarding potential concerns in these areas. Furthermore, the controversy level of 3.0 is correctly highlighted, along with its implications for investor sentiment and brand reputation. The report effectively summarizes the strengths and weaknesses of Apple's ESG profile, making it a faithful representation of the actual data."
        }
    },
    "SPY": {
        "Generated Report": "No ESG data available for SPY",
        "Reference ESG Data": {
            "error": "No ESG data available for SPY"
        },
        "Faithfulness Evaluation": "Could not evaluate due to error in data or report generation."
    },
    "QQQ": {
        "Generated Report": "No ESG data available for QQQ",
        "Reference ESG Data": {
            "error": "No ESG data available for QQQ"
        },
        "Faithfulness Evaluation": "Could not evaluate due to error in data or report generation."
    },
    "META": {
        "Generated Report": "META's total ESG risk score of 32.73 indicates a moderate level of ESG-related risks, with a notably low Environmental Risk Score of 2.41. This suggests that the company's environmental impact is relatively minimal compared to its peers, which is a positive indicator for sustainability.\n\nHowever, the Social Risk Score of 21.64 is a significant concern, indicating heightened risks associated with social issues, possibly including user privacy, data security, and the societal impact of its platforms. This elevated score reflects ongoing scrutiny and criticism regarding how the company manages its social responsibilities, which could lead to reputational damage and regulatory challenges.\n\nThe Governance Risk Score of 8.68 further highlights potential issues within META's governance structures, possibly related to board diversity, executive compensation, or shareholder rights. This score is relatively low compared to the average governance risks within its peer group, suggesting room for improvement in corporate governance practices.\n\nThe company's controversy level of 4.0, which is at the upper end of the scale, indicates frequent and significant controversies, thus raising red flags for investors. While META has made strides in environmental sustainability, the social and governance dimensions pose substantial risks that could impact long-term performance.\n\nIn summary, while META shows strengths in environmental sustainability, its significant social and governance risks, coupled with a high controversy level, warrant careful consideration for potential investors focused on ESG factors.",
        "Reference ESG Data": {
            "Stock": "META",
            "Total ESG Risk Score": 32.73,
            "Environmental Risk Score": 2.41,
            "Social Risk Score": 21.64,
            "Governance Risk Score": 8.68,
            "Controversy Level": 4.0,
            "Peer Controversy Min": 0.0,
            "Peer Controversy Avg": 0.6598984771573604,
            "Peer Controversy Max": 4.0
        },
        "Faithfulness Evaluation": {
            "Score": 0.9,
            "Explanation": "The generated ESG report accurately reflects the reference ESG data for META, particularly in terms of the total ESG risk score (32.73), environmental risk score (2.41), social risk score (21.64), governance risk score (8.68), and controversy level (4.0). The report correctly identifies the environmental impact as relatively minimal, which aligns with the low environmental risk score. It also appropriately highlights the significant social risks and governance issues, which are accurately represented by their respective scores.\n\nHowever, the report could improve by providing more context regarding the implications of the controversy level, such as specific examples of controversies or how they compare to peers, which would enhance the understanding of the risks involved. Overall, the report is very faithful to the actual data, with only minor areas for improvement in depth and specificity."
        }
    },
    "AMZN": {
        "Generated Report": "Amazon (AMZN) presents a mixed ESG profile characterized by a Total ESG Risk Score of 26.1, indicating moderate sustainability risks. The Environmental Risk Score of 8.3 suggests that while the company is making strides in addressing its ecological footprint, significant risks remain, particularly concerning carbon emissions, waste management, and resource utilization. \n\nThe Social Risk Score of 11.05 indicates heightened concerns regarding labor practices, employee welfare, and community impact. This score reflects ongoing scrutiny over working conditions in warehouses, employee treatment, and the broader implications of its market dominance on local businesses and economies.\n\nThe Governance Risk Score of 6.75 is relatively favorable, suggesting that Amazon maintains a reasonable structure for oversight and accountability. However, governance issues can still arise, especially in the context of transparency and shareholder engagement.\n\nThe Controversy Level of 3.0, significantly above the peer average of approximately 0.91, highlights that Amazon is involved in noteworthy controversies, potentially affecting its reputation and stakeholder trust. \n\nIn summary, while Amazon demonstrates commitment to improving its ESG practices, the combination of moderate environmental and social risks, along with a high controversy score, indicates that investors should be cautious. Ongoing scrutiny and evolving regulatory landscapes could further impact the company\u2019s sustainability trajectory and financial performance.",
        "Reference ESG Data": {
            "Stock": "AMZN",
            "Total ESG Risk Score": 26.1,
            "Environmental Risk Score": 8.3,
            "Social Risk Score": 11.05,
            "Governance Risk Score": 6.75,
            "Controversy Level": 3.0,
            "Peer Controversy Min": 0.0,
            "Peer Controversy Avg": 0.9104477611940298,
            "Peer Controversy Max": 4.0
        },
        "Faithfulness Evaluation": {
            "Score": 1.0,
            "Explanation": "The generated ESG report accurately reflects the provided reference ESG data for Amazon (AMZN). It correctly states the Total ESG Risk Score of 26.1 and breaks down the Environmental, Social, and Governance Risk Scores as 8.3, 11.05, and 6.75, respectively. The report also appropriately highlights the Controversy Level of 3.0 and compares it to the peer average of approximately 0.91, which is consistent with the reference data. The descriptions of the risks associated with environmental and social factors align with the scores provided, and the mention of ongoing scrutiny and potential impacts on reputation and financial performance is a reasonable interpretation of the data. Overall, the report is faithful to the actual ESG data, providing a comprehensive and accurate overview of Amazon's ESG profile."
        }
    },
    "TQQQ": {
        "Generated Report": "No ESG data available for TQQQ",
        "Reference ESG Data": {
            "error": "No ESG data available for TQQQ"
        },
        "Faithfulness Evaluation": "Could not evaluate due to error in data or report generation."
    },
    "AMD": {
        "Generated Report": "Advanced Micro Devices (AMD) presents a mixed ESG profile with a Total ESG Risk Score of 12.51, indicating a moderate level of risk. The Environmental Risk Score of 3.01 suggests that while the company faces some environmental challenges, they are relatively manageable compared to peers. AMD has made strides in improving energy efficiency and reducing carbon emissions, reflecting a commitment to sustainability within the semiconductor industry.\n\nThe Social Risk Score of 4.22 indicates more significant concerns in this area, particularly regarding labor practices and community engagement. As the tech industry faces scrutiny over diversity, equity, and inclusion, AMD's performance here will be critical for reputation and operational stability. \n\nThe Governance Risk Score of 5.28 is the highest among the three categories, highlighting potential vulnerabilities in corporate governance structures. This could involve issues related to board diversity, executive compensation, or shareholder rights, which may impact investor confidence and long-term performance.\n\nWith a Controversy Level of 1.0, AMD appears to have a relatively low incidence of controversies compared to its peers, whose average controversy score is 0.56. This suggests that while AMD is not without risk, it has managed to maintain a positive public image and minimize negative attention.\n\nIn conclusion, while AMD shows a commitment to addressing environmental concerns, it must enhance its social and governance practices to mitigate risks and bolster its sustainability profile.",
        "Reference ESG Data": {
            "Stock": "AMD",
            "Total ESG Risk Score": 12.51,
            "Environmental Risk Score": 3.01,
            "Social Risk Score": 4.22,
            "Governance Risk Score": 5.28,
            "Controversy Level": 1.0,
            "Peer Controversy Min": 0.0,
            "Peer Controversy Avg": 0.5583333333333333,
            "Peer Controversy Max": 3.0
        },
        "Faithfulness Evaluation": {
            "Score": 0.9,
            "Explanation": "The generated ESG report accurately reflects the Total ESG Risk Score of 12.51 and the specific Environmental, Social, and Governance Risk Scores of 3.01, 4.22, and 5.28, respectively. It correctly identifies the controversy level of 1.0 and compares it favorably to the peer average of 0.56, which is also accurate. \n\nHowever, while the report discusses AMD's commitment to sustainability and acknowledges areas for improvement in social and governance practices, it lacks specific examples or data points to substantiate these claims. The mention of \"strides in improving energy efficiency and reducing carbon emissions\" is somewhat vague and could be seen as an overstatement without concrete evidence or metrics. \n\nOverall, the report is largely faithful to the reference data but could enhance its accuracy by providing more detailed evidence of AMD's initiatives and performance in the ESG areas discussed."
        }
    },
    "NFLX": {
        "Generated Report": "Netflix (NFLX) exhibits a total ESG risk score of 15.88, indicating a moderate level of risk across environmental, social, and governance dimensions. The environmental risk score is notably low at 0.16, suggesting that Netflix's operations have minimal negative environmental impact, which is favorable for sustainability.\n\nHowever, the social risk score of 7.38 indicates significant concerns in this area. This score may reflect issues such as content representation, labor practices, and community engagement, which could affect the company's brand reputation and customer loyalty. In an industry where public perception is crucial, these social risks warrant close attention.\n\nThe governance risk score of 8.35 is relatively high, implying potential concerns regarding corporate governance practices. Issues such as executive compensation, board diversity, and shareholder rights could be areas of scrutiny that may impact investor confidence and operational stability.\n\nThe controversy level of 2.0 is above the peer average of 1.01, suggesting that Netflix has encountered notable controversies compared to its industry peers. This elevated level of controversy could pose reputational risks and may impact stakeholder trust.\n\nIn summary, while Netflix performs well environmentally, it faces significant social and governance challenges that could impact its long-term sustainability and risk profile. Addressing these concerns proactively is essential for mitigating risks and enhancing the company's ESG performance.",
        "Reference ESG Data": {
            "Stock": "NFLX",
            "Total ESG Risk Score": 15.88,
            "Environmental Risk Score": 0.16,
            "Social Risk Score": 7.38,
            "Governance Risk Score": 8.35,
            "Controversy Level": 2.0,
            "Peer Controversy Min": 0.0,
            "Peer Controversy Avg": 1.0070921985815602,
            "Peer Controversy Max": 3.0
        },
        "Faithfulness Evaluation": {
            "Score": 1.0,
            "Explanation": "The generated ESG report accurately reflects the reference ESG data provided. It correctly states the total ESG risk score of 15.88 and breaks down the environmental, social, and governance risk scores (0.16, 7.38, and 8.35, respectively) in a manner that aligns with the reference data. The report also appropriately highlights the controversy level of 2.0 and compares it to the peer average of 1.01, indicating that Netflix has a higher level of controversy than its peers. Overall, the report is faithful to the data, providing a clear and accurate assessment of Netflix's ESG performance and risks."
        }
    }
}