{
    "TSLA": {
        "Generated Report": "Tesla, Inc. (TSLA) presents a mixed picture in its ESG analysis, with a total ESG Risk Score of 24.76. The Environmental Risk Score of 3.04 indicates a relatively low level of environmental risk, which is consistent with its mission to accelerate the world's transition to sustainable energy. Tesla's commitment to electric vehicles and renewable energy technologies positions it favorably in the environmental aspect of ESG.\n\nHowever, the Social Risk Score of 14.13 is a significant area of concern. This score suggests potential risks related to labor practices, community relations, and product safety. The company's rapid growth and production challenges have led to scrutiny regarding worker conditions and labor relations, which could pose reputational risks and impact employee morale and retention.\n\nThe Governance Risk Score of 7.6 indicates moderate governance challenges, potentially linked to issues such as executive compensation, board diversity, and shareholder rights. Governance factors are vital for long-term sustainability and investor confidence.\n\nThe Controversy Level of 3.0, above the peer average of 1.75, highlights that Tesla faces notable public and media scrutiny, which can affect its brand reputation and market performance. The range of peer controversy (0.0 to 4.0) further emphasizes that while Tesla is a leader in the electric vehicle space, it must address its social and governance challenges to mitigate risks and enhance its sustainability profile. Overall, while Tesla is positioned well environmentally, significant social and governance issues require attention to sustain its long-term viability.",
        "Reference ESG Data": {
            "Stock": "TSLA",
            "Total ESG Risk Score": 24.76,
            "Environmental Risk Score": 3.04,
            "Social Risk Score": 14.13,
            "Governance Risk Score": 7.6,
            "Controversy Level": 3.0,
            "Peer Controversy Min": 0.0,
            "Peer Controversy Avg": 1.75,
            "Peer Controversy Max": 4.0
        },
        "Faithfulness Evaluation": {
            "Score": 1.0,
            "Explanation": "The generated ESG report accurately reflects the reference ESG data provided. It correctly states Tesla's total ESG Risk Score of 24.76 and breaks down the Environmental Risk Score (3.04), Social Risk Score (14.13), and Governance Risk Score (7.6) in a manner that aligns with the reference data. The report also appropriately discusses the implications of these scores, particularly highlighting the significant social risks and moderate governance challenges, which are consistent with the provided scores. Furthermore, the mention of the Controversy Level (3.0) and its comparison to the peer average (1.75) is accurate and contextualizes Tesla's position relative to its peers. Overall, the report is grounded in the actual data and provides a faithful representation of Tesla's ESG profile."
        }
    },
    "NVDA": {
        "Generated Report": "NVIDIA Corporation (NVDA) presents a mixed ESG profile. With a Total ESG Risk Score of 12.46, the company operates within a moderate risk environment, particularly highlighted by its Environmental Risk Score of 2.73, which indicates relatively low environmental concerns compared to industry peers. This suggests that NVDA is making strides in minimizing its ecological impact, likely through energy-efficient technologies and sustainable practices.\n\nHowever, the Social Risk Score of 4.08 indicates some challenges in social responsibility, including labor practices, community engagement, or product impact. This score may reflect potential issues related to workforce diversity, employee treatment, or relations with local communities, which could pose reputational risks.\n\nThe Governance Risk Score of 5.65 is notably higher, indicating greater risks in governance structures, including board diversity, executive compensation, and shareholder rights. This could lead to vulnerabilities in decision-making processes and stakeholder trust.\n\nThe Controversy Level of 2.0, while moderate, shows NVDA has faced some controversies, although not at the extremes of the peer group (min: 0.0, avg: 0.56, max: 3.0). Continuous monitoring of these controversies is essential, as they can significantly impact brand reputation and investor sentiment.\n\nIn summary, while NVDA shows promise in environmental practices, social and governance factors warrant attention. Addressing these issues proactively will be crucial for sustaining long-term growth and minimizing risks.",
        "Reference ESG Data": {
            "Stock": "NVDA",
            "Total ESG Risk Score": 12.46,
            "Environmental Risk Score": 2.73,
            "Social Risk Score": 4.08,
            "Governance Risk Score": 5.65,
            "Controversy Level": 2.0,
            "Peer Controversy Min": 0.0,
            "Peer Controversy Avg": 0.5583333333333333,
            "Peer Controversy Max": 3.0
        },
        "Faithfulness Evaluation": {
            "Score": 1.0,
            "Explanation": "The generated ESG report accurately reflects the provided reference ESG data for NVIDIA Corporation (NVDA). It correctly states the Total ESG Risk Score of 12.46 and provides a detailed breakdown of the Environmental Risk Score (2.73), Social Risk Score (4.08), and Governance Risk Score (5.65). The report also appropriately contextualizes the Controversy Level of 2.0 in relation to peer controversy metrics, indicating a moderate level of controversy without overstating or understating the company's position compared to its peers. The analysis of potential risks in social and governance factors aligns well with the scores provided, demonstrating a faithful representation of the actual data. Overall, the report is grounded in the reference data, justifying a perfect score for faithfulness."
        }
    },
    "AAPL": {
        "Generated Report": "Apple Inc. (AAPL) presents a mixed ESG profile based on its risk scores and controversy levels. With a Total ESG Risk Score of 18.75, the company demonstrates a relatively low environmental risk (2.05), indicating effective management of ecological impacts. This suggests a commitment to sustainability practices, particularly in areas such as renewable energy use and product lifecycle management.\n\nHowever, the Social (8.35) and Governance (8.35) Risk Scores are notably higher, indicating potential vulnerabilities in these aspects. The elevated Social Risk Score may stem from issues related to labor practices, supply chain management, and product accessibility. Similarly, the Governance Risk Score suggests concerns regarding corporate governance, possibly linked to transparency, shareholder rights, or executive compensation practices.\n\nThe controversy level of 3.0, aligned with the maximum peer controversy, highlights that AAPL faces significant scrutiny compared to its peers. This could pose reputational risks and affect investor sentiment, especially in an environment increasingly focused on ethical business practices.\n\nIn summary, while Apple shows strength in environmental management, the heightened social and governance risks warrant attention. A proactive approach to addressing these concerns could enhance its ESG standing and mitigate potential risks associated with stakeholder relations and regulatory compliance. Investors should monitor these factors closely, as they could influence long-term sustainability and financial performance.",
        "Reference ESG Data": {
            "Stock": "AAPL",
            "Total ESG Risk Score": 18.75,
            "Environmental Risk Score": 2.05,
            "Social Risk Score": 8.35,
            "Governance Risk Score": 8.35,
            "Controversy Level": 3.0,
            "Peer Controversy Min": 0.0,
            "Peer Controversy Avg": 0.5598290598290598,
            "Peer Controversy Max": 3.0
        },
        "Faithfulness Evaluation": {
            "Score": 0.9,
            "Explanation": "The generated ESG report is largely faithful to the reference ESG data, accurately reflecting the Total ESG Risk Score (18.75) and the Environmental Risk Score (2.05). It correctly identifies the Social and Governance Risk Scores as both being 8.35, highlighting the potential vulnerabilities in these areas. The report also mentions the controversy level of 3.0, which aligns with the maximum peer controversy, indicating that Apple Inc. faces significant scrutiny.\n\nHowever, the report could improve in precision by explicitly stating that the controversy level is at the maximum among peers, rather than just suggesting significant scrutiny. Additionally, while it discusses the implications of the social and governance risks, it could provide more context regarding how these scores compare to the industry average or peer performance, which would enhance the analysis. Overall, the report is accurate but could benefit from slight clarifications and additional context, justifying a score of 0.9."
        }
    },
    "SPY": {
        "Generated Report": "No ESG data available for SPY",
        "Reference ESG Data": {
            "error": "No ESG data available for SPY"
        },
        "Faithfulness Evaluation": "Could not evaluate due to error in data or report generation."
    },
    "QQQ": {
        "Generated Report": "No ESG data available for QQQ",
        "Reference ESG Data": {
            "error": "No ESG data available for QQQ"
        },
        "Faithfulness Evaluation": "Could not evaluate due to error in data or report generation."
    },
    "META": {
        "Generated Report": "Meta's total ESG risk score of 32.73 indicates a moderate level of overall risk, with significant differentiation between its environmental, social, and governance components. The environmental risk score of 2.41 is relatively low, suggesting that Meta's operations have a minimal impact on environmental factors. This is commendable, especially for a tech company where energy consumption and electronic waste are critical concerns.\n\nHowever, the social risk score of 21.64 raises significant red flags. This score reflects potential issues related to privacy, misinformation, user safety, and community impact, which have been focal points of criticism for Meta in recent years. The high social risk score indicates that the company may face reputational damage and regulatory scrutiny, which could affect its long-term sustainability and market position.\n\nThe governance risk score of 8.68, while higher than the environmental score, suggests challenges related to corporate governance practices, such as board diversity and shareholder rights. The controversy level of 4.0 is alarming, particularly when compared to an average peer controversy score of 0.66; this indicates that Meta is facing significant scrutiny compared to its peers.\n\nIn summary, while Meta demonstrates strong environmental performance, the elevated social and governance risks, alongside a high controversy level, pose considerable challenges. Investors should remain cautious, as these factors could influence the company's reputation, regulatory landscape, and ultimately, its financial performance.",
        "Reference ESG Data": {
            "Stock": "META",
            "Total ESG Risk Score": 32.73,
            "Environmental Risk Score": 2.41,
            "Social Risk Score": 21.64,
            "Governance Risk Score": 8.68,
            "Controversy Level": 4.0,
            "Peer Controversy Min": 0.0,
            "Peer Controversy Avg": 0.6598984771573604,
            "Peer Controversy Max": 4.0
        },
        "Faithfulness Evaluation": {
            "Score": 1.0,
            "Explanation": "The generated ESG report accurately reflects the provided reference ESG data for META. It correctly states the total ESG risk score of 32.73 and breaks down the environmental risk score (2.41), social risk score (21.64), and governance risk score (8.68) in a coherent manner. The report highlights the low environmental risk, the significant concerns regarding social risks, and the challenges in governance, all of which align with the reference data. Additionally, it appropriately notes the controversy level of 4.0 and compares it to the peer average, emphasizing the heightened scrutiny META faces relative to its peers. Overall, the report is faithful to the actual data, providing a comprehensive and accurate assessment of META's ESG performance."
        }
    },
    "AMZN": {
        "Generated Report": "Amazon (AMZN) presents a mixed ESG profile, with a total ESG risk score of 26.1, indicating a moderate level of risk. The Environmental Risk Score of 8.3 suggests that while the company has made strides towards sustainability, it still faces significant challenges, particularly related to its carbon footprint, waste management, and the environmental impact of its logistics and warehousing operations.\n\nThe Social Risk Score of 11.05 highlights potential concerns surrounding labor practices, employee treatment, and community relations. Issues such as warehouse working conditions and labor disputes have garnered public and regulatory scrutiny, which could pose reputational risks and operational disruptions if not adequately addressed.\n\nThe Governance Risk Score of 6.75 indicates a relatively sound governance structure, although there may be room for improvement in areas like board diversity and stakeholder engagement. \n\nThe company's Controversy Level of 3.0, significantly higher than the peer average of 0.91, suggests that Amazon has faced notable controversies, which can impact investor sentiment and brand loyalty. \n\nIn summary, while Amazon demonstrates a commitment to improving its ESG practices, significant environmental and social risks remain. Addressing these issues is crucial for mitigating potential reputational damage and aligning with evolving investor expectations regarding sustainability and corporate responsibility.",
        "Reference ESG Data": {
            "Stock": "AMZN",
            "Total ESG Risk Score": 26.1,
            "Environmental Risk Score": 8.3,
            "Social Risk Score": 11.05,
            "Governance Risk Score": 6.75,
            "Controversy Level": 3.0,
            "Peer Controversy Min": 0.0,
            "Peer Controversy Avg": 0.9104477611940298,
            "Peer Controversy Max": 4.0
        },
        "Faithfulness Evaluation": {
            "Score": 1.0,
            "Explanation": "The generated ESG report accurately reflects the reference ESG data for Amazon (AMZN). It correctly states the total ESG risk score of 26.1 and provides detailed insights into the Environmental Risk Score (8.3), Social Risk Score (11.05), and Governance Risk Score (6.75). The report also accurately notes the Controversy Level of 3.0 and compares it to the peer average of 0.91, highlighting the significant controversies faced by the company. The descriptions of the challenges in environmental sustainability, labor practices, and governance align well with the provided data, making the report faithful to the actual ESG metrics."
        }
    },
    "TQQQ": {
        "Generated Report": "No ESG data available for TQQQ",
        "Reference ESG Data": {
            "error": "No ESG data available for TQQQ"
        },
        "Faithfulness Evaluation": "Could not evaluate due to error in data or report generation."
    },
    "AMD": {
        "Generated Report": "AMD's total ESG risk score of 12.51 suggests a moderate level of overall sustainability risk. The breakdown reveals a relatively low Environmental Risk Score of 3.01, indicating that AMD is managing its environmental impact reasonably well, especially in comparison to peers in the semiconductor industry. \n\nThe Social Risk Score of 4.22 reflects potential challenges related to labor practices, community engagement, or product responsibility, but it remains manageable. This score suggests that while there are areas for improvement, AMD is not facing significant social controversies that could severely impact its reputation or operations.\n\nThe Governance Risk Score of 5.28 is noteworthy, as it indicates potential issues in corporate governance, which can include board diversity, executive compensation, and shareholder rights. This score is higher than both the environmental and social scores, suggesting that governance practices may require more scrutiny from investors.\n\nThe company's Controversy Level of 1.0 is relatively low, especially when compared to the peer controversy average of 0.56. This indicates that AMD has experienced minimal negative press or public backlash, positioning it favorably in terms of reputation.\n\nOverall, while AMD demonstrates strengths in environmental management and a low controversy level, attention should be given to improving social and governance practices to mitigate potential risks associated with these areas. Continuous monitoring and proactive engagement in these domains will be essential for sustaining investor confidence and long-term viability.",
        "Reference ESG Data": {
            "Stock": "AMD",
            "Total ESG Risk Score": 12.51,
            "Environmental Risk Score": 3.01,
            "Social Risk Score": 4.22,
            "Governance Risk Score": 5.28,
            "Controversy Level": 1.0,
            "Peer Controversy Min": 0.0,
            "Peer Controversy Avg": 0.5583333333333333,
            "Peer Controversy Max": 3.0
        },
        "Faithfulness Evaluation": {
            "Score": 1.0,
            "Explanation": "The generated ESG report accurately reflects the reference ESG data provided for AMD. It correctly states the total ESG risk score of 12.51 and breaks down the individual scores for Environmental (3.01), Social (4.22), and Governance (5.28) risks, aligning with the reference data. The report appropriately contextualizes these scores, indicating a moderate overall sustainability risk and highlighting the relatively low environmental risk. It also accurately describes the social and governance scores, noting the potential challenges in these areas without overstating the risks. Furthermore, the controversy level of 1.0 is correctly compared to the peer average, reinforcing the report's accuracy. Overall, the report is well-grounded in the actual data, making it perfectly faithful."
        }
    },
    "NFLX": {
        "Generated Report": "Netflix (NFLX) has a total ESG risk score of 15.88, indicating a relatively moderate level of overall risk, particularly when contrasted with its peer group. The Environmental Risk Score is notably low at 0.16, suggesting that the company's environmental impact is minimal, which is a positive indicator for sustainability. This score reflects Netflix's efforts in areas like energy efficiency and content delivery, especially in reducing the carbon footprint of streaming services.\n\nHowever, the Social Risk Score of 7.38 and Governance Risk Score of 8.35 are more concerning, highlighting significant risks in these areas. The social risks may stem from issues related to employee relations, diversity and inclusion, and content-related controversies. Governance risks could be tied to corporate structure, board diversity, or executive compensation practices. \n\nThe controversy level of 2.0, while below the peer average of 1.01, indicates that Netflix has faced notable challenges that could affect its reputation and stakeholder trust. While this score is not the highest in its peer group, it does suggest that the company is not immune to public scrutiny or backlash.\n\nIn summary, Netflix demonstrates strong environmental performance but faces heightened social and governance risks that could pose challenges to its long-term sustainability. Investors should monitor these areas closely, as they can influence the company's operational resilience and market perception.",
        "Reference ESG Data": {
            "Stock": "NFLX",
            "Total ESG Risk Score": 15.88,
            "Environmental Risk Score": 0.16,
            "Social Risk Score": 7.38,
            "Governance Risk Score": 8.35,
            "Controversy Level": 2.0,
            "Peer Controversy Min": 0.0,
            "Peer Controversy Avg": 1.0070921985815602,
            "Peer Controversy Max": 3.0
        },
        "Faithfulness Evaluation": {
            "Score": 1.0,
            "Explanation": "The generated ESG report accurately reflects the reference ESG data for Netflix (NFLX). It correctly states the total ESG risk score of 15.88 and provides a precise breakdown of the Environmental Risk Score (0.16), Social Risk Score (7.38), and Governance Risk Score (8.35). The report also appropriately interprets the controversy level of 2.0 in relation to the peer average of 1.01, indicating that while Netflix has some challenges, it is performing better than the average in its peer group. The analysis of risks related to social and governance factors aligns with the scores provided, and the mention of areas such as employee relations and corporate governance practices is consistent with common themes in ESG assessments. Overall, the report is faithful to the reference data and provides a clear and accurate assessment of Netflix's ESG performance."
        }
    }
}