{
    "TSLA": {
        "Generated Report": "Tesla, Inc. (TSLA) demonstrates a relatively low total ESG risk score of 24.76, indicating a moderate level of sustainability risk. The Environmental Risk Score of 3.04 reflects the company's commitment to renewable energy solutions and electric vehicle production, positioning it favorably within the environmental sector. However, the score does suggest some ongoing challenges, possibly related to resource extraction or manufacturing processes.\n\nThe Social Risk Score of 14.13 is notably higher, signaling significant potential risks related to labor practices, community relations, or product safety. This area warrants attention as it may impact the company's reputation and stakeholder relationships. Tesla has faced scrutiny regarding worker conditions and equity issues, which could elevate social risks further.\n\nThe Governance Risk Score of 7.6, while moderate, indicates potential concerns in management practices or board diversity. Governance structures are critical for long-term sustainability, and improvements in this area could enhance investor confidence.\n\nWith a Controversy Level of 3.0, TSLA's controversies are above the peer average (1.75), highlighting a need for the company to address public relations challenges effectively. As controversies can impact brand value and regulatory scrutiny, proactive measures are essential.\n\nIn summary, while Tesla exhibits strengths in environmental initiatives, its elevated social risk and controversy level indicate areas for improvement. Addressing these challenges will be crucial for enhancing its overall sustainability profile and mitigating potential risks.",
        "Reference ESG Data": {
            "Stock": "TSLA",
            "Total ESG Risk Score": 24.76,
            "Environmental Risk Score": 3.04,
            "Social Risk Score": 14.13,
            "Governance Risk Score": 7.6,
            "Controversy Level": 3.0,
            "Peer Controversy Min": 0.0,
            "Peer Controversy Avg": 1.75,
            "Peer Controversy Max": 4.0
        },
        "Faithfulness Evaluation": {
            "Score": 1.0,
            "Explanation": "The generated ESG report accurately reflects the reference ESG data for Tesla, Inc. (TSLA). It correctly states the total ESG risk score of 24.76 and provides a detailed breakdown of the Environmental Risk Score (3.04), Social Risk Score (14.13), and Governance Risk Score (7.6). The report appropriately contextualizes these scores, highlighting Tesla's strengths in environmental initiatives while also addressing the significant social risks and controversies the company faces. The mention of the controversy level being above the peer average (1.75) aligns with the reference data, indicating a faithful representation of Tesla's ESG profile. Overall, the report is grounded in the actual data provided, warranting a perfect score for faithfulness."
        }
    },
    "NVDA": {
        "Generated Report": "NVIDIA Corporation (NVDA) presents a mixed ESG profile, as indicated by its total ESG risk score of 12.46. This score suggests that while the company has some sustainability practices in place, there are notable risks that warrant attention.\n\nThe Environmental Risk Score of 2.73 indicates a relatively low level of environmental risk. Given NVIDIA's focus on energy-efficient technologies, particularly in the context of its GPU products and their applications in AI and data centers, the company appears to be making strides in mitigating its environmental impact. However, it is essential to monitor the implications of its manufacturing processes and supply chain sustainability.\n\nThe Social Risk Score of 4.08 reflects moderate risks related to labor practices, community relations, and product responsibility. As NVIDIA expands its workforce and operations, it must address potential labor concerns and ensure equitable practices, especially in a competitive tech talent market.\n\nThe Governance Risk Score of 5.65 is the highest among the three categories, indicating possible challenges in corporate governance practices. This could relate to issues such as board diversity, executive compensation, and shareholder rights, which are critical for investor confidence.\n\nThe controversy level of 2.0, higher than the peer average, suggests that NVIDIA has faced notable criticisms or incidents that could affect its reputation. This is particularly relevant as investors increasingly consider long-term sustainability impacts.\n\nIn summary, while NVIDIA demonstrates strengths in environmental initiatives, it must address social and governance risks to enhance its overall sustainability profile and investor confidence.",
        "Reference ESG Data": {
            "Stock": "NVDA",
            "Total ESG Risk Score": 12.46,
            "Environmental Risk Score": 2.73,
            "Social Risk Score": 4.08,
            "Governance Risk Score": 5.65,
            "Controversy Level": 2.0,
            "Peer Controversy Min": 0.0,
            "Peer Controversy Avg": 0.5583333333333333,
            "Peer Controversy Max": 3.0
        },
        "Faithfulness Evaluation": {
            "Score": 1.0,
            "Explanation": "The generated ESG report accurately reflects the provided reference ESG data for NVIDIA Corporation (NVDA). It correctly states the total ESG risk score of 12.46 and breaks down the individual scores for environmental (2.73), social (4.08), and governance (5.65) risks, aligning perfectly with the reference data. Additionally, the report appropriately discusses the controversy level of 2.0 and contextualizes it within the peer average, indicating a thorough understanding of the company's ESG profile. The analysis of the implications of these scores is well-articulated and grounded in the actual data, making the report fully faithful to the reference ESG data."
        }
    },
    "AAPL": {
        "Generated Report": "Apple Inc. (AAPL) presents a mixed ESG profile with a Total ESG Risk Score of 18.75, indicating a moderate level of risk. The Environmental Risk Score of 2.05 suggests that while the company has made some strides in sustainability, it still faces challenges related to its environmental impact, particularly in supply chain emissions and electronic waste.\n\nThe Social Risk Score of 8.35 is notably high, reflecting potential risks in labor practices, privacy issues, and community relations. This score warrants attention, especially given the scrutiny Apple has faced regarding labor conditions in its supply chain and the impact of its products on consumer data privacy.\n\nThe Governance Risk Score, also at 8.35, indicates potential issues in corporate governance, which may include board diversity, executive compensation, and shareholder rights. These factors can influence investor confidence and overall corporate reputation.\n\nA controversy level of 3.0 positions Apple at the higher end of the spectrum when compared to its peers, where the average controversy is significantly lower (0.56). The presence of controversies can impact stakeholder perceptions and lead to reputational risks.\n\nIn summary, while Apple demonstrates some commitment to sustainability, the elevated social and governance risks, coupled with a high controversy level, highlight areas for improvement. Investors should remain cautious and consider these factors when evaluating the company\u2019s long-term sustainability and potential risks.",
        "Reference ESG Data": {
            "Stock": "AAPL",
            "Total ESG Risk Score": 18.75,
            "Environmental Risk Score": 2.05,
            "Social Risk Score": 8.35,
            "Governance Risk Score": 8.35,
            "Controversy Level": 3.0,
            "Peer Controversy Min": 0.0,
            "Peer Controversy Avg": 0.5598290598290598,
            "Peer Controversy Max": 3.0
        },
        "Faithfulness Evaluation": {
            "Score": 1.0,
            "Explanation": "The generated ESG report accurately reflects the provided reference ESG data for Apple Inc. (AAPL). It correctly states the Total ESG Risk Score of 18.75 and provides detailed insights into the Environmental, Social, and Governance Risk Scores, which are 2.05, 8.35, and 8.35, respectively. The report also appropriately contextualizes the controversy level of 3.0, noting that it is significantly higher than the peer average of 0.56. The analysis of potential risks related to labor practices, privacy issues, corporate governance, and the implications of the controversy level are well-grounded in the data. Overall, the report is faithful to the reference data, providing a comprehensive and accurate assessment of Apple's ESG profile."
        }
    },
    "SPY": {
        "Generated Report": "No ESG data available for SPY",
        "Reference ESG Data": {
            "error": "No ESG data available for SPY"
        },
        "Faithfulness Evaluation": "Could not evaluate due to error in data or report generation."
    },
    "QQQ": {
        "Generated Report": "No ESG data available for QQQ",
        "Reference ESG Data": {
            "error": "No ESG data available for QQQ"
        },
        "Faithfulness Evaluation": "Could not evaluate due to error in data or report generation."
    },
    "META": {
        "Generated Report": "META's ESG assessment reveals a total risk score of 32.73, indicating a moderate level of overall risk. The Environmental Risk Score is notably low at 2.41, suggesting that the company has minimal environmental impact relative to its peers. This is a positive indicator of its sustainability practices in areas such as energy consumption and waste management.\n\nHowever, the Social Risk Score of 21.64 raises significant concerns, highlighting potential issues related to data privacy, user trust, and the impact of social media on mental health. This score is substantially higher than its environmental counterpart, indicating that social factors pose a more considerable risk to META's reputation and operational stability. The company's governance practices, while not as alarming, are reflected in a Governance Risk Score of 8.68, which suggests room for improvement in areas such as board diversity and executive accountability.\n\nThe controversy level of 4.0 aligns with the upper end of the peer spectrum, indicating that META has faced significant challenges and scrutiny in recent years. This level of controversy could lead to reputational damage and regulatory risks, particularly in light of ongoing discussions about content moderation and misinformation.\n\nIn summary, while META excels environmentally, its social and governance risks present critical challenges that could impact its long-term sustainability and stakeholder trust. Addressing these issues will be vital for mitigating risks and enhancing its ESG performance.",
        "Reference ESG Data": {
            "Stock": "META",
            "Total ESG Risk Score": 32.73,
            "Environmental Risk Score": 2.41,
            "Social Risk Score": 21.64,
            "Governance Risk Score": 8.68,
            "Controversy Level": 4.0,
            "Peer Controversy Min": 0.0,
            "Peer Controversy Avg": 0.6598984771573604,
            "Peer Controversy Max": 4.0
        },
        "Faithfulness Evaluation": {
            "Score": 1.0,
            "Explanation": "The generated ESG report accurately reflects the reference ESG data for META. It correctly states the total ESG risk score of 32.73 and provides detailed breakdowns of the Environmental Risk Score (2.41), Social Risk Score (21.64), and Governance Risk Score (8.68). The report also appropriately highlights the controversy level of 4.0, noting its position within the peer spectrum. The analysis of the implications of these scores is coherent and aligns well with the data provided. There are no discrepancies or inaccuracies in the report, making it perfectly faithful to the reference ESG data."
        }
    },
    "AMZN": {
        "Generated Report": "Amazon (AMZN) presents a mixed ESG profile, with a Total ESG Risk Score of 26.1 indicating a moderate level of risk. The Environmental Risk Score of 8.3 highlights significant concerns, particularly regarding the company's carbon footprint and waste management practices. Although Amazon has made commitments to sustainability, the scale of its operations raises questions about the effectiveness of these initiatives.\n\nThe Social Risk Score of 11.05 is notably higher than the environmental score, reflecting issues related to workforce treatment, labor practices, and community impact. Reports of employee dissatisfaction, labor disputes, and the working conditions in fulfillment centers have contributed to this elevated score, which could pose reputational risks and affect employee retention.\n\nThe Governance Risk Score of 6.75 suggests a relatively strong governance framework, although there may still be areas for improvement, particularly in stakeholder engagement and transparency.\n\nThe Controversy Level of 3.0 indicates that Amazon has faced multiple public controversies, which is significantly higher than the peer controversy average of 0.91. This level of controversy can lead to reputational damage and increased scrutiny from both investors and regulators.\n\nIn summary, while Amazon is taking steps towards sustainability, its high social risks and controversies could undermine its long-term sustainability goals. Investors should remain cautious and consider these risks when evaluating the company\u2019s overall ESG performance and future growth potential.",
        "Reference ESG Data": {
            "Stock": "AMZN",
            "Total ESG Risk Score": 26.1,
            "Environmental Risk Score": 8.3,
            "Social Risk Score": 11.05,
            "Governance Risk Score": 6.75,
            "Controversy Level": 3.0,
            "Peer Controversy Min": 0.0,
            "Peer Controversy Avg": 0.9104477611940298,
            "Peer Controversy Max": 4.0
        },
        "Faithfulness Evaluation": {
            "Score": 0.9,
            "Explanation": "The generated ESG report accurately reflects the reference ESG data for Amazon (AMZN) in terms of the Total ESG Risk Score (26.1), Environmental Risk Score (8.3), Social Risk Score (11.05), Governance Risk Score (6.75), and Controversy Level (3.0). The report effectively highlights the significant concerns related to environmental impact, social issues, and governance practices, which align with the scores provided. \n\nHowever, while the report mentions the controversy level being \"significantly higher than the peer controversy average of 0.91,\" it could be more explicit about the implications of this comparison. The report could also benefit from a more nuanced discussion of the governance score, as it describes it as \"relatively strong\" without acknowledging that it is still the lowest among the three risk categories. Overall, the report is largely faithful to the data but could improve in clarity and depth regarding comparisons and implications."
        }
    },
    "TQQQ": {
        "Generated Report": "No ESG data available for TQQQ",
        "Reference ESG Data": {
            "error": "No ESG data available for TQQQ"
        },
        "Faithfulness Evaluation": "Could not evaluate due to error in data or report generation."
    },
    "AMD": {
        "Generated Report": "Advanced Micro Devices (AMD) exhibits a Total ESG Risk Score of 12.51, with notable distinctions across its environmental, social, and governance dimensions. The Environmental Risk Score of 3.01 suggests that AMD faces moderate challenges related to sustainability practices, particularly in energy consumption and resource use typical of semiconductor manufacturing. However, this score is relatively low compared to industry standards, indicating proactive measures in environmental management.\n\nThe Social Risk Score of 4.22 reflects potential challenges in areas such as labor practices, community engagement, and product safety. This score, while higher than the environmental score, indicates that AMD may need to enhance its focus on workforce diversity, equity, and inclusion, as well as community relations to mitigate social risks.\n\nThe Governance Risk Score of 5.28 suggests that there are governance issues that may require attention, possibly related to board diversity, executive compensation, or shareholder rights. This aspect is critical as strong governance is essential for maintaining investor confidence and ensuring strategic alignment with ESG principles.\n\nAMD's Controversy Level of 1.0 indicates a low level of reported controversies, especially when compared to its peers, where the average is approximately 0.56. This reflects positively on the company\u2019s reputation and stakeholder trust.\n\nOverall, while AMD faces some risks, particularly in social and governance areas, its lower controversy level and proactive environmental practices suggest a commitment to improving sustainability. Continued focus on governance and social responsibility will be crucial in managing potential risks and enhancing its ESG profile.",
        "Reference ESG Data": {
            "Stock": "AMD",
            "Total ESG Risk Score": 12.51,
            "Environmental Risk Score": 3.01,
            "Social Risk Score": 4.22,
            "Governance Risk Score": 5.28,
            "Controversy Level": 1.0,
            "Peer Controversy Min": 0.0,
            "Peer Controversy Avg": 0.5583333333333333,
            "Peer Controversy Max": 3.0
        },
        "Faithfulness Evaluation": {
            "Score": 1.0,
            "Explanation": "The generated ESG report accurately reflects the provided reference ESG data for AMD. It correctly states the Total ESG Risk Score of 12.51 and breaks down the Environmental, Social, and Governance Risk Scores as 3.01, 4.22, and 5.28, respectively. The report also appropriately contextualizes these scores, noting the moderate environmental challenges typical of the semiconductor industry and highlighting the need for improvement in social and governance aspects. Additionally, the mention of a Controversy Level of 1.0 aligns with the reference data, and the comparison to peer controversy levels is accurately represented. Overall, the report is grounded in the actual data, providing a faithful and comprehensive overview of AMD's ESG performance."
        }
    },
    "NFLX": {
        "Generated Report": "Netflix, Inc. (NFLX) presents a mixed ESG profile, with a total ESG risk score of 15.88 indicating moderate potential risks. The Environmental Risk Score is notably low at 0.16, suggesting that the company has minimal direct environmental impact compared to its peers. This is a positive aspect, indicating effective management of environmental issues, especially in a sector where energy consumption for streaming services can be significant.\n\nHowever, the Social Risk Score of 7.38 raises concerns regarding the company's social practices, particularly in areas such as labor relations, content impact, and diversity. This score is considerably higher than the environmental score, highlighting potential vulnerabilities in how Netflix manages its social responsibilities, which could affect its reputation and stakeholder trust.\n\nThe Governance Risk Score of 8.35 indicates some governance challenges that may arise from issues such as board diversity, executive compensation, and shareholder rights. This score, while not excessively high, suggests room for improvement to enhance stakeholder confidence and mitigate risks associated with governance practices.\n\nThe Controversy Level of 2.0, while below the peer maximum of 3.0, signals that Netflix has faced noteworthy criticisms or controversies, which could impact its public perception and operational stability.\n\nIn summary, while Netflix excels in environmental management, it must address social and governance risks to strengthen its overall sustainability and reduce potential vulnerabilities in its operations and reputation.",
        "Reference ESG Data": {
            "Stock": "NFLX",
            "Total ESG Risk Score": 15.88,
            "Environmental Risk Score": 0.16,
            "Social Risk Score": 7.38,
            "Governance Risk Score": 8.35,
            "Controversy Level": 2.0,
            "Peer Controversy Min": 0.0,
            "Peer Controversy Avg": 1.0070921985815602,
            "Peer Controversy Max": 3.0
        },
        "Faithfulness Evaluation": {
            "Score": 0.9,
            "Explanation": "The generated ESG report accurately reflects the reference ESG data provided for Netflix, Inc. (NFLX). It correctly states the total ESG risk score of 15.88 and highlights the low Environmental Risk Score of 0.16, indicating minimal direct environmental impact. The report also appropriately discusses the higher Social Risk Score of 7.38 and Governance Risk Score of 8.35, pointing out the associated risks and areas for improvement in social and governance practices.\n\nThe mention of the Controversy Level of 2.0 is also consistent with the reference data, noting that it is below the peer maximum of 3.0, which is an important contextual detail. \n\nThe only minor issue is the phrase \"moderate potential risks\" regarding the total ESG risk score, which could be interpreted as slightly misleading since the score is relatively low compared to typical risk assessments. However, overall, the report is well-grounded in the actual data, leading to a high faithfulness score."
        }
    }
}