{
    "TSLA": {
        "Generated Report": "Tesla, Inc. (TSLA) presents a mixed picture in terms of ESG performance. With a total ESG risk score of 24.76, the company's risks are notably influenced by its Social and Governance dimensions, scoring 14.13 and 7.6, respectively. The Environmental risk score of 3.04 indicates relatively lower risks in this category, which is significant for a company that positions itself as a leader in sustainable energy and electric vehicles. \n\nHowever, the high Social risk score suggests potential challenges related to labor practices, community engagement, and other social factors. Tesla has faced scrutiny over workplace conditions, labor relations, and diversity initiatives, which could pose reputational and operational risks. \n\nThe Governance score of 7.6 indicates some concerns regarding corporate governance practices, which may affect investor confidence. The controversy level of 3.0, higher than the peer average of 1.75, highlights that Tesla is frequently in the media spotlight for issues that could impact its brand image and stakeholder trust.\n\nIn summary, while Tesla's environmental initiatives are commendable, the elevated social and governance risks warrant careful consideration. Investors should monitor these areas closely, as they may influence the company\u2019s long-term sustainability and operational effectiveness. Addressing these risks effectively could enhance Tesla's overall ESG profile and reduce potential vulnerabilities.",
        "Reference ESG Data": {
            "Stock": "TSLA",
            "Total ESG Risk Score": 24.76,
            "Environmental Risk Score": 3.04,
            "Social Risk Score": 14.13,
            "Governance Risk Score": 7.6,
            "Controversy Level": 3.0,
            "Peer Controversy Min": 0.0,
            "Peer Controversy Avg": 1.75,
            "Peer Controversy Max": 4.0
        },
        "Faithfulness Evaluation": {
            "Score": 1.0,
            "Explanation": "The generated ESG report accurately reflects the provided reference ESG data for Tesla, Inc. (TSLA). It correctly states the total ESG risk score of 24.76 and breaks down the individual scores for Environmental (3.04), Social (14.13), and Governance (7.6) risks. The report also appropriately discusses the implications of the high Social risk score and the Governance score, linking them to potential challenges and reputational risks that Tesla faces. Furthermore, it mentions the controversy level of 3.0 and compares it to the peer average of 1.75, which is consistent with the reference data. Overall, the report is well-grounded in the actual data and provides a faithful representation of Tesla's ESG performance."
        }
    },
    "NVDA": {
        "Generated Report": "NVIDIA Corporation (NVDA) presents a mixed ESG profile based on its risk scores. With a total ESG risk score of 12.46, the company exhibits moderate risks, particularly within the governance domain, which scores the highest at 5.65. This suggests potential vulnerabilities in leadership, accountability, and transparency that could affect long-term sustainability and stakeholder trust.\n\nThe environmental risk score of 2.73 indicates a relatively low impact in this area, reflecting NVIDIA's efforts to mitigate environmental impacts associated with its operations, especially in energy-intensive semiconductor manufacturing. However, continuous scrutiny on energy consumption and resource use remains critical as the company scales its production.\n\nThe social risk score of 4.08 indicates challenges related to labor practices, community engagement, or product impacts on society. This area may require further attention, especially given the increasing emphasis on social responsibility in the tech sector.\n\nNVIDIA's controversy level of 2.0, while higher than the peer average of 0.56, suggests that the company has faced some notable issues, although not at the highest severity. This level of controversy should be monitored closely, as it could impact brand reputation and stakeholder relations.\n\nOverall, while NVIDIA demonstrates a commitment to environmental sustainability, its governance and social risk scores warrant ongoing scrutiny. Investors should consider these factors when assessing the company's long-term viability and potential ESG-related risks.",
        "Reference ESG Data": {
            "Stock": "NVDA",
            "Total ESG Risk Score": 12.46,
            "Environmental Risk Score": 2.73,
            "Social Risk Score": 4.08,
            "Governance Risk Score": 5.65,
            "Controversy Level": 2.0,
            "Peer Controversy Min": 0.0,
            "Peer Controversy Avg": 0.5583333333333333,
            "Peer Controversy Max": 3.0
        },
        "Faithfulness Evaluation": {
            "Score": 1.0,
            "Explanation": "The generated ESG report accurately reflects the reference ESG data for NVIDIA Corporation (NVDA). It correctly states the total ESG risk score of 12.46 and breaks down the individual risk scores: governance at 5.65, environmental at 2.73, and social at 4.08. The report also appropriately discusses the controversy level of 2.0 in relation to the peer average of 0.56, indicating that NVIDIA has faced some notable issues but not at the highest severity. The commentary on the implications of these scores for long-term sustainability and stakeholder trust aligns well with the data provided. Overall, the report is faithful to the reference data and provides a comprehensive analysis of NVIDIA's ESG profile."
        }
    },
    "AAPL": {
        "Generated Report": "Apple Inc. (AAPL) presents a mixed picture in terms of ESG (Environmental, Social, and Governance) performance. With a total ESG risk score of 18.75, the company is positioned on the higher end of the risk spectrum. \n\n**Environmental Risk**: At 2.05, Apple's environmental risk score is relatively low, indicating that the company has made strides in sustainability initiatives, such as reducing carbon emissions and enhancing recycling programs. However, further improvements are necessary to mitigate any potential environmental impacts associated with its supply chain and product lifecycle.\n\n**Social Risk**: The social risk score of 8.35 suggests significant challenges. Apple has faced scrutiny over labor practices in its supply chain, particularly concerning worker conditions and rights. This score highlights the need for ongoing vigilance and improvement in social equity, community engagement, and labor relations.\n\n**Governance Risk**: Also at 8.35, the governance risk score points to potential issues in corporate governance, such as transparency and stakeholder engagement. Enhancing governance practices could strengthen investor confidence and align with broader sustainability goals.\n\n**Controversy Level**: A controversy level of 3.0, equal to the maximum in its peer group, indicates that AAPL has encountered notable controversies. This could impact its reputation and pose risks to investor sentiment.\n\nIn summary, while Apple has made commendable environmental efforts, its social and governance scores suggest areas of concern that could expose the company to material risks. Addressing these issues is vital for enhancing its overall ESG profile and mitigating potential financial impacts.",
        "Reference ESG Data": {
            "Stock": "AAPL",
            "Total ESG Risk Score": 18.75,
            "Environmental Risk Score": 2.05,
            "Social Risk Score": 8.35,
            "Governance Risk Score": 8.35,
            "Controversy Level": 3.0,
            "Peer Controversy Min": 0.0,
            "Peer Controversy Avg": 0.5598290598290598,
            "Peer Controversy Max": 3.0
        },
        "Faithfulness Evaluation": {
            "Score": 0.9,
            "Explanation": "The generated ESG report accurately reflects the reference ESG data for Apple Inc. (AAPL) in several key areas. The total ESG risk score of 18.75 is correctly stated, and the environmental risk score of 2.05 is described as low, which aligns with the data indicating Apple's sustainability initiatives. The social and governance risk scores of 8.35 are also accurately reported, highlighting significant challenges in these areas, particularly regarding labor practices and corporate governance.\n\nThe report's mention of the controversy level being 3.0, which is the maximum in its peer group, is also accurate and emphasizes the potential reputational risks for Apple. \n\nHowever, the report could be seen as slightly optimistic regarding the environmental initiatives without acknowledging that the low score does not eliminate the need for improvement in the environmental impact of the supply chain and product lifecycle. This nuance could have been better articulated. \n\nOverall, the report is grounded in the actual data and presents a faithful summary of Apple's ESG performance, hence the score of 0.9."
        }
    },
    "SPY": {
        "Generated Report": "No ESG data available for SPY",
        "Reference ESG Data": {
            "error": "No ESG data available for SPY"
        },
        "Faithfulness Evaluation": "Could not evaluate due to error in data or report generation."
    },
    "QQQ": {
        "Generated Report": "No ESG data available for QQQ",
        "Reference ESG Data": {
            "error": "No ESG data available for QQQ"
        },
        "Faithfulness Evaluation": "Could not evaluate due to error in data or report generation."
    },
    "META": {
        "Generated Report": "META's total ESG risk score of 32.73 indicates a moderate level of risk, with a notably high social risk score of 21.64, which suggests significant vulnerabilities in social dimensions, likely stemming from concerns related to data privacy, user safety, and content moderation. The environmental risk score of 2.41 is relatively low, indicating that META's operations may not pose substantial risks to environmental sustainability, although ongoing scrutiny regarding energy consumption and electronic waste remains pertinent.\n\nThe governance risk score of 8.68 reflects moderate concerns, potentially related to executive compensation, board diversity, and regulatory compliance. This score suggests that while there are governance challenges, they are not as severe as the social risks.\n\nMETA's controversy level of 4.0, which is aligned with the maximum level of peer controversy, indicates significant reputational risks, especially when compared to the peer average of 0.66. This heightened controversy could impact investor sentiment and stakeholder trust, particularly in light of ongoing scrutiny from regulators and public advocacy groups.\n\nOverall, while META demonstrates a strong environmental profile, the elevated social and governance risks, coupled with a high controversy score, pose considerable challenges to its long-term sustainability and could affect its operational stability and market position. Investors should closely monitor these risks and consider them in their investment decisions.",
        "Reference ESG Data": {
            "Stock": "META",
            "Total ESG Risk Score": 32.73,
            "Environmental Risk Score": 2.41,
            "Social Risk Score": 21.64,
            "Governance Risk Score": 8.68,
            "Controversy Level": 4.0,
            "Peer Controversy Min": 0.0,
            "Peer Controversy Avg": 0.6598984771573604,
            "Peer Controversy Max": 4.0
        },
        "Faithfulness Evaluation": {
            "Score": 0.9,
            "Explanation": "The generated ESG report accurately reflects the reference ESG data for META, particularly in terms of the total ESG risk score (32.73), social risk score (21.64), environmental risk score (2.41), governance risk score (8.68), and controversy level (4.0). The report effectively highlights the significant social vulnerabilities and the relatively low environmental risks, aligning well with the provided data. \n\nHowever, the statement that META demonstrates a \"strong environmental profile\" could be misleading given the low environmental risk score of 2.41, which does not necessarily imply strength but rather a lack of substantial environmental risks. This could be interpreted as an overstatement. Additionally, while the report mentions ongoing scrutiny regarding energy consumption and electronic waste, it does not elaborate on how these factors relate to the low environmental risk score, which could lead to some confusion.\n\nOverall, the report is largely faithful to the data but contains minor interpretative nuances that could mislead readers about the environmental profile. Thus, a score of 0.9 reflects its high accuracy with a slight deduction for the potential misinterpretation of the environmental risk context."
        }
    },
    "AMZN": {
        "Generated Report": "Amazon (AMZN) presents a mixed ESG profile with a total risk score of 26.1, indicating some notable concerns, particularly in the social and environmental dimensions. The Environmental Risk Score of 8.3 suggests significant challenges related to sustainability practices, particularly concerning carbon emissions, waste management, and resource use. Given the company's size and operations, it faces increasing scrutiny regarding its environmental impact and commitments to climate change mitigation.\n\nThe Social Risk Score of 11.05 is particularly concerning, highlighting issues related to labor practices, employee welfare, and community relations. Reports of workplace conditions and treatment of employees have drawn criticism, which can lead to reputational damage and regulatory scrutiny.\n\nThe Governance Risk Score of 6.75 shows moderate concerns, indicating potential issues in board diversity, executive compensation, and shareholder rights. Governance practices are essential for ensuring accountability and ethical behavior, especially for a company of Amazon\u2019s scale.\n\nThe Controversy Level of 3.0, significantly above the peer average of 0.91, indicates that Amazon has faced considerable public and media scrutiny, which can affect investor sentiment and lead to increased regulatory oversight.\n\nIn summary, while Amazon shows potential for growth, its elevated risk scores in environmental and social categories, combined with a high controversy level, suggest significant sustainability challenges and potential risks that investors should closely monitor.",
        "Reference ESG Data": {
            "Stock": "AMZN",
            "Total ESG Risk Score": 26.1,
            "Environmental Risk Score": 8.3,
            "Social Risk Score": 11.05,
            "Governance Risk Score": 6.75,
            "Controversy Level": 3.0,
            "Peer Controversy Min": 0.0,
            "Peer Controversy Avg": 0.9104477611940298,
            "Peer Controversy Max": 4.0
        },
        "Faithfulness Evaluation": {
            "Score": 1.0,
            "Explanation": "The generated ESG report accurately reflects the provided reference ESG data for Amazon (AMZN). It correctly states the total ESG risk score of 26.1 and provides detailed breakdowns of the Environmental Risk Score (8.3), Social Risk Score (11.05), and Governance Risk Score (6.75), all of which align with the reference data. The report also appropriately highlights the controversy level of 3.0 and compares it to the peer average, emphasizing the significant public and media scrutiny Amazon faces. Overall, the report is faithful to the actual data, providing a clear and accurate representation of Amazon's ESG profile without introducing any inaccuracies or misleading information."
        }
    },
    "TQQQ": {
        "Generated Report": "No ESG data available for TQQQ",
        "Reference ESG Data": {
            "error": "No ESG data available for TQQQ"
        },
        "Faithfulness Evaluation": "Could not evaluate due to error in data or report generation."
    },
    "AMD": {
        "Generated Report": "Advanced Micro Devices (AMD) exhibits a Total ESG Risk Score of 12.51, which suggests a moderate level of risk in its environmental, social, and governance practices. The Environmental Risk Score of 3.01 indicates that while AMD is aware of its environmental impact, there is still room for improvement, particularly in reducing its carbon footprint and enhancing resource efficiency.\n\nThe Social Risk Score of 4.22 reflects AMD's commitment to social responsibility but highlights potential vulnerabilities related to workforce issues, community engagement, or product safety. As a leading semiconductor manufacturer, AMD must continue to focus on fair labor practices and diversity initiatives to mitigate risks associated with employee relations and societal expectations.\n\nThe Governance Risk Score of 5.28 is the highest among the ESG categories, suggesting potential challenges in corporate governance structures and practices. This score underscores the importance of strong leadership, transparency, and ethical business conduct to maintain investor confidence and regulatory compliance.\n\nWith a Controversy Level of 1.0, AMD maintains a relatively low profile in terms of public disputes compared to its peers, where the average controversy level stands at approximately 0.56. This indicates that the company has managed to avoid significant scandals or operational disruptions.\n\nOverall, while AMD shows a commitment to sustainability, it faces risks that require continuous monitoring and proactive management to enhance its ESG performance and mitigate potential reputational impacts.",
        "Reference ESG Data": {
            "Stock": "AMD",
            "Total ESG Risk Score": 12.51,
            "Environmental Risk Score": 3.01,
            "Social Risk Score": 4.22,
            "Governance Risk Score": 5.28,
            "Controversy Level": 1.0,
            "Peer Controversy Min": 0.0,
            "Peer Controversy Avg": 0.5583333333333333,
            "Peer Controversy Max": 3.0
        },
        "Faithfulness Evaluation": {
            "Score": 1.0,
            "Explanation": "The generated ESG report accurately reflects the provided reference ESG data for AMD. The Total ESG Risk Score of 12.51 is correctly stated, and the breakdown of the Environmental, Social, and Governance Risk Scores (3.01, 4.22, and 5.28, respectively) aligns perfectly with the reference data. The report also appropriately contextualizes these scores, discussing AMD's environmental impact, social responsibility, and governance challenges in a manner that is consistent with the numerical values provided. Furthermore, the Controversy Level of 1.0 is accurately noted, and the comparison to peer controversy levels is correctly articulated. Overall, the report is grounded in the actual data, demonstrating a comprehensive understanding of AMD's ESG profile."
        }
    },
    "NFLX": {
        "Generated Report": "Netflix (NFLX) exhibits an overall ESG risk score of 15.88, indicating notable sustainability challenges, particularly on social and governance fronts. The environmental risk score is relatively low at 0.16, suggesting that the company's operations have minimal direct environmental impact. However, the social risk score of 7.38 raises concerns about issues such as labor practices, content diversity, and community engagement. This score is significantly higher than the average for its peers, which reflects a heightened vulnerability to social risk factors.\n\nGovernance is another area of concern, with a risk score of 8.35. This indicates potential weaknesses in corporate governance practices, which may include board diversity, executive compensation, and shareholder rights. The controversy level of 2.0 suggests that NFLX has faced moderate controversy, which is above the peer average of 1.01, implying that the company has encountered significant challenges in maintaining its reputation.\n\nOverall, while Netflix's environmental impact is minimal, the elevated social and governance risk scores highlight critical areas that could affect its long-term sustainability and investor confidence. The company should prioritize addressing these social and governance issues to mitigate potential risks and enhance its ESG performance. Promoting transparency in governance and fostering inclusive practices could be vital steps in improving its standing in the ESG landscape.",
        "Reference ESG Data": {
            "Stock": "NFLX",
            "Total ESG Risk Score": 15.88,
            "Environmental Risk Score": 0.16,
            "Social Risk Score": 7.38,
            "Governance Risk Score": 8.35,
            "Controversy Level": 2.0,
            "Peer Controversy Min": 0.0,
            "Peer Controversy Avg": 1.0070921985815602,
            "Peer Controversy Max": 3.0
        },
        "Faithfulness Evaluation": {
            "Score": 1.0,
            "Explanation": "The generated ESG report accurately reflects the reference ESG data for Netflix (NFLX). It correctly states the overall ESG risk score of 15.88 and provides a precise breakdown of the environmental risk score (0.16), social risk score (7.38), and governance risk score (8.35). The report also appropriately highlights the concerns related to social and governance aspects, aligning with the provided data. Furthermore, it mentions the controversy level of 2.0 and compares it accurately to the peer average of 1.01, indicating a proper understanding of the company's standing relative to its peers. Overall, the report is grounded in the actual data and presents a faithful representation of Netflix's ESG performance."
        }
    }
}