{
    "TSLA": {
        "Generated Report": "Tesla Inc. (TSLA) presents a mixed ESG profile, with a Total ESG Risk Score of 24.76 indicating moderate overall risk. The Environmental Risk Score of 3.04 is relatively low, suggesting that Tesla's core business model\u2014electric vehicles and renewable energy solutions\u2014aligns well with environmental sustainability goals. This score reflects the company's commitment to reducing carbon emissions and promoting clean energy technologies.\n\nHowever, the Social Risk Score of 14.13 raises significant concerns. This score indicates potential issues related to labor practices, workplace safety, and community engagement. Tesla has faced scrutiny over its treatment of workers, particularly regarding labor conditions in its manufacturing facilities. Addressing these social risks will be crucial for the company\u2019s long-term sustainability and reputation.\n\nThe Governance Risk Score of 7.6 suggests some challenges in corporate governance practices, which may include issues related to executive compensation, board diversity, or shareholder rights. With a Controversy Level of 3.0, Tesla is positioned above the peer average (1.75), indicating that it has been involved in various public controversies, which could further impact its reputation and stakeholder trust.\n\nIn conclusion, while Tesla is well-positioned in the environmental domain, it must proactively address social and governance issues to mitigate risks and enhance its sustainability profile. Continued vigilance and improvement in these areas are essential for maintaining investor confidence and achieving long-term success.",
        "Reference ESG Data": {
            "Stock": "TSLA",
            "Total ESG Risk Score": 24.76,
            "Environmental Risk Score": 3.04,
            "Social Risk Score": 14.13,
            "Governance Risk Score": 7.6,
            "Controversy Level": 3.0,
            "Peer Controversy Min": 0.0,
            "Peer Controversy Avg": 1.75,
            "Peer Controversy Max": 4.0
        },
        "Faithfulness Evaluation": {
            "Score": 1.0,
            "Explanation": "The generated ESG report accurately reflects the reference ESG data for Tesla Inc. (TSLA). It correctly states the Total ESG Risk Score of 24.76 and provides a detailed breakdown of the Environmental Risk Score (3.04), Social Risk Score (14.13), and Governance Risk Score (7.6). The report also appropriately contextualizes these scores, highlighting Tesla's strengths in environmental sustainability while addressing significant concerns in social and governance aspects. Furthermore, the mention of the Controversy Level of 3.0 and its comparison to the peer average (1.75) is precise and relevant. Overall, the report is grounded in the actual data and presents a faithful representation of Tesla's ESG profile."
        }
    },
    "NVDA": {
        "Generated Report": "NVIDIA Corporation (NVDA) presents a mixed ESG profile, with a total ESG risk score of 12.46, suggesting a moderate level of overall risk. The Environmental Risk Score of 2.73 is relatively low, indicating that the company is likely managing its environmental impact effectively, which is crucial for a technology firm in the semiconductor industry, known for its energy consumption and resource use.\n\nHowever, the Social Risk Score of 4.08 is higher, reflecting potential concerns related to labor practices, community engagement, or product safety. This score indicates areas where NVDA may need to enhance its social responsibility initiatives to mitigate risks associated with workforce management and stakeholder relations.\n\nThe Governance Risk Score of 5.65 is the highest among the three categories, suggesting that there may be issues related to board structure, management practices, or shareholder rights. Strong governance is essential for maintaining investor confidence and ensuring long-term sustainability.\n\nWith a Controversy Level of 2.0, NVDA experiences a moderate level of public scrutiny, with potential implications for its reputation and market performance. This level is notably higher than the peer average of 0.56, indicating that NVDA is facing more challenges than its competitors.\n\nIn summary, while NVDA shows strengths in environmental management, it faces notable social and governance risks that could impact its sustainability and investor perception in the long term. Addressing these areas will be crucial for enhancing its overall ESG standing.",
        "Reference ESG Data": {
            "Stock": "NVDA",
            "Total ESG Risk Score": 12.46,
            "Environmental Risk Score": 2.73,
            "Social Risk Score": 4.08,
            "Governance Risk Score": 5.65,
            "Controversy Level": 2.0,
            "Peer Controversy Min": 0.0,
            "Peer Controversy Avg": 0.5583333333333333,
            "Peer Controversy Max": 3.0
        },
        "Faithfulness Evaluation": {
            "Score": 1.0,
            "Explanation": "The generated ESG report accurately reflects the provided reference ESG data for NVIDIA Corporation (NVDA). It correctly states the total ESG risk score of 12.46 and breaks down the environmental, social, and governance risk scores as 2.73, 4.08, and 5.65, respectively. The report also appropriately discusses the implications of these scores, highlighting the company's strengths in environmental management while acknowledging the higher social and governance risks. Additionally, the mention of a controversy level of 2.0 and its comparison to the peer average of 0.56 is accurate. Overall, the report is grounded in the actual data and provides a faithful representation of NVDA's ESG profile."
        }
    },
    "AAPL": {
        "Generated Report": "Apple Inc. (AAPL) exhibits a total ESG risk score of 18.75, indicating a moderate level of risk in its environmental, social, and governance practices. The environmental risk score of 2.05 suggests relatively low exposure to environmental risks, reflecting the company's initiatives in renewable energy and sustainable product design. However, the social and governance risk scores, both at 8.35, highlight significant concerns in these areas.\n\nThe social risk score reflects potential issues related to labor practices, supply chain management, and product accessibility, which may affect Apple's reputation and operational stability. The governance score indicates potential risks related to board diversity, executive compensation, and shareholder rights, which could impact investor confidence and corporate decision-making.\n\nThe controversy level of 3.0 is concerning, particularly as it aligns with the upper limit of peer controversy, suggesting that Apple faces notable public scrutiny compared to its industry peers. This level of controversy could arise from various factors, including labor practices in its supply chain, environmental impacts, and data privacy issues.\n\nIn conclusion, while Apple demonstrates a strong commitment to environmental sustainability, its elevated social and governance risk scores, coupled with a high controversy level, indicate that the company must address these concerns proactively. Failure to do so could pose risks to its reputation, regulatory compliance, and long-term financial performance.",
        "Reference ESG Data": {
            "Stock": "AAPL",
            "Total ESG Risk Score": 18.75,
            "Environmental Risk Score": 2.05,
            "Social Risk Score": 8.35,
            "Governance Risk Score": 8.35,
            "Controversy Level": 3.0,
            "Peer Controversy Min": 0.0,
            "Peer Controversy Avg": 0.5598290598290598,
            "Peer Controversy Max": 3.0
        },
        "Faithfulness Evaluation": {
            "Score": 1.0,
            "Explanation": "The generated ESG report accurately reflects the reference ESG data for Apple Inc. (AAPL). It correctly states the total ESG risk score of 18.75 and the individual risk scores for environmental (2.05), social (8.35), and governance (8.35). The report also appropriately discusses the implications of these scores, particularly the significant concerns in social and governance areas, which are consistent with the provided data. Furthermore, the controversy level of 3.0 is accurately noted, along with its implications regarding public scrutiny. Overall, the report is grounded in the actual data and provides a faithful representation of Apple's ESG performance."
        }
    },
    "SPY": {
        "Generated Report": "No ESG data available for SPY",
        "Reference ESG Data": {
            "error": "No ESG data available for SPY"
        },
        "Faithfulness Evaluation": "Could not evaluate due to error in data or report generation."
    },
    "QQQ": {
        "Generated Report": "No ESG data available for QQQ",
        "Reference ESG Data": {
            "error": "No ESG data available for QQQ"
        },
        "Faithfulness Evaluation": "Could not evaluate due to error in data or report generation."
    },
    "META": {
        "Generated Report": "META's total ESG risk score of 32.73 indicates a moderate level of risk, with particular emphasis on social and governance aspects. The environmental risk score is relatively low at 2.41, suggesting that the company has minimal environmental impact compared to its peers. However, the social risk score of 21.64 is significantly higher, indicating potential concerns related to its impact on employees, customers, and broader societal issues. This score reflects ongoing criticisms regarding privacy, misinformation, and user safety on its platforms.\n\nThe governance risk score of 8.68 points to challenges in corporate governance practices, which may include issues related to board diversity, executive compensation, and shareholder rights. The controversy level of 4.0 is notable, especially when compared to the peer controversy average of 0.66. This high level of controversy suggests that META is frequently in the spotlight for negative reasons, which could affect investor confidence and public perception.\n\nIn summary, while META's environmental performance appears sound, the elevated social and governance risks warrant attention. The company faces significant reputational challenges due to controversies, which could translate into regulatory and operational risks. Investors should closely monitor developments in these areas to assess potential impacts on META's long-term sustainability and financial performance.",
        "Reference ESG Data": {
            "Stock": "META",
            "Total ESG Risk Score": 32.73,
            "Environmental Risk Score": 2.41,
            "Social Risk Score": 21.64,
            "Governance Risk Score": 8.68,
            "Controversy Level": 4.0,
            "Peer Controversy Min": 0.0,
            "Peer Controversy Avg": 0.6598984771573604,
            "Peer Controversy Max": 4.0
        },
        "Faithfulness Evaluation": {
            "Score": 1.0,
            "Explanation": "The generated ESG report accurately reflects the provided reference ESG data for META. It correctly states the total ESG risk score of 32.73 and provides a clear breakdown of the environmental risk score (2.41), social risk score (21.64), and governance risk score (8.68). The report also appropriately highlights the high controversy level of 4.0, particularly in comparison to the peer controversy average of 0.66, which underscores the company's challenges in maintaining a positive public image. The interpretations regarding the implications of these scores on investor confidence and the company's long-term sustainability are well-founded and align with the reference data. Overall, the report is faithful to the actual data provided."
        }
    },
    "AMZN": {
        "Generated Report": "Amazon (AMZN) presents a mixed ESG profile with a Total ESG Risk Score of 26.1. The Environmental Risk Score of 8.3 indicates that while the company faces some environmental challenges, it is relatively moderate compared to industry peers. However, ongoing concerns regarding its carbon footprint and packaging waste remain significant, especially in a market increasingly focused on sustainability.\n\nThe Social Risk Score of 11.05 is notably higher and suggests that Amazon faces considerable scrutiny over labor practices, employee treatment, and community relations. High-profile controversies regarding working conditions in warehouses and employee protests have fueled this score, impacting its reputation and potentially leading to regulatory challenges.\n\nThe Governance Risk Score of 6.75 is relatively low, indicating that the company's governance structures are comparatively sound. However, the Controversy Level of 3.0, which exceeds the peer average of 0.91, highlights that Amazon is frequently embroiled in significant public and media scrutiny. This level of controversy can lead to reputational risks and potential financial implications.\n\nIn summary, while Amazon has made strides in addressing environmental and governance issues, its elevated social risk and high controversy level indicate substantial challenges that could affect its long-term sustainability and investor confidence. Stakeholders should monitor these risks closely as the company navigates a complex ESG landscape.",
        "Reference ESG Data": {
            "Stock": "AMZN",
            "Total ESG Risk Score": 26.1,
            "Environmental Risk Score": 8.3,
            "Social Risk Score": 11.05,
            "Governance Risk Score": 6.75,
            "Controversy Level": 3.0,
            "Peer Controversy Min": 0.0,
            "Peer Controversy Avg": 0.9104477611940298,
            "Peer Controversy Max": 4.0
        },
        "Faithfulness Evaluation": {
            "Score": 1.0,
            "Explanation": "The generated ESG report accurately reflects the provided reference ESG data for Amazon (AMZN). It correctly states the Total ESG Risk Score of 26.1 and breaks down the Environmental Risk Score (8.3), Social Risk Score (11.05), and Governance Risk Score (6.75) in a manner that aligns with the reference data. The commentary on environmental challenges, social scrutiny, and governance structures is consistent with the scores provided. Additionally, the report appropriately highlights the Controversy Level of 3.0 and its implications, noting that it exceeds the peer average of 0.91. Overall, the report is faithful to the reference data, providing a comprehensive and accurate assessment of Amazon's ESG profile."
        }
    },
    "TQQQ": {
        "Generated Report": "No ESG data available for TQQQ",
        "Reference ESG Data": {
            "error": "No ESG data available for TQQQ"
        },
        "Faithfulness Evaluation": "Could not evaluate due to error in data or report generation."
    },
    "AMD": {
        "Generated Report": "AMD (Advanced Micro Devices) has a Total ESG Risk Score of 12.51, indicating that it faces moderate risks across environmental, social, and governance dimensions. The Environmental Risk Score of 3.01 suggests that while AMD is not a significant polluter, it still has room for improvement in resource management and minimizing environmental impact, particularly in areas like energy consumption and waste management.\n\nThe Social Risk Score of 4.22 highlights potential concerns related to labor practices, community engagement, and product responsibility. A focus on diversity, equity, and inclusion within the workforce may be beneficial for AMD to enhance its social standing and mitigate risks associated with employee relations.\n\nThe Governance Risk Score of 5.28 indicates that while governance practices are in place, there may be opportunities to strengthen transparency and accountability. This score is critical, as governance failures can significantly impact overall corporate reputation and stakeholder trust.\n\nWith a Controversy Level of 1.0, AMD is relatively low on the controversy spectrum compared to peers (min: 0.0, avg: 0.56, max: 3.0). This suggests that the company has managed to avoid major scandals, which is a positive indicator for investors concerned about reputational risks.\n\nOverall, while AMD shows potential in its sustainability efforts, it must address its social and governance risks to improve its ESG profile and mitigate potential future challenges.",
        "Reference ESG Data": {
            "Stock": "AMD",
            "Total ESG Risk Score": 12.51,
            "Environmental Risk Score": 3.01,
            "Social Risk Score": 4.22,
            "Governance Risk Score": 5.28,
            "Controversy Level": 1.0,
            "Peer Controversy Min": 0.0,
            "Peer Controversy Avg": 0.5583333333333333,
            "Peer Controversy Max": 3.0
        },
        "Faithfulness Evaluation": {
            "Score": 1.0,
            "Explanation": "The generated ESG report accurately reflects the reference ESG data for AMD. It correctly states the Total ESG Risk Score of 12.51 and provides detailed breakdowns of the Environmental, Social, and Governance Risk Scores, which align with the reference data (3.01, 4.22, and 5.28, respectively). The report also appropriately contextualizes the Controversy Level of 1.0, comparing it to peer averages and indicating a relatively low level of controversy. Furthermore, the report's insights into areas for improvement in environmental management, social practices, and governance transparency are consistent with the scores provided. Overall, the report is faithful to the actual data, making it a reliable summary of AMD's ESG performance."
        }
    },
    "NFLX": {
        "Generated Report": "Netflix (NFLX) presents a mixed picture in terms of ESG (Environmental, Social, and Governance) risk. With a total ESG Risk Score of 15.88, the company exhibits moderate risk, particularly in the social and governance dimensions, which are significantly higher than its environmental risk score.\n\nThe **Environmental Risk Score of 0.16** indicates minimal exposure to environmental issues, suggesting that Netflix is not heavily burdened by ecological concerns compared to its peers. This is a positive indicator of its sustainability practices, although the company could benefit from enhancing its environmental initiatives to align with broader industry trends.\n\nIn contrast, the **Social Risk Score of 7.38** and **Governance Risk Score of 8.35** suggest that Netflix faces considerable challenges in these areas. Socially, the company may need to address concerns related to workforce diversity, labor practices, and content inclusivity. Governance risks may stem from issues like board diversity, executive compensation, and regulatory compliance.\n\nThe **Controversy Level of 2.0**, while lower than the maximum of 3.0, is above the peer average of 1.007, indicating that Netflix has faced notable controversies that could impact its reputation and stakeholder trust.\n\nIn summary, while Netflix shows strength in environmental practices, it must address its social and governance risks to enhance its overall sustainability and mitigate potential reputational and operational risks. Continued focus on these areas will be critical for maintaining investor confidence and long-term viability.",
        "Reference ESG Data": {
            "Stock": "NFLX",
            "Total ESG Risk Score": 15.88,
            "Environmental Risk Score": 0.16,
            "Social Risk Score": 7.38,
            "Governance Risk Score": 8.35,
            "Controversy Level": 2.0,
            "Peer Controversy Min": 0.0,
            "Peer Controversy Avg": 1.0070921985815602,
            "Peer Controversy Max": 3.0
        },
        "Faithfulness Evaluation": {
            "Score": 0.9,
            "Explanation": "The generated ESG report accurately reflects the reference ESG data for Netflix (NFLX) in several key areas, including the total ESG Risk Score (15.88), Environmental Risk Score (0.16), Social Risk Score (7.38), Governance Risk Score (8.35), and Controversy Level (2.0). The report correctly identifies the company\u2019s strengths and weaknesses, particularly noting the minimal environmental risk and the higher social and governance risks. \n\nHowever, the report could improve in its contextualization of the controversy level, as it mentions that Netflix's controversy level is \"lower than the maximum of 3.0,\" but it does not explicitly state that this level is still above the peer average of 1.007, which is a significant point. Additionally, while the report suggests that Netflix is not heavily burdened by ecological concerns, it could have emphasized that the environmental score is notably low compared to industry standards, which might imply a lack of proactive environmental initiatives rather than just a \"positive indicator.\" \n\nOverall, the report is largely faithful to the reference data, with only minor areas for improvement in clarity and emphasis, justifying a score of 0.9."
        }
    }
}