{
    "TSLA": {
        "Generated Report": "Tesla, Inc. (TSLA) presents a mixed ESG profile with a total ESG risk score of 24.76, indicating notable risks in its operational practices. The Environmental Risk Score is relatively low at 3.04, reflective of Tesla's core mission to promote sustainable energy through electric vehicles and renewable energy products. This positions the company favorably within the environmental domain, emphasizing its commitment to reducing carbon emissions.\n\nHowever, the Social Risk Score is significantly higher at 14.13, suggesting potential vulnerabilities in areas such as labor practices, community relations, and stakeholder engagement. This elevated score may stem from criticisms regarding workplace conditions and employee treatment, which could pose reputational and operational risks.\n\nThe Governance Risk Score of 7.6 indicates moderate concerns related to board structure, executive compensation, and shareholder rights, which can affect investor confidence and company stability. The controversy level of 3.0 is above the peer average of 1.75, indicating that Tesla faces heightened scrutiny compared to its industry peers. This may impact its long-term sustainability if not addressed effectively.\n\nIn summary, while Tesla is positioned as a leader in environmental sustainability, its social and governance challenges could pose significant risks. Investors should remain vigilant regarding these aspects, as they may affect the company's reputation and operational efficiency moving forward.",
        "Reference ESG Data": {
            "Stock": "TSLA",
            "Total ESG Risk Score": 24.76,
            "Environmental Risk Score": 3.04,
            "Social Risk Score": 14.13,
            "Governance Risk Score": 7.6,
            "Controversy Level": 3.0,
            "Peer Controversy Min": 0.0,
            "Peer Controversy Avg": 1.75,
            "Peer Controversy Max": 4.0
        },
        "Faithfulness Evaluation": {
            "Score": 1.0,
            "Explanation": "The generated ESG report accurately reflects the provided reference ESG data for Tesla, Inc. (TSLA). It correctly states the total ESG risk score of 24.76 and breaks down the Environmental Risk Score (3.04), Social Risk Score (14.13), and Governance Risk Score (7.6) in a coherent manner. The report also appropriately highlights the controversy level of 3.0 and compares it to the peer average of 1.75, indicating a higher level of scrutiny faced by Tesla. The analysis of risks related to environmental sustainability, social practices, and governance is well-grounded in the data provided, making the report faithful to the actual ESG metrics."
        }
    },
    "NVDA": {
        "Generated Report": "NVIDIA Corporation (NVDA) presents a mixed ESG profile based on its total risk score of 12.46, which indicates a moderate level of sustainability risk. The Environmental Risk Score of 2.73 suggests that the company faces relatively low environmental risks, which may be attributed to its efforts in energy efficiency and sustainable practices in semiconductor manufacturing. \n\nHowever, the Social Risk Score of 4.08 indicates potential vulnerabilities in areas such as labor practices, community relations, or product responsibility. This score suggests that the company could face challenges related to its workforce or the societal impacts of its products, particularly given the growing emphasis on responsible AI usage and data privacy.\n\nThe Governance Risk Score of 5.65 is the highest among the three categories, pointing to possible concerns regarding board diversity, executive compensation, or shareholder rights. Governance practices are critical for long-term sustainability, and this score may reflect the need for NVDA to enhance its governance frameworks.\n\nThe Controversy Level of 2.0, while above the average of its peers (0.56), indicates that NVDA has faced some notable controversies, albeit not the highest in its sector. This suggests that while there are areas for improvement, the company is not embroiled in significant reputational crises.\n\nIn summary, while NVDA demonstrates strengths in environmental management, it should address social and governance risks to bolster its sustainability profile and mitigate potential future risks.",
        "Reference ESG Data": {
            "Stock": "NVDA",
            "Total ESG Risk Score": 12.46,
            "Environmental Risk Score": 2.73,
            "Social Risk Score": 4.08,
            "Governance Risk Score": 5.65,
            "Controversy Level": 2.0,
            "Peer Controversy Min": 0.0,
            "Peer Controversy Avg": 0.5583333333333333,
            "Peer Controversy Max": 3.0
        },
        "Faithfulness Evaluation": {
            "Score": 1.0,
            "Explanation": "The generated ESG report accurately reflects the provided reference ESG data for NVIDIA Corporation (NVDA). The total ESG Risk Score of 12.46 is correctly identified as indicating a moderate level of sustainability risk. The individual scores for Environmental (2.73), Social (4.08), and Governance (5.65) risks are also accurately reported, along with their implications for the company's sustainability practices. The report appropriately contextualizes the Controversy Level of 2.0 in relation to peer averages, indicating that while NVDA has faced some controversies, it is not at the highest end of the spectrum. Overall, the report is grounded in the actual data, providing a faithful representation of NVDA's ESG profile."
        }
    },
    "AAPL": {
        "Generated Report": "Apple Inc. (AAPL) exhibits an overall Total ESG Risk Score of 18.75, indicating a moderate level of ESG risk. The Environmental Risk Score of 2.05 suggests that while the company has made strides in sustainability, there remains room for improvement, particularly in reducing its carbon footprint and managing electronic waste. \n\nThe Social Risk Score of 8.35 points to significant challenges in areas such as labor practices and supply chain management, especially concerning working conditions in overseas factories. This score reflects ongoing scrutiny over labor rights, which can pose reputational risks and affect consumer perception.\n\nThe Governance Risk Score, also at 8.35, indicates potential concerns related to corporate governance practices. Investors may want to examine board diversity, executive compensation, and shareholder rights, as these elements can impact long-term sustainability and risk management.\n\nWith a Controversy Level of 3.0, AAPL is at the high end of the scale compared to peers, where the average controversy level is approximately 0.56. This suggests that AAPL has faced significant public criticism or legal challenges, which could impact its brand reputation and investor sentiment.\n\nIn summary, while AAPL demonstrates strengths in certain ESG areas, its elevated social and governance risks, coupled with a higher-than-average controversy level, warrant careful consideration from investors regarding long-term sustainability and potential reputational risks.",
        "Reference ESG Data": {
            "Stock": "AAPL",
            "Total ESG Risk Score": 18.75,
            "Environmental Risk Score": 2.05,
            "Social Risk Score": 8.35,
            "Governance Risk Score": 8.35,
            "Controversy Level": 3.0,
            "Peer Controversy Min": 0.0,
            "Peer Controversy Avg": 0.5598290598290598,
            "Peer Controversy Max": 3.0
        },
        "Faithfulness Evaluation": {
            "Score": 1.0,
            "Explanation": "The generated ESG report accurately reflects the provided reference ESG data for Apple Inc. (AAPL). It correctly states the Total ESG Risk Score of 18.75 and breaks down the Environmental, Social, and Governance Risk Scores as 2.05, 8.35, and 8.35, respectively. The report also appropriately highlights the significant social challenges and governance concerns, aligning with the scores provided. Furthermore, it accurately notes the Controversy Level of 3.0 and compares it to the peer average, emphasizing the implications for brand reputation and investor sentiment. Overall, the report is faithful to the reference data, providing a clear and accurate representation of AAPL's ESG performance."
        }
    },
    "SPY": {
        "Generated Report": "No ESG data available for SPY",
        "Reference ESG Data": {
            "error": "No ESG data available for SPY"
        },
        "Faithfulness Evaluation": "Could not evaluate due to error in data or report generation."
    },
    "QQQ": {
        "Generated Report": "No ESG data available for QQQ",
        "Reference ESG Data": {
            "error": "No ESG data available for QQQ"
        },
        "Faithfulness Evaluation": "Could not evaluate due to error in data or report generation."
    },
    "META": {
        "Generated Report": "META's total ESG risk score of 32.73 suggests a moderate level of risk, with a notably high social risk score of 21.64 indicating significant challenges in this area. The social dimension may reflect issues related to user privacy, data security, and the impact of its platforms on social dynamics, including misinformation and mental health concerns. This elevated social risk requires ongoing scrutiny, as it could lead to regulatory actions or reputational damage.\n\nThe environmental risk score of 2.41 indicates that META faces relatively low exposure in this domain, which is positive, especially compared to its peers. However, the company should remain vigilant in its sustainability initiatives, particularly as it scales operations and addresses environmental impacts associated with data centers and energy consumption.\n\nThe governance risk score of 8.68 points to potential vulnerabilities in corporate governance practices, which can affect stakeholder trust and operational effectiveness. This is particularly relevant given the increasing investor focus on accountability and transparency.\n\nThe controversy level of 4.0 is concerning, especially in comparison to the peer average of 0.66. This high level of controversy suggests that META has been involved in significant public disputes or criticisms, which could impact investor sentiment and regulatory scrutiny.\n\nIn summary, while META demonstrates strengths in environmental sustainability, the elevated social and governance risks, along with a high controversy level, pose significant challenges that could affect the company's long-term sustainability and reputation. Active management of these risks is essential for maintaining investor confidence and regulatory compliance.",
        "Reference ESG Data": {
            "Stock": "META",
            "Total ESG Risk Score": 32.73,
            "Environmental Risk Score": 2.41,
            "Social Risk Score": 21.64,
            "Governance Risk Score": 8.68,
            "Controversy Level": 4.0,
            "Peer Controversy Min": 0.0,
            "Peer Controversy Avg": 0.6598984771573604,
            "Peer Controversy Max": 4.0
        },
        "Faithfulness Evaluation": {
            "Score": 1.0,
            "Explanation": "The generated ESG report accurately reflects the reference ESG data provided for META. It correctly states the total ESG risk score of 32.73 and breaks down the individual risk scores for environmental (2.41), social (21.64), and governance (8.68) aspects, aligning perfectly with the reference data. The commentary on the implications of the social risk, environmental initiatives, governance vulnerabilities, and the controversy level (4.0) is well-grounded in the data. Additionally, the report appropriately compares the controversy level to the peer average, highlighting the significant disparity. Overall, the report is comprehensive and faithful to the actual ESG data, warranting a perfect score."
        }
    },
    "AMZN": {
        "Generated Report": "Amazon (AMZN) presents a mixed ESG profile based on its total risk score of 26.1, with notable strengths and weaknesses across environmental, social, and governance dimensions. \n\nThe Environmental Risk Score of 8.3 indicates some challenges, particularly related to carbon emissions, waste management, and resource consumption, which are critical in the context of the company's extensive logistics and operations. However, the company's ongoing investments in renewable energy and sustainability initiatives may help mitigate these risks over time.\n\nSocially, the score of 11.05 is concerning, reflecting issues related to labor practices, employee treatment, and community impact. Given Amazon's size, scrutiny surrounding worker conditions and compensation is significant and could pose reputational risks if not addressed adequately.\n\nOn the governance front, the score of 6.75 suggests moderate risks, possibly related to board diversity and executive compensation structures. The company's governance practices will be pivotal in navigating regulatory landscapes and stakeholder expectations.\n\nThe controversy level of 3.0, significantly above the peer average of 0.91, highlights that Amazon faces substantial scrutiny and criticism, which could affect its brand and investor relations. Companies with high controversy levels may experience volatility in stock performance due to reputational damage or regulatory challenges.\n\nIn summary, while Amazon is making strides in sustainability, significant risks remain that could impact its long-term viability and reputation. Addressing these ESG concerns proactively will be crucial for mitigating risks and enhancing stakeholder trust.",
        "Reference ESG Data": {
            "Stock": "AMZN",
            "Total ESG Risk Score": 26.1,
            "Environmental Risk Score": 8.3,
            "Social Risk Score": 11.05,
            "Governance Risk Score": 6.75,
            "Controversy Level": 3.0,
            "Peer Controversy Min": 0.0,
            "Peer Controversy Avg": 0.9104477611940298,
            "Peer Controversy Max": 4.0
        },
        "Faithfulness Evaluation": {
            "Score": 1.0,
            "Explanation": "The generated ESG report accurately reflects the reference ESG data for Amazon (AMZN). It correctly states the total ESG Risk Score of 26.1 and breaks down the Environmental (8.3), Social (11.05), and Governance (6.75) Risk Scores, aligning perfectly with the provided data. The report also appropriately addresses the controversy level of 3.0 and contextualizes it against the peer average of 0.91, highlighting the significant scrutiny Amazon faces. The discussion of risks and potential mitigation strategies is consistent with the scores presented, demonstrating a faithful representation of the actual data. Overall, the report is well-grounded in the reference data, warranting a perfect faithfulness score."
        }
    },
    "TQQQ": {
        "Generated Report": "No ESG data available for TQQQ",
        "Reference ESG Data": {
            "error": "No ESG data available for TQQQ"
        },
        "Faithfulness Evaluation": "Could not evaluate due to error in data or report generation."
    },
    "AMD": {
        "Generated Report": "AMD's total ESG Risk Score of 12.51 indicates a moderate level of risk, suggesting that while the company is addressing some sustainability issues, there are areas that require attention. Breaking down the scores, the Environmental Risk Score of 3.01 is relatively low, reflecting AMD's commitment to sustainable practices, possibly through initiatives like energy-efficient product designs and reducing carbon emissions. However, this area still holds potential for improvement, especially as the tech industry faces increasing scrutiny over environmental impacts.\n\nThe Social Risk Score of 4.22 is moderate, indicating potential challenges related to workplace practices, community engagement, or product responsibility. This suggests that AMD may need to enhance its policies or initiatives addressing employee welfare, diversity, and inclusion.\n\nThe Governance Risk Score of 5.28 is the highest among the three categories, indicating notable risks in corporate governance that could impact investor confidence. This could relate to board diversity, executive compensation practices, or transparency issues.\n\nAMD's controversy level of 1.0, while above the minimum peer controversy score of 0.0, is significantly lower than the peer average of 0.56, suggesting that the company has navigated controversies better than many of its peers. Nonetheless, continuous monitoring and proactive measures in governance and social practices will be essential for mitigating risks and enhancing overall sustainability. In conclusion, while AMD demonstrates a commitment to ESG principles, addressing governance and social factors will be key to improving its long-term sustainability profile.",
        "Reference ESG Data": {
            "Stock": "AMD",
            "Total ESG Risk Score": 12.51,
            "Environmental Risk Score": 3.01,
            "Social Risk Score": 4.22,
            "Governance Risk Score": 5.28,
            "Controversy Level": 1.0,
            "Peer Controversy Min": 0.0,
            "Peer Controversy Avg": 0.5583333333333333,
            "Peer Controversy Max": 3.0
        },
        "Faithfulness Evaluation": {
            "Score": 1.0,
            "Explanation": "The generated ESG report accurately reflects the reference ESG data provided for AMD. It correctly states the total ESG Risk Score of 12.51 and provides a breakdown of the Environmental, Social, and Governance Risk Scores as 3.01, 4.22, and 5.28, respectively. The descriptions of these scores align well with the implications of the scores themselves, indicating a moderate level of risk and areas for improvement. Additionally, the commentary on the controversy level of 1.0 is consistent with the reference data, noting that it is lower than the peer average while still being above the minimum. Overall, the report is faithful to the actual data, providing a clear and accurate assessment of AMD's ESG performance."
        }
    },
    "NFLX": {
        "Generated Report": "Netflix (NFLX) exhibits a total ESG Risk Score of 15.88, indicating a moderate level of sustainability challenges. The Environmental Risk Score of 0.16 suggests that the company's environmental impact is relatively low, which is favorable for investors focused on ecological sustainability. However, the higher Social Risk Score of 7.38 indicates significant concerns related to social factors, such as labor practices, diversity, and community impact.\n\nThe Governance Risk Score of 8.35 points to potential weaknesses in corporate governance practices, which may include issues like board diversity, executive compensation, and shareholder rights. This presents an area of concern as governance factors are critical for long-term stability and risk management.\n\nAdditionally, the Controversy Level of 2.0, which is above the peer average of 1.01, signals that Netflix has faced notable controversies, potentially impacting its reputation and stakeholder trust. The range of peer controversy scores (0.0 to 3.0) suggests variability within the industry, but Netflix's position towards the higher end may raise red flags for ESG-conscious investors.\n\nIn summary, while Netflix's environmental impact appears manageable, significant social and governance risks warrant careful consideration. Investors should monitor developments in these areas, as they could affect the company's reputation, regulatory compliance, and ultimately its financial performance.",
        "Reference ESG Data": {
            "Stock": "NFLX",
            "Total ESG Risk Score": 15.88,
            "Environmental Risk Score": 0.16,
            "Social Risk Score": 7.38,
            "Governance Risk Score": 8.35,
            "Controversy Level": 2.0,
            "Peer Controversy Min": 0.0,
            "Peer Controversy Avg": 1.0070921985815602,
            "Peer Controversy Max": 3.0
        },
        "Faithfulness Evaluation": {
            "Score": 1.0,
            "Explanation": "The generated ESG report accurately reflects the reference ESG data provided for Netflix (NFLX). It correctly states the total ESG Risk Score of 15.88 and breaks down the Environmental Risk Score (0.16), Social Risk Score (7.38), and Governance Risk Score (8.35) in a manner consistent with the reference data. The report also appropriately highlights the Controversy Level of 2.0 and compares it to the peer average, providing context for Netflix's position within its industry. All elements of the report align with the reference data, demonstrating a high level of faithfulness and accuracy."
        }
    }
}