{
    "TSLA": {
        "Generated Report": "Tesla, Inc. (TSLA) presents a mixed ESG profile with a total risk score of 24.76, indicating a moderate level of ESG-related risk. The company's Environmental Risk Score of 3.04 is relatively low, reflecting its core business model focused on electric vehicles and renewable energy solutions, which are inherently more sustainable compared to traditional automotive manufacturing. However, the social risk score of 14.13 raises concerns, particularly regarding labor practices and workplace culture, which have been subject to criticism and could impact its reputation and operational stability.\n\nThe Governance Risk Score of 7.6 suggests potential weaknesses in oversight and management practices, which is significant given the company's high profile and rapid growth. A score in this range indicates that governance issues could pose risks to investor confidence and stakeholder relationships.\n\nTesla's Controversy Level of 3.0 is notable, especially when compared to its peers, where the average controversy level is 1.75. This indicates that Tesla faces more scrutiny and potential public relations challenges than its competitors, which could affect its market position.\n\nIn summary, while Tesla's environmental initiatives are commendable, its social and governance risks present significant challenges. Addressing these issues will be crucial for the company to improve its overall sustainability and reduce potential risks to its long-term performance. Investors should remain vigilant regarding these factors as they may impact future growth and shareholder value.",
        "Reference ESG Data": {
            "Stock": "TSLA",
            "Total ESG Risk Score": 24.76,
            "Environmental Risk Score": 3.04,
            "Social Risk Score": 14.13,
            "Governance Risk Score": 7.6,
            "Controversy Level": 3.0,
            "Peer Controversy Min": 0.0,
            "Peer Controversy Avg": 1.75,
            "Peer Controversy Max": 4.0
        },
        "Faithfulness Evaluation": {
            "Score": 1.0,
            "Explanation": "The generated ESG report accurately reflects the reference ESG data for Tesla, Inc. (TSLA). It correctly states the total ESG risk score of 24.76, the environmental risk score of 3.04, the social risk score of 14.13, the governance risk score of 7.6, and the controversy level of 3.0. The report provides a balanced view of Tesla's strengths and weaknesses, particularly highlighting the low environmental risk in the context of its business model while also addressing the significant social and governance risks. Furthermore, it appropriately compares Tesla's controversy level with its peers, noting that it is higher than the average. Overall, the report is grounded in the actual data and presents a faithful summary of Tesla's ESG profile."
        }
    },
    "NVDA": {
        "Generated Report": "NVIDIA Corporation (NVDA) exhibits a total ESG risk score of 12.46, indicating a moderate level of risk in its operations. The Environmental Risk Score of 2.73 suggests that the company is performing relatively well in managing its environmental impact, particularly important given the energy-intensive nature of semiconductor manufacturing. However, there is room for improvement, especially in areas related to resource consumption and waste management.\n\nThe Social Risk Score of 4.08 points to potential challenges in labor practices, community relations, or product safety, which could affect the company's reputation and stakeholder trust. The comparatively higher Governance Risk Score of 5.65 indicates concerns related to corporate governance practices, such as board diversity, executive compensation, or shareholder rights. This may pose a risk to long-term investor confidence and regulatory scrutiny.\n\nThe Controversy Level of 2.0 shows that NVDA has faced some controversies, though it is lower than the peer average of approximately 0.56. This suggests that while NVDA is not among the most controversial companies in its sector, it is still susceptible to public scrutiny and potential reputational risks.\n\nIn summary, while NVDA demonstrates strengths in environmental management, the company must address its social and governance risks to enhance its overall sustainability profile. Stakeholders should monitor these areas closely, as they may impact both the company's performance and its attractiveness as a long-term investment.",
        "Reference ESG Data": {
            "Stock": "NVDA",
            "Total ESG Risk Score": 12.46,
            "Environmental Risk Score": 2.73,
            "Social Risk Score": 4.08,
            "Governance Risk Score": 5.65,
            "Controversy Level": 2.0,
            "Peer Controversy Min": 0.0,
            "Peer Controversy Avg": 0.5583333333333333,
            "Peer Controversy Max": 3.0
        },
        "Faithfulness Evaluation": {
            "Score": 0.9,
            "Explanation": "The generated ESG report accurately reflects the total ESG risk score of 12.46 and the individual scores for Environmental (2.73), Social (4.08), and Governance (5.65) risks, which are consistent with the reference data. The report correctly identifies the moderate level of risk associated with NVIDIA Corporation and provides a reasonable interpretation of the implications of these scores.\n\nHowever, there is a minor discrepancy regarding the Controversy Level. The report states that NVDA's controversy level of 2.0 is lower than the peer average of approximately 0.56, which is incorrect. In fact, a controversy level of 2.0 is significantly higher than the peer average of 0.56, indicating that NVDA is more controversial than its peers. This misinterpretation could lead stakeholders to underestimate the reputational risks associated with the company.\n\nOverall, the report is largely faithful to the reference data, but the misunderstanding of the controversy level slightly detracts from its accuracy."
        }
    },
    "AAPL": {
        "Generated Report": "Apple Inc. (AAPL) presents a mixed ESG profile, as indicated by its total ESG risk score of 18.75. The environmental risk score is relatively low at 2.05, suggesting that the company is making strides in minimizing its ecological footprint. Initiatives in renewable energy sourcing and waste reduction programs contribute positively to its environmental standing.\n\nHowever, the social and governance risk scores are notably higher at 8.35 each, indicating potential vulnerabilities in these areas. The social risk score may reflect issues related to labor practices, supply chain management, and product accessibility, raising concerns about how these factors could affect brand reputation and consumer trust. Similarly, the governance risk score suggests that there may be concerns regarding board diversity, executive compensation, and shareholder rights.\n\nThe controversy level of 3.0 places AAPL at the higher end of the spectrum compared to its peers, with an average controversy score of 0.56. This indicates that while the company is engaged in notable controversies, it is not alone in facing such challenges. The maximum peer controversy score of 3.0 suggests that the industry is fraught with issues, but AAPL must address its own controversies proactively to maintain its market position.\n\nIn summary, while Apple demonstrates strong environmental performance, its elevated social and governance risks, along with a significant controversy level, warrant careful monitoring. Addressing these risks will be crucial for enhancing its sustainability profile and mitigating potential future liabilities.",
        "Reference ESG Data": {
            "Stock": "AAPL",
            "Total ESG Risk Score": 18.75,
            "Environmental Risk Score": 2.05,
            "Social Risk Score": 8.35,
            "Governance Risk Score": 8.35,
            "Controversy Level": 3.0,
            "Peer Controversy Min": 0.0,
            "Peer Controversy Avg": 0.5598290598290598,
            "Peer Controversy Max": 3.0
        },
        "Faithfulness Evaluation": {
            "Score": 0.9,
            "Explanation": "The generated ESG report is largely faithful to the reference ESG data, accurately reflecting the total ESG risk score of 18.75 and the environmental risk score of 2.05. It correctly identifies the social and governance risk scores as both being 8.35, which indicates vulnerabilities in those areas. The report also appropriately discusses the controversy level of 3.0 and compares it to the peer controversy average of 0.56, providing context for Apple's position relative to its peers.\n\nHowever, the report could improve by explicitly stating that the peer controversy maximum is also 3.0, which would reinforce the understanding that Apple is at the upper limit of controversy within its industry. Additionally, while the report mentions potential issues related to labor practices and governance, it does not cite specific examples or recent controversies that could provide a clearer picture of the risks involved. This lack of specific context slightly detracts from the overall faithfulness of the report, hence the score of 0.9 instead of a perfect 1."
        }
    },
    "SPY": {
        "Generated Report": "No ESG data available for SPY",
        "Reference ESG Data": {
            "error": "No ESG data available for SPY"
        },
        "Faithfulness Evaluation": "Could not evaluate due to error in data or report generation."
    },
    "QQQ": {
        "Generated Report": "No ESG data available for QQQ",
        "Reference ESG Data": {
            "error": "No ESG data available for QQQ"
        },
        "Faithfulness Evaluation": "Could not evaluate due to error in data or report generation."
    },
    "META": {
        "Generated Report": "META's overall ESG risk score of 32.73 indicates a moderate level of risk, with the most significant concerns arising from its social and governance dimensions. The Environmental Risk Score of 2.41 suggests that META has relatively low environmental risks, indicating effective management of ecological impacts. However, the Social Risk Score of 21.64 is notably high, reflecting potential vulnerabilities in areas such as data privacy, user security, and social responsibility. This score signals that META may face scrutiny from regulators and stakeholders regarding its treatment of user data and the societal implications of its platform.\n\nThe Governance Risk Score of 8.68, while lower than the social risk, still points to potential issues in corporate governance practices that could affect decision-making and accountability. \n\nWith a Controversy Level of 4.0, META is positioned at the higher end of the spectrum, indicating that it has faced significant public and media scrutiny. This is concerning, especially when compared to peers, where the average controversy level is just 0.66. Such high controversy could lead to reputational risks and regulatory challenges, potentially impacting investor confidence and stock performance.\n\nIn summary, while META maintains a low environmental risk profile, its elevated social risks, governance concerns, and high controversy level pose substantial sustainability challenges that investors should monitor closely.",
        "Reference ESG Data": {
            "Stock": "META",
            "Total ESG Risk Score": 32.73,
            "Environmental Risk Score": 2.41,
            "Social Risk Score": 21.64,
            "Governance Risk Score": 8.68,
            "Controversy Level": 4.0,
            "Peer Controversy Min": 0.0,
            "Peer Controversy Avg": 0.6598984771573604,
            "Peer Controversy Max": 4.0
        },
        "Faithfulness Evaluation": {
            "Score": 1.0,
            "Explanation": "The generated ESG report accurately reflects the reference ESG data for META. The overall ESG risk score of 32.73 is correctly identified as moderate. The report appropriately highlights the low Environmental Risk Score of 2.41, indicating effective management of ecological impacts. It also accurately emphasizes the high Social Risk Score of 21.64, discussing the associated vulnerabilities and potential scrutiny regarding data privacy and social responsibility. The Governance Risk Score of 8.68 is correctly noted as a concern, and the Controversy Level of 4.0 is accurately contextualized against peer averages, illustrating the significant public and media scrutiny META faces. Overall, the report is faithful to the provided data, making it a reliable summary of META's ESG performance."
        }
    },
    "AMZN": {
        "Generated Report": "Amazon (AMZN) exhibits a Total ESG Risk Score of 26.1, which indicates a moderate level of risk in its environmental, social, and governance practices. The Environmental Risk Score of 8.3 suggests that while Amazon is taking steps toward sustainability, it still faces significant challenges, particularly in areas such as carbon emissions, waste management, and resource usage. The company is increasingly investing in renewable energy and sustainable practices, but its large operational footprint remains a concern.\n\nThe Social Risk Score of 11.05 is notably higher, reflecting ongoing issues related to labor practices, employee treatment, and community impacts. Reports of warehouse working conditions and employee dissatisfaction have garnered media attention, potentially affecting Amazon's reputation and stakeholder relations.\n\nThe Governance Risk Score of 6.75 indicates relatively moderate governance challenges. While the company has a robust board structure, concerns over executive compensation and shareholder engagement persist, which could impact investor trust.\n\nThe Controversy Level of 3.0, compared to peers\u2019 average of 0.91, highlights that Amazon is involved in more controversies than its competitors. This elevated level poses reputational risks that could translate into financial performance issues.\n\nIn summary, while Amazon is making strides in sustainability, it faces notable risks across environmental and social dimensions, compounded by a higher-than-average controversy level. Addressing these areas will be crucial for mitigating risks and enhancing its long-term sustainability profile.",
        "Reference ESG Data": {
            "Stock": "AMZN",
            "Total ESG Risk Score": 26.1,
            "Environmental Risk Score": 8.3,
            "Social Risk Score": 11.05,
            "Governance Risk Score": 6.75,
            "Controversy Level": 3.0,
            "Peer Controversy Min": 0.0,
            "Peer Controversy Avg": 0.9104477611940298,
            "Peer Controversy Max": 4.0
        },
        "Faithfulness Evaluation": {
            "Score": 1.0,
            "Explanation": "The generated ESG report is perfectly faithful to the provided reference ESG data. It accurately reflects the Total ESG Risk Score of 26.1 and breaks down the Environmental, Social, and Governance Risk Scores as 8.3, 11.05, and 6.75, respectively. The report also correctly identifies the Controversy Level of 3.0 and compares it to the peer average of 0.91, highlighting Amazon's higher involvement in controversies. The descriptions of the risks associated with environmental practices, social issues, and governance challenges are consistent with the scores provided, demonstrating a clear understanding of the implications of these scores. Overall, the report is grounded in the actual data, providing an accurate and comprehensive overview of Amazon's ESG performance."
        }
    },
    "TQQQ": {
        "Generated Report": "No ESG data available for TQQQ",
        "Reference ESG Data": {
            "error": "No ESG data available for TQQQ"
        },
        "Faithfulness Evaluation": "Could not evaluate due to error in data or report generation."
    },
    "AMD": {
        "Generated Report": "AMD's total ESG Risk Score of 12.51 indicates a moderate level of risk, with notable scores across its environmental, social, and governance dimensions. The Environmental Risk Score of 3.01 suggests that while there are some concerns, they are not as pronounced as in other sectors. AMD has made strides in reducing its carbon footprint and improving energy efficiency in semiconductor manufacturing, but ongoing challenges exist related to resource consumption and e-waste.\n\nThe Social Risk Score of 4.22 is relatively higher, reflecting potential issues related to labor practices, diversity, and community engagement. As a tech company, AMD must continuously address workforce diversity and ensure equitable labor practices, which are increasingly scrutinized by investors and consumers.\n\nGovernance Risk Score of 5.28 indicates governance-related concerns, possibly including executive compensation, board diversity, or shareholder rights. This score is critical as strong governance is essential for long-term sustainability and risk management.\n\nThe Controversy Level of 1.0 is relatively low compared to the peer average (0.56), suggesting that AMD has not been significantly embroiled in controversies that could affect its reputation and operational stability. This positions AMD favorably in comparison to its peers but highlights the need for ongoing vigilance.\n\nOverall, while AMD demonstrates a solid commitment to sustainability, it must proactively manage its social and governance risks to enhance its ESG profile and mitigate potential long-term challenges.",
        "Reference ESG Data": {
            "Stock": "AMD",
            "Total ESG Risk Score": 12.51,
            "Environmental Risk Score": 3.01,
            "Social Risk Score": 4.22,
            "Governance Risk Score": 5.28,
            "Controversy Level": 1.0,
            "Peer Controversy Min": 0.0,
            "Peer Controversy Avg": 0.5583333333333333,
            "Peer Controversy Max": 3.0
        },
        "Faithfulness Evaluation": {
            "Score": 1.0,
            "Explanation": "The generated ESG report accurately reflects the reference ESG data for AMD. The total ESG Risk Score of 12.51 is correctly identified as indicating a moderate level of risk. The breakdown of the Environmental Risk Score (3.01), Social Risk Score (4.22), and Governance Risk Score (5.28) aligns with the reference data, providing a clear understanding of the company's risk profile in each dimension. The commentary on AMD's efforts in reducing its carbon footprint and addressing social issues is consistent with the scores provided, and the mention of the low Controversy Level (1.0) compared to the peer average (0.56) is also accurate. Overall, the report is well-grounded in the actual data, making it a faithful representation of AMD's ESG standing."
        }
    },
    "NFLX": {
        "Generated Report": "Netflix (NFLX) presents a mixed ESG profile, with a total ESG risk score of 15.88 indicating moderate risk exposure. The environmental risk score is notably low at 0.16, suggesting that the company has minimal environmental impact compared to its peers. This is particularly positive, as the media and entertainment sector often faces scrutiny regarding carbon emissions and resource consumption.\n\nHowever, the social risk score of 7.38 raises concerns, indicating potential challenges related to social responsibility, including issues like employee relations, diversity, and community impact. This score is significantly higher than the environmental score, highlighting that social factors could be a critical area for improvement.\n\nThe governance risk score of 8.35 also poses potential risks, reflecting issues related to board diversity, executive compensation, and overall corporate governance practices. This score is indicative of the importance of strong governance frameworks to mitigate risks associated with decision-making and ethical practices.\n\nThe controversy level of 2.0, while moderate, suggests a history of incidents that could affect the company's reputation and stakeholder trust. Compared to peers, Netflix\u2019s controversy level is above the average, indicating that it has faced more scrutiny than many competitors.\n\nOverall, while Netflix shows strengths in environmental performance, its higher social and governance risks warrant attention. Addressing these areas could enhance its sustainability profile and mitigate potential risks to its brand and operations in the future.",
        "Reference ESG Data": {
            "Stock": "NFLX",
            "Total ESG Risk Score": 15.88,
            "Environmental Risk Score": 0.16,
            "Social Risk Score": 7.38,
            "Governance Risk Score": 8.35,
            "Controversy Level": 2.0,
            "Peer Controversy Min": 0.0,
            "Peer Controversy Avg": 1.0070921985815602,
            "Peer Controversy Max": 3.0
        },
        "Faithfulness Evaluation": {
            "Score": 1.0,
            "Explanation": "The generated ESG report accurately reflects the reference ESG data provided for Netflix (NFLX). It correctly states the total ESG risk score of 15.88 and breaks down the environmental risk score (0.16), social risk score (7.38), governance risk score (8.35), and controversy level (2.0). Each of these figures is presented in a way that aligns with the reference data, providing a clear and faithful representation of Netflix's ESG profile. The report also contextualizes the scores effectively, discussing the implications of the social and governance risks in relation to the company's overall sustainability profile. There are no discrepancies or inaccuracies in the information presented, making the report fully faithful to the reference data."
        }
    }
}