{
    "TSLA": {
        "Generated Report": "Tesla, Inc. (TSLA) presents a mixed ESG profile with a total risk score of 24.76, indicating an elevated level of overall ESG risk. The environmental risk score is relatively low at 3.04, reflecting the company's commitment to sustainable practices through its electric vehicle production and renewable energy initiatives. This positions Tesla favorably within the environmental aspect of ESG, especially in comparison to traditional automotive manufacturers.\n\nHowever, the social risk score is significantly higher at 14.13, suggesting potential vulnerabilities related to labor practices, workplace safety, and community impact. This elevated social risk may stem from controversies surrounding employee treatment and workplace culture, which can negatively affect both reputation and operational stability.\n\nThe governance risk score of 7.6 is also notable, indicating possible concerns related to corporate governance structures and practices. This score is compounded by a controversy level of 3.0, which is above the peer average of 1.75, signaling that Tesla faces more scrutiny and criticism than its competitors. \n\nOverall, while Tesla excels in environmental performance, its social and governance risks warrant close attention. Investors should weigh these factors carefully, as the company's sustainability narrative is overshadowed by significant social and governance challenges that could impact its long-term viability and brand reputation.",
        "Reference ESG Data": {
            "Stock": "TSLA",
            "Total ESG Risk Score": 24.76,
            "Environmental Risk Score": 3.04,
            "Social Risk Score": 14.13,
            "Governance Risk Score": 7.6,
            "Controversy Level": 3.0,
            "Peer Controversy Min": 0.0,
            "Peer Controversy Avg": 1.75,
            "Peer Controversy Max": 4.0
        },
        "Faithfulness Evaluation": {
            "Score": 1.0,
            "Explanation": "The generated ESG report accurately reflects the reference ESG data for Tesla, Inc. (TSLA). It correctly states the total ESG risk score of 24.76 and breaks down the environmental risk score (3.04), social risk score (14.13), and governance risk score (7.6) in a coherent manner. The report also appropriately highlights the controversy level of 3.0, noting that it is above the peer average of 1.75, which aligns with the provided reference data. The analysis of Tesla's strengths in environmental performance and weaknesses in social and governance aspects is well-grounded in the actual data, making the report faithful to the reference ESG data."
        }
    },
    "NVDA": {
        "Generated Report": "NVIDIA Corporation (NVDA) presents a mixed ESG risk profile, with a total ESG risk score of 12.46, indicating a moderate level of risk. The Environmental Risk Score of 2.73 suggests that while there are some environmental concerns, they are relatively contained compared to industry standards. This is favorable in an era where tech companies face increasing scrutiny over their carbon footprints and resource usage.\n\nThe Social Risk Score of 4.08 indicates moderate social risks, which may stem from labor practices, community impact, or product-related concerns. However, the Governance Risk Score of 5.65 is higher, highlighting potential vulnerabilities in corporate governance, such as board diversity, executive compensation, and shareholder rights. Governance is critical, especially in a rapidly evolving industry like technology, where ethical considerations can significantly impact reputation and financial performance.\n\nThe Controversy Level of 2.0 is relatively low compared to the peer average of 0.56, suggesting that NVDA has managed to avoid major scandals, although there is still some level of controversy that could pose reputational risks.\n\nIn summary, while NVDA shows strengths in environmental management, its higher governance risks and moderate social concerns warrant attention. Investors should consider these factors in their sustainability assessments, as they could impact the company's long-term viability and market perception.",
        "Reference ESG Data": {
            "Stock": "NVDA",
            "Total ESG Risk Score": 12.46,
            "Environmental Risk Score": 2.73,
            "Social Risk Score": 4.08,
            "Governance Risk Score": 5.65,
            "Controversy Level": 2.0,
            "Peer Controversy Min": 0.0,
            "Peer Controversy Avg": 0.5583333333333333,
            "Peer Controversy Max": 3.0
        },
        "Faithfulness Evaluation": {
            "Score": 0.9,
            "Explanation": "The generated ESG report is largely faithful to the provided reference ESG data. It accurately states the total ESG risk score of 12.46 and provides a reasonable interpretation of the Environmental, Social, and Governance risk scores, which are 2.73, 4.08, and 5.65, respectively. The report correctly identifies the governance risk as the highest, which aligns with the data.\n\nHowever, there is a slight discrepancy regarding the Controversy Level. The report states that NVDA's controversy level of 2.0 is \"relatively low\" compared to the peer average of 0.56. This is misleading, as a controversy level of 2.0 is significantly higher than the average of 0.56, indicating a higher level of controversy than peers, not a lower one. This misrepresentation affects the overall assessment of NVDA's risk profile.\n\nOverall, while the report is mostly accurate and grounded in the actual data, the mischaracterization of the controversy level slightly detracts from its faithfulness."
        }
    },
    "AAPL": {
        "Generated Report": "Apple Inc. (AAPL) presents a mixed picture in terms of ESG (Environmental, Social, and Governance) risk analysis. With a total ESG Risk Score of 18.75, the company demonstrates a relatively low environmental risk score of 2.05, indicating that its environmental practices are generally favorable compared to industry standards. This suggests that Apple is making efforts to mitigate its environmental impact, particularly in areas such as carbon neutrality and sustainable materials.\n\nHowever, the social and governance risk scores are notably higher, both at 8.35. This raises concerns regarding labor practices, privacy issues, and corporate governance structures. Given the increasing scrutiny on tech companies regarding employee treatment and data privacy, these scores signal potential vulnerabilities that could impact Apple\u2019s reputation and financial performance.\n\nThe controversy level stands at 3.0, which is at the upper end of the peer range (0.0 - 3.0). This elevates the risk of reputational damage, especially when compared to the average peer controversy score of 0.56. The high controversy level could result from previous incidents related to labor conditions, supply chain challenges, or privacy breaches.\n\nIn conclusion, while Apple is making strides in environmental sustainability, its social and governance risks warrant close attention. Stakeholders should monitor potential controversies and their implications for the company\u2019s long-term sustainability and market position.",
        "Reference ESG Data": {
            "Stock": "AAPL",
            "Total ESG Risk Score": 18.75,
            "Environmental Risk Score": 2.05,
            "Social Risk Score": 8.35,
            "Governance Risk Score": 8.35,
            "Controversy Level": 3.0,
            "Peer Controversy Min": 0.0,
            "Peer Controversy Avg": 0.5598290598290598,
            "Peer Controversy Max": 3.0
        },
        "Faithfulness Evaluation": {
            "Score": 0.9,
            "Explanation": "The generated ESG report accurately reflects the reference ESG data for Apple Inc. (AAPL) in several key areas, including the total ESG Risk Score of 18.75 and the environmental risk score of 2.05, which is described as relatively low. The report correctly identifies the social and governance risk scores of 8.35 each, highlighting concerns related to labor practices and corporate governance, which aligns with the data provided.\n\nHowever, while the report mentions the controversy level of 3.0 and notes that it is at the upper end of the peer range, it could have provided more context regarding the implications of this score in relation to the average peer controversy score of 0.56. The report does well to emphasize the potential reputational risks associated with this high controversy level, but it could be seen as slightly lacking in depth regarding the specific incidents that may have contributed to this score.\n\nOverall, the report is largely faithful to the reference data, with only minor areas for improvement in contextualizing the controversy level."
        }
    },
    "SPY": {
        "Generated Report": "No ESG data available for SPY",
        "Reference ESG Data": {
            "error": "No ESG data available for SPY"
        },
        "Faithfulness Evaluation": "Could not evaluate due to error in data or report generation."
    },
    "QQQ": {
        "Generated Report": "No ESG data available for QQQ",
        "Reference ESG Data": {
            "error": "No ESG data available for QQQ"
        },
        "Faithfulness Evaluation": "Could not evaluate due to error in data or report generation."
    },
    "META": {
        "Generated Report": "META's total ESG risk score of 32.73 indicates a moderate level of sustainability risk, with notable variances across the environmental, social, and governance dimensions. The environmental risk score of 2.41 suggests that while META may have some environmental concerns, they are relatively low compared to other dimensions. This could imply that the company's operations and product lifecycle are not heavily detrimental to the environment.\n\nThe social risk score of 21.64 is significantly higher, highlighting potential issues related to labor practices, community engagement, and user privacy. Given the nature of META's business, social risks could stem from privacy controversies, misinformation on platforms, and the broader implications of social media on mental health, all of which may impact the company\u2019s reputation and operational stability.\n\nThe governance risk score of 8.68 indicates moderate concerns in areas such as board diversity, executive compensation, and shareholder rights. High governance risks can undermine investor confidence and lead to increased scrutiny from regulators.\n\nThe controversy level of 4.0, which is at the upper end compared to peers, suggests that META has faced significant public scrutiny and operational challenges. This elevated level of controversy could lead to reputational damage and impact stakeholder trust.\n\nIn summary, while META has a relatively low environmental risk, its high social risk and controversy levels warrant close monitoring, as they pose significant potential risks to its long-term sustainability and reputation.",
        "Reference ESG Data": {
            "Stock": "META",
            "Total ESG Risk Score": 32.73,
            "Environmental Risk Score": 2.41,
            "Social Risk Score": 21.64,
            "Governance Risk Score": 8.68,
            "Controversy Level": 4.0,
            "Peer Controversy Min": 0.0,
            "Peer Controversy Avg": 0.6598984771573604,
            "Peer Controversy Max": 4.0
        },
        "Faithfulness Evaluation": {
            "Score": 1.0,
            "Explanation": "The generated ESG report accurately reflects the reference ESG data for META. It correctly states the total ESG risk score of 32.73 and provides a clear breakdown of the environmental (2.41), social (21.64), and governance (8.68) risk scores, aligning with the reference data. The report also accurately identifies the controversy level as 4.0, noting its significance in relation to peer controversy levels. The interpretations regarding the implications of these scores on META's sustainability and reputation are well-founded and consistent with the data provided. Overall, the report is faithful to the actual ESG data, warranting a perfect score of 1.0."
        }
    },
    "AMZN": {
        "Generated Report": "Amazon (AMZN) presents a mixed picture in terms of ESG performance, evidenced by its Total ESG Risk Score of 26.1. The Environmental Risk Score of 8.3 indicates notable challenges, particularly related to its carbon footprint, packaging waste, and energy consumption. As a major logistics and e-commerce player, Amazon faces increasing scrutiny regarding its environmental impact, especially as climate concerns rise among consumers and regulators.\n\nThe Social Risk Score of 11.05 is significant, reflecting issues related to labor practices, workplace conditions, and community impacts. Amazon has faced criticism over employee treatment, particularly in its warehouses, and this could pose reputational risks and affect workforce retention and productivity.\n\nThe Governance Risk Score of 6.75 suggests a relatively strong governance framework, but there is still room for improvement, particularly in transparency and shareholder engagement. The Controversy Level of 3.0, while moderate, indicates that the company has faced several public disputes, which may affect its brand image and stakeholder trust.\n\nWhen compared to peers, AMZN's controversy level stands out, with an average peer controversy of 0.91, highlighting the need for proactive measures to mitigate risks. Overall, while Amazon is a leader in the e-commerce sector, its environmental and social challenges could pose significant sustainability risks if not addressed effectively. Investors should monitor these aspects closely as they could impact long-term performance and stakeholder relations.",
        "Reference ESG Data": {
            "Stock": "AMZN",
            "Total ESG Risk Score": 26.1,
            "Environmental Risk Score": 8.3,
            "Social Risk Score": 11.05,
            "Governance Risk Score": 6.75,
            "Controversy Level": 3.0,
            "Peer Controversy Min": 0.0,
            "Peer Controversy Avg": 0.9104477611940298,
            "Peer Controversy Max": 4.0
        },
        "Faithfulness Evaluation": {
            "Score": 0.95,
            "Explanation": "The generated ESG report for Amazon (AMZN) is largely faithful to the provided reference ESG data. The Total ESG Risk Score of 26.1, Environmental Risk Score of 8.3, Social Risk Score of 11.05, Governance Risk Score of 6.75, and Controversy Level of 3.0 are accurately reflected in the report. \n\nThe report effectively highlights the key areas of concern, such as environmental impact and social issues related to labor practices, which align with the respective risk scores. Additionally, it correctly notes the moderate controversy level and compares it to the peer average, emphasizing the need for Amazon to address these challenges proactively. \n\nThe only minor issue is the phrasing regarding the peer controversy average, which could be clearer. The report states that AMZN's controversy level \"stands out\" compared to the average peer controversy of 0.91, which may imply a more significant deviation than what the data suggests, as 3.0 is indeed much higher than the average. However, this does not significantly detract from the overall accuracy of the report.\n\nOverall, the report is well-grounded in the actual data, providing a comprehensive overview of Amazon's ESG performance."
        }
    },
    "TQQQ": {
        "Generated Report": "No ESG data available for TQQQ",
        "Reference ESG Data": {
            "error": "No ESG data available for TQQQ"
        },
        "Faithfulness Evaluation": "Could not evaluate due to error in data or report generation."
    },
    "AMD": {
        "Generated Report": "AMD's total ESG risk score of 12.51 indicates a moderate level of risk, with varying scores across the three primary pillars: Environmental (3.01), Social (4.22), and Governance (5.28). The environmental risk score is relatively low, suggesting that AMD is managing its ecological footprint and sustainability initiatives effectively. However, the social and governance scores are higher, indicating potential concerns in these areas that could impact stakeholder trust and company reputation.\n\nThe social risk score of 4.22 reflects challenges related to workforce equality, labor practices, or community relations, which are critical factors in the tech industry. The governance risk score of 5.28 suggests potential issues with corporate governance practices, such as board diversity, executive compensation, or shareholder rights, which could pose risks to long-term performance and investor confidence.\n\nAMD's controversy level is low at 1.0, significantly below the peer average of 0.56, suggesting that the company has experienced few significant controversies compared to its peers. This positions AMD favorably in terms of reputational risk compared to the industry.\n\nOverall, while AMD demonstrates strength in environmental management, attention is needed to address social and governance risks to enhance its sustainability profile. Continuous monitoring of these areas is essential to mitigate potential risks and capitalize on ESG opportunities in an increasingly conscientious market.",
        "Reference ESG Data": {
            "Stock": "AMD",
            "Total ESG Risk Score": 12.51,
            "Environmental Risk Score": 3.01,
            "Social Risk Score": 4.22,
            "Governance Risk Score": 5.28,
            "Controversy Level": 1.0,
            "Peer Controversy Min": 0.0,
            "Peer Controversy Avg": 0.5583333333333333,
            "Peer Controversy Max": 3.0
        },
        "Faithfulness Evaluation": {
            "Score": 1.0,
            "Explanation": "The generated ESG report accurately reflects the reference ESG data for AMD. It correctly states the total ESG risk score of 12.51 and breaks down the scores for each pillar: Environmental (3.01), Social (4.22), and Governance (5.28). The report appropriately characterizes the environmental risk as relatively low and highlights the higher social and governance scores, which align with the potential concerns mentioned in the reference data. \n\nAdditionally, the report correctly identifies the controversy level of 1.0 and compares it favorably against the peer average of 0.56, indicating that AMD has experienced fewer controversies than its peers. The overall assessment of AMD's strengths and areas for improvement is consistent with the provided data. Therefore, the report is entirely faithful to the reference ESG data."
        }
    },
    "NFLX": {
        "Generated Report": "Netflix (NFLX) presents a mixed ESG profile, with a total ESG risk score of 15.88, indicating a moderate level of overall risk. The environmental risk score is notably low at 0.16, suggesting that Netflix has minimal environmental impact and is potentially proactive in its sustainability initiatives. This is a positive indicator for investors focused on environmental stewardship.\n\nHowever, the company faces higher social (7.38) and governance (8.35) risk scores, which signal potential vulnerabilities in its social practices and governance structures. The social risk score may reflect concerns related to workforce management, content diversity, or community engagement, while the governance risk score suggests areas for improvement in corporate governance practices, such as board diversity, executive pay, or shareholder rights.\n\nThe controversy level of 2.0 positions Netflix above the peer average (1.01), indicating that the company has encountered notable controversies, albeit less severe than its maximum peer score of 3.0. This could suggest reputational risks that may impact investor sentiment and stakeholder trust.\n\nIn summary, while Netflix exhibits strong environmental performance, its higher social and governance risks, along with a notable controversy level, warrant attention. Investors should consider these factors when evaluating the company's long-term sustainability and potential risks, particularly in a climate where corporate accountability and social responsibility are increasingly prioritized.",
        "Reference ESG Data": {
            "Stock": "NFLX",
            "Total ESG Risk Score": 15.88,
            "Environmental Risk Score": 0.16,
            "Social Risk Score": 7.38,
            "Governance Risk Score": 8.35,
            "Controversy Level": 2.0,
            "Peer Controversy Min": 0.0,
            "Peer Controversy Avg": 1.0070921985815602,
            "Peer Controversy Max": 3.0
        },
        "Faithfulness Evaluation": {
            "Score": 1.0,
            "Explanation": "The generated ESG report accurately reflects the provided reference ESG data for Netflix (NFLX). The total ESG risk score of 15.88 is correctly stated, and the environmental risk score of 0.16 is described as low, indicating minimal environmental impact. The report appropriately highlights the higher social (7.38) and governance (8.35) risk scores, suggesting vulnerabilities in these areas, which aligns with the reference data. Additionally, the controversy level of 2.0 is correctly noted as being above the peer average of 1.01, indicating a higher level of controversies compared to peers. Overall, the report is well-grounded in the actual data, providing a faithful representation of Netflix's ESG profile."
        }
    }
}