{
    "TSLA": {
        "Generated Report": "Tesla Inc. (TSLA) presents a mixed profile regarding its ESG risks, with a total risk score of 24.76 indicating notable concerns, particularly in the social and governance dimensions. The Environmental Risk Score of 3.04 is relatively low, reflecting Tesla's core business model centered around sustainable energy solutions and electric vehicles. This positions the company favorably within the environmental aspect, aligning with global sustainability goals. \n\nHowever, the Social Risk Score of 14.13 is significantly higher, suggesting that Tesla faces considerable challenges in areas such as labor practices, employee relations, and community impacts. These issues may stem from reported controversies surrounding workplace conditions and management practices, which could affect the company's reputation and operational stability.\n\nThe Governance Risk Score of 7.6 indicates moderate concerns in governance practices, which could relate to board diversity, executive compensation, and transparency. The controversy level of 3.0, above the peer average of 1.75, highlights that Tesla is experiencing more significant scrutiny compared to its peers, indicating an elevated risk that could impact investor sentiment and brand trust.\n\nIn conclusion, while Tesla\u2019s environmental initiatives are commendable, the elevated social and governance risks necessitate ongoing monitoring. To enhance sustainability and mitigate potential risks, Tesla should focus on improving labor relations and governance practices, ensuring that its innovative edge does not come at the expense of social responsibility.",
        "Reference ESG Data": {
            "Stock": "TSLA",
            "Total ESG Risk Score": 24.76,
            "Environmental Risk Score": 3.04,
            "Social Risk Score": 14.13,
            "Governance Risk Score": 7.6,
            "Controversy Level": 3.0,
            "Peer Controversy Min": 0.0,
            "Peer Controversy Avg": 1.75,
            "Peer Controversy Max": 4.0
        },
        "Faithfulness Evaluation": {
            "Score": 1.0,
            "Explanation": "The generated ESG report accurately reflects the reference ESG data for Tesla Inc. (TSLA). The total ESG risk score of 24.76 is correctly stated, and the breakdown of the Environmental Risk Score (3.04), Social Risk Score (14.13), and Governance Risk Score (7.6) aligns perfectly with the reference data. Furthermore, the report appropriately highlights the significant social challenges and moderate governance concerns, as well as the controversy level of 3.0, which is indeed above the peer average of 1.75. The report's analysis of Tesla's strengths in environmental initiatives and the need for improvement in social and governance areas is consistent with the provided data. Overall, the report is comprehensive, accurate, and grounded in the actual ESG data, justifying a perfect faithfulness score of 1.0."
        }
    },
    "NVDA": {
        "Generated Report": "NVIDIA Corporation (NVDA) exhibits a total ESG risk score of 12.46, indicating a moderate level of risk across environmental, social, and governance dimensions. The breakdown reveals an Environmental Risk Score of 2.73, which suggests that the company is relatively better positioned in terms of environmental sustainability compared to its peers, given the average environmental concerns in the tech industry.\n\nHowever, the Social Risk Score of 4.08 and Governance Risk Score of 5.65 highlight areas for concern. The higher governance score suggests potential challenges related to corporate governance practices, which could impact stakeholder trust and operational integrity. Social risks may stem from labor practices, diversity and inclusion, and community engagement, areas that require continuous monitoring and improvement.\n\nThe controversy level of 2.0 signifies a moderate level of public and media scrutiny, especially in comparison to peers (min: 0.0, avg: 0.56, max: 3.0). This indicates that while NVDA has faced some controversies, it is not among the most severely impacted companies in its sector.\n\nIn summary, while NVDA shows strengths in environmental sustainability, the higher social and governance scores, coupled with a moderate controversy level, suggest that the company should enhance its practices in these areas to mitigate risks and improve its overall sustainability profile. Continuous engagement with stakeholders and proactive measures in governance and social responsibility will be key to addressing potential risks.",
        "Reference ESG Data": {
            "Stock": "NVDA",
            "Total ESG Risk Score": 12.46,
            "Environmental Risk Score": 2.73,
            "Social Risk Score": 4.08,
            "Governance Risk Score": 5.65,
            "Controversy Level": 2.0,
            "Peer Controversy Min": 0.0,
            "Peer Controversy Avg": 0.5583333333333333,
            "Peer Controversy Max": 3.0
        },
        "Faithfulness Evaluation": {
            "Score": 1.0,
            "Explanation": "The generated ESG report accurately reflects the provided reference ESG data for NVIDIA Corporation (NVDA). It correctly states the total ESG risk score of 12.46 and provides a precise breakdown of the Environmental Risk Score (2.73), Social Risk Score (4.08), and Governance Risk Score (5.65). The report also appropriately interprets the controversy level of 2.0 in relation to peer controversy metrics, indicating a moderate level of scrutiny. Furthermore, the analysis of strengths and weaknesses aligns well with the scores, suggesting areas for improvement without introducing inaccuracies or misleading information. Overall, the report is grounded in the actual data, making it perfectly faithful."
        }
    },
    "AAPL": {
        "Generated Report": "Apple Inc. (AAPL) presents a nuanced ESG profile, with a Total ESG Risk Score of 18.75, indicating a moderate risk level. The Environmental Risk Score of 2.05 is relatively low, suggesting that Apple is performing well in sustainability practices, particularly in areas like energy efficiency and reduction of carbon emissions. However, the Social and Governance Risk Scores, both standing at 8.35, indicate significant risks in these areas, highlighting potential challenges related to labor practices, supply chain management, and corporate governance.\n\nThe Controversy Level of 3.0, which is on par with the maximum among its peers, points to notable incidents that may affect public perception and stakeholder trust. With a Peer Controversy Average of approximately 0.56, this elevated level of controversy suggests that Apple has faced issues that could impact its brand and operational stability. \n\nIn summary, while Apple excels in environmental performance, its social and governance risks warrant close attention. The high controversy level signals potential challenges that could arise from negative public sentiment or regulatory scrutiny. Investors should weigh these factors against Apple's strong market position and ongoing commitments to sustainability. Addressing its social and governance concerns could enhance Apple's overall ESG standing and mitigate future risks.",
        "Reference ESG Data": {
            "Stock": "AAPL",
            "Total ESG Risk Score": 18.75,
            "Environmental Risk Score": 2.05,
            "Social Risk Score": 8.35,
            "Governance Risk Score": 8.35,
            "Controversy Level": 3.0,
            "Peer Controversy Min": 0.0,
            "Peer Controversy Avg": 0.5598290598290598,
            "Peer Controversy Max": 3.0
        },
        "Faithfulness Evaluation": {
            "Score": 1.0,
            "Explanation": "The generated ESG report accurately reflects the provided reference ESG data for Apple Inc. (AAPL). It correctly states the Total ESG Risk Score of 18.75 and breaks down the Environmental Risk Score (2.05), Social Risk Score (8.35), and Governance Risk Score (8.35) in a manner that aligns with the reference data. The report also appropriately highlights the Controversy Level of 3.0, noting its significance relative to the peer controversy metrics. The analysis of the implications of these scores is coherent and consistent with the data, emphasizing the strengths and weaknesses of Apple's ESG profile. Overall, the report is faithful to the reference data, providing a clear and accurate summary of Apple's ESG standing."
        }
    },
    "SPY": {
        "Generated Report": "No ESG data available for SPY",
        "Reference ESG Data": {
            "error": "No ESG data available for SPY"
        },
        "Faithfulness Evaluation": "Could not evaluate due to error in data or report generation."
    },
    "QQQ": {
        "Generated Report": "No ESG data available for QQQ",
        "Reference ESG Data": {
            "error": "No ESG data available for QQQ"
        },
        "Faithfulness Evaluation": "Could not evaluate due to error in data or report generation."
    },
    "META": {
        "Generated Report": "META's total ESG risk score of 32.73 indicates a moderate level of risk across environmental, social, and governance dimensions. The Environmental Risk Score of 2.41 is relatively low, suggesting that META has a minimal impact on environmental factors, which is positive in terms of sustainability. However, the Social Risk Score stands at 21.64, highlighting significant concerns in this area, likely driven by issues related to data privacy, misinformation, and the social implications of its platforms. This elevated score reflects potential reputational risks and regulatory scrutiny.\n\nThe Governance Risk Score of 8.68 indicates some governance challenges, which may relate to board diversity, executive compensation, or shareholder rights. While not the highest, the score suggests room for improvement in governance practices.\n\nThe controversy level of 4.0 is concerning, particularly as it matches the maximum level observed among peers. This places META at a higher risk of being adversely affected by public perception and regulatory actions compared to its competitors, which have an average controversy score of approximately 0.66. \n\nOverall, while META is performing well environmentally, its social and governance risks present substantial challenges. Investors should be cautious of the potential for reputational damage and regulatory consequences stemming from its social controversies and consider these factors in their investment decisions. Effective management of these risks will be crucial for META's long-term sustainability and investor confidence.",
        "Reference ESG Data": {
            "Stock": "META",
            "Total ESG Risk Score": 32.73,
            "Environmental Risk Score": 2.41,
            "Social Risk Score": 21.64,
            "Governance Risk Score": 8.68,
            "Controversy Level": 4.0,
            "Peer Controversy Min": 0.0,
            "Peer Controversy Avg": 0.6598984771573604,
            "Peer Controversy Max": 4.0
        },
        "Faithfulness Evaluation": {
            "Score": 1.0,
            "Explanation": "The generated ESG report accurately reflects the provided reference ESG data for META. It correctly states the total ESG risk score of 32.73 and breaks down the environmental, social, and governance risk scores as 2.41, 21.64, and 8.68 respectively. The report appropriately highlights the low environmental risk as a positive aspect while emphasizing the significant social risks associated with data privacy and misinformation, which aligns with the high social risk score. The governance risk score is also accurately described, indicating challenges that require attention. Furthermore, the report correctly notes the controversy level of 4.0, which is the maximum among peers, and contrasts it with the average controversy score of 0.66, providing a clear context for META's standing. Overall, the report is grounded in the actual data, making it perfectly faithful to the reference ESG data provided."
        }
    },
    "AMZN": {
        "Generated Report": "Amazon (AMZN) exhibits a total ESG risk score of 26.1, indicating a moderate level of overall risk in its environmental, social, and governance practices. The environmental risk score of 8.3 suggests that while the company is taking steps towards sustainability, it still faces significant challenges, particularly regarding its carbon footprint and resource management, which have been focal points for criticism.\n\nThe social risk score of 11.05 is notably higher, reflecting concerns related to labor practices, employee treatment, and community impact. Amazon has faced scrutiny over working conditions in its warehouses, which may pose reputational risks and potentially hinder employee retention and recruitment efforts.\n\nGovernance risk score at 6.75 indicates a relatively sound governance structure, but there may still be room for improvement in transparency and stakeholder engagement, particularly in addressing the criticisms highlighted in the environmental and social dimensions.\n\nThe controversy level of 3.0, compared to peer averages, suggests that Amazon is facing a higher degree of public scrutiny relative to its competitors, which could impact its brand reputation and customer loyalty. \n\nOverall, while Amazon is actively working on enhancing its ESG practices, significant risks remain, particularly in the social realm. Continued vigilance and proactive measures are essential to mitigate these risks and enhance long-term sustainability.",
        "Reference ESG Data": {
            "Stock": "AMZN",
            "Total ESG Risk Score": 26.1,
            "Environmental Risk Score": 8.3,
            "Social Risk Score": 11.05,
            "Governance Risk Score": 6.75,
            "Controversy Level": 3.0,
            "Peer Controversy Min": 0.0,
            "Peer Controversy Avg": 0.9104477611940298,
            "Peer Controversy Max": 4.0
        },
        "Faithfulness Evaluation": {
            "Score": 1.0,
            "Explanation": "The generated ESG report accurately reflects the reference ESG data provided for Amazon (AMZN). It correctly states the total ESG risk score of 26.1 and breaks down the environmental, social, and governance risk scores as 8.3, 11.05, and 6.75 respectively. The report also appropriately discusses the implications of these scores, such as the challenges related to sustainability, labor practices, and governance transparency. Furthermore, it accurately mentions the controversy level of 3.0 and contextualizes it against peer averages, indicating a higher degree of scrutiny. Overall, the report is faithful to the reference data, providing a comprehensive and accurate overview of Amazon's ESG performance."
        }
    },
    "TQQQ": {
        "Generated Report": "No ESG data available for TQQQ",
        "Reference ESG Data": {
            "error": "No ESG data available for TQQQ"
        },
        "Faithfulness Evaluation": "Could not evaluate due to error in data or report generation."
    },
    "AMD": {
        "Generated Report": "AMD's total ESG Risk Score of 12.51 indicates a moderate level of risk, with environmental, social, and governance scores of 3.01, 4.22, and 5.28, respectively. The environmental score reflects a relatively low risk, suggesting that AMD is managing its ecological impact effectively, which is critical in the tech industry where resource consumption and electronic waste are significant concerns.\n\nThe social risk score of 4.22 suggests that while the company faces some challenges, it is likely addressing issues related to workforce diversity, labor practices, and community engagement. However, there is room for improvement in enhancing its social responsibility initiatives.\n\nThe governance risk score of 5.28 signals a higher level of potential risk in this area, which could reflect concerns around corporate governance practices, board diversity, or shareholder rights. This score warrants closer scrutiny from investors, as strong governance is crucial for long-term sustainability.\n\nAdditionally, AMD's controversy level of 1.0 is relatively low compared to its peers, whose average controversy score is 0.56. This suggests that the company has faced fewer significant controversies, indicating an overall positive reputation in the market. \n\nIn conclusion, while AMD demonstrates solid performance in environmental and social aspects, governance remains a potential risk area. Continued focus on improving governance practices will be essential for enhancing its sustainability profile and mitigating risks moving forward.",
        "Reference ESG Data": {
            "Stock": "AMD",
            "Total ESG Risk Score": 12.51,
            "Environmental Risk Score": 3.01,
            "Social Risk Score": 4.22,
            "Governance Risk Score": 5.28,
            "Controversy Level": 1.0,
            "Peer Controversy Min": 0.0,
            "Peer Controversy Avg": 0.5583333333333333,
            "Peer Controversy Max": 3.0
        },
        "Faithfulness Evaluation": {
            "Score": 0.9,
            "Explanation": "The generated ESG report accurately reflects the reference ESG data for AMD, including the total ESG Risk Score of 12.51 and the individual scores for environmental (3.01), social (4.22), and governance (5.28) risks. The descriptions of these scores are consistent with the data provided, particularly in terms of the implications of each score on AMD's risk profile.\n\nHowever, there is a slight inconsistency regarding the controversy level. The report states that AMD's controversy level of 1.0 is \"relatively low compared to its peers,\" but it fails to clarify that the average peer controversy score is 0.56, which is significantly lower than AMD's score. This could mislead readers into thinking that AMD's controversy level is more favorable than it actually is when compared to its peers. \n\nOverall, the report is largely faithful to the reference data, but the misrepresentation of the controversy level slightly detracts from its overall accuracy."
        }
    },
    "NFLX": {
        "Generated Report": "Netflix (NFLX) presents a mixed ESG profile, with a total risk score of 15.88 that indicates moderate sustainability concerns. The environmental risk score is notably low at 0.16, suggesting that the company is performing well in terms of environmental impacts relative to its peers. This is commendable, considering the growing importance of sustainability in media production and distribution.\n\nHowever, the social risk score of 7.38 and governance risk score of 8.35 highlight significant vulnerabilities. The higher social score may reflect issues related to labor practices, content diversity, and customer engagement, which are critical in maintaining a positive public image and ensuring long-term stakeholder support. The governance score suggests potential challenges in accountability and transparency, factors that can significantly impact investor confidence.\n\nThe controversy level of 2.0, while lower than the peer average of 1.01, indicates that Netflix has faced some public scrutiny, which could affect its reputation and operational stability. This level of controversy is notable, especially in an industry where brand perception is crucial.\n\nOverall, while Netflix shows strengths in environmental practices, it must address social and governance risks to enhance its sustainability profile. Continued scrutiny and proactive measures in these areas will be essential to mitigate potential risks and secure its position as a leader in the entertainment sector.",
        "Reference ESG Data": {
            "Stock": "NFLX",
            "Total ESG Risk Score": 15.88,
            "Environmental Risk Score": 0.16,
            "Social Risk Score": 7.38,
            "Governance Risk Score": 8.35,
            "Controversy Level": 2.0,
            "Peer Controversy Min": 0.0,
            "Peer Controversy Avg": 1.0070921985815602,
            "Peer Controversy Max": 3.0
        },
        "Faithfulness Evaluation": {
            "Score": 1.0,
            "Explanation": "The generated ESG report accurately reflects the reference ESG data for Netflix (NFLX). It correctly states the total ESG risk score of 15.88 and provides a precise breakdown of the environmental risk score (0.16), social risk score (7.38), governance risk score (8.35), and controversy level (2.0). The report contextualizes these scores effectively, highlighting the strengths and weaknesses in Netflix's ESG profile. It also appropriately compares the controversy level to the peer average, reinforcing the accuracy of the information presented. Overall, the report is faithful to the actual data, providing a comprehensive overview of Netflix's ESG standing."
        }
    }
}