{
    "TSLA": {
        "Generated Report": "Tesla, Inc. (TSLA) presents a mixed ESG profile characterized by a total ESG risk score of 24.76, indicating moderate risks across various dimensions. The Environmental Risk Score of 3.04 suggests that the company is performing relatively well in environmental aspects, especially given its role in promoting electric vehicles and renewable energy technologies. However, this score does not account for the broader environmental impacts associated with battery production and resource extraction.\n\nThe Social Risk Score of 14.13 is notably high, reflecting potential challenges in labor practices, employee relations, and community engagement. These issues may stem from reported concerns regarding workplace conditions and labor disputes, which could affect Tesla's reputation and operational stability.\n\nThe Governance Risk Score of 7.6 indicates moderate governance challenges, possibly linked to leadership decisions, transparency, and regulatory compliance. Notably, the company's Controversy Level of 3.0 is above the peer average of 1.75, signaling that Tesla is more frequently associated with negative events compared to its competitors. This elevated controversy level could pose reputational risks and impact investor sentiment.\n\nIn conclusion, while Tesla's environmental initiatives are commendable, it faces significant social and governance-related challenges. Investors should consider these risks alongside Tesla's innovative potential in the clean energy sector when assessing the company's sustainability and long-term viability.",
        "Reference ESG Data": {
            "Stock": "TSLA",
            "Total ESG Risk Score": 24.76,
            "Environmental Risk Score": 3.04,
            "Social Risk Score": 14.13,
            "Governance Risk Score": 7.6,
            "Controversy Level": 3.0,
            "Peer Controversy Min": 0.0,
            "Peer Controversy Avg": 1.75,
            "Peer Controversy Max": 4.0
        },
        "Faithfulness Evaluation": {
            "Score": 1.0,
            "Explanation": "The generated ESG report accurately reflects the provided reference ESG data for Tesla, Inc. (TSLA). It correctly states the total ESG risk score of 24.76 and breaks down the individual scores for environmental (3.04), social (14.13), and governance (7.6) risks. The report also appropriately highlights the controversy level of 3.0 and compares it to the peer average of 1.75, emphasizing Tesla's relatively higher association with negative events. All the information presented aligns with the reference data, demonstrating a faithful representation of Tesla's ESG profile. The analysis of the implications of these scores is well-founded and relevant, further supporting the accuracy of the report."
        }
    },
    "NVDA": {
        "Generated Report": "NVIDIA Corporation (NVDA) presents a mixed ESG profile, with a total ESG risk score of 12.46 indicating a moderate level of risk. The Environmental Risk Score of 2.73 suggests that the company is relatively responsible in its environmental practices, particularly important in the tech sector, which can have significant ecological footprints. However, there is room for improvement, especially in energy consumption and e-waste management.\n\nThe Social Risk Score of 4.08 indicates potential concerns related to labor practices, community engagement, and product safety. While this score is not excessively high, it suggests that NVDA should continue to focus on improving its social impact, particularly as the tech industry faces scrutiny regarding diversity, equity, and inclusion.\n\nNVIDIA's Governance Risk Score of 5.65 is the highest among the three categories, indicating potential challenges in corporate governance practices. This may include issues related to board diversity, executive compensation, and shareholder rights. Given that governance is a critical factor for long-term sustainability, addressing these concerns should be a priority for the company.\n\nThe Controversy Level of 2.0 shows that NVDA has faced some issues compared to peers, with an average peer controversy of 0.56. While not in the highest range, this level indicates the presence of notable controversies that could impact investor perception and stakeholder trust.\n\nIn summary, while NVIDIA demonstrates strengths in environmental metrics, it faces notable social and governance risks that need to be managed to enhance its overall sustainability profile.",
        "Reference ESG Data": {
            "Stock": "NVDA",
            "Total ESG Risk Score": 12.46,
            "Environmental Risk Score": 2.73,
            "Social Risk Score": 4.08,
            "Governance Risk Score": 5.65,
            "Controversy Level": 2.0,
            "Peer Controversy Min": 0.0,
            "Peer Controversy Avg": 0.5583333333333333,
            "Peer Controversy Max": 3.0
        },
        "Faithfulness Evaluation": {
            "Score": 0.9,
            "Explanation": "The generated ESG report accurately reflects the total ESG risk score of 12.46 and provides a reasonable interpretation of the Environmental, Social, and Governance risk scores (2.73, 4.08, and 5.65 respectively). The report correctly identifies the governance risk as the highest, indicating potential challenges, and discusses the implications of the controversy level of 2.0 in relation to peer averages. \n\nHowever, while the report mentions \"room for improvement\" in environmental practices and highlights specific concerns in social and governance areas, it could benefit from more precise language regarding the implications of these scores and how they compare to industry standards. Additionally, it does not explicitly mention the peer controversy minimum and maximum, which could provide further context. Thus, while the report is largely faithful to the reference data, slight enhancements in detail and context could improve its accuracy and grounding in the actual data."
        }
    },
    "AAPL": {
        "Generated Report": "Apple Inc. (AAPL) demonstrates a mixed ESG profile, characterized by a Total ESG Risk Score of 18.75. The Environmental Risk Score of 2.05 indicates a relatively low level of environmental risk, suggesting effective management of environmental impacts, possibly due to initiatives in renewable energy and sustainable product design.\n\nHowever, the Social and Governance Risk Scores, both at 8.35, raise concerns. The elevated Social Risk Score may indicate challenges in labor practices, supply chain ethics, or community relations, which could affect the company's reputation and stakeholder trust. The Governance Risk Score reflects potential issues in corporate governance, such as board diversity, executive compensation, and shareholder rights, which are critical for long-term sustainability.\n\nThe Controversy Level of 3.0, while at the higher end of the spectrum compared to peers (average of 0.56), signals that Apple has faced significant public scrutiny or incidents that could impact its brand image. This level of controversy may pose reputational risks and could influence investor sentiment negatively.\n\nIn summary, while Apple shows strength in environmental management, the higher social and governance risks, coupled with a notable level of controversy, suggest that the company needs to enhance its practices in these areas to mitigate potential risks and improve its overall sustainability profile. Investors should monitor these aspects closely to assess future implications for performance and reputation.",
        "Reference ESG Data": {
            "Stock": "AAPL",
            "Total ESG Risk Score": 18.75,
            "Environmental Risk Score": 2.05,
            "Social Risk Score": 8.35,
            "Governance Risk Score": 8.35,
            "Controversy Level": 3.0,
            "Peer Controversy Min": 0.0,
            "Peer Controversy Avg": 0.5598290598290598,
            "Peer Controversy Max": 3.0
        },
        "Faithfulness Evaluation": {
            "Score": 0.9,
            "Explanation": "The generated ESG report accurately reflects the Total ESG Risk Score of 18.75 and the Environmental Risk Score of 2.05, which indicates effective management of environmental impacts. The report appropriately highlights the elevated Social and Governance Risk Scores of 8.35, indicating potential challenges in those areas. Additionally, the mention of a Controversy Level of 3.0 aligns with the provided data, noting that this is significantly higher than the peer average of 0.56, which is a crucial point for assessing reputational risks.\n\nHowever, the report could improve by providing more specific examples or data points regarding the social and governance challenges faced by Apple, as well as elaborating on the implications of the controversy level in relation to specific incidents or public scrutiny. Overall, the report is faithful to the reference data, but the slight lack of depth in discussing the implications of the risks slightly detracts from its overall accuracy."
        }
    },
    "SPY": {
        "Generated Report": "No ESG data available for SPY",
        "Reference ESG Data": {
            "error": "No ESG data available for SPY"
        },
        "Faithfulness Evaluation": "Could not evaluate due to error in data or report generation."
    },
    "QQQ": {
        "Generated Report": "No ESG data available for QQQ",
        "Reference ESG Data": {
            "error": "No ESG data available for QQQ"
        },
        "Faithfulness Evaluation": "Could not evaluate due to error in data or report generation."
    },
    "META": {
        "Generated Report": "META's total ESG risk score of 32.73 suggests a moderate level of risk, with notable strengths and weaknesses across the three pillars of ESG. The Environmental Risk Score of 2.41 indicates minimal environmental concerns, reflecting the company's efforts to mitigate its ecological footprint, such as initiatives to reduce energy consumption and enhance data center efficiency.\n\nHowever, the Social Risk Score of 21.64 raises significant concerns. This high score points to potential risks related to user privacy, data security, and social impacts stemming from content moderation policies. Given the intensifying scrutiny on social media platforms regarding misinformation and user safety, these factors could pose reputational risks and regulatory challenges for META.\n\nThe Governance Risk Score of 8.68 suggests moderate governance issues, which could stem from board structure, shareholder rights, or transparency practices. While this score is not alarmingly high, it indicates that there may be areas for improvement in governance practices.\n\nThe controversy level of 4.0, particularly when compared to peer averages, highlights that META faces significant reputational challenges. With peer controversies averaging 0.66, META's higher score suggests that it is more frequently at the center of public and media scrutiny.\n\nIn summary, while META demonstrates strengths in environmental management, its elevated social risk and controversy levels warrant close attention from investors and stakeholders, as they could impact the company's long-term sustainability and market position.",
        "Reference ESG Data": {
            "Stock": "META",
            "Total ESG Risk Score": 32.73,
            "Environmental Risk Score": 2.41,
            "Social Risk Score": 21.64,
            "Governance Risk Score": 8.68,
            "Controversy Level": 4.0,
            "Peer Controversy Min": 0.0,
            "Peer Controversy Avg": 0.6598984771573604,
            "Peer Controversy Max": 4.0
        },
        "Faithfulness Evaluation": {
            "Score": 0.9,
            "Explanation": "The generated ESG report for META is largely faithful to the provided reference ESG data. It accurately reflects the total ESG risk score of 32.73 and correctly identifies the Environmental Risk Score (2.41), Social Risk Score (21.64), and Governance Risk Score (8.68). The report effectively communicates the implications of these scores, particularly the significant social risks and the moderate governance issues.\n\nHowever, there is a slight discrepancy regarding the interpretation of the controversy level. While the report states that META's controversy level is 4.0, which is indeed accurate, it could be misleading when it compares this to the peer average of 0.66. The report implies that META's controversy level is significantly higher than its peers, which is true, but it does not clarify that the peer controversy max is also 4.0, indicating that while META has a high controversy score, it is not unique among its peers. This could lead to an overemphasis on the controversy aspect without acknowledging the broader context.\n\nOverall, the report is well-grounded in the actual data with minor nuances that could be clarified for complete accuracy, hence the score of 0.9."
        }
    },
    "AMZN": {
        "Generated Report": "Amazon (AMZN) exhibits a total ESG risk score of 26.1, indicating moderate risk in its environmental, social, and governance practices. The environmental risk score of 8.3 suggests that while Amazon is making strides in sustainability, challenges remain, particularly in areas like carbon emissions and resource management. The company's commitment to renewable energy and carbon neutrality by 2040 are positive steps, yet ongoing scrutiny regarding its logistics and packaging practices continues to pose risks.\n\nThe social risk score of 11.05 is notably high, reflecting concerns related to labor practices, employee treatment, and community impact. The controversies surrounding warehouse conditions and labor rights have raised questions about the company's social responsibility, which could affect its reputation and employee retention.\n\nThe governance risk score of 6.75 indicates a moderately strong governance structure, but there are areas for improvement, particularly in transparency and shareholder engagement. The controversy level of 3.0 is significant, especially when compared to peer averages, suggesting that Amazon faces higher scrutiny than many competitors. \n\nIn summary, while Amazon is actively addressing its environmental and governance challenges, its social risks and controversy level require ongoing management to mitigate potential reputational damage and ensure sustainable long-term growth. Stakeholders should monitor these areas closely as they could impact the company\u2019s financial performance and public perception.",
        "Reference ESG Data": {
            "Stock": "AMZN",
            "Total ESG Risk Score": 26.1,
            "Environmental Risk Score": 8.3,
            "Social Risk Score": 11.05,
            "Governance Risk Score": 6.75,
            "Controversy Level": 3.0,
            "Peer Controversy Min": 0.0,
            "Peer Controversy Avg": 0.9104477611940298,
            "Peer Controversy Max": 4.0
        },
        "Faithfulness Evaluation": {
            "Score": 1.0,
            "Explanation": "The generated ESG report accurately reflects the provided reference ESG data for Amazon (AMZN). The total ESG risk score of 26.1 is correctly stated, and the individual scores for environmental (8.3), social (11.05), and governance (6.75) risks are also consistent with the reference data. The report appropriately highlights the moderate risk associated with these scores and discusses specific areas of concern, such as carbon emissions, labor practices, and governance transparency, which align with the risk scores provided. Additionally, the mention of a controversy level of 3.0 and its implications compared to peer averages is well-articulated. Overall, the report is grounded in the actual data and provides a faithful representation of Amazon's ESG performance."
        }
    },
    "TQQQ": {
        "Generated Report": "No ESG data available for TQQQ",
        "Reference ESG Data": {
            "error": "No ESG data available for TQQQ"
        },
        "Faithfulness Evaluation": "Could not evaluate due to error in data or report generation."
    },
    "AMD": {
        "Generated Report": "AMD's total ESG risk score of 12.51 indicates a moderate level of overall risk, with specific strengths and weaknesses across environmental, social, and governance dimensions. The environmental risk score of 3.01 suggests that while AMD is making strides in sustainability, there are areas for improvement, especially in energy consumption and e-waste management, which are critical in the semiconductor industry.\n\nThe social risk score of 4.22 highlights potential concerns related to labor practices, community engagement, and product responsibility. Given the increasing scrutiny on supply chain ethics and workforce diversity, AMD may face reputational risks if these issues are not adequately addressed.\n\nAMD\u2019s governance risk score of 5.28 indicates a relatively higher level of risk in this area, suggesting potential challenges in board diversity, executive compensation, and shareholder rights. Strong governance practices are essential for long-term sustainability, particularly in a competitive landscape.\n\nThe controversy level of 1.0, significantly lower than the peer average of 0.56, suggests that AMD has managed to avoid major public controversies, which is a positive indicator for investors. However, it is essential for the company to remain vigilant and proactive in addressing ESG issues to mitigate potential risks.\n\nIn summary, while AMD demonstrates a solid foundational approach to ESG, enhancing its environmental and governance practices will be crucial in improving its sustainability profile and reducing associated risks.",
        "Reference ESG Data": {
            "Stock": "AMD",
            "Total ESG Risk Score": 12.51,
            "Environmental Risk Score": 3.01,
            "Social Risk Score": 4.22,
            "Governance Risk Score": 5.28,
            "Controversy Level": 1.0,
            "Peer Controversy Min": 0.0,
            "Peer Controversy Avg": 0.5583333333333333,
            "Peer Controversy Max": 3.0
        },
        "Faithfulness Evaluation": {
            "Score": 1.0,
            "Explanation": "The generated ESG report accurately reflects the reference ESG data provided for AMD. It correctly states the total ESG risk score of 12.51 and breaks down the environmental, social, and governance risk scores as 3.01, 4.22, and 5.28, respectively. The commentary on each risk area aligns with the scores, indicating both strengths and weaknesses. Furthermore, the report accurately notes the controversy level of 1.0 and compares it favorably to the peer average of 0.56, reinforcing AMD's positive standing in this regard. Overall, the report is grounded in the actual data and presents a faithful representation of AMD's ESG profile."
        }
    },
    "NFLX": {
        "Generated Report": "Netflix (NFLX) exhibits a total ESG risk score of 15.88, indicating a moderate level of sustainability risk when compared to its peers. Breaking down the scores, the Environmental Risk Score is notably low at 0.16, suggesting that Netflix has minimal environmental impact and is likely managing its carbon footprint and resource usage effectively.\n\nHowever, the Social Risk Score of 7.38 and Governance Risk Score of 8.35 are considerably higher, indicating areas of concern. The social risk score reflects potential issues related to labor practices, diversity, content appropriateness, or customer relations. The governance score suggests possible challenges in corporate governance, which could relate to board diversity, executive compensation, or transparency issues.\n\nThe company's Controversy Level stands at 2.0, which is above the peer average of 1.01 but below the maximum of 3.0. This indicates that while Netflix has faced some controversies\u2014possibly related to content decisions or labor practices\u2014it is not at the highest risk tier. Nonetheless, the elevated controversy score compared to peers raises red flags for investors who prioritize social and governance factors.\n\nIn summary, while Netflix demonstrates robust environmental performance, the elevated social and governance risks, along with its controversy level, suggest potential vulnerabilities that could impact its reputation and operational stability. Investors should monitor these aspects closely as they could affect long-term sustainability and profitability.",
        "Reference ESG Data": {
            "Stock": "NFLX",
            "Total ESG Risk Score": 15.88,
            "Environmental Risk Score": 0.16,
            "Social Risk Score": 7.38,
            "Governance Risk Score": 8.35,
            "Controversy Level": 2.0,
            "Peer Controversy Min": 0.0,
            "Peer Controversy Avg": 1.0070921985815602,
            "Peer Controversy Max": 3.0
        },
        "Faithfulness Evaluation": {
            "Score": 1.0,
            "Explanation": "The generated ESG report accurately reflects the reference ESG data for Netflix (NFLX). It correctly states the total ESG risk score of 15.88 and provides a precise breakdown of the Environmental Risk Score (0.16), Social Risk Score (7.38), and Governance Risk Score (8.35). The report also accurately describes the controversy level of 2.0, contextualizing it against the peer average of 1.01 and the maximum of 3.0. Furthermore, the interpretations regarding the implications of these scores for investors are well-aligned with the data provided. Overall, the report is faithful to the reference data, providing an accurate and grounded assessment of Netflix's ESG performance."
        }
    }
}