{
    "TSLA": {
        "Generated Report": "Tesla Inc. (TSLA) exhibits a mixed ESG risk profile, with a total ESG Risk Score of 24.76. The Environmental Risk Score of 3.04 is relatively low, suggesting that Tesla's sustainability initiatives, particularly in renewable energy and electric vehicles (EVs), are positively impacting its environmental footprint. This aligns with the company's mission to accelerate the world's transition to sustainable energy.\n\nHowever, the Social Risk Score of 14.13 raises significant concerns. This score indicates potential issues related to labor practices, customer relations, and community impacts, which could pose reputational and operational risks. The company's controversies, reflected in a Controversy Level of 3.0, suggest that it has faced notable public scrutiny, particularly regarding workplace conditions and leadership decisions. Compared to peers, TSLA's controversy level is relatively high, with the average at 1.75, indicating that Tesla may be more exposed to social backlash than its competitors.\n\nThe Governance Risk Score of 7.6 highlights potential weaknesses in management practices or board oversight, which could further exacerbate stakeholder concerns. Given these factors, while Tesla is a leader in environmental initiatives, its high social and governance risks warrant attention. Investors should consider these elements carefully, as social and governance challenges could impact the company\u2019s long-term sustainability and financial performance. Addressing these issues will be crucial for Tesla to enhance its ESG profile and mitigate potential risks.",
        "Reference ESG Data": {
            "Stock": "TSLA",
            "Total ESG Risk Score": 24.76,
            "Environmental Risk Score": 3.04,
            "Social Risk Score": 14.13,
            "Governance Risk Score": 7.6,
            "Controversy Level": 3.0,
            "Peer Controversy Min": 0.0,
            "Peer Controversy Avg": 1.75,
            "Peer Controversy Max": 4.0
        },
        "Faithfulness Evaluation": {
            "Score": 1.0,
            "Explanation": "The generated ESG report accurately reflects the reference ESG data for Tesla Inc. (TSLA). It correctly states the total ESG Risk Score of 24.76 and breaks down the individual scores for Environmental (3.04), Social (14.13), and Governance (7.6) risks. The report also appropriately discusses the implications of these scores, particularly highlighting the concerns raised by the high Social Risk Score and the Controversy Level of 3.0, which is indeed higher than the peer average of 1.75. The analysis of Tesla's strengths in environmental initiatives alongside its weaknesses in social and governance aspects is well-aligned with the provided data. Overall, the report is faithful to the reference data and provides a coherent narrative that accurately reflects Tesla's ESG profile."
        }
    },
    "NVDA": {
        "Generated Report": "NVIDIA Corporation (NVDA) presents a mixed picture in its ESG (Environmental, Social, and Governance) analysis. With a total ESG risk score of 12.46, the company is positioned in a moderate risk category, suggesting that while it faces certain challenges, it is not among the highest-risk entities in its sector.\n\nThe environmental risk score of 2.73 indicates relatively low environmental concerns, reflecting NVDA's commitment to sustainable practices in its operations and product offerings. This is particularly significant in the semiconductor industry, where resource consumption and waste management are critical issues.\n\nHowever, the social risk score of 4.08 highlights potential vulnerabilities, particularly in areas related to labor practices, community engagement, and diversity within the workforce. This score indicates that NVDA could face scrutiny from stakeholders regarding its social impact and employee relations.\n\nThe governance risk score of 5.65 suggests room for improvement in corporate governance practices, including transparency, board diversity, and shareholder rights. This score is notably higher than its environmental and social counterparts, indicating a need for NVDA to strengthen its governance frameworks.\n\nThe controversy level of 2.0, while moderate, is above the peer average (0.56), suggesting that NVDA has encountered some notable issues that could affect its reputation and investor sentiment.\n\nOverall, while NVDA demonstrates strengths in environmental efforts, the company must address social and governance risks to enhance its sustainability profile and mitigate potential vulnerabilities in a rapidly evolving market.",
        "Reference ESG Data": {
            "Stock": "NVDA",
            "Total ESG Risk Score": 12.46,
            "Environmental Risk Score": 2.73,
            "Social Risk Score": 4.08,
            "Governance Risk Score": 5.65,
            "Controversy Level": 2.0,
            "Peer Controversy Min": 0.0,
            "Peer Controversy Avg": 0.5583333333333333,
            "Peer Controversy Max": 3.0
        },
        "Faithfulness Evaluation": {
            "Score": 1.0,
            "Explanation": "The generated ESG report accurately reflects the reference ESG data for NVIDIA Corporation (NVDA). It correctly states the total ESG risk score of 12.46 and provides a breakdown of the environmental risk score (2.73), social risk score (4.08), and governance risk score (5.65). The report also appropriately discusses the controversy level of 2.0, noting that it is above the peer average of 0.56. The descriptions of the implications of these scores are consistent with the data provided, indicating a faithful representation of NVDA's ESG standing. Overall, the report is grounded in the actual data, making it perfectly faithful."
        }
    },
    "AAPL": {
        "Generated Report": "Apple Inc. (AAPL) presents a mixed ESG profile, with a Total ESG Risk Score of 18.75 indicating moderate risk exposure. The Environmental Risk Score of 2.05 reflects relatively low environmental concerns, suggesting that the company has made strides in sustainability initiatives, such as renewable energy usage and responsible product sourcing.\n\nHowever, the Social and Governance Risk Scores both stand at 8.35, indicating significant risks in these areas. The Social Risk Score suggests potential challenges related to labor practices, supply chain management, and community impacts, which may stem from the complexities of operating in various global markets. Governance issues might relate to executive pay, board diversity, or shareholder rights, which are critical for investor confidence.\n\nThe Controversy Level of 3.0, aligned with the maximum among peers, raises red flags. While Apple is not alone in facing controversies, its score indicates a need for improved stakeholder engagement and transparency regarding its operations and practices. The peer controversy average of 0.56 highlights that AAPL has a higher controversy level than the industry average, which could expose the company to reputational risks and potential backlash from consumers and investors.\n\nIn conclusion, while Apple has made progress in environmental sustainability, the elevated social and governance risks combined with a high controversy level suggest that the company needs to enhance its practices and communication strategies to mitigate potential risks and align more closely with stakeholder expectations.",
        "Reference ESG Data": {
            "Stock": "AAPL",
            "Total ESG Risk Score": 18.75,
            "Environmental Risk Score": 2.05,
            "Social Risk Score": 8.35,
            "Governance Risk Score": 8.35,
            "Controversy Level": 3.0,
            "Peer Controversy Min": 0.0,
            "Peer Controversy Avg": 0.5598290598290598,
            "Peer Controversy Max": 3.0
        },
        "Faithfulness Evaluation": {
            "Score": 1.0,
            "Explanation": "The generated ESG report accurately reflects the provided reference ESG data for Apple Inc. (AAPL). It correctly states the Total ESG Risk Score of 18.75 and breaks down the Environmental Risk Score (2.05), Social Risk Score (8.35), and Governance Risk Score (8.35) in a manner consistent with the reference data. The report also appropriately discusses the implications of these scores, particularly the significance of the high Social and Governance Risk Scores and the Controversy Level of 3.0, which aligns with the maximum among peers. Furthermore, the mention of the peer controversy average of 0.56 provides context for Apple's relative standing in the industry. Overall, the report is grounded in the actual data, making it fully faithful to the reference ESG data."
        }
    },
    "SPY": {
        "Generated Report": "No ESG data available for SPY",
        "Reference ESG Data": {
            "error": "No ESG data available for SPY"
        },
        "Faithfulness Evaluation": "Could not evaluate due to error in data or report generation."
    },
    "QQQ": {
        "Generated Report": "No ESG data available for QQQ",
        "Reference ESG Data": {
            "error": "No ESG data available for QQQ"
        },
        "Faithfulness Evaluation": "Could not evaluate due to error in data or report generation."
    },
    "META": {
        "Generated Report": "META's total ESG risk score of 32.73 suggests a moderate level of overall risk, with notable concerns in the social and governance categories. The environmental risk score is relatively low at 2.41, indicating that META has minimal environmental impacts compared to its peers. However, the social risk score of 21.64 is significantly high, reflecting potential issues related to user privacy, data security, and content moderation, which have been prominent in the public discourse surrounding the company. \n\nGovernance risk, rated at 8.68, signals potential concerns in corporate governance practices, possibly related to board diversity, executive compensation, or shareholder rights. The controversy level of 4.0 indicates that META has faced significant scrutiny and criticism, aligning with its high social risk score. In comparison to its peers, which have an average controversy score of approximately 0.66, META stands out as a company with more severe reputational risks.\n\nIn conclusion, while META exhibits low environmental risks, its elevated social and governance scores highlight substantial challenges that could impact its long-term sustainability and investment attractiveness. Stakeholders should closely monitor how the company addresses these social issues and governance practices to mitigate potential risks and enhance its ESG performance.",
        "Reference ESG Data": {
            "Stock": "META",
            "Total ESG Risk Score": 32.73,
            "Environmental Risk Score": 2.41,
            "Social Risk Score": 21.64,
            "Governance Risk Score": 8.68,
            "Controversy Level": 4.0,
            "Peer Controversy Min": 0.0,
            "Peer Controversy Avg": 0.6598984771573604,
            "Peer Controversy Max": 4.0
        },
        "Faithfulness Evaluation": {
            "Score": 1.0,
            "Explanation": "The generated ESG report accurately reflects the reference ESG data provided for META. It correctly states the total ESG risk score of 32.73 and breaks down the environmental, social, and governance risk scores as 2.41, 21.64, and 8.68, respectively. The report also appropriately highlights the significant concerns in the social and governance categories, aligning with the high social risk score and the controversy level of 4.0. Furthermore, it compares META's controversy level to its peers, noting the stark difference between META's score and the peer average of approximately 0.66. Overall, the report is grounded in the actual data and presents a faithful representation of META's ESG performance."
        }
    },
    "AMZN": {
        "Generated Report": "Amazon (AMZN) presents a mixed ESG risk profile, with a total ESG Risk Score of 26.1. The Environmental Risk Score of 8.3 indicates moderate concerns, primarily related to issues such as carbon emissions, waste management, and energy consumption. As one of the largest e-commerce and cloud computing companies, Amazon faces scrutiny over its environmental impact, particularly in light of its substantial logistics operations.\n\nThe Social Risk Score of 11.05 is notably higher, reflecting challenges related to labor practices, employee treatment, and community relations. The company's practices have been criticized for workplace conditions in fulfillment centers and the treatment of gig workers, which can pose reputational risks and impact employee retention.\n\nWith a Governance Risk Score of 6.75, Amazon's governance practices appear relatively stable, though there may be concerns regarding board diversity and executive compensation. The Controversy Level of 3.0 suggests that while the company has faced significant scrutiny, it is not at the highest level of controversy compared to peers, whose average controversy score is 0.91.\n\nOverall, while Amazon is making strides in sustainability initiatives, the elevated social risk and moderate environmental concerns highlight potential vulnerabilities. Investors should remain vigilant about these factors as they could impact long-term performance, stakeholder relations, and regulatory scrutiny. Addressing these issues proactively could enhance its ESG standing and mitigate risks.",
        "Reference ESG Data": {
            "Stock": "AMZN",
            "Total ESG Risk Score": 26.1,
            "Environmental Risk Score": 8.3,
            "Social Risk Score": 11.05,
            "Governance Risk Score": 6.75,
            "Controversy Level": 3.0,
            "Peer Controversy Min": 0.0,
            "Peer Controversy Avg": 0.9104477611940298,
            "Peer Controversy Max": 4.0
        },
        "Faithfulness Evaluation": {
            "Score": 1.0,
            "Explanation": "The generated ESG report accurately reflects the provided reference ESG data for Amazon (AMZN). It correctly states the total ESG Risk Score of 26.1 and breaks down the individual scores for Environmental (8.3), Social (11.05), and Governance (6.75) risks, aligning perfectly with the reference data. The report also appropriately discusses the implications of these scores, such as the moderate environmental concerns and significant social risks, which are consistent with the data provided. Additionally, the mention of the Controversy Level of 3.0 and its context compared to peer controversy averages is accurate. Overall, the report is grounded in the actual data and provides a faithful representation of Amazon's ESG profile."
        }
    },
    "TQQQ": {
        "Generated Report": "No ESG data available for TQQQ",
        "Reference ESG Data": {
            "error": "No ESG data available for TQQQ"
        },
        "Faithfulness Evaluation": "Could not evaluate due to error in data or report generation."
    },
    "AMD": {
        "Generated Report": "Advanced Micro Devices (AMD) exhibits a total ESG risk score of 12.51, which suggests a moderate level of risk in its operations. The breakdown of the scores reveals a relatively strong performance in environmental aspects (3.01), indicating that AMD is taking steps to mitigate its environmental impact, although there is still room for improvement. \n\nThe social risk score of 4.22 indicates potential challenges related to stakeholder engagement, labor practices, or community relations, which may require closer scrutiny. Governance risk is the highest at 5.28, highlighting possible concerns in corporate governance practices, including decision-making processes and board diversity.\n\nThe controversy level of 1.0 is notably low compared to its peers, with an average controversy level of 0.56 and a maximum of 3.0. This suggests that AMD has managed to avoid significant scandals or public relations issues that could negatively impact its reputation.\n\nOverall, while AMD's environmental performance is commendable, the higher governance risk score warrants attention. The company\u2019s relatively low controversy level reflects positively on its public image, but ongoing diligence in governance and social aspects is essential to mitigate potential risks. In conclusion, AMD demonstrates a commitment to sustainability, yet it must address governance and social challenges to enhance its overall ESG profile and reduce future risks.",
        "Reference ESG Data": {
            "Stock": "AMD",
            "Total ESG Risk Score": 12.51,
            "Environmental Risk Score": 3.01,
            "Social Risk Score": 4.22,
            "Governance Risk Score": 5.28,
            "Controversy Level": 1.0,
            "Peer Controversy Min": 0.0,
            "Peer Controversy Avg": 0.5583333333333333,
            "Peer Controversy Max": 3.0
        },
        "Faithfulness Evaluation": {
            "Score": 1.0,
            "Explanation": "The generated ESG report accurately reflects the reference ESG data for AMD. It correctly states the total ESG risk score of 12.51 and provides a detailed breakdown of the environmental (3.01), social (4.22), and governance (5.28) risk scores. The report also appropriately highlights the low controversy level of 1.0 and compares it favorably against peer averages, which is consistent with the reference data. The analysis of AMD's strengths and weaknesses in environmental, social, and governance aspects aligns well with the provided scores, and the recommendations for improvement are reasonable given the context of the scores. Overall, the report is faithful to the actual data, meriting a perfect score."
        }
    },
    "NFLX": {
        "Generated Report": "Netflix (NFLX) presents a mixed ESG profile based on its risk scores and controversy level. The total ESG Risk Score of 15.88 suggests a moderate level of risk, with a notably low Environmental Risk Score of 0.16, indicating that the company has minimal direct environmental impact. This is a positive aspect, especially in an industry increasingly scrutinized for its energy consumption and carbon footprint.\n\nHowever, the higher Social Risk Score of 7.38 and Governance Risk Score of 8.35 highlight significant areas of concern. The elevated social risks may stem from issues related to content diversity, labor practices, or employee satisfaction, while the governance score suggests potential weaknesses in corporate governance practices or board diversity.\n\nThe controversy level of 2.0, while lower than the maximum of 3.0, indicates that Netflix has faced some controversies, but this is relatively moderate compared to its peers, where the average is approximately 1.01. This indicates that while the company is not free from scrutiny, it is performing better than some competitors.\n\nIn summary, while Netflix excels in environmental sustainability, its social and governance challenges present potential risks to its long-term sustainability. Investors should monitor these aspects closely, as they could impact the company's reputation and operational performance in an increasingly ESG-conscious market.",
        "Reference ESG Data": {
            "Stock": "NFLX",
            "Total ESG Risk Score": 15.88,
            "Environmental Risk Score": 0.16,
            "Social Risk Score": 7.38,
            "Governance Risk Score": 8.35,
            "Controversy Level": 2.0,
            "Peer Controversy Min": 0.0,
            "Peer Controversy Avg": 1.0070921985815602,
            "Peer Controversy Max": 3.0
        },
        "Faithfulness Evaluation": {
            "Score": 0.9,
            "Explanation": "The generated ESG report accurately reflects the reference ESG data for Netflix (NFLX) in several key areas, such as the total ESG Risk Score (15.88), the low Environmental Risk Score (0.16), and the higher Social (7.38) and Governance (8.35) Risk Scores. The report also correctly notes the controversy level of 2.0 and compares it to peer averages, providing context for Netflix's performance relative to competitors.\n\nHowever, the report could improve by explicitly stating that the total ESG Risk Score of 15.88 indicates a moderate level of risk rather than implying it is simply \"mixed.\" Additionally, while the report discusses the implications of social and governance challenges, it could benefit from more specific examples or data points to substantiate the claims about content diversity, labor practices, or governance weaknesses. Overall, the report is largely faithful to the reference data but lacks some depth and specificity, warranting a score of 0.9."
        }
    }
}