{
    "TSLA": {
        "Generated Report": "Tesla, Inc. (TSLA) presents a mixed ESG profile, with a total ESG risk score of 24.76, indicating a moderate level of overall risk. The Environmental Risk Score stands at 3.04, which is relatively low and reflects positively on the company\u2019s commitment to sustainability, particularly as a leader in electric vehicles and renewable energy solutions. This score suggests that Tesla is effectively managing its environmental impact, which aligns with its mission to accelerate the world's transition to sustainable energy.\n\nHowever, the Social Risk Score of 14.13 raises concerns, highlighting potential issues related to labor practices, community engagement, and customer relations. This elevated score suggests that Tesla may face challenges in addressing social equity and stakeholder relationships, which could pose reputational risks and affect long-term sustainability.\n\nThe Governance Risk Score of 7.6 is moderate and indicates some governance-related challenges, possibly linked to executive compensation, board diversity, or shareholder rights. \n\nThe Controversy Level of 3.0, significantly higher than the peer average of 1.75, suggests that Tesla has encountered notable controversies, which could impact investor sentiment and regulatory scrutiny.\n\nIn conclusion, while Tesla shows strong environmental performance, its elevated social risk score and controversy level indicate potential vulnerabilities that could affect its sustainability and overall risk profile. Investors should weigh these factors carefully when considering Tesla as part of an ESG-focused investment strategy.",
        "Reference ESG Data": {
            "Stock": "TSLA",
            "Total ESG Risk Score": 24.76,
            "Environmental Risk Score": 3.04,
            "Social Risk Score": 14.13,
            "Governance Risk Score": 7.6,
            "Controversy Level": 3.0,
            "Peer Controversy Min": 0.0,
            "Peer Controversy Avg": 1.75,
            "Peer Controversy Max": 4.0
        },
        "Faithfulness Evaluation": {
            "Score": 1.0,
            "Explanation": "The generated ESG report accurately reflects the reference ESG data provided for Tesla, Inc. (TSLA). It correctly states the total ESG risk score of 24.76 and breaks down the environmental, social, and governance risk scores as 3.04, 14.13, and 7.6, respectively. The report also appropriately highlights the controversy level of 3.0 and compares it to the peer average of 1.75, indicating a notable level of controversy. The analysis of Tesla's strengths in environmental performance and weaknesses in social risk and governance aligns well with the data, making the report both comprehensive and faithful to the actual ESG metrics."
        }
    },
    "NVDA": {
        "Generated Report": "NVIDIA Corporation (NVDA) displays a moderate overall ESG risk profile with a Total ESG Risk Score of 12.46, indicating manageable sustainability risks. The Environmental Risk Score of 2.73 suggests minimal environmental impact, reflecting the company's initiatives in energy efficiency and commitment to reducing carbon emissions. However, there is room for improvement, particularly as the tech industry faces increasing scrutiny over environmental practices.\n\nThe Social Risk Score of 4.08 highlights potential concerns related to labor practices, community engagement, and product responsibility. This score suggests that while NVIDIA maintains a solid social framework, there are areas for enhancement, especially given the industry's focus on diversity and inclusion.\n\nThe Governance Risk Score of 5.65 indicates a higher level of concern in this area, with potential issues related to board diversity, executive compensation, and shareholder rights. This score warrants attention, as governance practices are critical in maintaining investor trust and ensuring long-term sustainability.\n\nThe Controversy Level of 2.0, above the peer average of 0.56, suggests that NVIDIA has faced notable challenges or negative publicity, which could impact its reputation and investor sentiment. Although the controversy is not extreme, it is essential for the company to address these issues proactively.\n\nIn summary, while NVDA demonstrates strengths in environmental performance, the higher scores in social and governance areas, along with its controversy level, indicate potential risks that need to be monitored for sustainable growth.",
        "Reference ESG Data": {
            "Stock": "NVDA",
            "Total ESG Risk Score": 12.46,
            "Environmental Risk Score": 2.73,
            "Social Risk Score": 4.08,
            "Governance Risk Score": 5.65,
            "Controversy Level": 2.0,
            "Peer Controversy Min": 0.0,
            "Peer Controversy Avg": 0.5583333333333333,
            "Peer Controversy Max": 3.0
        },
        "Faithfulness Evaluation": {
            "Score": 0.9,
            "Explanation": "The generated ESG report accurately reflects the Total ESG Risk Score of 12.46 and provides a reasonable interpretation of the Environmental, Social, and Governance Risk Scores (2.73, 4.08, and 5.65, respectively). The descriptions of each score align well with the reference data, indicating manageable sustainability risks and areas for improvement. \n\nHowever, the report could be slightly misleading regarding the Environmental Risk Score, which is described as suggesting \"minimal environmental impact.\" While 2.73 is relatively low, it is not necessarily indicative of minimal impact; it is better characterized as a moderate risk. \n\nThe mention of the Controversy Level being above the peer average is accurate, but the report could have emphasized the significance of this discrepancy more clearly. Overall, the report is mostly faithful to the reference data, with minor nuances that could be better articulated, justifying a score of 0.9."
        }
    },
    "AAPL": {
        "Generated Report": "Apple Inc. (AAPL) presents a mixed ESG profile based on its risk scores and controversy level. With a total ESG Risk Score of 18.75, the company exhibits relatively low environmental risk (2.05) compared to social and governance risks (both at 8.35). This suggests that while Apple has made strides in environmental sustainability\u2014such as reducing carbon emissions and enhancing product recyclability\u2014social and governance challenges remain significant.\n\nThe social risk score indicates potential issues related to labor practices, supply chain management, and customer privacy concerns. Apple's substantial reliance on overseas manufacturing raises questions about labor conditions and ethical sourcing, which may expose the company to reputational risks. Similarly, governance risks may stem from issues like executive compensation, shareholder rights, and overall transparency.\n\nThe controversy level of 3.0 places Apple at the higher end of the spectrum compared to its peers, where the minimum is 0.0 and the average is approximately 0.56. This elevated controversy level signifies that Apple has faced notable criticisms or scandals, which could impact investor sentiment and stakeholder trust.\n\nOverall, while Apple demonstrates a commitment to environmental sustainability, the significant social and governance risks suggest that the company should enhance its practices in these areas to mitigate potential reputational damage and align more closely with stakeholder expectations. Addressing these risks could bolster Apple's standing in the ESG landscape and support long-term value creation.",
        "Reference ESG Data": {
            "Stock": "AAPL",
            "Total ESG Risk Score": 18.75,
            "Environmental Risk Score": 2.05,
            "Social Risk Score": 8.35,
            "Governance Risk Score": 8.35,
            "Controversy Level": 3.0,
            "Peer Controversy Min": 0.0,
            "Peer Controversy Avg": 0.5598290598290598,
            "Peer Controversy Max": 3.0
        },
        "Faithfulness Evaluation": {
            "Score": 0.9,
            "Explanation": "The generated ESG report accurately reflects the reference ESG data for Apple Inc. (AAPL) in several key areas. The total ESG Risk Score of 18.75 is correctly stated, as are the environmental, social, and governance risk scores of 2.05, 8.35, and 8.35 respectively. The report appropriately highlights the relatively low environmental risk compared to the higher social and governance risks, aligning with the data provided.\n\nThe mention of the controversy level being 3.0 is also accurate, and the comparison to peer controversy levels (minimum of 0.0 and average of approximately 0.56) is well articulated. The report effectively discusses the implications of these scores, particularly regarding labor practices and governance issues, which are pertinent to Apple's operations.\n\nHowever, the report could be slightly improved by providing more specific examples or data points related to the controversies faced by Apple, which would enhance its grounding in the actual data. Nonetheless, the overall analysis and conclusions drawn are largely faithful to the reference data, justifying a score of 0.9."
        }
    },
    "SPY": {
        "Generated Report": "No ESG data available for SPY",
        "Reference ESG Data": {
            "error": "No ESG data available for SPY"
        },
        "Faithfulness Evaluation": "Could not evaluate due to error in data or report generation."
    },
    "QQQ": {
        "Generated Report": "No ESG data available for QQQ",
        "Reference ESG Data": {
            "error": "No ESG data available for QQQ"
        },
        "Faithfulness Evaluation": "Could not evaluate due to error in data or report generation."
    },
    "META": {
        "Generated Report": "META's ESG risk scores indicate a balanced but nuanced sustainability profile. The total ESG risk score of 32.73 suggests a moderate level of risk. Breaking it down further, the Environmental Risk Score of 2.41 is relatively low, indicating that META has not faced significant environmental challenges compared to its peers. This suggests that the company is making strides in minimizing its environmental footprint.\n\nHowever, the Social Risk Score of 21.64 raises concerns. This score reflects significant risks related to social issues, potentially encompassing data privacy, misinformation, user safety, and labor practices. META's governance score of 8.68, while higher than its environmental score, points to potential governance challenges, possibly relating to board structure, executive compensation, or regulatory compliance.\n\nThe controversy level of 4.0 is concerning, especially considering that the peer average is only 0.66. This high level of controversy suggests that META has been involved in significant public or regulatory scrutiny, which could impact its reputation and operational stability.\n\nIn summary, while META demonstrates a low environmental risk, the elevated social risk and governance concerns, coupled with a high controversy level, indicate that the company faces substantial challenges that could affect its long-term sustainability and investment appeal. Investors should monitor these areas closely as they could lead to increased volatility and reputational damage.",
        "Reference ESG Data": {
            "Stock": "META",
            "Total ESG Risk Score": 32.73,
            "Environmental Risk Score": 2.41,
            "Social Risk Score": 21.64,
            "Governance Risk Score": 8.68,
            "Controversy Level": 4.0,
            "Peer Controversy Min": 0.0,
            "Peer Controversy Avg": 0.6598984771573604,
            "Peer Controversy Max": 4.0
        },
        "Faithfulness Evaluation": {
            "Score": 0.9,
            "Explanation": "The generated ESG report is largely faithful to the reference ESG data, accurately reflecting the total ESG risk score of 32.73 and the breakdown of the environmental (2.41), social (21.64), and governance (8.68) risk scores. It correctly identifies the low environmental risk and highlights the significant social risk, which is a critical aspect of META's profile. The report also appropriately notes the high controversy level of 4.0, especially in comparison to the peer average of 0.66, which is a significant point of concern.\n\nHowever, the report could be slightly improved by providing more context on how the social and governance risks specifically relate to META's operations, as well as a clearer explanation of the implications of the controversy level. While it captures the essence of the data well, the lack of specific examples or deeper analysis on the implications of the governance score slightly detracts from its overall faithfulness. Thus, a score of 0.9 reflects a high level of accuracy with minor areas for enhancement."
        }
    },
    "AMZN": {
        "Generated Report": "Amazon (AMZN) presents a mixed ESG profile, with a total ESG Risk Score of 26.1 indicating a moderate level of risk. The Environmental Risk Score of 8.3 suggests that the company faces significant challenges related to its environmental impact, notably in areas like carbon emissions, waste management, and resource usage. This is particularly relevant given the company's extensive logistics operations and the increasing scrutiny on corporate carbon footprints.\n\nThe Social Risk Score of 11.05 is concerning, reflecting potential risks associated with labor practices, community relations, and customer engagement. Amazon has faced criticism over worker treatment and workplace conditions, which can lead to reputational damage and operational disruptions.\n\nThe Governance Risk Score of 6.75 indicates that while there are governance issues, they are less pronounced than environmental and social concerns. Nevertheless, governance practices remain crucial for ensuring long-term sustainability and accountability, particularly in a rapidly changing regulatory landscape.\n\nThe Controversy Level of 3.0, significantly above the peer average of 0.91, highlights that Amazon is involved in notable controversies, which could affect its brand and stakeholder trust. \n\nIn conclusion, while Amazon is a dominant player in e-commerce and technology, its elevated risks across environmental and social dimensions, coupled with a high controversy level, suggest that investors should remain cautious and actively monitor these factors in their ESG assessments.",
        "Reference ESG Data": {
            "Stock": "AMZN",
            "Total ESG Risk Score": 26.1,
            "Environmental Risk Score": 8.3,
            "Social Risk Score": 11.05,
            "Governance Risk Score": 6.75,
            "Controversy Level": 3.0,
            "Peer Controversy Min": 0.0,
            "Peer Controversy Avg": 0.9104477611940298,
            "Peer Controversy Max": 4.0
        },
        "Faithfulness Evaluation": {
            "Score": 1.0,
            "Explanation": "The generated ESG report accurately reflects the reference ESG data for Amazon (AMZN). It correctly states the total ESG Risk Score of 26.1 and provides detailed breakdowns of the Environmental Risk Score (8.3), Social Risk Score (11.05), and Governance Risk Score (6.75), all of which align with the reference data. The commentary on the controversy level being 3.0, which is significantly higher than the peer average of 0.91, is also accurately represented. The report effectively contextualizes these scores by discussing the implications of Amazon's operations and the associated risks, making it a faithful representation of the actual ESG data."
        }
    },
    "TQQQ": {
        "Generated Report": "No ESG data available for TQQQ",
        "Reference ESG Data": {
            "error": "No ESG data available for TQQQ"
        },
        "Faithfulness Evaluation": "Could not evaluate due to error in data or report generation."
    },
    "AMD": {
        "Generated Report": "Advanced Micro Devices (AMD) demonstrates a total ESG risk score of 12.51, which suggests a moderate level of risk across environmental, social, and governance dimensions. The Environmental Risk Score of 3.01 indicates that while AMD has room for improvement, it is relatively lower compared to peers in the semiconductor industry. This score reflects the company\u2019s efforts in energy efficiency and sustainable manufacturing practices.\n\nThe Social Risk Score of 4.22 points to potential vulnerabilities, particularly regarding labor practices, community engagement, and diversity initiatives. While AMD has made strides in promoting diversity, ongoing scrutiny in this area could expose the company to social risks.\n\nA Governance Risk Score of 5.28 suggests that AMD faces significant challenges in its governance practices, including board diversity and shareholder rights. This score is higher than the environmental and social scores, indicating that governance issues may pose a notable risk to stakeholders.\n\nThe Controversy Level of 1.0, significantly below the peer average of 0.56, reflects a relatively low incidence of negative events or public disputes. This positions AMD favorably within its sector, as lower controversy levels often correlate with better reputational stability.\n\nOverall, while AMD shows potential in its sustainability practices, it must address governance and social challenges to enhance its ESG profile and mitigate potential risks. Continuous monitoring of these areas will be crucial for maintaining investor confidence and ensuring long-term sustainability.",
        "Reference ESG Data": {
            "Stock": "AMD",
            "Total ESG Risk Score": 12.51,
            "Environmental Risk Score": 3.01,
            "Social Risk Score": 4.22,
            "Governance Risk Score": 5.28,
            "Controversy Level": 1.0,
            "Peer Controversy Min": 0.0,
            "Peer Controversy Avg": 0.5583333333333333,
            "Peer Controversy Max": 3.0
        },
        "Faithfulness Evaluation": {
            "Score": 1.0,
            "Explanation": "The generated ESG report accurately reflects the provided reference ESG data for AMD. It correctly states the total ESG risk score of 12.51 and breaks down the environmental, social, and governance risk scores as 3.01, 4.22, and 5.28, respectively. The report also appropriately contextualizes these scores, indicating that AMD has room for improvement in environmental practices and highlights the potential vulnerabilities in social and governance areas. Additionally, the controversy level of 1.0 is correctly noted as being significantly below the peer average of 0.56, which is an important aspect of the report. Overall, the report is faithful to the reference data, providing an accurate and comprehensive overview of AMD's ESG profile."
        }
    },
    "NFLX": {
        "Generated Report": "Netflix (NFLX) demonstrates a mixed ESG profile, with a total risk score of 15.88, indicating moderate risk. The Environmental Risk Score is notably low at 0.16, suggesting that the company has minimal direct environmental impact or related controversies. This is a positive aspect, especially as consumer preferences increasingly favor sustainable practices.\n\nHowever, the Social Risk Score stands at 7.38, indicating significant concerns in this area. This could relate to issues such as content representation, labor practices, or community engagement. Additionally, the Governance Risk Score of 8.35 raises red flags regarding the company's governance practices, which may include executive compensation, board diversity, or shareholder rights.\n\nThe controversy level of 2.0 is above the peer average of 1.01, indicating that Netflix has faced more significant controversies compared to its peers, although still below the maximum level of 3.0. This suggests that while there are issues to address, they are not at the highest severity.\n\nIn summary, while Netflix shows strength in environmental aspects, its social and governance risks warrant attention. Stakeholders should monitor the company's strategies to address social and governance challenges, as these could impact its reputation and operational stability. Overall, Netflix's ESG profile reflects a need for improvement, particularly in social and governance dimensions, to enhance long-term sustainability and mitigate potential risks.",
        "Reference ESG Data": {
            "Stock": "NFLX",
            "Total ESG Risk Score": 15.88,
            "Environmental Risk Score": 0.16,
            "Social Risk Score": 7.38,
            "Governance Risk Score": 8.35,
            "Controversy Level": 2.0,
            "Peer Controversy Min": 0.0,
            "Peer Controversy Avg": 1.0070921985815602,
            "Peer Controversy Max": 3.0
        },
        "Faithfulness Evaluation": {
            "Score": 1.0,
            "Explanation": "The generated ESG report accurately reflects the provided reference ESG data for Netflix (NFLX). It correctly states the total ESG risk score of 15.88 and provides a detailed breakdown of the Environmental Risk Score (0.16), Social Risk Score (7.38), Governance Risk Score (8.35), and controversy level (2.0). The report contextualizes these scores effectively, noting the low environmental impact, significant social concerns, and governance issues, all of which align with the reference data. Additionally, it appropriately compares the controversy level to the peer average, highlighting Netflix's position relative to its peers. Overall, the report is faithful to the actual data, providing a comprehensive and accurate summary of Netflix's ESG profile."
        }
    }
}