{
    "TSLA": {
        "Generated Report": "Tesla, Inc. (TSLA) presents a mixed picture in terms of ESG performance, with a total ESG Risk Score of 24.76. The Environmental Risk Score is relatively low at 3.04, highlighting Tesla's strong commitment to sustainability through its electric vehicle production and renewable energy initiatives. This positions the company favorably in the context of environmental concerns, particularly as global demand for clean energy solutions grows.\n\nHowever, the Social Risk Score of 14.13 indicates significant vulnerabilities in this area. This elevated score suggests potential issues related to labor practices, workplace culture, and community relations, which could pose reputational risks and affect employee retention and recruitment. Furthermore, the Governance Risk Score of 7.6 raises concerns about corporate governance practices, which may include board diversity, executive compensation, and shareholder rights.\n\nThe Controversy Level at 3.0 reflects a moderate level of controversies surrounding the company, higher than the peer average of 1.75. This suggests that while Tesla is a leader in the electric vehicle market, it faces challenges that could impact investor perception and stakeholder trust.\n\nIn summary, while Tesla excels environmentally, significant social and governance risks, coupled with a higher-than-average controversy level, may hinder its overall sustainability profile and expose it to potential operational and reputational risks. Investors should carefully consider these factors when evaluating Tesla's long-term viability and impact on sustainability.",
        "Reference ESG Data": {
            "Stock": "TSLA",
            "Total ESG Risk Score": 24.76,
            "Environmental Risk Score": 3.04,
            "Social Risk Score": 14.13,
            "Governance Risk Score": 7.6,
            "Controversy Level": 3.0,
            "Peer Controversy Min": 0.0,
            "Peer Controversy Avg": 1.75,
            "Peer Controversy Max": 4.0
        },
        "Faithfulness Evaluation": {
            "Score": 1.0,
            "Explanation": "The generated ESG report accurately reflects the provided reference ESG data for Tesla, Inc. (TSLA). It correctly states the total ESG Risk Score of 24.76 and provides a detailed breakdown of the Environmental Risk Score (3.04), Social Risk Score (14.13), and Governance Risk Score (7.6). The report also appropriately highlights the implications of these scores, particularly the significant vulnerabilities in social and governance aspects, and contextualizes the controversy level (3.0) in relation to peer averages. Overall, the report is faithful to the reference data, providing a comprehensive and accurate assessment of Tesla's ESG performance."
        }
    },
    "NVDA": {
        "Generated Report": "NVIDIA Corporation (NVDA) presents a mixed ESG profile, with a total ESG risk score of 12.46, indicating a moderate level of risk. Breaking down the scores, the Environmental Risk Score of 2.73 is relatively low, suggesting that the company is effectively managing its environmental impacts. This is crucial in the semiconductor industry, which often faces scrutiny over energy consumption and waste management. \n\nHowever, the Social Risk Score of 4.08 indicates potential vulnerabilities in areas such as labor practices, community engagement, and product safety. This warrants attention, especially in a sector increasingly focused on social responsibility and ethical labor practices.\n\nThe Governance Risk Score is the highest at 5.65, highlighting potential concerns related to corporate governance practices, such as board diversity, executive compensation, and shareholder rights. Strong governance is critical for mitigating risks and ensuring long-term sustainability.\n\nNVIDIA's Controversy Level of 2.0, while higher than the peer average of 0.56, remains moderate compared to the maximum of 3.0. This suggests that the company has faced some controversies, which could impact its reputation and investor sentiment.\n\nIn conclusion, while NVDA demonstrates positive environmental management, the higher social and governance risk scores, along with a notable controversy level, indicate that investors should monitor these areas closely. Addressing these risks will be essential for sustaining long-term growth and maintaining stakeholder trust.",
        "Reference ESG Data": {
            "Stock": "NVDA",
            "Total ESG Risk Score": 12.46,
            "Environmental Risk Score": 2.73,
            "Social Risk Score": 4.08,
            "Governance Risk Score": 5.65,
            "Controversy Level": 2.0,
            "Peer Controversy Min": 0.0,
            "Peer Controversy Avg": 0.5583333333333333,
            "Peer Controversy Max": 3.0
        },
        "Faithfulness Evaluation": {
            "Score": 1.0,
            "Explanation": "The generated ESG report accurately reflects the reference ESG data provided for NVIDIA Corporation (NVDA). It correctly states the total ESG risk score of 12.46 and breaks down the Environmental Risk Score (2.73), Social Risk Score (4.08), and Governance Risk Score (5.65) in a manner consistent with the reference data. The report also appropriately contextualizes these scores within the semiconductor industry, highlighting relevant issues such as energy consumption and labor practices. Furthermore, it accurately notes the controversy level of 2.0 and compares it to the peer average, providing a clear understanding of the company's standing relative to its peers. Overall, the report is faithful to the actual data, making it a reliable summary of NVDA's ESG profile."
        }
    },
    "AAPL": {
        "Generated Report": "Apple Inc. (AAPL) exhibits a total ESG Risk Score of 18.75, indicating a moderate level of sustainability risk. The Environmental Risk Score stands at a relatively low 2.05, suggesting that Apple is actively managing its environmental impact, which is critical given the increasing scrutiny on tech companies regarding their carbon footprints and resource usage.\n\nIn contrast, the Social and Governance Risk Scores, both at 8.35, highlight significant areas of concern. The elevated social risk could relate to labor practices, supply chain issues, or product safety concerns, which are critical for a company of Apple\u2019s scale and global presence. Similarly, the governance score indicates potential vulnerabilities in corporate governance practices, possibly reflecting issues such as executive compensation, board diversity, or shareholder rights.\n\nThe controversy level of 3.0, while within the range of peer companies (average at 0.56), suggests that Apple has faced notable public scrutiny or incidents that could impact its reputation and investor perception. This is particularly relevant as stakeholder expectations around corporate responsibility continue to rise.\n\nIn conclusion, while Apple demonstrates strong environmental management, its social and governance risks warrant close attention. Investors should consider these factors, along with the company\u2019s controversy level, when assessing the overall sustainability and potential risks associated with AAPL. A proactive approach to improving social and governance practices could mitigate risks and enhance long-term value.",
        "Reference ESG Data": {
            "Stock": "AAPL",
            "Total ESG Risk Score": 18.75,
            "Environmental Risk Score": 2.05,
            "Social Risk Score": 8.35,
            "Governance Risk Score": 8.35,
            "Controversy Level": 3.0,
            "Peer Controversy Min": 0.0,
            "Peer Controversy Avg": 0.5598290598290598,
            "Peer Controversy Max": 3.0
        },
        "Faithfulness Evaluation": {
            "Score": 1.0,
            "Explanation": "The generated ESG report accurately reflects the reference ESG data for Apple Inc. (AAPL). It correctly states the total ESG Risk Score of 18.75 and the Environmental Risk Score of 2.05, indicating a low environmental risk. The report also accurately identifies the Social and Governance Risk Scores as both being 8.35, which highlights significant concerns in these areas. Furthermore, the controversy level of 3.0 is correctly noted, and the report appropriately contextualizes this score by comparing it to the peer controversy average. Overall, the report is faithful to the provided data, providing a clear and accurate assessment of Apple's ESG risks and considerations for investors."
        }
    },
    "SPY": {
        "Generated Report": "No ESG data available for SPY",
        "Reference ESG Data": {
            "error": "No ESG data available for SPY"
        },
        "Faithfulness Evaluation": "Could not evaluate due to error in data or report generation."
    },
    "QQQ": {
        "Generated Report": "No ESG data available for QQQ",
        "Reference ESG Data": {
            "error": "No ESG data available for QQQ"
        },
        "Faithfulness Evaluation": "Could not evaluate due to error in data or report generation."
    },
    "META": {
        "Generated Report": "META's ESG risk assessment reveals a mixed sustainability profile, with a total ESG risk score of 32.73 indicating moderate risk. The Environmental Risk Score of 2.41 is relatively low, suggesting that META's environmental impact is manageable and may not pose significant risks to investors. This score reflects the company's efforts to implement sustainable practices, particularly in reducing its carbon footprint and increasing energy efficiency.\n\nHowever, the Social Risk Score of 21.64 is considerably higher, indicating significant potential risks associated with social factors. This score highlights issues such as user privacy, data security, and the societal impacts of content moderation. Given the increasing scrutiny on social media platforms, these risks could affect META's reputation and lead to regulatory challenges.\n\nThe Governance Risk Score of 8.68 is moderate, suggesting that while there are governance concerns, they are not as pressing as the social risks. The controversy level of 4.0, which matches the peer maximum, further emphasizes the intensity of scrutiny surrounding META. This high level of controversy indicates that the company is often in the spotlight for various issues, which can lead to reputational damage and potential financial implications.\n\nIn conclusion, while META shows relatively strong environmental performance, the elevated social risk and high controversy level warrant close monitoring. Investors should consider these factors when assessing the company's long-term sustainability and potential risks.",
        "Reference ESG Data": {
            "Stock": "META",
            "Total ESG Risk Score": 32.73,
            "Environmental Risk Score": 2.41,
            "Social Risk Score": 21.64,
            "Governance Risk Score": 8.68,
            "Controversy Level": 4.0,
            "Peer Controversy Min": 0.0,
            "Peer Controversy Avg": 0.6598984771573604,
            "Peer Controversy Max": 4.0
        },
        "Faithfulness Evaluation": {
            "Score": 1.0,
            "Explanation": "The generated ESG report accurately reflects the provided reference ESG data for META. It correctly states the total ESG risk score of 32.73 and breaks down the individual scores for environmental (2.41), social (21.64), and governance (8.68) risks, aligning perfectly with the reference data. The report also appropriately discusses the implications of these scores, particularly emphasizing the significant social risks and high controversy level (4.0), which is consistent with the reference data indicating that this is the maximum among peers. Overall, the report is faithful to the actual data and provides a clear and accurate assessment of META's ESG profile."
        }
    },
    "AMZN": {
        "Generated Report": "Amazon (AMZN) presents a mixed ESG profile, with a total ESG risk score of 26.1, indicating a moderate level of risk. The environmental risk score of 8.3 suggests that the company faces significant challenges in its environmental practices, particularly concerning carbon emissions, waste management, and resource usage. This score reflects ongoing scrutiny over its logistics and fulfillment operations, which are energy-intensive.\n\nThe social risk score of 11.05 is notably higher, highlighting substantial concerns related to labor practices, employee treatment, and community impact. Reports of worker dissatisfaction, warehouse conditions, and strikes have contributed to this elevated score, suggesting that social sustainability is a critical area for improvement.\n\nGovernance risk, at 6.75, indicates relatively better practices compared to environmental and social domains, although there remains room for enhancement in transparency and stakeholder engagement. The controversy level of 3.0 is significant and exceeds both the peer average (0.91) and maximum (4.0), indicating that Amazon is frequently in the news for negative reasons, which could affect its reputation and investor sentiment.\n\nIn summary, while Amazon has made strides in certain areas, its high social and environmental risk scores, coupled with a substantial controversy level, pose potential risks to its long-term sustainability and attractiveness to ESG-focused investors. Continuous oversight and proactive measures are essential for mitigating these risks and improving its overall ESG standing.",
        "Reference ESG Data": {
            "Stock": "AMZN",
            "Total ESG Risk Score": 26.1,
            "Environmental Risk Score": 8.3,
            "Social Risk Score": 11.05,
            "Governance Risk Score": 6.75,
            "Controversy Level": 3.0,
            "Peer Controversy Min": 0.0,
            "Peer Controversy Avg": 0.9104477611940298,
            "Peer Controversy Max": 4.0
        },
        "Faithfulness Evaluation": {
            "Score": 1.0,
            "Explanation": "The generated ESG report accurately reflects the reference ESG data provided. It correctly states the total ESG risk score of 26.1 and breaks down the environmental risk score (8.3), social risk score (11.05), and governance risk score (6.75) in alignment with the reference data. The report also appropriately highlights the controversy level of 3.0 and compares it to the peer controversy average (0.91) and maximum (4.0), emphasizing the significance of Amazon's controversy level. The descriptions of the challenges in environmental practices, social issues, and governance are consistent with the scores given, demonstrating a faithful representation of the data. Overall, the report is well-grounded in the actual ESG data, justifying a perfect score for faithfulness."
        }
    },
    "TQQQ": {
        "Generated Report": "No ESG data available for TQQQ",
        "Reference ESG Data": {
            "error": "No ESG data available for TQQQ"
        },
        "Faithfulness Evaluation": "Could not evaluate due to error in data or report generation."
    },
    "AMD": {
        "Generated Report": "AMD\u2019s total ESG risk score of 12.51 suggests a moderate level of sustainability risk, with individual scores indicating varying degrees of concern across environmental, social, and governance dimensions. \n\nThe Environmental Risk Score of 3.01 is relatively low, indicating that AMD is performing reasonably well in managing its environmental impact. However, continued attention to areas such as energy consumption and resource management is crucial, especially in the tech industry, where environmental regulations are tightening.\n\nThe Social Risk Score of 4.22 indicates some challenges in this area, potentially reflecting issues related to labor practices, community engagement, or product safety. Companies in the semiconductor industry are often scrutinized for their workforce diversity and inclusion practices, which could be an area for AMD to enhance its social responsibility.\n\nThe Governance Risk Score of 5.28 is the highest among the three, suggesting potential weaknesses in governance structures or practices. This could involve board diversity, executive pay, or stakeholder engagement. Improving governance practices is vital for maintaining investor confidence and ensuring long-term sustainability.\n\nThe controversy level of 1.0, significantly lower than the peer average of 0.56, indicates that AMD has experienced fewer negative events compared to its peers, which is a positive sign. However, the company should remain vigilant and proactive in addressing any emerging issues to mitigate risks and enhance its ESG profile further. Overall, while AMD shows strengths in environmental management, it needs to focus on social and governance aspects to improve its overall sustainability standing.",
        "Reference ESG Data": {
            "Stock": "AMD",
            "Total ESG Risk Score": 12.51,
            "Environmental Risk Score": 3.01,
            "Social Risk Score": 4.22,
            "Governance Risk Score": 5.28,
            "Controversy Level": 1.0,
            "Peer Controversy Min": 0.0,
            "Peer Controversy Avg": 0.5583333333333333,
            "Peer Controversy Max": 3.0
        },
        "Faithfulness Evaluation": {
            "Score": 1.0,
            "Explanation": "The generated ESG report accurately reflects the provided reference ESG data for AMD. It correctly states the total ESG risk score of 12.51 and breaks down the individual scores for environmental (3.01), social (4.22), and governance (5.28) risks, aligning with the reference data. The report also appropriately contextualizes these scores, indicating a moderate level of sustainability risk and emphasizing the need for improvement in social and governance areas. Furthermore, the controversy level of 1.0 is correctly noted as being lower than the peer average of 0.56, which is a positive aspect highlighted in the report. Overall, the report is faithful to the reference data, providing an accurate and comprehensive overview of AMD's ESG performance."
        }
    },
    "NFLX": {
        "Generated Report": "Netflix (NFLX) presents a mixed ESG profile, with a total ESG Risk Score of 15.88 that indicates notable risks, particularly in the social and governance dimensions. The Environmental Risk Score is low at 0.16, suggesting that Netflix has minimal environmental impact, which is a positive aspect of its sustainability efforts.\n\nHowever, the Social Risk Score of 7.38 highlights significant concerns, likely stemming from issues related to content management, labor practices, and diversity within the workforce. This elevated score indicates that social factors could pose reputational risks and affect stakeholder relations.\n\nThe Governance Risk Score of 8.35 is also concerning, suggesting potential weaknesses in corporate governance practices, which could lead to issues such as lack of accountability or transparency. This may deter investors looking for robust governance structures.\n\nFurthermore, the controversy level of 2.0, higher than the peer average of 1.01, indicates that Netflix has faced notable controversies compared to its peers, which can adversely impact its brand image and investor confidence.\n\nIn summary, while Netflix demonstrates a strong performance on environmental issues, the elevated social and governance risks, coupled with a higher controversy level, indicate areas of concern that could impact its long-term sustainability and investor appeal. Addressing these risks will be essential for improving its overall ESG standing and mitigating potential impacts on financial performance.",
        "Reference ESG Data": {
            "Stock": "NFLX",
            "Total ESG Risk Score": 15.88,
            "Environmental Risk Score": 0.16,
            "Social Risk Score": 7.38,
            "Governance Risk Score": 8.35,
            "Controversy Level": 2.0,
            "Peer Controversy Min": 0.0,
            "Peer Controversy Avg": 1.0070921985815602,
            "Peer Controversy Max": 3.0
        },
        "Faithfulness Evaluation": {
            "Score": 1.0,
            "Explanation": "The generated ESG report accurately reflects the provided reference ESG data for Netflix (NFLX). It correctly states the total ESG Risk Score of 15.88 and provides a detailed breakdown of the Environmental Risk Score (0.16), Social Risk Score (7.38), and Governance Risk Score (8.35). The report also appropriately highlights the controversy level of 2.0 and compares it to the peer average, which is accurate as per the reference data. The analysis of risks related to social and governance factors aligns well with the scores given, and the implications for investor confidence and brand image are valid interpretations of the data. Overall, the report is faithful to the reference data, providing a comprehensive and accurate assessment of Netflix's ESG profile."
        }
    }
}