{
    "TSLA": {
        "Generated Report": "Tesla Inc. (TSLA) exhibits a Total ESG Risk Score of 24.76, which indicates a moderate level of risk in the context of environmental, social, and governance factors. The Environmental Risk Score of 3.04 suggests that while Tesla is positioned as a leader in electric vehicles and renewable energy solutions, there are specific environmental concerns that need to be addressed, particularly around resource extraction and battery production.\n\nThe Social Risk Score of 14.13 is notably high, indicating significant challenges in areas such as labor practices, employee relations, and community impact. This score reflects ongoing scrutiny over workplace conditions and potential labor disputes, which could pose reputational risks and affect operational efficiency.\n\nThe Governance Risk Score of 7.6 indicates a moderately high level of governance-related risks, potentially stemming from issues related to executive compensation, board diversity, and transparency. The Controversy Level of 3.0, which is above the peer average of 1.75, highlights that Tesla faces more public and media scrutiny compared to its competitors, which could impact investor perception and market performance.\n\nIn summary, while Tesla is an innovative leader in sustainability, it must address its social and governance risks to enhance its ESG profile. The company's challenges in these areas suggest the need for improved practices and policies to mitigate potential risks and enhance stakeholder trust.",
        "Reference ESG Data": {
            "Stock": "TSLA",
            "Total ESG Risk Score": 24.76,
            "Environmental Risk Score": 3.04,
            "Social Risk Score": 14.13,
            "Governance Risk Score": 7.6,
            "Controversy Level": 3.0,
            "Peer Controversy Min": 0.0,
            "Peer Controversy Avg": 1.75,
            "Peer Controversy Max": 4.0
        },
        "Faithfulness Evaluation": {
            "Score": 1.0,
            "Explanation": "The generated ESG report accurately reflects the reference ESG data provided for Tesla Inc. (TSLA). It correctly states the Total ESG Risk Score of 24.76 and breaks down the Environmental, Social, and Governance Risk Scores as 3.04, 14.13, and 7.6, respectively. The report also appropriately discusses the implications of these scores, particularly highlighting the significant social risks and governance challenges, which align with the data. Additionally, it accurately notes the Controversy Level of 3.0 and its comparison to the peer average of 1.75. Overall, the report is grounded in the actual data and presents a faithful representation of Tesla's ESG profile."
        }
    },
    "NVDA": {
        "Generated Report": "NVIDIA Corporation (NVDA) presents a mixed ESG profile based on its risk scores and controversy level. With a total ESG risk score of 12.46, the company is positioned within a moderate risk category. \n\n**Environmental Analysis**: NVDA's Environmental Risk Score of 2.73 indicates it faces relatively low environmental risks compared to its peers. The company's commitment to sustainability initiatives, such as energy-efficient computing and reducing greenhouse gas emissions, contributes positively to this score. However, as the technology sector evolves, it must continue to innovate to minimize its environmental footprint.\n\n**Social Assessment**: The Social Risk Score of 4.08 highlights potential challenges in areas such as labor practices and community impact. NVDA should focus on enhancing diversity, equity, and inclusion within its workforce and addressing any social concerns that could affect its reputation and employee morale.\n\n**Governance Evaluation**: With a Governance Risk Score of 5.65, NVDA exhibits higher governance risks relative to its peers. This can stem from factors like executive compensation and board diversity. Strengthening governance practices could enhance stakeholder trust and mitigate risks associated with management decisions.\n\n**Controversy Level**: A controversy level of 2.0, while above the peer average of 0.56, is not excessively high. This suggests that NVDA has faced some controversies, which the company must address proactively to maintain its reputation.\n\nIn summary, while NVDA's ESG performance shows strengths, particularly in environmental aspects, the company must enhance its social and governance practices to further mitigate risks and bolster its sustainability profile.",
        "Reference ESG Data": {
            "Stock": "NVDA",
            "Total ESG Risk Score": 12.46,
            "Environmental Risk Score": 2.73,
            "Social Risk Score": 4.08,
            "Governance Risk Score": 5.65,
            "Controversy Level": 2.0,
            "Peer Controversy Min": 0.0,
            "Peer Controversy Avg": 0.5583333333333333,
            "Peer Controversy Max": 3.0
        },
        "Faithfulness Evaluation": {
            "Score": 0.9,
            "Explanation": "The generated ESG report for NVIDIA Corporation (NVDA) is largely faithful to the reference ESG data. It accurately presents the total ESG risk score of 12.46 and correctly categorizes it within a moderate risk category. The environmental, social, and governance risk scores are also reported accurately as 2.73, 4.08, and 5.65, respectively. The commentary on each aspect aligns well with the scores provided, particularly noting the low environmental risks and the higher governance risks.\n\nHowever, the report could improve by providing more context regarding the controversy level. While it mentions that a controversy level of 2.0 is above the peer average of 0.56, it does not clarify that this level is still relatively moderate compared to the maximum peer controversy score of 3.0. This omission slightly detracts from the overall accuracy and completeness of the report.\n\nOverall, the report is well-grounded in the actual data, but a minor adjustment in the discussion of the controversy level would enhance its faithfulness."
        }
    },
    "AAPL": {
        "Generated Report": "Apple Inc. (AAPL) presents a mixed ESG profile based on its risk scores and controversy levels. The total ESG risk score of 18.75 indicates that while the company is generally performing well in sustainability, there are notable concerns, particularly in the social and governance dimensions, both rated at 8.35.\n\nThe environmental risk score of 2.05 suggests that Apple is relatively strong in its environmental practices, reflecting efforts to reduce carbon emissions, enhance energy efficiency, and utilize renewable materials. However, the social and governance scores highlight potential vulnerabilities. The social score may be influenced by labor practices, supply chain issues, and customer privacy concerns, while the governance score points to risks related to corporate governance structures and shareholder engagement.\n\nThe controversy level of 3.0 indicates that Apple has faced significant public scrutiny and media attention regarding certain practices, which aligns with its risk scores being higher than the peer average of 0.56. This suggests that while Apple maintains a strong environmental standing, it must address social and governance issues more effectively to mitigate reputational risks and enhance investor confidence.\n\nIn summary, while Apple's environmental initiatives are commendable, the elevated social and governance risks, compounded by a notable controversy level, warrant close monitoring. Addressing these areas will be crucial for the company's long-term sustainability and resilience against ESG-related challenges.",
        "Reference ESG Data": {
            "Stock": "AAPL",
            "Total ESG Risk Score": 18.75,
            "Environmental Risk Score": 2.05,
            "Social Risk Score": 8.35,
            "Governance Risk Score": 8.35,
            "Controversy Level": 3.0,
            "Peer Controversy Min": 0.0,
            "Peer Controversy Avg": 0.5598290598290598,
            "Peer Controversy Max": 3.0
        },
        "Faithfulness Evaluation": {
            "Score": 0.9,
            "Explanation": "The generated ESG report for Apple Inc. (AAPL) is largely faithful to the provided reference ESG data. It accurately reflects the total ESG risk score of 18.75 and correctly identifies the environmental risk score of 2.05, as well as the social and governance risk scores of 8.35 each. The report appropriately highlights the strengths in environmental practices and the concerns in social and governance dimensions.\n\nHowever, the report's interpretation of the controversy level could be misleading. While it states that the controversy level is 3.0, it does not clarify that this level is at the maximum for peers, which could imply a more severe situation than suggested by the comparison to the peer average of 0.56. This could lead to a misunderstanding of the severity of Apple's controversies relative to its peers.\n\nOverall, the report is well-grounded in the actual data, but the slight ambiguity regarding the controversy level prevents it from achieving a perfect score."
        }
    },
    "SPY": {
        "Generated Report": "No ESG data available for SPY",
        "Reference ESG Data": {
            "error": "No ESG data available for SPY"
        },
        "Faithfulness Evaluation": "Could not evaluate due to error in data or report generation."
    },
    "QQQ": {
        "Generated Report": "No ESG data available for QQQ",
        "Reference ESG Data": {
            "error": "No ESG data available for QQQ"
        },
        "Faithfulness Evaluation": "Could not evaluate due to error in data or report generation."
    },
    "META": {
        "Generated Report": "META's total ESG risk score of 32.73 indicates a moderate level of risk, with significant implications for its sustainability profile. The breakdown of the scores reveals that the social risk score (21.64) is the most concerning aspect of its ESG performance. This suggests that META faces substantial challenges related to social issues, which may include user privacy, content moderation, and community impact. Given the increasing scrutiny on tech companies regarding their social responsibilities, this score highlights potential vulnerabilities, especially in relation to public perception and regulatory pressures.\n\nThe environmental risk score of 2.41 indicates a relatively low concern in terms of environmental impact, suggesting that META may be managing its ecological footprint effectively. However, the governance risk score of 8.68 points to potential weaknesses in corporate governance practices, which could affect decision-making and stakeholder trust.\n\nThe controversy level of 4.0 is notably high, particularly when compared to the peer average of 0.66. This suggests that META has encountered significant public and media scrutiny, which could adversely impact its brand reputation and investor confidence.\n\nIn summary, while META shows strengths in environmental management, the elevated social risk and controversy levels warrant careful monitoring. Addressing these issues will be crucial for enhancing its sustainability and mitigating potential risks in an increasingly ESG-conscious market.",
        "Reference ESG Data": {
            "Stock": "META",
            "Total ESG Risk Score": 32.73,
            "Environmental Risk Score": 2.41,
            "Social Risk Score": 21.64,
            "Governance Risk Score": 8.68,
            "Controversy Level": 4.0,
            "Peer Controversy Min": 0.0,
            "Peer Controversy Avg": 0.6598984771573604,
            "Peer Controversy Max": 4.0
        },
        "Faithfulness Evaluation": {
            "Score": 1.0,
            "Explanation": "The generated ESG report accurately reflects the provided reference ESG data for META. It correctly states the total ESG risk score of 32.73 and provides a clear breakdown of the environmental (2.41), social (21.64), and governance (8.68) risk scores. The report appropriately highlights the social risk score as the most concerning aspect, aligning with the data that indicates significant challenges in this area. Additionally, the mention of a controversy level of 4.0, which is indeed high compared to the peer average of 0.66, is accurately represented. The analysis of implications for public perception, regulatory pressures, and corporate governance is well-grounded in the provided data. Overall, the report is faithful to the reference data, providing a comprehensive and accurate assessment of META's ESG performance."
        }
    },
    "AMZN": {
        "Generated Report": "Amazon (AMZN) has a Total ESG Risk Score of 26.1, indicating a moderate level of risk across environmental, social, and governance dimensions. The Environmental Risk Score of 8.3 suggests that while Amazon is taking steps towards sustainability, it still faces significant challenges, particularly related to its carbon footprint from logistics and packaging. \n\nThe Social Risk Score of 11.05 is concerning, reflecting potential issues related to labor practices, employee treatment, and community impacts. This score is substantially higher than the peer average, indicating that social factors could pose a greater risk to the company\u2019s reputation and operational stability.\n\nThe Governance Risk Score of 6.75, while lower than the social risk, suggests that there are governance-related concerns that could affect stakeholder trust. This might include issues related to executive pay, board diversity, and shareholder rights.\n\nThe Controversy Level of 3.0 places Amazon at a higher risk than its peers, with the minimum controversy at 0.0 and an average of approximately 0.91. This indicates ongoing public scrutiny and potential backlash from various stakeholder groups.\n\nIn summary, while Amazon is making strides in sustainability, significant risks remain, particularly in social practices and governance. The company must address these issues to enhance its ESG profile and mitigate potential reputational and operational risks in an increasingly ESG-conscious market.",
        "Reference ESG Data": {
            "Stock": "AMZN",
            "Total ESG Risk Score": 26.1,
            "Environmental Risk Score": 8.3,
            "Social Risk Score": 11.05,
            "Governance Risk Score": 6.75,
            "Controversy Level": 3.0,
            "Peer Controversy Min": 0.0,
            "Peer Controversy Avg": 0.9104477611940298,
            "Peer Controversy Max": 4.0
        },
        "Faithfulness Evaluation": {
            "Score": 1.0,
            "Explanation": "The generated ESG report accurately reflects the provided reference ESG data for Amazon (AMZN). It correctly states the Total ESG Risk Score of 26.1 and breaks down the Environmental Risk Score (8.3), Social Risk Score (11.05), and Governance Risk Score (6.75) with appropriate context regarding the implications of these scores. The report also accurately describes the Controversy Level of 3.0 in relation to peer controversy metrics, noting that Amazon's controversy level is significantly higher than the peer average of approximately 0.91. The language used in the report is consistent with the data, providing a faithful representation of Amazon's ESG risks and challenges. Therefore, the report is perfectly faithful to the reference data."
        }
    },
    "TQQQ": {
        "Generated Report": "No ESG data available for TQQQ",
        "Reference ESG Data": {
            "error": "No ESG data available for TQQQ"
        },
        "Faithfulness Evaluation": "Could not evaluate due to error in data or report generation."
    },
    "AMD": {
        "Generated Report": "AMD's total ESG risk score of 12.51 indicates a moderate level of overall risk, with distinct areas of concern and strength. The environmental risk score of 3.01 suggests that while AMD is making efforts to manage its environmental impact, there is still room for improvement, particularly in areas such as energy efficiency and waste management.\n\nThe social risk score of 4.22 reflects potential challenges related to labor practices, community engagement, and product responsibility. This score signals that AMD may face scrutiny regarding its workforce diversity, employee welfare, or customer relations. \n\nThe governance risk score of 5.28 is the highest among the three categories, indicating that governance practices may present notable risks. This could involve issues related to executive compensation, board diversity, or shareholder rights, which can affect investor confidence and corporate reputation.\n\nThe controversy level of 1.0 is relatively low compared to the peer average of 0.56 and the maximum of 3.0. This suggests that AMD has managed to avoid significant controversies that could detract from its ESG performance, which is a positive sign for investors.\n\nIn conclusion, while AMD demonstrates a commitment to sustainability, the company must address its governance and social risks to enhance its overall ESG profile. Continued improvement in these areas could strengthen AMD's reputation and mitigate potential risks moving forward.",
        "Reference ESG Data": {
            "Stock": "AMD",
            "Total ESG Risk Score": 12.51,
            "Environmental Risk Score": 3.01,
            "Social Risk Score": 4.22,
            "Governance Risk Score": 5.28,
            "Controversy Level": 1.0,
            "Peer Controversy Min": 0.0,
            "Peer Controversy Avg": 0.5583333333333333,
            "Peer Controversy Max": 3.0
        },
        "Faithfulness Evaluation": {
            "Score": 1.0,
            "Explanation": "The generated ESG report accurately reflects the reference ESG data for AMD. It correctly states the total ESG risk score of 12.51 and provides a breakdown of the environmental, social, and governance risk scores (3.01, 4.22, and 5.28, respectively). The report also appropriately contextualizes the controversy level of 1.0, comparing it favorably against the peer average and maximum. Furthermore, the report's commentary on areas for improvement aligns with the scores provided, particularly in governance and social aspects. Overall, the report is faithful to the reference data, providing a clear and accurate representation of AMD's ESG performance."
        }
    },
    "NFLX": {
        "Generated Report": "Netflix (NFLX) demonstrates a mixed ESG profile, with a total ESG risk score of 15.88 indicating moderate risk exposure. The Environmental Risk Score is notably low at 0.16, suggesting that Netflix has minimal direct environmental impact, which is commendable in the context of the entertainment industry. However, the Social Risk Score of 7.38 indicates significant potential vulnerabilities, particularly in areas such as content diversity, workforce treatment, and community engagement. This score highlights the importance of addressing social equity and representation within its programming and corporate practices.\n\nThe Governance Risk Score at 8.35 raises concerns about governance structures, possibly reflecting issues related to board diversity, executive compensation, or shareholder engagement. Effective governance is crucial for maintaining investor confidence and ensuring long-term sustainability.\n\nThe controversy level of 2.0, while above the peer average of 1.01, indicates that Netflix has faced some notable controversies, but they are not as severe compared to the highest peer levels. This suggests that while there are risks associated with reputation and stakeholder trust, they are manageable.\n\nIn summary, while Netflix performs well environmentally, it must address social and governance challenges to mitigate risks and enhance its sustainability profile. Strengthening these areas could improve its overall ESG standing and appeal to socially conscious investors.",
        "Reference ESG Data": {
            "Stock": "NFLX",
            "Total ESG Risk Score": 15.88,
            "Environmental Risk Score": 0.16,
            "Social Risk Score": 7.38,
            "Governance Risk Score": 8.35,
            "Controversy Level": 2.0,
            "Peer Controversy Min": 0.0,
            "Peer Controversy Avg": 1.0070921985815602,
            "Peer Controversy Max": 3.0
        },
        "Faithfulness Evaluation": {
            "Score": 1.0,
            "Explanation": "The generated ESG report accurately reflects the reference ESG data provided for Netflix (NFLX). The total ESG risk score of 15.88 is correctly stated as indicating moderate risk exposure. The Environmental Risk Score of 0.16 is described as low, which aligns with the reference data indicating minimal direct environmental impact. The Social Risk Score of 7.38 is correctly identified as significant, highlighting potential vulnerabilities in social equity and representation, which is consistent with the data. The Governance Risk Score of 8.35 is also accurately noted as a concern regarding governance structures. Furthermore, the controversy level of 2.0 is correctly contextualized as being above the peer average, indicating manageable risks. Overall, the report provides a faithful and comprehensive overview of Netflix's ESG profile based on the reference data."
        }
    }
}