{
    "TSLA": {
        "Generated Report": "Tesla, Inc. (TSLA) exhibits a total ESG risk score of 24.76, indicating a moderate level of overall ESG risks. The Environmental Risk Score is relatively low at 3.04, reflecting Tesla's commitment to sustainability through its electric vehicle production and renewable energy initiatives. This positions the company favorably in terms of environmental impact, aligning with global efforts to reduce carbon emissions.\n\nHowever, the Social Risk Score is notably higher at 14.13, suggesting potential challenges in social governance, which may include labor practices, workforce diversity, and community relations. This score is a critical area of concern, as it indicates that Tesla may face scrutiny or backlash related to its treatment of employees and social equity initiatives.\n\nThe Governance Risk Score of 7.6 further highlights concerns regarding corporate governance practices, which could include issues related to board diversity, executive compensation, and shareholder rights. \n\nThe Controversy Level of 3.0 suggests that Tesla is involved in a moderate level of controversies compared to its peers, who average a lower controversy score of 1.75. This could impact investor sentiment and brand reputation, especially in light of increased public scrutiny on corporate behavior.\n\nIn summary, while Tesla demonstrates strong environmental performance, significant risks persist in social and governance areas. Investors should be aware of these factors, as they may influence the company's long-term sustainability and performance.",
        "Reference ESG Data": {
            "Stock": "TSLA",
            "Total ESG Risk Score": 24.76,
            "Environmental Risk Score": 3.04,
            "Social Risk Score": 14.13,
            "Governance Risk Score": 7.6,
            "Controversy Level": 3.0,
            "Peer Controversy Min": 0.0,
            "Peer Controversy Avg": 1.75,
            "Peer Controversy Max": 4.0
        },
        "Faithfulness Evaluation": {
            "Score": 1.0,
            "Explanation": "The generated ESG report accurately reflects the provided reference ESG data for Tesla, Inc. (TSLA). It correctly states the total ESG risk score of 24.76 and breaks down the individual scores for environmental (3.04), social (14.13), and governance (7.6) risks, aligning perfectly with the reference data. The report also appropriately contextualizes these scores, indicating a moderate overall risk level and highlighting the specific areas of concern, particularly in social and governance aspects. Additionally, the mention of the controversy level (3.0) and its comparison to the peer average (1.75) is accurate and relevant. Overall, the report is faithful to the actual data, providing a clear and comprehensive overview of Tesla's ESG performance."
        }
    },
    "NVDA": {
        "Generated Report": "NVIDIA Corporation (NVDA) presents a mixed ESG profile based on its risk scores and controversy level. With a total ESG Risk Score of 12.46, the company is positioned moderately within the context of its industry peers. \n\nThe Environmental Risk Score of 2.73 indicates relatively low exposure to environmental risks, suggesting that NVIDIA is likely taking steps to minimize its ecological footprint. However, it is essential to monitor ongoing initiatives in energy consumption and waste management as the tech sector faces increasing scrutiny regarding sustainability practices.\n\nThe Social Risk Score of 4.08 is higher than the environmental score, indicating potential challenges related to labor practices, community engagement, or product safety. This area needs attention, as social issues can impact reputation and operational stability.\n\nThe Governance Risk Score of 5.65 is the highest among the three categories, raising concerns about the company's governance practices, transparency, or board diversity. Strengthening governance frameworks could mitigate risks and enhance investor confidence.\n\nThe controversy level of 2.0, while above the peer average of 0.56, is not excessively high, but it highlights that NVDA has faced notable issues that could affect stakeholder perception. Given the maximum peer controversy score of 3.0, NVDA's position suggests it should focus on mitigating controversies to improve its ESG standing.\n\nIn summary, while NVIDIA has a relatively solid environmental performance, it must address social and governance risks to enhance its sustainability profile and reduce potential vulnerabilities.",
        "Reference ESG Data": {
            "Stock": "NVDA",
            "Total ESG Risk Score": 12.46,
            "Environmental Risk Score": 2.73,
            "Social Risk Score": 4.08,
            "Governance Risk Score": 5.65,
            "Controversy Level": 2.0,
            "Peer Controversy Min": 0.0,
            "Peer Controversy Avg": 0.5583333333333333,
            "Peer Controversy Max": 3.0
        },
        "Faithfulness Evaluation": {
            "Score": 0.9,
            "Explanation": "The generated ESG report is largely faithful to the reference ESG data, accurately reflecting the total ESG Risk Score of 12.46 and the individual risk scores for Environmental (2.73), Social (4.08), and Governance (5.65). It correctly identifies the controversy level of 2.0 and compares it to the peer average, providing a contextual understanding of NVIDIA's position among its peers.\n\nHowever, the report could be improved by providing more specific details about the nature of the social and governance risks mentioned, as well as clearer recommendations for addressing these issues. While it does mention the need for improvement in these areas, it lacks concrete examples or initiatives that NVIDIA could undertake. This slight lack of specificity in addressing the risks contributes to a minor deduction in the score. Overall, the report is accurate and grounded in the actual data, making it highly faithful."
        }
    },
    "AAPL": {
        "Generated Report": "Apple Inc. (AAPL) exhibits a total ESG risk score of 18.75, indicating a relatively moderate level of risk. The Environmental Risk Score of 2.05 suggests that Apple is performing well in environmental management, especially given its commitments to carbon neutrality and sustainable sourcing of materials. However, the Social and Governance Risk Scores both stand at 8.35, highlighting significant concerns in these areas.\n\nThe Social Risk Score reflects potential challenges related to labor practices, supply chain ethics, and community impact. Apple's reliance on global supply chains, particularly in regions with varying labor standards, may expose it to scrutiny and reputational risks. Governance practices, while generally robust, could benefit from increased transparency and stakeholder engagement, particularly concerning executive compensation and board diversity.\n\nThe Controversy Level of 3.0, aligned with the peer average, indicates that Apple is facing notable reputational challenges, though not exceeding those of its peers. This level of controversy suggests that while the company has made progress, it still faces significant public and regulatory scrutiny, particularly regarding its labor practices and environmental impact.\n\nIn conclusion, while Apple demonstrates strong environmental performance, its social and governance aspects pose potential risks that could affect its long-term sustainability and reputation. Stakeholders should monitor these areas closely, as they could influence future performance and investor sentiment.",
        "Reference ESG Data": {
            "Stock": "AAPL",
            "Total ESG Risk Score": 18.75,
            "Environmental Risk Score": 2.05,
            "Social Risk Score": 8.35,
            "Governance Risk Score": 8.35,
            "Controversy Level": 3.0,
            "Peer Controversy Min": 0.0,
            "Peer Controversy Avg": 0.5598290598290598,
            "Peer Controversy Max": 3.0
        },
        "Faithfulness Evaluation": {
            "Score": 1.0,
            "Explanation": "The generated ESG report accurately reflects the reference ESG data provided for Apple Inc. (AAPL). It correctly states the total ESG risk score of 18.75 and the Environmental Risk Score of 2.05, both of which align perfectly with the reference data. The report appropriately highlights the significant Social and Governance Risk Scores of 8.35 each, indicating concerns in these areas, which is consistent with the data. Additionally, the report's mention of the Controversy Level being 3.0 aligns with the reference data and accurately contextualizes it in relation to peer averages. Overall, the report is faithful to the actual data, providing a comprehensive and accurate assessment of Apple's ESG performance."
        }
    },
    "SPY": {
        "Generated Report": "No ESG data available for SPY",
        "Reference ESG Data": {
            "error": "No ESG data available for SPY"
        },
        "Faithfulness Evaluation": "Could not evaluate due to error in data or report generation."
    },
    "QQQ": {
        "Generated Report": "No ESG data available for QQQ",
        "Reference ESG Data": {
            "error": "No ESG data available for QQQ"
        },
        "Faithfulness Evaluation": "Could not evaluate due to error in data or report generation."
    },
    "META": {
        "Generated Report": "META's Total ESG Risk Score of 32.73 suggests a moderate level of overall sustainability risk, with particular vulnerabilities in its social and governance dimensions. The Environmental Risk Score of 2.41 indicates minimal environmental concerns, suggesting that META effectively manages its ecological footprint. However, the significantly higher Social Risk Score of 21.64 raises red flags regarding the company's social practices, which may include issues related to user privacy, data security, and the impact of its platforms on mental health and societal well-being.\n\nThe Governance Risk Score of 8.68 points to potential weaknesses in corporate governance, which may relate to board diversity, executive compensation, or shareholder rights. The company's Controversy Level of 4.0 is noteworthy, especially when compared to a peer average of approximately 0.66, indicating that META has faced significant public scrutiny and criticism, potentially affecting its reputation and stakeholder trust.\n\nIn conclusion, while META demonstrates solid environmental management, its elevated social and governance risks, compounded by a high controversy level, pose significant challenges. These factors could impact the company\u2019s long-term sustainability and investment attractiveness. Stakeholders should monitor META's efforts to address these social and governance issues to mitigate potential risks and enhance its ESG profile.",
        "Reference ESG Data": {
            "Stock": "META",
            "Total ESG Risk Score": 32.73,
            "Environmental Risk Score": 2.41,
            "Social Risk Score": 21.64,
            "Governance Risk Score": 8.68,
            "Controversy Level": 4.0,
            "Peer Controversy Min": 0.0,
            "Peer Controversy Avg": 0.6598984771573604,
            "Peer Controversy Max": 4.0
        },
        "Faithfulness Evaluation": {
            "Score": 1.0,
            "Explanation": "The generated ESG report accurately reflects the reference ESG data for META. It correctly states the Total ESG Risk Score of 32.73 and provides a clear interpretation of the Environmental Risk Score (2.41), Social Risk Score (21.64), and Governance Risk Score (8.68). The report highlights the significant social and governance vulnerabilities, which aligns with the provided scores. Additionally, it appropriately notes the high Controversy Level of 4.0 in comparison to the peer average, emphasizing the company's challenges in reputation management. Overall, the report is grounded in the actual data, making it perfectly faithful."
        }
    },
    "AMZN": {
        "Generated Report": "Amazon (AMZN) presents a mixed ESG profile with a total ESG risk score of 26.1, indicating a moderate level of sustainability risk. The Environmental Risk Score of 8.3 suggests that while the company is taking steps toward sustainability, it still faces significant challenges, particularly in areas related to carbon emissions, waste management, and resource consumption. This score indicates a need for continued improvement in its environmental practices to align with global sustainability goals.\n\nThe Social Risk Score of 11.05 is notably high, highlighting potential issues related to labor practices, employee treatment, and community impact. Concerns about working conditions and employee satisfaction could pose reputational risks and impact operational stability, which investors should monitor closely.\n\nThe Governance Risk Score of 6.75 reflects a reasonable level of oversight and accountability, but there is room for enhancement, particularly in transparency and stakeholder engagement.\n\nWith a Controversy Level of 3.0, Amazon is more contentious compared to its peers, whose controversy averages around 0.91. This elevated level indicates that the company is frequently in the spotlight for various issues, which could lead to negative publicity and impact investor sentiment.\n\nIn summary, while Amazon is making strides in some areas, it must address significant environmental and social risks to improve its overall ESG standing and mitigate potential reputational and operational threats.",
        "Reference ESG Data": {
            "Stock": "AMZN",
            "Total ESG Risk Score": 26.1,
            "Environmental Risk Score": 8.3,
            "Social Risk Score": 11.05,
            "Governance Risk Score": 6.75,
            "Controversy Level": 3.0,
            "Peer Controversy Min": 0.0,
            "Peer Controversy Avg": 0.9104477611940298,
            "Peer Controversy Max": 4.0
        },
        "Faithfulness Evaluation": {
            "Score": 1.0,
            "Explanation": "The generated ESG report accurately reflects the reference ESG data for Amazon (AMZN). It correctly states the total ESG risk score of 26.1 and provides detailed breakdowns of the Environmental Risk Score (8.3), Social Risk Score (11.05), and Governance Risk Score (6.75). The report also appropriately notes the Controversy Level of 3.0, comparing it to the peer controversy average of 0.91, which highlights Amazon's elevated controversy status. The descriptions of the risks and areas for improvement align well with the provided data, ensuring that the report is both accurate and grounded in the actual ESG metrics. Overall, the report is comprehensive and faithful to the reference data."
        }
    },
    "TQQQ": {
        "Generated Report": "No ESG data available for TQQQ",
        "Reference ESG Data": {
            "error": "No ESG data available for TQQQ"
        },
        "Faithfulness Evaluation": "Could not evaluate due to error in data or report generation."
    },
    "AMD": {
        "Generated Report": "AMD's total ESG risk score of 12.51 indicates a moderate level of sustainability risk, with key contributions from its environmental, social, and governance dimensions. The environmental risk score of 3.01 suggests that AMD faces some challenges in managing its ecological footprint, which could be tied to factors such as energy consumption in its semiconductor manufacturing processes. \n\nThe social risk score of 4.22 reflects potential issues related to labor practices, community engagement, or product safety, areas that are particularly scrutinized in the tech industry. Governance risk, at 5.28, highlights possible concerns regarding board diversity, executive compensation, or shareholder rights, which are crucial for maintaining investor trust and regulatory compliance.\n\nThe company's controversy level is relatively low at 1.0, especially when compared to its peers, where the average controversy score is 0.56. This low level of controversy indicates that AMD has managed to avoid significant public relations crises or legal issues that might otherwise elevate its risk profile.\n\nIn summary, while AMD demonstrates a commendable ability to navigate controversies, its moderate ESG risk scores\u2014particularly in governance and social areas\u2014suggest potential vulnerabilities. Investors should monitor these risks closely, especially as regulatory landscapes evolve and stakeholder expectations around sustainability increase. Addressing these areas could enhance AMD's overall sustainability profile and reduce potential risks moving forward.",
        "Reference ESG Data": {
            "Stock": "AMD",
            "Total ESG Risk Score": 12.51,
            "Environmental Risk Score": 3.01,
            "Social Risk Score": 4.22,
            "Governance Risk Score": 5.28,
            "Controversy Level": 1.0,
            "Peer Controversy Min": 0.0,
            "Peer Controversy Avg": 0.5583333333333333,
            "Peer Controversy Max": 3.0
        },
        "Faithfulness Evaluation": {
            "Score": 1.0,
            "Explanation": "The generated ESG report accurately reflects the provided reference ESG data for AMD. It correctly states the total ESG risk score of 12.51 and breaks down the contributions from the environmental (3.01), social (4.22), and governance (5.28) dimensions, aligning with the reference data. The report also appropriately discusses the controversy level of 1.0 and compares it to the peer average of 0.56, which is consistent with the reference data. Overall, the report maintains a faithful representation of the ESG metrics and their implications, making it a reliable summary of AMD's ESG performance."
        }
    },
    "NFLX": {
        "Generated Report": "Netflix (NFLX) exhibits a total ESG risk score of 15.88, indicating a moderate level of risk. The environmental risk score is remarkably low at 0.16, suggesting that the company has minimal environmental impact, which is positive in the context of sustainability. However, the social risk score of 7.38 and governance risk score of 8.35 highlight significant concerns in these areas.\n\nThe social risk score indicates potential issues related to labor practices, diversity and inclusion, and community impact. Given the company's global reach and influence, addressing these social factors is crucial for maintaining stakeholder trust and brand reputation. The governance risk score suggests potential vulnerabilities in corporate oversight, ethical practices, and transparency, which could lead to regulatory scrutiny or reputational damage.\n\nThe controversy level of 2.0, while lower than the maximum peer controversy score of 3.0, is above the average peer controversy score of 1.01. This suggests that Netflix has faced more significant controversies than its peers, emphasizing the need for improved risk management and stakeholder engagement strategies.\n\nIn summary, while Netflix shows strong environmental performance, its social and governance risks warrant attention. The company should enhance its efforts in these areas to mitigate potential risks and bolster its long-term sustainability and reputation.",
        "Reference ESG Data": {
            "Stock": "NFLX",
            "Total ESG Risk Score": 15.88,
            "Environmental Risk Score": 0.16,
            "Social Risk Score": 7.38,
            "Governance Risk Score": 8.35,
            "Controversy Level": 2.0,
            "Peer Controversy Min": 0.0,
            "Peer Controversy Avg": 1.0070921985815602,
            "Peer Controversy Max": 3.0
        },
        "Faithfulness Evaluation": {
            "Score": 1.0,
            "Explanation": "The generated ESG report accurately reflects the reference ESG data provided. It correctly states the total ESG risk score of 15.88 and breaks down the environmental risk score (0.16), social risk score (7.38), and governance risk score (8.35) in a clear and coherent manner. The report also appropriately discusses the implications of these scores, particularly the low environmental impact and the significant concerns in social and governance aspects. Furthermore, it accurately mentions the controversy level of 2.0 and contextualizes it against the peer controversy scores, highlighting Netflix's position relative to its peers. Overall, the report is faithful to the reference data, providing a comprehensive and accurate assessment of Netflix's ESG performance."
        }
    }
}