{
    "TSLA": {
        "Generated Report": "Tesla Inc. (TSLA) presents a mixed picture in its ESG profile, with a total ESG risk score of 24.76 indicating a moderate level of risk. The Environmental Risk Score of 3.04 is relatively low, reflecting Tesla's commitment to sustainable practices through its electric vehicle production and renewable energy initiatives. This positions the company favorably in terms of environmental responsibility, aligning with global efforts to reduce carbon emissions.\n\nHowever, the Social Risk Score of 14.13 raises concerns, suggesting significant challenges related to labor practices, workplace safety, and community relations. This score is notably high compared to its peers, which could expose Tesla to reputational risks and potential regulatory scrutiny.\n\nThe Governance Risk Score of 7.6 indicates moderate governance issues, possibly linked to executive decisions, board diversity, and transparency practices. The controversy level of 3.0 is above the peer average of 1.75, suggesting that Tesla faces heightened scrutiny regarding its operational practices and corporate governance.\n\nIn summary, while Tesla's environmental performance is commendable, its social and governance risks warrant attention. Investors should monitor these areas closely, as they could impact the company's long-term sustainability and profitability. Addressing the social and governance challenges will be crucial for Tesla to mitigate risks and enhance its overall ESG standing.",
        "Reference ESG Data": {
            "Stock": "TSLA",
            "Total ESG Risk Score": 24.76,
            "Environmental Risk Score": 3.04,
            "Social Risk Score": 14.13,
            "Governance Risk Score": 7.6,
            "Controversy Level": 3.0,
            "Peer Controversy Min": 0.0,
            "Peer Controversy Avg": 1.75,
            "Peer Controversy Max": 4.0
        },
        "Faithfulness Evaluation": {
            "Score": 1.0,
            "Explanation": "The generated ESG report accurately reflects the provided reference ESG data for Tesla Inc. (TSLA). It correctly states the total ESG risk score of 24.76 and provides a detailed breakdown of the Environmental Risk Score (3.04), Social Risk Score (14.13), and Governance Risk Score (7.6). The report also appropriately highlights the controversy level of 3.0 and compares it to the peer average of 1.75, indicating a higher scrutiny level for Tesla. The interpretations of these scores align well with the underlying data, presenting a balanced view of Tesla's ESG profile. Overall, the report is faithful to the reference data, making it a reliable summary of Tesla's ESG standing."
        }
    },
    "NVDA": {
        "Generated Report": "NVIDIA Corporation (NVDA) presents a mixed ESG profile based on its risk scores and controversy level. The total ESG risk score of 12.46 indicates that there are significant concerns, particularly in the governance and social dimensions. \n\nThe Environmental Risk Score of 2.73 is relatively low, suggesting that NVIDIA is performing well in managing environmental impacts, particularly relevant given the energy-intensive nature of semiconductor manufacturing. However, the Social Risk Score of 4.08 indicates potential vulnerabilities in areas such as labor practices, community engagement, and product safety. This score could reflect challenges related to workforce diversity, employee welfare, and the implications of its technology.\n\nThe Governance Risk Score of 5.65 is the highest among the three categories, indicating notable concerns in corporate governance practices. This could involve issues related to board diversity, executive compensation, or shareholder rights, which may affect investor confidence and long-term sustainability.\n\nThe controversy level of 2.0, while moderate, is higher than the peer average of 0.56. This suggests that NVIDIA has faced notable controversies compared to its peers, which could pose reputational risks and impact stakeholder trust.\n\nOverall, while NVIDIA demonstrates strong environmental management, it faces significant social and governance challenges that could impact its sustainability and performance if not addressed effectively. Investors should monitor these areas closely to mitigate potential risks.",
        "Reference ESG Data": {
            "Stock": "NVDA",
            "Total ESG Risk Score": 12.46,
            "Environmental Risk Score": 2.73,
            "Social Risk Score": 4.08,
            "Governance Risk Score": 5.65,
            "Controversy Level": 2.0,
            "Peer Controversy Min": 0.0,
            "Peer Controversy Avg": 0.5583333333333333,
            "Peer Controversy Max": 3.0
        },
        "Faithfulness Evaluation": {
            "Score": 0.95,
            "Explanation": "The generated ESG report is largely faithful to the reference ESG data. It accurately presents the total ESG risk score of 12.46 and breaks down the individual risk scores for environmental (2.73), social (4.08), and governance (5.65) dimensions, reflecting the actual data. The report correctly identifies the governance score as the highest, indicating significant concerns in that area, and it appropriately highlights the controversy level of 2.0, noting that it is above the peer average of 0.56.\n\nThe only minor point of contention is the phrasing around the \"significant concerns\" in governance and social dimensions; while the scores indicate vulnerabilities, the language could imply a stronger negative connotation than the data strictly supports. However, this does not significantly detract from the overall accuracy of the report. Thus, the report is very faithful to the provided data, meriting a high score."
        }
    },
    "AAPL": {
        "Generated Report": "Apple Inc. (AAPL) presents a mixed ESG profile based on its risk scores and controversy level. With a total ESG risk score of 18.75, the company falls into a moderate-risk category. The Environmental Risk Score of 2.05 indicates relatively low environmental concerns, suggesting that Apple is actively managing its environmental impact, likely through initiatives aimed at reducing carbon emissions and promoting sustainability in its supply chain.\n\nHowever, the Social and Governance Risk Scores, both at 8.35, highlight significant risks in these areas. The social score may reflect challenges related to labor practices, supply chain conditions, or product accessibility, while the governance score could indicate potential issues with board diversity, executive compensation, or shareholder rights. These elevated scores warrant close attention from investors, as they could impact Apple's reputation and operational stability.\n\nThe controversy level of 3.0, which is on par with the maximum among its peers, suggests that Apple has faced notable scrutiny or negative publicity. While the peer average controversy score is much lower at 0.56, this disparity indicates that Apple may be more susceptible to reputational risks compared to its competitors.\n\nIn summary, while Apple demonstrates commendable environmental management, its social and governance challenges, coupled with a high controversy level, pose potential risks to its long-term sustainability and investor confidence. Stakeholders should monitor these areas closely to gauge future performance.",
        "Reference ESG Data": {
            "Stock": "AAPL",
            "Total ESG Risk Score": 18.75,
            "Environmental Risk Score": 2.05,
            "Social Risk Score": 8.35,
            "Governance Risk Score": 8.35,
            "Controversy Level": 3.0,
            "Peer Controversy Min": 0.0,
            "Peer Controversy Avg": 0.5598290598290598,
            "Peer Controversy Max": 3.0
        },
        "Faithfulness Evaluation": {
            "Score": 0.9,
            "Explanation": "The generated ESG report for Apple Inc. (AAPL) is largely faithful to the reference ESG data, accurately reflecting the total ESG risk score of 18.75 and the specific risk scores for environmental (2.05), social (8.35), and governance (8.35). It correctly identifies the moderate risk category and highlights the significant concerns in the social and governance areas, which aligns with the provided scores.\n\nHowever, while the report mentions the controversy level of 3.0 and compares it to the peer average, it could have more explicitly stated that this level is at the maximum among peers, which is a crucial detail. The report also implies that Apple is actively managing its environmental impact, which, while likely true, is not directly supported by the reference data and could be seen as an assumption rather than a fact.\n\nOverall, the report is accurate and grounded in the actual data, but the slight omission of the context regarding the controversy level and the assumption about environmental management detracts from its perfect faithfulness."
        }
    },
    "SPY": {
        "Generated Report": "No ESG data available for SPY",
        "Reference ESG Data": {
            "error": "No ESG data available for SPY"
        },
        "Faithfulness Evaluation": "Could not evaluate due to error in data or report generation."
    },
    "QQQ": {
        "Generated Report": "No ESG data available for QQQ",
        "Reference ESG Data": {
            "error": "No ESG data available for QQQ"
        },
        "Faithfulness Evaluation": "Could not evaluate due to error in data or report generation."
    },
    "META": {
        "Generated Report": "META's total ESG risk score of 32.73 suggests a moderate level of risk in terms of environmental, social, and governance factors. The breakdown of scores indicates that the most significant concerns lie within the social domain, with a score of 21.64, which highlights potential issues related to user privacy, misinformation, and community impacts. This elevated social risk is critical, especially given META's role in shaping public discourse and its influence on societal behaviors.\n\nThe environmental risk score is relatively low at 2.41, indicating that META is likely managing its environmental impact effectively compared to industry peers. However, the governance risk score of 8.68, while not the highest, suggests there are governance challenges that could affect the company's decision-making and accountability.\n\nThe controversy level of 4.0 is noteworthy, especially when compared to the peer controversy average of 0.66. This high level of controversy indicates that META has faced significant scrutiny and backlash, which can impact its reputation and stakeholder trust. \n\nOverall, while META appears to manage its environmental impacts well, the high social risk and controversy levels signify a need for enhanced strategies to address governance and social concerns. Investors should be cautious and monitor developments related to these risks, as they could impact long-term sustainability and financial performance.",
        "Reference ESG Data": {
            "Stock": "META",
            "Total ESG Risk Score": 32.73,
            "Environmental Risk Score": 2.41,
            "Social Risk Score": 21.64,
            "Governance Risk Score": 8.68,
            "Controversy Level": 4.0,
            "Peer Controversy Min": 0.0,
            "Peer Controversy Avg": 0.6598984771573604,
            "Peer Controversy Max": 4.0
        },
        "Faithfulness Evaluation": {
            "Score": 1.0,
            "Explanation": "The generated ESG report accurately reflects the provided reference ESG data for META. The total ESG risk score of 32.73 is correctly identified as moderate, and the breakdown of scores aligns perfectly with the reference data: the social risk score of 21.64 is highlighted as the most significant concern, which is consistent with the data. The environmental risk score of 2.41 is described as low, indicating effective management of environmental impacts, which is also in line with the reference data. The governance risk score of 8.68 is mentioned appropriately, noting potential challenges. Furthermore, the controversy level of 4.0 is accurately compared to the peer average of 0.66, emphasizing the significant scrutiny META faces. Overall, the report is comprehensive and accurately grounded in the actual data, meriting a perfect score for faithfulness."
        }
    },
    "AMZN": {
        "Generated Report": "Amazon (AMZN) presents a mixed ESG profile, with a total ESG risk score of 26.1, indicating moderate risk across environmental, social, and governance dimensions. The environmental risk score of 8.3 suggests that while Amazon has made strides in sustainability, such as commitments to renewable energy and reducing carbon emissions, challenges remain, particularly in waste management and resource usage due to its vast logistics network.\n\nThe social risk score of 11.05 is a critical area of concern, reflecting issues related to labor practices, employee treatment, and community impact. Reports of worker dissatisfaction, safety violations, and scrutiny over warehouse conditions raise questions about the company's commitment to social responsibility. This score is significantly higher than the peer controversy average of 0.91, indicating that Amazon faces unique social challenges compared to its industry peers.\n\nThe governance risk score of 6.75 suggests a relatively stable governance framework; however, the controversy level of 3.0 points to ongoing public scrutiny and potential reputational risks. This level of controversy exceeds the peer maximum of 4.0, indicating that Amazon's ESG-related challenges are more pronounced than those faced by its competitors.\n\nIn summary, while Amazon is actively working on improving its sustainability practices, significant risks remain, particularly in social aspects. Investors should closely monitor these issues, as they could impact the company\u2019s long-term viability and reputation in an increasingly ESG-focused market.",
        "Reference ESG Data": {
            "Stock": "AMZN",
            "Total ESG Risk Score": 26.1,
            "Environmental Risk Score": 8.3,
            "Social Risk Score": 11.05,
            "Governance Risk Score": 6.75,
            "Controversy Level": 3.0,
            "Peer Controversy Min": 0.0,
            "Peer Controversy Avg": 0.9104477611940298,
            "Peer Controversy Max": 4.0
        },
        "Faithfulness Evaluation": {
            "Score": 0.8,
            "Explanation": "The generated ESG report accurately reflects the total ESG risk score of 26.1, as well as the individual environmental (8.3), social (11.05), and governance (6.75) risk scores. However, there is a significant error regarding the interpretation of the controversy level. The report states that Amazon's controversy level of 3.0 exceeds the peer maximum of 4.0, which is incorrect; 3.0 is below the maximum of 4.0. This misrepresentation could lead to misunderstandings about the severity of Amazon's controversies compared to its peers. Additionally, while the report mentions Amazon's efforts in sustainability, it could benefit from a more nuanced discussion of specific initiatives or metrics to support its claims. Overall, the report is mostly faithful to the reference data but contains a critical error regarding the controversy level, impacting its overall accuracy."
        }
    },
    "TQQQ": {
        "Generated Report": "No ESG data available for TQQQ",
        "Reference ESG Data": {
            "error": "No ESG data available for TQQQ"
        },
        "Faithfulness Evaluation": "Could not evaluate due to error in data or report generation."
    },
    "AMD": {
        "Generated Report": "AMD's total ESG risk score of 12.51 indicates a moderate level of risk, with specific scores reflecting its environmental (3.01), social (4.22), and governance (5.28) dimensions. The environmental risk is relatively low, suggesting the company is managing its ecological footprint effectively, which is crucial in the semiconductor industry known for energy-intensive processes.\n\nSocial risks, scored at 4.22, suggest that while AMD has some challenges regarding workforce and community relations, these are manageable and not overly detrimental to its reputation. Governance risk, at 5.28, is the highest among the three dimensions, indicating potential vulnerabilities in corporate governance practices that could affect stakeholder confidence and long-term sustainability.\n\nThe controversy level of 1.0 is notably low compared to its peers, where the average sits around 0.56. This suggests that, despite some governance risks, AMD has generally avoided significant public disputes or scandals, reflecting positively on its brand reputation.\n\nOverall, while AMD shows strengths in environmental management and a low level of controversy, attention should be paid to governance practices to mitigate risks that could arise from potential mismanagement or lack of transparency. By addressing these governance concerns, AMD can enhance its sustainability profile and reduce overall ESG risks, further strengthening its position in the competitive technology landscape.",
        "Reference ESG Data": {
            "Stock": "AMD",
            "Total ESG Risk Score": 12.51,
            "Environmental Risk Score": 3.01,
            "Social Risk Score": 4.22,
            "Governance Risk Score": 5.28,
            "Controversy Level": 1.0,
            "Peer Controversy Min": 0.0,
            "Peer Controversy Avg": 0.5583333333333333,
            "Peer Controversy Max": 3.0
        },
        "Faithfulness Evaluation": {
            "Score": 1.0,
            "Explanation": "The generated ESG report accurately reflects the provided reference ESG data for AMD. It correctly states the total ESG risk score of 12.51 and breaks down the environmental, social, and governance risk scores as 3.01, 4.22, and 5.28, respectively. The report's interpretation of these scores aligns well with the data, indicating a moderate level of risk and providing context for each dimension. \n\nAdditionally, the mention of the controversy level of 1.0 and its comparison to peer averages is accurate and adds depth to the analysis. The report effectively communicates the implications of these scores, particularly regarding governance risks and the importance of addressing them for long-term sustainability. Overall, the report is grounded in the actual data and provides a faithful representation of AMD's ESG profile."
        }
    },
    "NFLX": {
        "Generated Report": "Netflix (NFLX) presents a mixed picture in terms of ESG performance. The total ESG risk score of 15.88 indicates a moderate level of risk, with specific areas of concern stemming from its social and governance practices.\n\nThe environmental risk score is notably low at 0.16, suggesting that NFLX has made substantial efforts to minimize its environmental impact, possibly through energy-efficient streaming technologies and sustainable operational practices. However, the company faces more significant challenges in social and governance dimensions, with social and governance risk scores of 7.38 and 8.35, respectively. This indicates potential vulnerabilities in areas such as labor practices, content diversity, and stakeholder engagement.\n\nThe controversy level of 2.0, while lower than the maximum of 3.0, is above the peer average of 1.01, signaling that NFLX has encountered notable issues that may affect its reputation and stakeholder trust. The existing controversies could stem from factors such as content-related disputes, corporate governance decisions, or employee relations, which could lead to reputational risks and impact investment sentiment.\n\nOverall, while Netflix demonstrates commendable performance in environmental sustainability, its heightened social and governance risks, combined with a higher-than-average controversy level, warrant careful monitoring. Investors should consider these factors when evaluating NFLX's long-term sustainability and potential risks in the evolving ESG landscape.",
        "Reference ESG Data": {
            "Stock": "NFLX",
            "Total ESG Risk Score": 15.88,
            "Environmental Risk Score": 0.16,
            "Social Risk Score": 7.38,
            "Governance Risk Score": 8.35,
            "Controversy Level": 2.0,
            "Peer Controversy Min": 0.0,
            "Peer Controversy Avg": 1.0070921985815602,
            "Peer Controversy Max": 3.0
        },
        "Faithfulness Evaluation": {
            "Score": 0.9,
            "Explanation": "The generated ESG report accurately reflects the key metrics from the reference ESG data, including the total ESG risk score of 15.88, the low environmental risk score of 0.16, and the higher social and governance risk scores of 7.38 and 8.35, respectively. The report correctly identifies the controversy level of 2.0 and notes that it is above the peer average of 1.01, which is a critical aspect of the analysis. \n\nHowever, while the report provides a solid overview of the company's ESG performance, it could benefit from a more nuanced discussion of the implications of the controversy level and how it compares to peers, as well as a clearer connection between the specific social and governance challenges mentioned and the scores provided. The phrase \"notable issues that may affect its reputation and stakeholder trust\" is somewhat vague and could be more specific. Overall, the report is largely faithful to the reference data, but slight improvements in specificity and depth could enhance its accuracy."
        }
    }
}