{
    "TSLA": {
        "Generated Report": "Tesla Inc. (TSLA) presents a mixed ESG profile, with a total risk score of 24.76, indicating a moderate level of overall risk. The Environmental Risk Score of 3.04 is relatively low, reflecting the company's commitment to sustainable energy solutions and electric vehicles, which contribute positively to environmental goals. However, the Social Risk Score of 14.13 highlights concerns regarding labor practices, community relations, and product safety, suggesting that Tesla may face reputational risks and operational challenges in these areas.\n\nThe Governance Risk Score of 7.6 indicates potential weaknesses in corporate governance practices, which could affect stakeholder confidence and regulatory compliance. Tesla's Controversy Level of 3.0 is significantly above the peer average of 1.75, indicating that the company has faced notable controversies that could impact its brand and market position. This level of controversy suggests heightened scrutiny from investors and consumers alike.\n\nIn summary, while Tesla's environmental initiatives are commendable, the elevated social and governance risks, coupled with a high controversy level, suggest that the company must address these issues to enhance its sustainability profile. Stakeholders should monitor these areas closely, as they pose potential risks to Tesla's reputation and financial performance in the evolving ESG landscape.",
        "Reference ESG Data": {
            "Stock": "TSLA",
            "Total ESG Risk Score": 24.76,
            "Environmental Risk Score": 3.04,
            "Social Risk Score": 14.13,
            "Governance Risk Score": 7.6,
            "Controversy Level": 3.0,
            "Peer Controversy Min": 0.0,
            "Peer Controversy Avg": 1.75,
            "Peer Controversy Max": 4.0
        },
        "Faithfulness Evaluation": {
            "Score": 1.0,
            "Explanation": "The generated ESG report accurately reflects the reference ESG data provided for Tesla Inc. (TSLA). It correctly states the total ESG Risk Score of 24.76 and breaks down the Environmental Risk Score (3.04), Social Risk Score (14.13), and Governance Risk Score (7.6) in a manner that aligns with the reference data. The report also appropriately highlights the controversy level of 3.0 and compares it to the peer average of 1.75, indicating a higher level of scrutiny for Tesla. Overall, the report provides a faithful and comprehensive summary of Tesla's ESG profile, making it fully grounded in the actual data."
        }
    },
    "NVDA": {
        "Generated Report": "NVIDIA Corporation (NVDA) exhibits a total ESG risk score of 12.46, indicating moderate overall sustainability risks. The breakdown reveals a relatively low Environmental Risk Score of 2.73, suggesting that NVDA is performing reasonably well in environmental management, particularly in comparison to peers within the technology sector. This score reflects the company's commitment to sustainable practices, including energy-efficient technologies and initiatives aimed at reducing carbon emissions.\n\nHowever, the Social Risk Score of 4.08 indicates potential vulnerabilities in areas such as labor practices, community impact, and product responsibility. This score suggests that NVDA may face challenges related to workforce diversity, employee welfare, or the societal implications of its products.\n\nThe Governance Risk Score of 5.65 is the highest among the three categories, signaling potential concerns in corporate governance, which could include board diversity, executive compensation, or shareholder rights. This score necessitates closer scrutiny of NVDA's governance practices to mitigate risks related to regulatory compliance and stakeholder engagement.\n\nThe company\u2019s Controversy Level of 2.0, while above the peer average of 0.56, remains manageable. This indicates that NVDA has encountered some issues but has not been embroiled in significant scandals.\n\nIn summary, while NVDA demonstrates strengths in environmental performance, attention should be given to social and governance factors to enhance its overall ESG profile and mitigate potential risks.",
        "Reference ESG Data": {
            "Stock": "NVDA",
            "Total ESG Risk Score": 12.46,
            "Environmental Risk Score": 2.73,
            "Social Risk Score": 4.08,
            "Governance Risk Score": 5.65,
            "Controversy Level": 2.0,
            "Peer Controversy Min": 0.0,
            "Peer Controversy Avg": 0.5583333333333333,
            "Peer Controversy Max": 3.0
        },
        "Faithfulness Evaluation": {
            "Score": 1.0,
            "Explanation": "The generated ESG report accurately reflects the reference ESG data provided for NVIDIA Corporation (NVDA). The total ESG risk score of 12.46 is correctly stated, and the breakdown of the Environmental Risk Score (2.73), Social Risk Score (4.08), and Governance Risk Score (5.65) aligns perfectly with the reference data. The report also appropriately contextualizes these scores, indicating that the Environmental Risk is low, while the Social and Governance Risks are higher, which is consistent with the data. Furthermore, the mention of the Controversy Level of 2.0 and its comparison to the peer average is accurate and provides a clear understanding of NVDA's standing relative to its peers. Overall, the report is faithful to the actual data, providing a comprehensive and accurate analysis of NVDA's ESG performance."
        }
    },
    "AAPL": {
        "Generated Report": "Apple Inc. (AAPL) presents a mixed sustainability profile based on its ESG risk scores. The total ESG risk score stands at 18.75, indicating a moderate level of risk in its operations. \n\n**Environmental Risk Score (2.05)**: Apple has relatively low environmental risk, reflecting its commitment to sustainability initiatives, including renewable energy use and carbon neutrality goals. This positive aspect may mitigate potential risks associated with environmental regulations and public scrutiny.\n\n**Social Risk Score (8.35)**: The social risk score reveals significant concerns, particularly related to labor practices and supply chain management. Issues such as working conditions in manufacturing facilities and the treatment of workers in supply chains can pose reputational risks and regulatory challenges.\n\n**Governance Risk Score (8.35)**: The governance score mirrors the social risk, suggesting potential weaknesses in corporate governance practices. This includes transparency in decision-making processes and diversity within leadership, which can impact stakeholder trust and investor confidence.\n\n**Controversy Level (3.0)**: With a controversy level of 3.0, AAPL is on the higher end of the scale, indicating that the company has faced notable public scrutiny. This level is equal to the maximum peer controversy, suggesting that AAPL is at risk of reputational damage that could affect its market position.\n\nIn summary, while Apple excels in environmental practices, it faces significant social and governance challenges that could expose it to risks, particularly regarding public perception and regulatory compliance. Investors should monitor these areas closely.",
        "Reference ESG Data": {
            "Stock": "AAPL",
            "Total ESG Risk Score": 18.75,
            "Environmental Risk Score": 2.05,
            "Social Risk Score": 8.35,
            "Governance Risk Score": 8.35,
            "Controversy Level": 3.0,
            "Peer Controversy Min": 0.0,
            "Peer Controversy Avg": 0.5598290598290598,
            "Peer Controversy Max": 3.0
        },
        "Faithfulness Evaluation": {
            "Score": 0.9,
            "Explanation": "The ESG report accurately reflects the reference data provided for Apple Inc. (AAPL), particularly in terms of the total ESG risk score (18.75), environmental risk score (2.05), social risk score (8.35), governance risk score (8.35), and controversy level (3.0). The descriptions of the environmental, social, and governance risks are consistent with the respective scores, highlighting the company's strengths and weaknesses appropriately. \n\nHowever, the report could be considered slightly less faithful due to the phrase \"Apple excels in environmental practices,\" which may imply a stronger positive connotation than the relatively low environmental risk score of 2.05 suggests. While the score is low, it does not necessarily indicate excellence but rather a lower level of risk compared to other factors. Therefore, while the report is largely accurate, the wording could lead to a misinterpretation of the environmental performance."
        }
    },
    "SPY": {
        "Generated Report": "No ESG data available for SPY",
        "Reference ESG Data": {
            "error": "No ESG data available for SPY"
        },
        "Faithfulness Evaluation": "Could not evaluate due to error in data or report generation."
    },
    "QQQ": {
        "Generated Report": "No ESG data available for QQQ",
        "Reference ESG Data": {
            "error": "No ESG data available for QQQ"
        },
        "Faithfulness Evaluation": "Could not evaluate due to error in data or report generation."
    },
    "META": {
        "Generated Report": "META's total ESG risk score of 32.73 indicates a moderate level of risk, with notable disparities across the environmental, social, and governance dimensions. The environmental risk score of 2.41 is relatively low, suggesting that META's operations have a negligible impact on ecological factors, which is positive for sustainability. However, the social risk score of 21.64 raises significant concerns, reflecting potential issues related to user privacy, misinformation, and the societal impacts of its platform. This area presents a considerable challenge for META, especially in an era where social responsibility is increasingly scrutinized.\n\nThe governance risk score of 8.68 indicates some vulnerabilities in corporate governance practices, which may affect stakeholder trust and decision-making transparency. The controversy level of 4.0 is concerning, especially when compared to the peer average of approximately 0.66. This suggests that META faces more frequent and severe controversies than its peers, which could lead to reputational damage and regulatory scrutiny.\n\nOverall, while META shows strengths in environmental sustainability, the elevated social and governance risks, coupled with a high controversy level, suggest that the company is navigating a complex landscape. Addressing these social and governance issues is crucial for improving its overall ESG profile and mitigating potential risks that could impact long-term value creation.",
        "Reference ESG Data": {
            "Stock": "META",
            "Total ESG Risk Score": 32.73,
            "Environmental Risk Score": 2.41,
            "Social Risk Score": 21.64,
            "Governance Risk Score": 8.68,
            "Controversy Level": 4.0,
            "Peer Controversy Min": 0.0,
            "Peer Controversy Avg": 0.6598984771573604,
            "Peer Controversy Max": 4.0
        },
        "Faithfulness Evaluation": {
            "Score": 1.0,
            "Explanation": "The generated ESG report accurately reflects the reference ESG data provided for META. It correctly states the total ESG risk score of 32.73 and breaks down the environmental risk score (2.41), social risk score (21.64), and governance risk score (8.68) in a manner that aligns with the reference data. The report appropriately highlights the low environmental risk, the significant concerns regarding social risks, and the vulnerabilities in governance practices. Additionally, it accurately notes the controversy level of 4.0 and compares it to the peer average, emphasizing META's higher controversy level. Overall, the report is faithful to the actual data, providing a clear and accurate assessment of META's ESG profile."
        }
    },
    "AMZN": {
        "Generated Report": "Amazon (AMZN) presents a mixed ESG profile, with a Total ESG Risk Score of 26.1, indicating moderate risk. The Environmental Risk Score of 8.3 highlights concerns, particularly regarding emissions, waste management, and resource consumption, which are critical for a company of its size and operational scale. Although Amazon has made strides in sustainability initiatives, such as commitments to renewable energy and carbon neutrality, its environmental footprint remains significant.\n\nThe Social Risk Score of 11.05 raises additional red flags. Issues related to labor practices, employee treatment, and community impact are prominent, often leading to public scrutiny and potential reputational damage. The company has faced criticism regarding working conditions in warehouses, which could affect employee retention and overall morale.\n\nThe Governance Risk Score of 6.75 suggests room for improvement in corporate governance practices, including board diversity and executive compensation alignment with long-term sustainability goals. \n\nWith a Controversy Level of 3.0, Amazon is positioned above the peer average (0.91) but below the maximum (4.0), indicating it is subject to significant scrutiny compared to its industry peers. \n\nIn summary, while Amazon is actively addressing its ESG challenges, the moderate risk scores across environmental, social, and governance dimensions, combined with a heightened controversy level, signal potential vulnerabilities that investors should closely monitor.",
        "Reference ESG Data": {
            "Stock": "AMZN",
            "Total ESG Risk Score": 26.1,
            "Environmental Risk Score": 8.3,
            "Social Risk Score": 11.05,
            "Governance Risk Score": 6.75,
            "Controversy Level": 3.0,
            "Peer Controversy Min": 0.0,
            "Peer Controversy Avg": 0.9104477611940298,
            "Peer Controversy Max": 4.0
        },
        "Faithfulness Evaluation": {
            "Score": 1.0,
            "Explanation": "The generated ESG report accurately reflects the reference ESG data provided for Amazon (AMZN). It correctly states the Total ESG Risk Score of 26.1 and breaks down the Environmental Risk Score (8.3), Social Risk Score (11.05), and Governance Risk Score (6.75) in a manner that is consistent with the reference data. Additionally, it appropriately discusses the implications of these scores, including the company's environmental initiatives and social issues related to labor practices, which align with the scores given. The report also accurately mentions the Controversy Level of 3.0 and contextualizes it against the peer controversy average, providing a faithful representation of Amazon's ESG standing. Overall, the report is grounded in the actual data, making it perfectly faithful."
        }
    },
    "TQQQ": {
        "Generated Report": "No ESG data available for TQQQ",
        "Reference ESG Data": {
            "error": "No ESG data available for TQQQ"
        },
        "Faithfulness Evaluation": "Could not evaluate due to error in data or report generation."
    },
    "AMD": {
        "Generated Report": "Advanced Micro Devices (AMD) presents a mixed ESG profile with a total ESG risk score of 12.51, indicating some level of risk associated with its sustainability practices. The breakdown of scores shows a relatively low Environmental Risk Score of 3.01, suggesting that AMD is managing its environmental impacts effectively, particularly in a sector known for substantial energy consumption and waste generation.\n\nHowever, the Social Risk Score of 4.22 and Governance Risk Score of 5.28 indicate areas that may require attention. The social score reflects potential challenges related to labor practices, community engagement, or supply chain management, which could impact AMD's reputation and operational effectiveness. The governance score, being the highest among the three, raises concerns about corporate governance practices, including board diversity, executive compensation, and shareholder rights.\n\nThe company's Controversy Level of 1.0 is relatively low compared to peers, where the average stands at approximately 0.56. This suggests that while AMD has faced some controversies, they are not significant compared to others in the industry.\n\nIn summary, AMD demonstrates a commendable approach to environmental responsibility but faces potential risks in social and governance dimensions. Stakeholders should monitor these areas closely, as improvements in governance and social practices could enhance the company's overall sustainability and mitigate future risks.",
        "Reference ESG Data": {
            "Stock": "AMD",
            "Total ESG Risk Score": 12.51,
            "Environmental Risk Score": 3.01,
            "Social Risk Score": 4.22,
            "Governance Risk Score": 5.28,
            "Controversy Level": 1.0,
            "Peer Controversy Min": 0.0,
            "Peer Controversy Avg": 0.5583333333333333,
            "Peer Controversy Max": 3.0
        },
        "Faithfulness Evaluation": {
            "Score": 1.0,
            "Explanation": "The generated ESG report accurately reflects the reference ESG data provided for AMD. The total ESG risk score of 12.51 is correctly stated, and the breakdown of the Environmental Risk Score (3.01), Social Risk Score (4.22), and Governance Risk Score (5.28) aligns perfectly with the reference data. The report also correctly identifies the Controversy Level of 1.0 and compares it favorably to the peer average of approximately 0.56, indicating that AMD's controversies are indeed relatively low. The interpretations regarding the implications of these scores for AMD's sustainability practices are reasonable and grounded in the actual data. Overall, the report is faithful to the reference data and provides a coherent analysis of AMD's ESG profile."
        }
    },
    "NFLX": {
        "Generated Report": "Netflix (NFLX) exhibits a total ESG risk score of 15.88, indicating a moderate level of sustainability risk. The Environmental Risk Score is notably low at 0.16, suggesting that Netflix's operations have minimal negative impact on the environment, which is favorable for sustainability. However, the Social Risk Score of 7.38 and the Governance Risk Score of 8.35 highlight significant areas of concern. \n\nThe Social Risk Score reflects potential issues related to labor practices, content diversity, and community engagement, which could impact the company's reputation and stakeholder relations. The Governance Risk Score indicates possible vulnerabilities in corporate governance structures, including board diversity, shareholder rights, and executive compensation policies, potentially affecting investor confidence and long-term performance.\n\nThe controversy level of 2.0 is above the peer average of 1.007, suggesting that Netflix has faced notable disputes or criticisms compared to its industry peers. This higher level of controversy may expose the company to reputational risks and regulatory scrutiny, which could impact its operational stability and market perception.\n\nIn summary, while Netflix scores well environmentally, the elevated social and governance risks, combined with a higher than average controversy level, indicate areas that require attention. Addressing these risks is crucial for enhancing the company's sustainability profile and mitigating potential impacts on its long-term value.",
        "Reference ESG Data": {
            "Stock": "NFLX",
            "Total ESG Risk Score": 15.88,
            "Environmental Risk Score": 0.16,
            "Social Risk Score": 7.38,
            "Governance Risk Score": 8.35,
            "Controversy Level": 2.0,
            "Peer Controversy Min": 0.0,
            "Peer Controversy Avg": 1.0070921985815602,
            "Peer Controversy Max": 3.0
        },
        "Faithfulness Evaluation": {
            "Score": 1.0,
            "Explanation": "The generated ESG report accurately reflects the reference ESG data for Netflix (NFLX). It correctly states the total ESG risk score of 15.88 and provides a precise breakdown of the Environmental Risk Score (0.16), Social Risk Score (7.38), and Governance Risk Score (8.35). The report appropriately interprets these scores, highlighting the low environmental impact while addressing the significant social and governance concerns. Furthermore, it accurately mentions the controversy level of 2.0 and compares it to the peer average of 1.007, indicating a higher level of controversy for Netflix. Overall, the report is well-grounded in the actual data, making it perfectly faithful."
        }
    }
}