{
    "TSLA": {
        "Generated Report": "Tesla, Inc. (TSLA) presents a mixed ESG profile based on the provided risk scores and controversy levels. The total ESG risk score of 24.76 suggests that while the company is making strides in sustainability, there are notable risks that investors should consider.\n\n**Environmental Risk**: With a low environmental risk score of 3.04, Tesla demonstrates a strong commitment to reducing carbon emissions through its electric vehicle (EV) production and renewable energy initiatives. This positions the company favorably in an increasingly eco-conscious market.\n\n**Social Risk**: The social risk score of 14.13 is notably high, indicating potential challenges related to labor practices, workplace culture, and community engagement. This score may reflect ongoing concerns about employee treatment and safety, which could impact Tesla's reputation and operational continuity.\n\n**Governance Risk**: The governance risk score of 7.6 points to some weaknesses in corporate governance structures, potentially affecting investor confidence and decision-making processes. \n\n**Controversy Level**: With a controversy level of 3.0, Tesla's reputation is at risk from various incidents, including leadership decisions and public statements that may not align with stakeholder expectations. This level of controversy is above the average for its peers, which may warrant caution for ESG-focused investors.\n\nIn summary, while Tesla excels in environmental initiatives, the high social risk and governance concerns, combined with significant controversy, present substantial risks that could affect the company's long-term sustainability and investor attractiveness.",
        "Reference ESG Data": {
            "Stock": "TSLA",
            "Total ESG Risk Score": 24.76,
            "Environmental Risk Score": 3.04,
            "Social Risk Score": 14.13,
            "Governance Risk Score": 7.6,
            "Controversy Level": 3.0,
            "Peer Controversy Min": 0.0,
            "Peer Controversy Avg": 1.75,
            "Peer Controversy Max": 4.0
        },
        "Faithfulness Evaluation": {
            "Score": 0.9,
            "Explanation": "The generated ESG report is largely faithful to the provided reference ESG data. It accurately reflects the total ESG risk score of 24.76 and provides a clear breakdown of the environmental, social, and governance risk scores (3.04, 14.13, and 7.6, respectively). The report correctly identifies the high social risk and governance concerns, as well as the controversy level of 3.0, which is above the peer average. \n\nHowever, the phrase \"making strides in sustainability\" could be misleading, as the environmental risk score, while low, does not necessarily indicate a strong overall sustainability performance when considered alongside the higher social and governance risks. The report could also benefit from more context regarding the implications of the controversy level relative to the peer average. Therefore, while the report is mostly accurate, slight nuances in language and context could improve its faithfulness."
        }
    },
    "NVDA": {
        "Generated Report": "NVIDIA Corporation (NVDA) presents a mixed ESG profile, evidenced by its total ESG Risk Score of 12.46, which indicates a moderate level of general risk. The Environmental Risk Score of 2.73 suggests that while the company faces some environmental challenges, these are relatively manageable compared to its peers. This may be due to NVIDIA\u2019s commitment to sustainable practices, such as energy-efficient products and initiatives to reduce carbon emissions.\n\nHowever, the Social Risk Score of 4.08 indicates a higher level of concern, particularly regarding labor practices, community relations, and diversity and inclusion efforts. This could pose reputational risks if not addressed adequately, especially in a sector that increasingly prioritizes social responsibility.\n\nThe Governance Risk Score of 5.65 is the highest among the three categories, indicating potential issues related to board structure, executive compensation, and shareholder rights. This could raise red flags for investors focused on governance practices.\n\nNVIDIA\u2019s Controversy Level of 2.0, while above the peer average of 0.56, suggests that the company has faced some noteworthy controversies but is not at the highest risk level. The peer controversy range indicates that while NVDA\u2019s controversies are significant, they are not outliers.\n\nIn summary, while NVIDIA has strengths in environmental considerations, it must enhance its social and governance practices to mitigate risks and improve its overall sustainability profile. Investors should monitor these areas closely to assess long-term viability in an evolving ESG landscape.",
        "Reference ESG Data": {
            "Stock": "NVDA",
            "Total ESG Risk Score": 12.46,
            "Environmental Risk Score": 2.73,
            "Social Risk Score": 4.08,
            "Governance Risk Score": 5.65,
            "Controversy Level": 2.0,
            "Peer Controversy Min": 0.0,
            "Peer Controversy Avg": 0.5583333333333333,
            "Peer Controversy Max": 3.0
        },
        "Faithfulness Evaluation": {
            "Score": 1.0,
            "Explanation": "The generated ESG report accurately reflects the reference ESG data for NVIDIA Corporation (NVDA). It correctly states the total ESG Risk Score of 12.46 and provides a breakdown of the Environmental Risk Score (2.73), Social Risk Score (4.08), and Governance Risk Score (5.65), all of which align with the reference data. The report appropriately contextualizes the controversy level of 2.0, noting that it is above the peer average of 0.56 but not at the highest risk level, which is consistent with the provided data. The analysis of strengths and weaknesses in environmental, social, and governance practices is coherent and grounded in the actual scores. Overall, the report is faithful to the reference data, providing an accurate and comprehensive overview of NVIDIA's ESG profile."
        }
    },
    "AAPL": {
        "Generated Report": "Apple Inc. (AAPL) presents a mixed picture in its ESG profile, with a total risk score of 18.75 indicating a moderate level of overall risk. The Environmental Risk Score of 2.05 suggests that Apple maintains relatively low environmental risks, likely due to its initiatives focused on renewable energy and sustainable materials. However, the Social Risk Score and Governance Risk Score, both at 8.35, highlight significant concerns in these areas.\n\nThe social risks may stem from labor practices in its supply chain and product accessibility issues, while governance risks could relate to board diversity and shareholder rights. The controversy level of 3.0 is notably higher than the peer controversy average of 0.56, indicating that Apple has faced substantial scrutiny compared to its peers, which could adversely affect its reputation and investor sentiment.\n\nOverall, while Apple demonstrates strong environmental management, the elevated social and governance risks, coupled with a higher controversy level, suggest that the company must enhance its practices in these areas to mitigate potential reputational damage and align with growing stakeholder expectations. Continuous monitoring and proactive measures in social responsibility and governance are essential for Apple to maintain its competitive edge and sustainability credentials in an increasingly ESG-conscious market.",
        "Reference ESG Data": {
            "Stock": "AAPL",
            "Total ESG Risk Score": 18.75,
            "Environmental Risk Score": 2.05,
            "Social Risk Score": 8.35,
            "Governance Risk Score": 8.35,
            "Controversy Level": 3.0,
            "Peer Controversy Min": 0.0,
            "Peer Controversy Avg": 0.5598290598290598,
            "Peer Controversy Max": 3.0
        },
        "Faithfulness Evaluation": {
            "Score": 1.0,
            "Explanation": "The generated ESG report accurately reflects the provided reference ESG data for Apple Inc. (AAPL). It correctly states the total ESG risk score of 18.75 and provides a detailed breakdown of the Environmental Risk Score (2.05), Social Risk Score (8.35), and Governance Risk Score (8.35). The report also appropriately highlights the controversy level of 3.0, noting its significance in comparison to the peer controversy average of 0.56. The explanations regarding potential social and governance risks are grounded in the scores provided, and the overall assessment aligns with the data. Therefore, the report is faithful to the reference data."
        }
    },
    "SPY": {
        "Generated Report": "No ESG data available for SPY",
        "Reference ESG Data": {
            "error": "No ESG data available for SPY"
        },
        "Faithfulness Evaluation": "Could not evaluate due to error in data or report generation."
    },
    "QQQ": {
        "Generated Report": "No ESG data available for QQQ",
        "Reference ESG Data": {
            "error": "No ESG data available for QQQ"
        },
        "Faithfulness Evaluation": "Could not evaluate due to error in data or report generation."
    },
    "META": {
        "Generated Report": "META's total ESG risk score of 32.73 indicates a moderate level of environmental, social, and governance risks, with notable concerns particularly in the social dimension. The Environmental Risk Score of 2.41 suggests that META has relatively low environmental impact, which is positive for sustainability. However, the Social Risk Score of 21.64 is significantly higher, highlighting potential issues related to data privacy, misinformation, and user engagement, which have historically led to public scrutiny and regulatory challenges.\n\nThe Governance Risk Score of 8.68 reflects moderate concerns in governance practices, suggesting that there may be areas for improvement in transparency and accountability. The company's controversy level of 4.0, the maximum within its peer group, indicates that it has faced significant public and media backlash, which can impact its reputation and operational stability.\n\nIn comparison to peers, META's controversy level is markedly higher than the average of 0.66, indicating that while the company is positioned within a challenging industry, it faces unique reputational risks that could affect investor confidence and regulatory scrutiny.\n\nIn summary, while META demonstrates low environmental risks, its elevated social and governance concerns, alongside a high controversy level, present substantial challenges. Investors should remain vigilant regarding potential regulatory developments and public perception, as these factors could impact META's long-term sustainability and performance.",
        "Reference ESG Data": {
            "Stock": "META",
            "Total ESG Risk Score": 32.73,
            "Environmental Risk Score": 2.41,
            "Social Risk Score": 21.64,
            "Governance Risk Score": 8.68,
            "Controversy Level": 4.0,
            "Peer Controversy Min": 0.0,
            "Peer Controversy Avg": 0.6598984771573604,
            "Peer Controversy Max": 4.0
        },
        "Faithfulness Evaluation": {
            "Score": 0.9,
            "Explanation": "The generated ESG report accurately reflects the reference ESG data for META in several key areas, including the total ESG risk score, environmental risk score, social risk score, governance risk score, and controversy level. The report correctly identifies the moderate level of risk overall and highlights the significant concerns in the social dimension, which aligns with the provided data.\n\nHowever, the report could be slightly misleading in its comparison of the controversy level. While it states that META's controversy level of 4.0 is \"markedly higher than the average of 0.66,\" it does not clarify that the average is based on peers and that the maximum controversy level is indeed 4.0, which could imply that META is at the extreme end of the spectrum among its peers. This lack of clarity could lead to misinterpretation of the severity of META's situation relative to its peers.\n\nOverall, the report is largely faithful to the data, but the potential for misunderstanding in the comparison could warrant a slight deduction in the score."
        }
    },
    "AMZN": {
        "Generated Report": "Amazon (AMZN) presents a mixed ESG profile, highlighted by a total ESG risk score of 26.1. This score indicates a moderate level of risk, driven primarily by its social and environmental impacts. \n\nThe Environmental Risk Score of 8.3 suggests concerns related to Amazon\u2019s carbon footprint, waste management, and resource consumption. As a major logistics and e-commerce player, the company faces scrutiny over its greenhouse gas emissions and sustainability practices, particularly in packaging and energy use.\n\nThe Social Risk Score of 11.05 is notably high, reflecting issues related to labor practices, employee treatment, and community impact. Amazon has faced criticism over working conditions in its warehouses and its treatment of gig workers, raising concerns about its social responsibility and stakeholder engagement.\n\nThe Governance Risk Score of 6.75 is relatively lower, indicating that while there are governance challenges, they are not as pronounced as social and environmental issues. However, the controversy level of 3.0 is significant when compared to peers, with a minimum of 0 and an average of 0.91. This indicates that Amazon has encountered notable public and regulatory scrutiny, which could pose reputational and operational risks.\n\nIn summary, while Amazon has made strides in addressing its ESG challenges, its elevated social and environmental risk scores, alongside a high controversy level, underscore the need for enhanced sustainability strategies and stakeholder engagement to mitigate potential risks and improve its overall ESG standing.",
        "Reference ESG Data": {
            "Stock": "AMZN",
            "Total ESG Risk Score": 26.1,
            "Environmental Risk Score": 8.3,
            "Social Risk Score": 11.05,
            "Governance Risk Score": 6.75,
            "Controversy Level": 3.0,
            "Peer Controversy Min": 0.0,
            "Peer Controversy Avg": 0.9104477611940298,
            "Peer Controversy Max": 4.0
        },
        "Faithfulness Evaluation": {
            "Score": 1.0,
            "Explanation": "The generated ESG report accurately reflects the reference ESG data provided for Amazon (AMZN). It correctly states the total ESG risk score of 26.1 and breaks down the individual scores for environmental (8.3), social (11.05), and governance (6.75) risks, aligning perfectly with the reference data. The report also appropriately discusses the implications of these scores, particularly the high social risk score and the significant controversy level of 3.0 in comparison to peers. The analysis of Amazon's challenges and the call for enhanced sustainability strategies are consistent with the data presented. Overall, the report is faithful to the reference data, providing a clear and accurate representation of Amazon's ESG profile."
        }
    },
    "TQQQ": {
        "Generated Report": "No ESG data available for TQQQ",
        "Reference ESG Data": {
            "error": "No ESG data available for TQQQ"
        },
        "Faithfulness Evaluation": "Could not evaluate due to error in data or report generation."
    },
    "AMD": {
        "Generated Report": "AMD's overall ESG Risk Score of 12.51 indicates a relatively low level of ESG-related risks compared to industry peers. The Environmental Risk Score of 3.01 suggests that while AMD is not without environmental challenges, it is performing better than many competitors. The company has made strides in energy efficiency and sustainable product design, which helps mitigate potential environmental risks.\n\nThe Social Risk Score of 4.22 highlights some areas of concern, particularly in workforce diversity and community engagement. While this score is not alarmingly high, it suggests that AMD may need to enhance its social initiatives to improve its standing and address potential reputational risks.\n\nThe Governance Risk Score of 5.28 is the highest among the three categories, indicating that there may be room for improvement in governance practices. This score suggests potential risks related to board diversity, executive compensation, and shareholder rights, which could impact investor confidence if not properly managed.\n\nAMD's Controversy Level of 1.0 is relatively low, especially when compared to the peer average of 0.56 and maximum of 3.0. This low level of controversy indicates that the company has effectively managed public relations and stakeholder perceptions, which is a positive sign for investors.\n\nIn summary, while AMD demonstrates a solid ESG profile, focusing on governance and social issues will be crucial for further enhancing its sustainability and mitigating potential risks.",
        "Reference ESG Data": {
            "Stock": "AMD",
            "Total ESG Risk Score": 12.51,
            "Environmental Risk Score": 3.01,
            "Social Risk Score": 4.22,
            "Governance Risk Score": 5.28,
            "Controversy Level": 1.0,
            "Peer Controversy Min": 0.0,
            "Peer Controversy Avg": 0.5583333333333333,
            "Peer Controversy Max": 3.0
        },
        "Faithfulness Evaluation": {
            "Score": 1.0,
            "Explanation": "The generated ESG report accurately reflects the provided reference ESG data for AMD. The overall ESG Risk Score of 12.51 is correctly stated as indicating a relatively low level of ESG-related risks. Each individual risk score\u2014Environmental (3.01), Social (4.22), and Governance (5.28)\u2014is presented with appropriate context, highlighting areas of concern and suggesting where improvements can be made. Additionally, the report correctly interprets the Controversy Level of 1.0 as low compared to the peer averages, reinforcing the notion that AMD has managed its public relations effectively. Overall, the report is well-grounded in the actual data, providing a faithful representation of AMD's ESG profile."
        }
    },
    "NFLX": {
        "Generated Report": "Netflix (NFLX) presents a mixed sustainability profile according to its ESG risk scores. With a total ESG Risk Score of 15.88, the company exhibits relatively low environmental risk (0.16), indicating that its operations are not significantly detrimental to the environment. This is a positive aspect, especially as companies face increasing scrutiny regarding their environmental impact.\n\nHowever, the social (7.38) and governance (8.35) risk scores suggest that there are notable concerns in these areas. The social risk score is particularly concerning, as it may reflect issues related to employee treatment, diversity and inclusion, or content-related controversies. Governance risk, while higher than environmental risk, also raises flags regarding corporate practices and board oversight.\n\nThe controversy level of 2.0 indicates that Netflix has encountered some significant issues, though it is lower than the maximum peer controversy score of 3.0. This suggests that while controversies exist, they are not as severe as those faced by some peers. However, with an average peer controversy level of approximately 1.01, Netflix's controversies are above the norm, which could lead to reputational risks and potential financial impacts.\n\nIn conclusion, while Netflix shows strengths in environmental sustainability, it must address its social and governance challenges to improve its overall ESG standing and mitigate potential risks to its reputation and operational stability.",
        "Reference ESG Data": {
            "Stock": "NFLX",
            "Total ESG Risk Score": 15.88,
            "Environmental Risk Score": 0.16,
            "Social Risk Score": 7.38,
            "Governance Risk Score": 8.35,
            "Controversy Level": 2.0,
            "Peer Controversy Min": 0.0,
            "Peer Controversy Avg": 1.0070921985815602,
            "Peer Controversy Max": 3.0
        },
        "Faithfulness Evaluation": {
            "Score": 1.0,
            "Explanation": "The generated ESG report accurately reflects the reference ESG data for Netflix (NFLX). It correctly states the total ESG Risk Score of 15.88 and provides the specific environmental, social, and governance risk scores (0.16, 7.38, and 8.35, respectively). The report also appropriately interprets the controversy level of 2.0 in relation to peer controversy scores, noting that while Netflix has faced some significant issues, they are not as severe as those of some peers. The analysis of strengths and weaknesses aligns well with the data provided, making the report a faithful representation of the actual ESG metrics."
        }
    }
}