{
    "TSLA": {
        "Generated Report": "Tesla Inc. (TSLA) presents a mixed profile in terms of ESG (Environmental, Social, Governance) performance based on its risk scores. The total ESG Risk Score of 24.76 indicates a moderate level of risk, with a particularly low Environmental Risk Score of 3.04. This suggests that Tesla's commitment to sustainability through its electric vehicles and renewable energy solutions is strong, positioning the company favorably in the environmental aspect.\n\nHowever, the Social Risk Score of 14.13 raises concerns, reflecting issues related to labor practices, community relations, and customer satisfaction. This score is significant compared to the governance aspect, which scores 7.6, indicating potential weaknesses in corporate governance practices, such as board diversity or transparency.\n\nThe Controversy Level of 3.0 is noteworthy, especially when compared to peer averages (0.0 to 4.0), suggesting that while Tesla has faced notable controversies, it falls within a moderate range. This could indicate reputational risks that may impact investor confidence and customer loyalty.\n\nIn summary, while Tesla excels in environmental sustainability, it faces notable social and governance challenges that could affect its long-term viability and reputation. Investors should monitor these risks closely, as they could impact the company's market position and growth trajectory in an increasingly ESG-focused investment landscape.",
        "Reference ESG Data": {
            "Stock": "TSLA",
            "Total ESG Risk Score": 24.76,
            "Environmental Risk Score": 3.04,
            "Social Risk Score": 14.13,
            "Governance Risk Score": 7.6,
            "Controversy Level": 3.0,
            "Peer Controversy Min": 0.0,
            "Peer Controversy Avg": 1.75,
            "Peer Controversy Max": 4.0
        },
        "Faithfulness Evaluation": {
            "Score": 0.9,
            "Explanation": "The generated ESG report accurately reflects the reference ESG data for Tesla Inc. (TSLA) in terms of the total ESG Risk Score, Environmental Risk Score, Social Risk Score, Governance Risk Score, and Controversy Level. The report correctly identifies the moderate total ESG risk and highlights the low environmental risk while acknowledging the higher social and governance risks. \n\nHowever, the report could improve its faithfulness by providing more context on the implications of the scores, particularly the social risk, which is notably high. While it mentions concerns related to labor practices and community relations, it could further elaborate on specific controversies or issues that contribute to this score. Additionally, the report states that Tesla's controversy level is \"noteworthy\" but does not clearly articulate how it compares to peers beyond simply stating the range, which could enhance clarity. \n\nOverall, the report is largely faithful to the reference data, but slight improvements in detail and context could elevate its accuracy and comprehensiveness."
        }
    },
    "NVDA": {
        "Generated Report": "NVIDIA Corporation (NVDA) presents a mixed ESG profile based on its risk scores and controversy level. With a total ESG Risk Score of 12.46, the company is positioned on the lower end of the risk spectrum, indicating a relatively favorable sustainability outlook compared to peers. \n\nThe Environmental Risk Score of 2.73 is notably low, suggesting that NVDA is effectively managing environmental impacts, particularly in a sector often scrutinized for energy consumption and waste generation. However, the Social Risk Score of 4.08 indicates moderate risks related to social factors, which may include concerns around labor practices and community engagement. \n\nThe Governance Risk Score of 5.65 is the highest among the three categories, reflecting potential vulnerabilities in corporate governance practices. This score may raise flags regarding board diversity, executive compensation, and shareholder rights, which are critical for long-term sustainability and stakeholder trust.\n\nThe controversy level of 2.0 is above the peer average (0.56) but below the maximum (3.0), suggesting that NVDA has faced some controversies, but they are not at the highest levels seen in the industry. \n\nIn summary, while NVIDIA demonstrates strong environmental performance and manages some social risks, governance issues and a higher-than-average controversy level warrant vigilance. Investors should continue to monitor these areas as they could impact the company\u2019s long-term sustainability and reputation.",
        "Reference ESG Data": {
            "Stock": "NVDA",
            "Total ESG Risk Score": 12.46,
            "Environmental Risk Score": 2.73,
            "Social Risk Score": 4.08,
            "Governance Risk Score": 5.65,
            "Controversy Level": 2.0,
            "Peer Controversy Min": 0.0,
            "Peer Controversy Avg": 0.5583333333333333,
            "Peer Controversy Max": 3.0
        },
        "Faithfulness Evaluation": {
            "Score": 0.9,
            "Explanation": "The generated ESG report is largely faithful to the provided reference ESG data. It accurately reflects the total ESG Risk Score of 12.46 and correctly categorizes the Environmental Risk Score (2.73), Social Risk Score (4.08), and Governance Risk Score (5.65). The commentary on the environmental performance being strong and the governance issues being a concern aligns well with the scores provided. \n\nHowever, while the report mentions that the controversy level of 2.0 is above the peer average (0.56), it could be clearer about the significance of this comparison. The report states that the controversy level is \"above the peer average\" but does not explicitly mention that the peer controversy average is significantly lower than NVDA's score, which could imply a more serious concern than presented. \n\nOverall, the report is accurate and grounded in the actual data, but the slight lack of clarity regarding the controversy level's implications prevents it from achieving a perfect score."
        }
    },
    "AAPL": {
        "Generated Report": "Apple Inc. (AAPL) presents a mixed ESG profile, as indicated by its Total ESG Risk Score of 18.75, which suggests a moderate level of risk. The Environmental Risk Score of 2.05 is relatively low, reflecting the company\u2019s ongoing efforts to enhance sustainability initiatives, such as transitioning to renewable energy sources and improving product recyclability. However, there is room for improvement, particularly in reducing carbon emissions and expanding the circular economy.\n\nThe Social Risk Score of 8.35 signals significant concerns, primarily related to labor practices and supply chain issues. Apple's reliance on global suppliers has led to scrutiny over working conditions, especially in regions with less stringent labor regulations. Addressing these concerns is critical for mitigating reputational risks and aligning with social responsibility expectations.\n\nThe Governance Risk Score, also at 8.35, indicates potential weaknesses in corporate governance practices. While Apple has a strong brand reputation, transparency and accountability in decision-making processes remain essential for investor confidence.\n\nThe Controversy Level of 3.0, while average among peers, showcases that Apple has faced notable controversies, which could impact stakeholder perception. With peer controversy levels averaging around 0.56, Apple\u2019s heightened controversy underscores the importance of proactive risk management strategies.\n\nIn conclusion, while Apple demonstrates strengths in environmental initiatives, it must address social and governance risks to enhance its overall ESG standing and safeguard against potential reputational and operational impacts.",
        "Reference ESG Data": {
            "Stock": "AAPL",
            "Total ESG Risk Score": 18.75,
            "Environmental Risk Score": 2.05,
            "Social Risk Score": 8.35,
            "Governance Risk Score": 8.35,
            "Controversy Level": 3.0,
            "Peer Controversy Min": 0.0,
            "Peer Controversy Avg": 0.5598290598290598,
            "Peer Controversy Max": 3.0
        },
        "Faithfulness Evaluation": {
            "Score": 0.9,
            "Explanation": "The generated ESG report accurately reflects the Total ESG Risk Score of 18.75 and the Environmental Risk Score of 2.05, which are consistent with the reference data. The report correctly identifies the Social and Governance Risk Scores as both being 8.35, highlighting significant concerns in these areas. Additionally, the mention of the Controversy Level of 3.0 aligns with the reference data, and the comparison to peer controversy levels is appropriately contextualized.\n\nHowever, while the report does a good job of summarizing the risks and areas for improvement, it could be slightly more precise in its language regarding the implications of the controversy level and the specific areas of governance that need attention. The phrase \"while average among peers\" could be misleading since it suggests that the controversy level is acceptable, whereas it is notably higher than the peer average. This nuance could be better articulated to enhance the report's accuracy. Overall, the report is largely faithful to the data, with minor areas for improvement in clarity and precision."
        }
    },
    "SPY": {
        "Generated Report": "No ESG data available for SPY",
        "Reference ESG Data": {
            "error": "No ESG data available for SPY"
        },
        "Faithfulness Evaluation": "Could not evaluate due to error in data or report generation."
    },
    "QQQ": {
        "Generated Report": "No ESG data available for QQQ",
        "Reference ESG Data": {
            "error": "No ESG data available for QQQ"
        },
        "Faithfulness Evaluation": "Could not evaluate due to error in data or report generation."
    },
    "META": {
        "Generated Report": "META's total ESG risk score of 32.73 suggests a moderate level of overall risk, with significant concerns stemming from its social and governance metrics. The social risk score of 21.64 is particularly high, indicating potential issues related to user privacy, content moderation, and societal impact, which have historically attracted scrutiny and criticism. This is further evidenced by the company's controversy level of 4.0, aligning with the higher end of the peer range, suggesting that while META is not alone in facing challenges, it is more frequently in the spotlight compared to its peers.\n\nThe environmental risk score of 2.41 is relatively low, indicating that META may have a smaller environmental footprint or fewer related controversies. However, this does not fully mitigate the potential reputational and operational risks associated with social and governance factors. The governance risk score of 8.68, while moderate, points to potential issues in board structure, executive pay, or shareholder rights, which could impact long-term sustainability and investor confidence.\n\nOverall, while META shows strengths in environmental performance, the elevated social and governance risks, along with a high controversy level, suggest that it faces significant challenges that could impact its sustainability and investment attractiveness. Investors should remain vigilant regarding these risks and consider the company's strategies for addressing them in the future.",
        "Reference ESG Data": {
            "Stock": "META",
            "Total ESG Risk Score": 32.73,
            "Environmental Risk Score": 2.41,
            "Social Risk Score": 21.64,
            "Governance Risk Score": 8.68,
            "Controversy Level": 4.0,
            "Peer Controversy Min": 0.0,
            "Peer Controversy Avg": 0.6598984771573604,
            "Peer Controversy Max": 4.0
        },
        "Faithfulness Evaluation": {
            "Score": 1.0,
            "Explanation": "The generated ESG report accurately reflects the reference ESG data provided for META. It correctly states the total ESG risk score of 32.73 and breaks down the individual scores for environmental (2.41), social (21.64), and governance (8.68) risks. The report appropriately highlights the significant concerns related to social and governance metrics, aligning with the high social risk score and the controversy level of 4.0, which is at the upper end of the peer range. The analysis of the environmental risk score as relatively low is also accurate, and the report effectively communicates the implications of these scores for investors. Overall, the report is grounded in the actual data and provides a faithful representation of META's ESG profile."
        }
    },
    "AMZN": {
        "Generated Report": "Amazon (AMZN) exhibits a total ESG risk score of 26.1, indicating a moderate level of risk within the environmental, social, and governance domains. The environmental risk score of 8.3 suggests that while the company has made strides in sustainability, challenges remain, particularly regarding its carbon footprint and resource consumption. \n\nThe social risk score of 11.05 is notable, reflecting potential concerns related to labor practices, community impact, and customer data privacy. This score is higher than the average among peers, indicating that Amazon may face heightened scrutiny from stakeholders about its workforce treatment and societal contributions.\n\nWith a governance risk score of 6.75, governance-related risks appear relatively lower compared to environmental and social aspects. However, the controversy level of 3.0 is significant, surpassing both the peer average of 0.91 and the maximum of 4.0. This suggests that Amazon has encountered notable public disputes or criticisms, which could impact its reputation and investor confidence.\n\nIn summary, while Amazon is making progress in various ESG initiatives, it faces substantial risks, particularly in social and environmental areas, compounded by a high controversy level. Stakeholders should closely monitor these factors as they could affect the company\u2019s long-term sustainability and financial performance.",
        "Reference ESG Data": {
            "Stock": "AMZN",
            "Total ESG Risk Score": 26.1,
            "Environmental Risk Score": 8.3,
            "Social Risk Score": 11.05,
            "Governance Risk Score": 6.75,
            "Controversy Level": 3.0,
            "Peer Controversy Min": 0.0,
            "Peer Controversy Avg": 0.9104477611940298,
            "Peer Controversy Max": 4.0
        },
        "Faithfulness Evaluation": {
            "Score": 1.0,
            "Explanation": "The generated ESG report accurately reflects the provided reference ESG data for Amazon (AMZN). It correctly states the total ESG risk score of 26.1 and breaks down the environmental risk score (8.3), social risk score (11.05), and governance risk score (6.75) in a manner consistent with the reference data. Additionally, it appropriately highlights the controversy level of 3.0, noting that it exceeds the peer average and maximum, which aligns with the reference data. The report's interpretation of the scores and the implications for stakeholders are well-founded and grounded in the actual data, demonstrating a faithful representation of Amazon's ESG standing."
        }
    },
    "TQQQ": {
        "Generated Report": "No ESG data available for TQQQ",
        "Reference ESG Data": {
            "error": "No ESG data available for TQQQ"
        },
        "Faithfulness Evaluation": "Could not evaluate due to error in data or report generation."
    },
    "AMD": {
        "Generated Report": "AMD's total ESG risk score of 12.51 indicates a relatively moderate level of risk compared to its peers. The breakdown of scores reveals strengths and weaknesses across the three dimensions of ESG:\n\n1. **Environmental (3.01)**: AMD's environmental risk score is relatively low, suggesting that the company has effective measures in place to manage its ecological impacts. However, continuous improvement is necessary, especially in energy consumption and waste management, as the semiconductor industry faces increasing scrutiny over its environmental footprint.\n\n2. **Social (4.22)**: The social risk score indicates a higher level of concern compared to environmental factors. This suggests potential issues in areas such as labor practices, community engagement, or product safety. Addressing these concerns is vital for AMD to maintain its social license to operate and enhance stakeholder trust.\n\n3. **Governance (5.28)**: The governance risk score is the highest among the three areas, indicating significant potential risks related to corporate governance practices. This could encompass board diversity, executive compensation, and transparency. Strengthening governance practices will be crucial for mitigating risks and aligning with shareholder expectations.\n\nThe controversy level of 1.0, while low, does suggest that AMD has faced some public scrutiny, but it remains below the peer average. Overall, while AMD demonstrates a foundational commitment to ESG principles, it must address its social and governance risks proactively to enhance its sustainability profile and resilience against potential challenges.",
        "Reference ESG Data": {
            "Stock": "AMD",
            "Total ESG Risk Score": 12.51,
            "Environmental Risk Score": 3.01,
            "Social Risk Score": 4.22,
            "Governance Risk Score": 5.28,
            "Controversy Level": 1.0,
            "Peer Controversy Min": 0.0,
            "Peer Controversy Avg": 0.5583333333333333,
            "Peer Controversy Max": 3.0
        },
        "Faithfulness Evaluation": {
            "Score": 1.0,
            "Explanation": "The generated ESG report accurately reflects the reference ESG data provided for AMD. The total ESG risk score of 12.51 is correctly stated, and the breakdown of the environmental (3.01), social (4.22), and governance (5.28) risk scores aligns perfectly with the reference data. The report appropriately contextualizes these scores, indicating that AMD's environmental risk is relatively low, while social and governance risks are higher, which is consistent with the data. Additionally, the mention of the controversy level being 1.0 and below the peer average is accurate and provides a clear understanding of AMD's standing in comparison to its peers. Overall, the report is faithful to the actual data, providing a comprehensive and accurate assessment of AMD's ESG performance."
        }
    },
    "NFLX": {
        "Generated Report": "Netflix (NFLX) demonstrates a mixed ESG profile, with a total ESG risk score of 15.88, indicating moderate risk, primarily driven by social and governance factors. \n\nThe environmental risk score of 0.16 is notably low, suggesting that Netflix has minimal environmental impact relative to its peers. This reflects a commitment to sustainability, likely through energy-efficient production and operations, as well as initiatives aimed at reducing carbon emissions.\n\nIn contrast, the social risk score of 7.38 indicates significant concerns, particularly around issues such as content representation, diversity, and employee treatment. This score suggests that Netflix may face challenges in maintaining a positive social impact, which could affect its reputation and stakeholder trust.\n\nThe governance risk score of 8.35 is also elevated, highlighting potential vulnerabilities in corporate governance practices. This could stem from concerns related to board diversity, executive compensation, and shareholder rights, which are crucial for long-term sustainability.\n\nAdditionally, the controversy level of 2.0, while above the peer average of 1.01, indicates that Netflix has encountered some level of controversy, but not to the extent of its most contentious peers. This may result from public backlash over content decisions or labor practices.\n\nOverall, while Netflix excels in environmental performance, it must address social and governance issues to mitigate risks and enhance its sustainability profile. Engaging with stakeholders and improving practices in these areas will be critical for its long-term success and reputation.",
        "Reference ESG Data": {
            "Stock": "NFLX",
            "Total ESG Risk Score": 15.88,
            "Environmental Risk Score": 0.16,
            "Social Risk Score": 7.38,
            "Governance Risk Score": 8.35,
            "Controversy Level": 2.0,
            "Peer Controversy Min": 0.0,
            "Peer Controversy Avg": 1.0070921985815602,
            "Peer Controversy Max": 3.0
        },
        "Faithfulness Evaluation": {
            "Score": 0.9,
            "Explanation": "The generated ESG report accurately reflects the total ESG risk score of 15.88 and the individual risk scores for environmental (0.16), social (7.38), and governance (8.35) aspects, which are consistent with the reference data. The report correctly identifies the low environmental risk score and highlights the significant social and governance concerns, aligning with the provided data.\n\nHowever, the report could be seen as slightly less faithful due to the phrasing around the controversy level. While it correctly states that the controversy level is 2.0 and above the peer average of 1.01, it does not mention the peer controversy minimum and maximum, which could provide additional context regarding Netflix's relative standing among peers. Furthermore, the report implies a degree of commitment to sustainability without citing specific initiatives, which could be perceived as an assumption rather than a grounded fact.\n\nOverall, the report is largely accurate and grounded in the actual data, but it could benefit from more precise contextualization regarding peer comparisons and specific sustainability initiatives."
        }
    }
}