{
    "TSLA": {
        "Generated Report": "Tesla, Inc. (TSLA) presents a mixed profile in terms of ESG risks, with a total risk score of 24.76. The environmental risk score of 3.04 is relatively low, reflecting the company\u2019s commitment to sustainable transportation and renewable energy solutions. Tesla's core business model aligns well with environmental sustainability, as it focuses on electric vehicles (EVs) and energy storage products.\n\nHowever, the social risk score of 14.13 raises significant concerns. This score indicates potential issues related to labor practices, worker safety, and community relations. Tesla has faced scrutiny regarding workplace conditions and employee complaints, which can impact its reputation and operational sustainability.\n\nThe governance risk score of 7.6 is moderate, suggesting that there may be areas for improvement in corporate governance practices. This score should be monitored closely, as governance issues can lead to regulatory challenges and affect investor confidence.\n\nThe controversy level of 3.0 is notable, especially when compared to peer averages, indicating that Tesla has been involved in several controversies that may pose reputational risks. With peers averaging a controversy level of 1.75, Tesla's higher score suggests it may face more intense scrutiny.\n\nIn summary, while Tesla\u2019s environmental initiatives are commendable, the social and governance risks, compounded by a higher controversy level, could pose challenges to its long-term sustainability and reputation in the marketplace. Investors should weigh these factors carefully when assessing the company\u2019s ESG profile.",
        "Reference ESG Data": {
            "Stock": "TSLA",
            "Total ESG Risk Score": 24.76,
            "Environmental Risk Score": 3.04,
            "Social Risk Score": 14.13,
            "Governance Risk Score": 7.6,
            "Controversy Level": 3.0,
            "Peer Controversy Min": 0.0,
            "Peer Controversy Avg": 1.75,
            "Peer Controversy Max": 4.0
        },
        "Faithfulness Evaluation": {
            "Score": 1.0,
            "Explanation": "The generated ESG report accurately reflects the reference ESG data provided for Tesla, Inc. (TSLA). The total ESG risk score of 24.76 is correctly stated, as are the individual scores for environmental (3.04), social (14.13), and governance (7.6) risks. The report appropriately highlights the low environmental risk and the significant concerns regarding social risks, aligning with the data. It also correctly notes the moderate governance risk and the controversy level of 3.0, comparing it effectively to the peer average of 1.75. The analysis of how these factors could impact Tesla's reputation and long-term sustainability is consistent with the data, making the report fully faithful to the reference ESG data."
        }
    },
    "NVDA": {
        "Generated Report": "NVIDIA Corporation (NVDA) presents a mixed ESG profile characterized by a total ESG risk score of 12.46, indicating moderate risk exposure. The environmental risk score is relatively low at 2.73, suggesting that the company has taken steps to mitigate environmental impact, particularly in terms of energy efficiency and sustainable practices in semiconductor manufacturing. However, ongoing scrutiny regarding the environmental implications of mining and data centers may pose future challenges.\n\nThe social risk score of 4.08 indicates some vulnerabilities, particularly in labor practices and workforce diversity. As the tech industry increasingly faces calls for equitable hiring and inclusive workplace cultures, NVDA may need to enhance its initiatives in these areas to improve its social standing.\n\nThe governance risk score of 5.65 is higher than both its environmental and social counterparts, highlighting potential governance challenges. This may reflect issues related to board diversity, executive compensation, or shareholder rights, which could impact investor perception and company reputation.\n\nWith a controversy level of 2.0, NVDA's engagement in controversies is moderate compared to its peers, where the average lies at 0.56. This suggests that while the company is not free from criticism, it is relatively well-positioned within its sector.\n\nIn conclusion, while NVDA exhibits strengths in environmental performance, its social and governance aspects require attention. Addressing these risks proactively will enhance its sustainability profile and potentially improve long-term financial performance.",
        "Reference ESG Data": {
            "Stock": "NVDA",
            "Total ESG Risk Score": 12.46,
            "Environmental Risk Score": 2.73,
            "Social Risk Score": 4.08,
            "Governance Risk Score": 5.65,
            "Controversy Level": 2.0,
            "Peer Controversy Min": 0.0,
            "Peer Controversy Avg": 0.5583333333333333,
            "Peer Controversy Max": 3.0
        },
        "Faithfulness Evaluation": {
            "Score": 1.0,
            "Explanation": "The generated ESG report accurately reflects the reference ESG data for NVIDIA Corporation (NVDA). It correctly states the total ESG risk score of 12.46 and provides a detailed breakdown of the environmental risk score (2.73), social risk score (4.08), and governance risk score (5.65). The report also appropriately contextualizes the controversy level of 2.0, comparing it to the peer average of 0.56, which is consistent with the reference data. The analysis of potential challenges and areas for improvement aligns well with the scores provided, demonstrating a faithful representation of NVDA's ESG profile. Overall, the report is grounded in the actual data, justifying a perfect faithfulness score."
        }
    },
    "AAPL": {
        "Generated Report": "Apple Inc. (AAPL) presents a mixed picture in terms of ESG sustainability, with total ESG risk score at 18.75. The environmental risk score of 2.05 indicates relatively low environmental concerns, suggesting that the company performs well in terms of sustainability practices, such as reducing carbon emissions and promoting recycling initiatives. This positioning may be appealing to environmentally conscious investors.\n\nHowever, the social and governance risk scores are both at 8.35, indicating significant risks in these areas. The social risk score suggests potential issues related to labor practices, supply chain management, and community impact, which could raise concerns among socially responsible investors. Similarly, the governance score reflects the need for strong corporate governance practices and transparency, particularly regarding board diversity and shareholder rights.\n\nThe controversy level of 3.0, which aligns with the maximum level among peers, signals that Apple has faced notable challenges or scandals that could influence public perception and investor sentiment. Despite the company's leading market position and innovation, these controversies might pose reputational risks and impact customer loyalty.\n\nIn conclusion, while Apple demonstrates commendable environmental performance, its elevated social and governance risks, coupled with a high controversy level, warrant careful consideration for investors focused on ESG factors. Addressing these areas could enhance its overall sustainability profile and mitigate potential risks.",
        "Reference ESG Data": {
            "Stock": "AAPL",
            "Total ESG Risk Score": 18.75,
            "Environmental Risk Score": 2.05,
            "Social Risk Score": 8.35,
            "Governance Risk Score": 8.35,
            "Controversy Level": 3.0,
            "Peer Controversy Min": 0.0,
            "Peer Controversy Avg": 0.5598290598290598,
            "Peer Controversy Max": 3.0
        },
        "Faithfulness Evaluation": {
            "Score": 1.0,
            "Explanation": "The generated ESG report accurately reflects the reference ESG data provided for Apple Inc. (AAPL). It correctly states the total ESG risk score of 18.75 and the environmental risk score of 2.05, indicating low environmental concerns. The report also accurately mentions the social and governance risk scores of 8.35, highlighting significant risks in those areas. Furthermore, it correctly identifies the controversy level of 3.0, which aligns with the maximum level among peers. The report effectively summarizes the implications of these scores for investors, making it a faithful representation of the actual data."
        }
    },
    "SPY": {
        "Generated Report": "No ESG data available for SPY",
        "Reference ESG Data": {
            "error": "No ESG data available for SPY"
        },
        "Faithfulness Evaluation": "Could not evaluate due to error in data or report generation."
    },
    "QQQ": {
        "Generated Report": "No ESG data available for QQQ",
        "Reference ESG Data": {
            "error": "No ESG data available for QQQ"
        },
        "Faithfulness Evaluation": "Could not evaluate due to error in data or report generation."
    },
    "META": {
        "Generated Report": "META exhibits a total ESG risk score of 32.73, indicating a moderate level of sustainability risk. The environmental risk score of 2.41 is relatively low, suggesting that the company has made strides in managing its ecological footprint and is less exposed to environmental liabilities compared to its peers. \n\nHowever, the social risk score of 21.64 raises concerns, positioning META significantly above the average controversy level of 0.66 among peers. This elevated score reflects potential issues related to data privacy, misinformation, and user safety, which have been focal points of regulatory scrutiny and public concern. The controversy level of 4.0 signifies a high degree of reputational risk, with implications for stakeholder trust and regulatory compliance.\n\nWith a governance risk score of 8.68, META appears to have some structural challenges, possibly linked to board diversity, executive compensation, or shareholder rights. While the governance score is not alarming, it suggests room for improvement in transparency and accountability.\n\nIn summary, while META maintains a manageable environmental risk profile, the significant social risk and high controversy level present notable threats to its long-term sustainability. Investors should closely monitor these social dynamics and governance practices, as they may impact META's market position and regulatory landscape moving forward.",
        "Reference ESG Data": {
            "Stock": "META",
            "Total ESG Risk Score": 32.73,
            "Environmental Risk Score": 2.41,
            "Social Risk Score": 21.64,
            "Governance Risk Score": 8.68,
            "Controversy Level": 4.0,
            "Peer Controversy Min": 0.0,
            "Peer Controversy Avg": 0.6598984771573604,
            "Peer Controversy Max": 4.0
        },
        "Faithfulness Evaluation": {
            "Score": 1.0,
            "Explanation": "The generated ESG report accurately reflects the reference ESG data for META. It correctly states the total ESG risk score of 32.73 and provides a detailed breakdown of the environmental, social, and governance risk scores, which align perfectly with the reference data (2.41 for environmental, 21.64 for social, and 8.68 for governance). The report also appropriately highlights the high controversy level of 4.0 and compares it to the peer controversy average, emphasizing the elevated social risk and its implications. Overall, the report is grounded in the actual data, making it fully faithful."
        }
    },
    "AMZN": {
        "Generated Report": "Amazon (AMZN) presents a mixed ESG profile, with a total ESG risk score of 26.1, indicating moderate risk in sustainability practices. The Environmental Risk Score of 8.3 suggests challenges in managing environmental impacts, particularly given the company's scale and logistics operations, which contribute significantly to carbon emissions. However, Amazon has made commitments to achieve net-zero carbon by 2040, indicating a proactive approach to mitigating environmental risks.\n\nThe Social Risk Score of 11.05 signals notable concerns, particularly regarding labor practices and workplace conditions, which have been subjects of scrutiny. Employee treatment and community impact are critical areas that may pose reputational risks, especially as public awareness and activism grow.\n\nThe Governance Risk Score of 6.75 reflects relatively better practices, though there is room for improvement in transparency and stakeholder engagement. The controversy level of 3.0, considerably higher than the peer average of 0.91, highlights heightened scrutiny and potential reputational threats. This suggests that while Amazon is a leader in e-commerce and cloud services, it faces significant challenges related to public perception and regulatory pressures.\n\nIn summary, while Amazon is making strides in environmental initiatives, its social practices and governance structures require enhanced attention to mitigate risks and improve its overall sustainability profile. Investors should weigh these factors in the context of long-term value creation and reputational stability.",
        "Reference ESG Data": {
            "Stock": "AMZN",
            "Total ESG Risk Score": 26.1,
            "Environmental Risk Score": 8.3,
            "Social Risk Score": 11.05,
            "Governance Risk Score": 6.75,
            "Controversy Level": 3.0,
            "Peer Controversy Min": 0.0,
            "Peer Controversy Avg": 0.9104477611940298,
            "Peer Controversy Max": 4.0
        },
        "Faithfulness Evaluation": {
            "Score": 1.0,
            "Explanation": "The generated ESG report accurately reflects the provided reference ESG data for Amazon (AMZN). It correctly states the total ESG risk score of 26.1 and breaks down the individual scores for environmental (8.3), social (11.05), and governance (6.75) risks, all of which align with the reference data. The report also appropriately highlights the controversy level of 3.0 and compares it to the peer average of 0.91, accurately indicating that Amazon's controversy level is significantly higher than its peers. Furthermore, the report discusses Amazon's commitments and challenges in a balanced manner, providing a comprehensive overview of the company's ESG profile. Overall, the report is faithful to the actual data, justifying the score of 1.0."
        }
    },
    "TQQQ": {
        "Generated Report": "No ESG data available for TQQQ",
        "Reference ESG Data": {
            "error": "No ESG data available for TQQQ"
        },
        "Faithfulness Evaluation": "Could not evaluate due to error in data or report generation."
    },
    "AMD": {
        "Generated Report": "Advanced Micro Devices (AMD) presents a mixed ESG profile based on its risk scores and controversy level. With a total ESG risk score of 12.51, the company is positioned within a moderate risk category. \n\nThe Environmental Risk Score of 3.01 indicates a relatively low impact on environmental factors compared to peers, suggesting that AMD has implemented practices to mitigate its environmental footprint, particularly in the energy-intensive semiconductor industry. However, continuous improvement in sustainability initiatives would be beneficial as global scrutiny around environmental practices intensifies.\n\nThe Social Risk Score of 4.22 reflects potential challenges in areas such as workforce diversity, labor practices, and community engagement. This score indicates a need for AMD to enhance its social responsibility efforts and focus on employee well-being and equitable practices to bolster its reputation and stakeholder trust.\n\nThe Governance Risk Score of 5.28 is the highest among the three categories, suggesting possible governance issues that could involve board diversity, executive compensation, or shareholder rights. Improving governance frameworks will be crucial for AMD to ensure transparency and accountability.\n\nThe controversy level of 1.0 is relatively low, especially when compared to the peer average of 0.56, indicating that AMD has managed to avoid significant public relations issues or scandals. Overall, while AMD demonstrates strengths in its environmental initiatives, attention to social and governance aspects will be essential to enhance its sustainability profile and mitigate potential risks in the future.",
        "Reference ESG Data": {
            "Stock": "AMD",
            "Total ESG Risk Score": 12.51,
            "Environmental Risk Score": 3.01,
            "Social Risk Score": 4.22,
            "Governance Risk Score": 5.28,
            "Controversy Level": 1.0,
            "Peer Controversy Min": 0.0,
            "Peer Controversy Avg": 0.5583333333333333,
            "Peer Controversy Max": 3.0
        },
        "Faithfulness Evaluation": {
            "Score": 1.0,
            "Explanation": "The generated ESG report accurately reflects the reference ESG data provided for AMD. It correctly states the total ESG risk score of 12.51 and breaks down the individual risk scores for environmental (3.01), social (4.22), and governance (5.28), aligning with the reference data. The report also appropriately contextualizes the controversy level of 1.0, highlighting its relative low standing compared to the peer average of 0.56. The analysis of each risk category is consistent with the scores, emphasizing areas for improvement without misrepresenting the data. Overall, the report is faithful to the reference data, providing an accurate and grounded assessment of AMD's ESG profile."
        }
    },
    "NFLX": {
        "Generated Report": "Netflix's overall ESG risk score of 15.88 suggests a moderate level of risk, with notable disparities across the three dimensions of ESG analysis. The Environmental Risk Score is particularly low at 0.16, indicating that Netflix has minimal environmental risks compared to its peers. This could be attributed to its operational model, which is primarily digital and thus has a reduced carbon footprint relative to traditional content production and distribution companies.\n\nIn contrast, the Social Risk Score of 7.38 and Governance Risk Score of 8.35 are significantly higher, highlighting potential vulnerabilities in these areas. The social risks may stem from content-related controversies, labor practices, or data privacy concerns, while governance issues could involve board diversity, executive compensation, and shareholder rights. \n\nThe controversy level of 2.0 places Netflix above the peer average of 1.01, suggesting that it has faced notable scrutiny or incidents, which may adversely impact its reputation and stakeholder trust. The maximum controversy score among peers is 3.0, indicating that while Netflix is not the most controversial, it does have room for improvement in managing public perception and stakeholder relations.\n\nIn summary, while Netflix excels in environmental sustainability, it must address social and governance risks to enhance its overall ESG profile and mitigate potential reputational and operational risks moving forward.",
        "Reference ESG Data": {
            "Stock": "NFLX",
            "Total ESG Risk Score": 15.88,
            "Environmental Risk Score": 0.16,
            "Social Risk Score": 7.38,
            "Governance Risk Score": 8.35,
            "Controversy Level": 2.0,
            "Peer Controversy Min": 0.0,
            "Peer Controversy Avg": 1.0070921985815602,
            "Peer Controversy Max": 3.0
        },
        "Faithfulness Evaluation": {
            "Score": 1.0,
            "Explanation": "The generated ESG report accurately reflects the reference ESG data provided for Netflix (NFLX). It correctly states the overall ESG risk score of 15.88 and provides a detailed breakdown of the Environmental Risk Score (0.16), Social Risk Score (7.38), and Governance Risk Score (8.35). The report appropriately contextualizes these scores, particularly highlighting the low environmental risk and the higher social and governance risks, which aligns with the data. \n\nAdditionally, the controversy level of 2.0 is accurately reported, and the comparison to the peer average of 1.01 is correctly noted, indicating that Netflix is above average in terms of controversy. The report also discusses potential areas for improvement, which is consistent with the data's implications. Overall, the report is faithful to the reference data, presenting a coherent and accurate analysis of Netflix's ESG standing."
        }
    }
}